Workbook

Sheet Инструкция
A1: Шаблон деления разработки сайта или мобильного приложения на первый и последующие релизы
A3: Назначение файла | B3: Помочь разделить разработку цифрового товара на первый релиз и последующие релизы так, чтобы быстро и экономно выйти на рынок, но не разрушить ценностное предложение, удержание и потенциал роста аудитории
A4: Логика работы | B4: 1) перенесите выводы всех предыдущих анализов в лист «Банк_анализа»; 2) опишите страницы, экраны, функции, интеграции и контентные блоки в листе «Реестр_единиц»; 3) заполните баллы 1–5; 4) используйте расчетный рекомендованный релиз; 5) проверьте первый релиз на целостность ценности и монетизации
A5: Принцип первого релиза | B5: Первый релиз должен содержать минимальный набор, который позволяет пользователю получить заявленную ценность, бизнесу – проверить спрос и монетизацию, а продукту – собрать данные для следующего роста
A6: Что нельзя переносить из первого релиза | B6: Нельзя переносить элементы, без которых пользователь не достигает ключевого результата, невозможно проверить основную гипотезу, не работает единица монетизации, не собирается критически важная обратная связь или разрывается основной пользовательский сценарий
A7: Как читать расчет | B7: Рекомендованный релиз формируется по баллам: связь с ценностным предложением, критичность для первого дохода, удержание, рост, доказательность, рыночный стандарт, быстрота и дешевизна реализации, технический риск и риск потери ценности при переносе
A8: Редактируемые поля | B8: Желтые поля предназначены для ввода. Зеленые поля являются расчетными. Справочники и выпадающие списки находятся на листе «Справочники»
A10: Шаг | B10: Действие | C10: Результат
A11: 1 | B11: Собрать выводы из анализа проблем, отзывов, конкурентов, ценностного предложения, цифрового товара, Канвас, сценариев и страниц/экранов | C11: Единый банк доказанных оснований для решений по релизам
A12: 2 | B12: Разложить будущий сайт или приложение на интерфейсные и функциональные единицы | C12: Перечень кандидатов на включение в релизы
A13: 3 | B13: Оценить каждую единицу по шкалам 1–5 | C13: Сравнимые баллы для быстрого и обоснованного выбора состава первого релиза
A14: 4 | B14: Проверить, не нарушается ли ценностное предложение, монетизация, удержание и рост при переносе части функций | C14: Сбалансированный первый релиз без избыточной разработки
A15: 5 | B15: Сформировать дорожную карту последующих релизов | C15: Последовательность развития продукта после выхода на рынок

Sheet Банк_анализа
A1: ID вывода | B1: Вид анализа | C1: Объект анализа | D1: Ключевой вывод | E1: Проблема / потребность | F1: Пользовательский сегмент | G1: Доказательство | H1: Источник / ссылка | I1: Достоверность 1–5 | J1: Значимость 1–5 | K1: Вывод для релизов | L1: Связанная единица разработки
A2: A-001 | B2: Проблемы клиентов | C2: Проблема P-002 | D2: Нет единого инструмента для всех нотаций проекта | E2: Нет единого инструмента | F2: Студенты и аналитики ПО | G2: ЛР5: IDEF0, DFD, сети Петри не найдены у 8 конкурентов | H2: 6.1; ЛР5 | I2: 4 | J2: 5 | K2: Ядро ценности - выбор нотации и редактор в первый релиз | L2: U-007, U-008
A3: A-002 | B3: Рыночный стандарт | C3: Стандарт товара | D3: Бесплатный доступ, экспорт, интеграции - у 8 из 8; документация и безопасность - у 6 из 8 | E3: Ожидаемый минимум | F3: Все | G3: ЛР5: листы 07_Стандарт_рынка, 10_Стандарт | H3: ЛР5 | I3: 4 | J3: 5 | K3: Стандарт включается в первый релиз в базовой форме | L3: U-003, U-009, U-004
A4: A-003 | B4: Монетизация | C4: Единица монетизации | D4: Подписка Pro 40 у.е. в год; Free без оплаты | E4: Платежная готовность | F4: Аналитики и разработчики | G4: 6.1: M-001; опрос: 18 из 27 готовы платить | H4: 6.1; ЛР4 | I4: 3 | J4: 5 | K4: Один проверяемый способ монетизации обязателен в первом релизе | L4: U-003, U-006
A5: A-004 | B5: Бизнес-логика | C5: Сценарии 6.3 | D5: Критический сценарий - оформление подписки; высокие - первая диаграмма и экспорт | E5: Основные сценарии | F5: Все роли | G5: 6.3: индекс сценариев | H5: 6.3 | I5: 4 | J5: 5 | K5: Сценарии S-004, S-006, S-008 входят в первый релиз | L5: U-008, U-009, U-006
A6: A-005 | B6: Страницы и экраны | C6: Приоритет единиц 6.4 | D6: P1 по формуле: выбор нотации, редактор, экспорт; тарифы, регистрация, оплата - цепочка воронки | E6: Состав интерфейса | F6: Все роли | G6: 6.4: лист Приоритизация | H6: 6.4 | I6: 4 | J6: 5 | K6: Цепочка обнаружение - выбор - оплата - результат сохраняется | L6: U-003, U-005, U-006
A7: A-006 | B7: Рост | C7: Каналы | D7: Основной канал - поиск 47-59 % трафика; реферальные механики - перенос | E7: Рост аудитории | F7: Студенты | G7: ЛР4: Similarweb Pro | H7: ЛР4 | I7: 4 | J7: 3 | K7: Рост аудитории переносится в релиз 3 | L7: U-018
A8: A-007 | B8: Конкурентные преимущества | C8: Eraser, Mermaid Chart | D8: Лимиты ИИ используются как тарифный ограничитель; технический риск высокий | E8: ИИ-ассистент | F8: Аналитики | G8: Страницы тарифов, 01.10.2026 | H8: ЛР5 | I8: 4 | J8: 3 | K8: ИИ-ассистент - во второй релиз | L8: U-013
A9: A-008 | B9: Отзывы и опрос | C9: Опрос студентов | D9: Коллаборация важна 26 из 27; сложность реализации высокая | E9: Совместная работа | F9: Студенты | G9: ЛР4: survey_students.csv (данные пробного опроса) | H9: ЛР4 | I9: 2 | J9: 4 | K9: Совместное редактирование - в релиз 3 или 4 | L9: U-017

Sheet Реестр_единиц
A1: ID | B1: Тип единицы | C1: Название единицы разработки | D1: Роль / сегмент | E1: Связанный сценарий | F1: Блок Канвас | G1: Связь с ценностным предложением 1–5 | H1: Критичность для первого дохода 1–5 | I1: Потенциал удержания 1–5 | J1: Потенциал роста аудитории 1–5 | K1: Доказательность 1–5 | L1: Рыночный стандарт 1–5 | M1: Быстрота реализации 1–5 | N1: Дешевизна реализации 1–5 | O1: Технический риск 1–5 | P1: Риск потери ценности при переносе 1–5 | Q1: Балл первого релиза | R1: Балл следующих релизов | S1: Рекомендованный релиз | T1: Решение | U1: Обоснование
A2: U-001 | B2: Страница сайта | C2: Главная страница | D2: Посетитель | E2: SC-001 | F2: Каналы | G2: 4 | H2: 3 | I2: 2 | J2: 4 | K2: 4 | L2: 5 | M2: 5 | N2: 5 | O2: 1 | P2: 3 | Q2: =ROUND((G2*0.18)+(H2*0.15)+(I2*0.12)+(J2*0.08)+(K2*0.13)+(L2*0.1)+(M2*0.12)+(N2*0.12)-(O2*0.07)+(P2*0.1),2) -> 4.18 | R2: =ROUND((I2*0.16)+(J2*0.2)+(K2*0.12)+(L2*0.1)+((6-M2)*0.08)+((6-N2)*0.08)+(O2*0.06)+(P2*0.14)+(G2*0.06),2) -> 2.98 | S2: =IF(A2="","",IF(AND(G2>=4,H2>=4,K2>=3,P2>=4),"Первый релиз",IF(Q2>=3.7,"Первый релиз",IF(R2>=3.6,"Следующий релиз","Не включать / проверить")))) -> Первый релиз | T2: =IF(A2="","",IF(S2="Первый релиз","Включить в минимальный рыночный выпуск",IF(S2="Следующий релиз","Запланировать после проверки первого релиза","Оставить как гипотезу / проверить позже"))) -> Включить в минимальный рыночный выпуск | U2: Объясняет обещание и ведет к регистрации; поиск - основной канал (ЛР4)
A3: U-002 | B3: Страница сайта | C3: Возможности и нотации | D3: Посетитель | E3: SC-002 | F3: Ценностные предложения | G3: 5 | H3: 3 | I3: 2 | J3: 4 | K3: 4 | L3: 4 | M3: 4 | N3: 4 | O3: 1 | P3: 4 | Q3: =ROUND((G3*0.18)+(H3*0.15)+(I3*0.12)+(J3*0.08)+(K3*0.13)+(L3*0.1)+(M3*0.12)+(N3*0.12)-(O3*0.07)+(P3*0.1),2) -> 4.12 | R3: =ROUND((I3*0.16)+(J3*0.2)+(K3*0.12)+(L3*0.1)+((6-M3)*0.08)+((6-N3)*0.08)+(O3*0.06)+(P3*0.14)+(G3*0.06),2) -> 3.24 | S3: =IF(A3="","",IF(AND(G3>=4,H3>=4,K3>=3,P3>=4),"Первый релиз",IF(Q3>=3.7,"Первый релиз",IF(R3>=3.6,"Следующий релиз","Не включать / проверить")))) -> Первый релиз | T3: =IF(A3="","",IF(S3="Первый релиз","Включить в минимальный рыночный выпуск",IF(S3="Следующий релиз","Запланировать после проверки первого релиза","Оставить как гипотезу / проверить позже"))) -> Включить в минимальный рыночный выпуск | U3: Показывает конкурентное отличие: нотации IDEF0, DFD, сети Петри (ЛР5)
A4: U-003 | B4: Страница сайта | C4: Тарифы Free и Pro | D4: Потенциальный клиент | E4: SC-002 | F4: Потоки доходов | G4: 4 | H4: 5 | I4: 3 | J4: 3 | K4: 4 | L4: 5 | M4: 5 | N4: 5 | O4: 1 | P4: 4 | Q4: =ROUND((G4*0.18)+(H4*0.15)+(I4*0.12)+(J4*0.08)+(K4*0.13)+(L4*0.1)+(M4*0.12)+(N4*0.12)-(O4*0.07)+(P4*0.1),2) -> 4.62 | R4: =ROUND((I4*0.16)+(J4*0.2)+(K4*0.12)+(L4*0.1)+((6-M4)*0.08)+((6-N4)*0.08)+(O4*0.06)+(P4*0.14)+(G4*0.06),2) -> 3.08 | S4: =IF(A4="","",IF(AND(G4>=4,H4>=4,K4>=3,P4>=4),"Первый релиз",IF(Q4>=3.7,"Первый релиз",IF(R4>=3.6,"Следующий релиз","Не включать / проверить")))) -> Первый релиз | T4: =IF(A4="","",IF(S4="Первый релиз","Включить в минимальный рыночный выпуск",IF(S4="Следующий релиз","Запланировать после проверки первого релиза","Оставить как гипотезу / проверить позже"))) -> Включить в минимальный рыночный выпуск | U4: Открытая страница тарифов у 5 из 8 конкурентов (ЛР5)
A5: U-004 | B5: Страница сайта | C5: Документация и примеры | D5: Активный пользователь | E5: SC-010 | F5: Отношения с клиентами | G5: 3 | H5: 2 | I5: 4 | J5: 3 | K5: 4 | L5: 4 | M5: 3 | N5: 3 | O5: 2 | P5: 3 | Q5: =ROUND((G5*0.18)+(H5*0.15)+(I5*0.12)+(J5*0.08)+(K5*0.13)+(L5*0.1)+(M5*0.12)+(N5*0.12)-(O5*0.07)+(P5*0.1),2) -> 3.36 | R5: =ROUND((I5*0.16)+(J5*0.2)+(K5*0.12)+(L5*0.1)+((6-M5)*0.08)+((6-N5)*0.08)+(O5*0.06)+(P5*0.14)+(G5*0.06),2) -> 3.32 | S5: =IF(A5="","",IF(AND(G5>=4,H5>=4,K5>=3,P5>=4),"Первый релиз",IF(Q5>=3.7,"Первый релиз",IF(R5>=3.6,"Следующий релиз","Не включать / проверить")))) -> Не включать / проверить | T5: =IF(A5="","",IF(S5="Первый релиз","Включить в минимальный рыночный выпуск",IF(S5="Следующий релиз","Запланировать после проверки первого релиза","Оставить как гипотезу / проверить позже"))) -> Оставить как гипотезу / проверить позже | U5: Документация у 6 из 8 конкурентов (ЛР5)
A6: U-005 | B6: Страница сайта | C6: Регистрация и вход | D6: Новый пользователь | E6: SC-003 | F6: Каналы | G6: 4 | H6: 4 | I6: 4 | J6: 3 | K6: 4 | L6: 5 | M6: 4 | N6: 4 | O6: 2 | P6: 5 | Q6: =ROUND((G6*0.18)+(H6*0.15)+(I6*0.12)+(J6*0.08)+(K6*0.13)+(L6*0.1)+(M6*0.12)+(N6*0.12)-(O6*0.07)+(P6*0.1),2) -> 4.38 | R6: =ROUND((I6*0.16)+(J6*0.2)+(K6*0.12)+(L6*0.1)+((6-M6)*0.08)+((6-N6)*0.08)+(O6*0.06)+(P6*0.14)+(G6*0.06),2) -> 3.6 | S6: =IF(A6="","",IF(AND(G6>=4,H6>=4,K6>=3,P6>=4),"Первый релиз",IF(Q6>=3.7,"Первый релиз",IF(R6>=3.6,"Следующий релиз","Не включать / проверить")))) -> Первый релиз | T6: =IF(A6="","",IF(S6="Первый релиз","Включить в минимальный рыночный выпуск",IF(S6="Следующий релиз","Запланировать после проверки первого релиза","Оставить как гипотезу / проверить позже"))) -> Включить в минимальный рыночный выпуск | U6: Вход нужен для сохранения диаграмм и подписки
A7: U-006 | B7: Страница сайта | C7: Оплата Pro | D7: Платящий клиент | E7: SC-008 | F7: Потоки доходов | G7: 4 | H7: 5 | I7: 4 | J7: 2 | K7: 3 | L7: 5 | M7: 3 | N7: 3 | O7: 4 | P7: 4 | Q7: =ROUND((G7*0.18)+(H7*0.15)+(I7*0.12)+(J7*0.08)+(K7*0.13)+(L7*0.1)+(M7*0.12)+(N7*0.12)-(O7*0.07)+(P7*0.1),2) -> 3.84 | R7: =ROUND((I7*0.16)+(J7*0.2)+(K7*0.12)+(L7*0.1)+((6-M7)*0.08)+((6-N7)*0.08)+(O7*0.06)+(P7*0.14)+(G7*0.06),2) -> 3.42 | S7: =IF(A7="","",IF(AND(G7>=4,H7>=4,K7>=3,P7>=4),"Первый релиз",IF(Q7>=3.7,"Первый релиз",IF(R7>=3.6,"Следующий релиз","Не включать / проверить")))) -> Первый релиз | T7: =IF(A7="","",IF(S7="Первый релиз","Включить в минимальный рыночный выпуск",IF(S7="Следующий релиз","Запланировать после проверки первого релиза","Оставить как гипотезу / проверить позже"))) -> Включить в минимальный рыночный выпуск | U7: Монетизация - граница экономии (6.5, п. 7.5)
A8: U-007 | B8: Экран приложения | C8: Выбор нотации и шаблона | D8: Новый пользователь | E8: SC-005 | F8: Ценностные предложения | G8: 5 | H8: 3 | I8: 3 | J8: 3 | K8: 4 | L8: 5 | M8: 5 | N8: 5 | O8: 1 | P8: 5 | Q8: =ROUND((G8*0.18)+(H8*0.15)+(I8*0.12)+(J8*0.08)+(K8*0.13)+(L8*0.1)+(M8*0.12)+(N8*0.12)-(O8*0.07)+(P8*0.1),2) -> 4.6 | R8: =ROUND((I8*0.16)+(J8*0.2)+(K8*0.12)+(L8*0.1)+((6-M8)*0.08)+((6-N8)*0.08)+(O8*0.06)+(P8*0.14)+(G8*0.06),2) -> 3.28 | S8: =IF(A8="","",IF(AND(G8>=4,H8>=4,K8>=3,P8>=4),"Первый релиз",IF(Q8>=3.7,"Первый релиз",IF(R8>=3.6,"Следующий релиз","Не включать / проверить")))) -> Первый релиз | T8: =IF(A8="","",IF(S8="Первый релиз","Включить в минимальный рыночный выпуск",IF(S8="Следующий релиз","Запланировать после проверки первого релиза","Оставить как гипотезу / проверить позже"))) -> Включить в минимальный рыночный выпуск | U8: Вход в ядро ценности; показывает набор нотаций
A9: U-008 | B9: Экран приложения | C9: Рабочая область редактора | D9: Новый пользователь | E9: SC-004 | F9: Ценностные предложения | G9: 5 | H9: 4 | I9: 5 | J9: 4 | K9: 4 | L9: 5 | M9: 2 | N9: 2 | O9: 4 | P9: 5 | Q9: =ROUND((G9*0.18)+(H9*0.15)+(I9*0.12)+(J9*0.08)+(K9*0.13)+(L9*0.1)+(M9*0.12)+(N9*0.12)-(O9*0.07)+(P9*0.1),2) -> 4.14 | R9: =ROUND((I9*0.16)+(J9*0.2)+(K9*0.12)+(L9*0.1)+((6-M9)*0.08)+((6-N9)*0.08)+(O9*0.06)+(P9*0.14)+(G9*0.06),2) -> 4.46 | S9: =IF(A9="","",IF(AND(G9>=4,H9>=4,K9>=3,P9>=4),"Первый релиз",IF(Q9>=3.7,"Первый релиз",IF(R9>=3.6,"Следующий релиз","Не включать / проверить")))) -> Первый релиз | T9: =IF(A9="","",IF(S9="Первый релиз","Включить в минимальный рыночный выпуск",IF(S9="Следующий релиз","Запланировать после проверки первого релиза","Оставить как гипотезу / проверить позже"))) -> Включить в минимальный рыночный выпуск | U9: Ядро цифрового товара
A10: U-009 | B10: Экран приложения | C10: Результат и экспорт | D10: Новый пользователь | E10: SC-006 | F10: Ценностные предложения | G10: 5 | H10: 4 | I10: 3 | J10: 4 | K10: 5 | L10: 5 | M10: 4 | N10: 4 | O10: 2 | P10: 5 | Q10: =ROUND((G10*0.18)+(H10*0.15)+(I10*0.12)+(J10*0.08)+(K10*0.13)+(L10*0.1)+(M10*0.12)+(N10*0.12)-(O10*0.07)+(P10*0.1),2) -> 4.65 | R10: =ROUND((I10*0.16)+(J10*0.2)+(K10*0.12)+(L10*0.1)+((6-M10)*0.08)+((6-N10)*0.08)+(O10*0.06)+(P10*0.14)+(G10*0.06),2) -> 3.82 | S10: =IF(A10="","",IF(AND(G10>=4,H10>=4,K10>=3,P10>=4),"Первый релиз",IF(Q10>=3.7,"Первый релиз",IF(R10>=3.6,"Следующий релиз","Не включать / проверить")))) -> Первый релиз | T10: =IF(A10="","",IF(S10="Первый релиз","Включить в минимальный рыночный выпуск",IF(S10="Следующий релиз","Запланировать после проверки первого релиза","Оставить как гипотезу / проверить позже"))) -> Включить в минимальный рыночный выпуск | U10: Экспорт у 8 из 8 конкурентов; PNG важен 27 из 27 (опрос)
A11: U-010 | B11: Экран приложения | C11: Мои диаграммы | D11: Активный пользователь | E11: SC-007 | F11: Отношения с клиентами | G11: 4 | H11: 2 | I11: 5 | J11: 2 | K11: 3 | L11: 4 | M11: 3 | N11: 3 | O11: 3 | P11: 3 | Q11: =ROUND((G11*0.18)+(H11*0.15)+(I11*0.12)+(J11*0.08)+(K11*0.13)+(L11*0.1)+(M11*0.12)+(N11*0.12)-(O11*0.07)+(P11*0.1),2) -> 3.38 | R11: =ROUND((I11*0.16)+(J11*0.2)+(K11*0.12)+(L11*0.1)+((6-M11)*0.08)+((6-N11)*0.08)+(O11*0.06)+(P11*0.14)+(G11*0.06),2) -> 3.28 | S11: =IF(A11="","",IF(AND(G11>=4,H11>=4,K11>=3,P11>=4),"Первый релиз",IF(Q11>=3.7,"Первый релиз",IF(R11>=3.6,"Следующий релиз","Не включать / проверить")))) -> Не включать / проверить | T11: =IF(A11="","",IF(S11="Первый релиз","Включить в минимальный рыночный выпуск",IF(S11="Следующий релиз","Запланировать после проверки первого релиза","Оставить как гипотезу / проверить позже"))) -> Оставить как гипотезу / проверить позже | U11: Возврат пользователя; история версий у 5 из 8
A12: U-011 | B12: Экран приложения | C12: Подсказка об ошибке синтаксиса | D12: Новый пользователь | E12: SC-009 | F12: Отношения с клиентами | G12: 4 | H12: 2 | I12: 4 | J12: 3 | K12: 2 | L12: 2 | M12: 2 | N12: 2 | O12: 4 | P12: 3 | Q12: =ROUND((G12*0.18)+(H12*0.15)+(I12*0.12)+(J12*0.08)+(K12*0.13)+(L12*0.1)+(M12*0.12)+(N12*0.12)-(O12*0.07)+(P12*0.1),2) -> 2.7 | R12: =ROUND((I12*0.16)+(J12*0.2)+(K12*0.12)+(L12*0.1)+((6-M12)*0.08)+((6-N12)*0.08)+(O12*0.06)+(P12*0.14)+(G12*0.06),2) -> 3.22 | S12: =IF(A12="","",IF(AND(G12>=4,H12>=4,K12>=3,P12>=4),"Первый релиз",IF(Q12>=3.7,"Первый релиз",IF(R12>=3.6,"Следующий релиз","Не включать / проверить")))) -> Не включать / проверить | T12: =IF(A12="","",IF(S12="Первый релиз","Включить в минимальный рыночный выпуск",IF(S12="Следующий релиз","Запланировать после проверки первого релиза","Оставить как гипотезу / проверить позже"))) -> Оставить как гипотезу / проверить позже | U12: Данных о реализации у конкурентов нет (гипотеза)
A13: U-012 | B13: Экран приложения | C13: Профиль и подписка | D13: Платящий клиент | E13: SC-008 | F13: Потоки доходов | G13: 3 | H13: 4 | I13: 4 | J13: 2 | K13: 3 | L13: 4 | M13: 4 | N13: 4 | O13: 2 | P13: 3 | Q13: =ROUND((G13*0.18)+(H13*0.15)+(I13*0.12)+(J13*0.08)+(K13*0.13)+(L13*0.1)+(M13*0.12)+(N13*0.12)-(O13*0.07)+(P13*0.1),2) -> 3.69 | R13: =ROUND((I13*0.16)+(J13*0.2)+(K13*0.12)+(L13*0.1)+((6-M13)*0.08)+((6-N13)*0.08)+(O13*0.06)+(P13*0.14)+(G13*0.06),2) -> 2.84 | S13: =IF(A13="","",IF(AND(G13>=4,H13>=4,K13>=3,P13>=4),"Первый релиз",IF(Q13>=3.7,"Первый релиз",IF(R13>=3.6,"Следующий релиз","Не включать / проверить")))) -> Не включать / проверить | T13: =IF(A13="","",IF(S13="Первый релиз","Включить в минимальный рыночный выпуск",IF(S13="Следующий релиз","Запланировать после проверки первого релиза","Оставить как гипотезу / проверить позже"))) -> Оставить как гипотезу / проверить позже | U13: Продление подписки
... A21: U-020 | B21: Функция | C21: Командный тариф | D21: Администратор клиента | E21: SC-011 | F21: Потоки доходов | G21: 3 | H21: 4 | I21: 3 | J21: 3 | K21: 2 | L21: 3 | M21: 2 | N21: 2 | O21: 3 | P21: 2 | Q21: =ROUND((G21*0.18)+(H21*0.15)+(I21*0.12)+(J21*0.08)+(K21*0.13)+(L21*0.1)+(M21*0.12)+(N21*0.12)-(O21*0.07)+(P21*0.1),2) -> 2.77 | R21: =ROUND((I21*0.16)+(J21*0.2)+(K21*0.12)+(L21*0.1)+((6-M21)*0.08)+((6-N21)*0.08)+(O21*0.06)+(P21*0.14)+(G21*0.06),2) -> 2.9 | S21: =IF(A21="","",IF(AND(G21>=4,H21>=4,K21>=3,P21>=4),"Первый релиз",IF(Q21>=3.7,"Первый релиз",IF(R21>=3.6,"Следующий релиз","Не включать / проверить")))) -> Не включать / проверить | T21: =IF(A21="","",IF(S21="Первый релиз","Включить в минимальный рыночный выпуск",IF(S21="Следующий релиз","Запланировать после проверки первого релиза","Оставить как гипотезу / проверить позже"))) -> Оставить как гипотезу / проверить позже | U21: Enterprise у 4 из 8 конкурентов
Q22: =ROUND((G22*0.18)+(H22*0.15)+(I22*0.12)+(J22*0.08)+(K22*0.13)+(L22*0.1)+(M22*0.12)+(N22*0.12)-(O22*0.07)+(P22*0.1),2) -> 0 | R22: =ROUND((I22*0.16)+(J22*0.2)+(K22*0.12)+(L22*0.1)+((6-M22)*0.08)+((6-N22)*0.08)+(O22*0.06)+(P22*0.14)+(G22*0.06),2) -> 0.96 | S22: =IF(A22="","",IF(AND(G22>=4,H22>=4,K22>=3,P22>=4),"Первый релиз",IF(Q22>=3.7,"Первый релиз",IF(R22>=3.6,"Следующий релиз","Не включать / проверить")))) | T22: =IF(A22="","",IF(S22="Первый релиз","Включить в минимальный рыночный выпуск",IF(S22="Следующий релиз","Запланировать после проверки первого релиза","Оставить как гипотезу / проверить позже")))
Q23: =ROUND((G23*0.18)+(H23*0.15)+(I23*0.12)+(J23*0.08)+(K23*0.13)+(L23*0.1)+(M23*0.12)+(N23*0.12)-(O23*0.07)+(P23*0.1),2) -> 0 | R23: =ROUND((I23*0.16)+(J23*0.2)+(K23*0.12)+(L23*0.1)+((6-M23)*0.08)+((6-N23)*0.08)+(O23*0.06)+(P23*0.14)+(G23*0.06),2) -> 0.96 | S23: =IF(A23="","",IF(AND(G23>=4,H23>=4,K23>=3,P23>=4),"Первый релиз",IF(Q23>=3.7,"Первый релиз",IF(R23>=3.6,"Следующий релиз","Не включать / проверить")))) | T23: =IF(A23="","",IF(S23="Первый релиз","Включить в минимальный рыночный выпуск",IF(S23="Следующий релиз","Запланировать после проверки первого релиза","Оставить как гипотезу / проверить позже")))
Q24: =ROUND((G24*0.18)+(H24*0.15)+(I24*0.12)+(J24*0.08)+(K24*0.13)+(L24*0.1)+(M24*0.12)+(N24*0.12)-(O24*0.07)+(P24*0.1),2) -> 0 | R24: =ROUND((I24*0.16)+(J24*0.2)+(K24*0.12)+(L24*0.1)+((6-M24)*0.08)+((6-N24)*0.08)+(O24*0.06)+(P24*0.14)+(G24*0.06),2) -> 0.96 | S24: =IF(A24="","",IF(AND(G24>=4,H24>=4,K24>=3,P24>=4),"Первый релиз",IF(Q24>=3.7,"Первый релиз",IF(R24>=3.6,"Следующий релиз","Не включать / проверить")))) | T24: =IF(A24="","",IF(S24="Первый релиз","Включить в минимальный рыночный выпуск",IF(S24="Следующий релиз","Запланировать после проверки первого релиза","Оставить как гипотезу / проверить позже")))
Q25: =ROUND((G25*0.18)+(H25*0.15)+(I25*0.12)+(J25*0.08)+(K25*0.13)+(L25*0.1)+(M25*0.12)+(N25*0.12)-(O25*0.07)+(P25*0.1),2) -> 0 | R25: =ROUND((I25*0.16)+(J25*0.2)+(K25*0.12)+(L25*0.1)+((6-M25)*0.08)+((6-N25)*0.08)+(O25*0.06)+(P25*0.14)+(G25*0.06),2) -> 0.96 | S25: =IF(A25="","",IF(AND(G25>=4,H25>=4,K25>=3,P25>=4),"Первый релиз",IF(Q25>=3.7,"Первый релиз",IF(R25>=3.6,"Следующий релиз","Не включать / проверить")))) | T25: =IF(A25="","",IF(S25="Первый релиз","Включить в минимальный рыночный выпуск",IF(S25="Следующий релиз","Запланировать после проверки первого релиза","Оставить как гипотезу / проверить позже")))
Q26: =ROUND((G26*0.18)+(H26*0.15)+(I26*0.12)+(J26*0.08)+(K26*0.13)+(L26*0.1)+(M26*0.12)+(N26*0.12)-(O26*0.07)+(P26*0.1),2) -> 0 | R26: =ROUND((I26*0.16)+(J26*0.2)+(K26*0.12)+(L26*0.1)+((6-M26)*0.08)+((6-N26)*0.08)+(O26*0.06)+(P26*0.14)+(G26*0.06),2) -> 0.96 | S26: =IF(A26="","",IF(AND(G26>=4,H26>=4,K26>=3,P26>=4),"Первый релиз",IF(Q26>=3.7,"Первый релиз",IF(R26>=3.6,"Следующий релиз","Не включать / проверить")))) | T26: =IF(A26="","",IF(S26="Первый релиз","Включить в минимальный рыночный выпуск",IF(S26="Следующий релиз","Запланировать после проверки первого релиза","Оставить как гипотезу / проверить позже")))
Q27: =ROUND((G27*0.18)+(H27*0.15)+(I27*0.12)+(J27*0.08)+(K27*0.13)+(L27*0.1)+(M27*0.12)+(N27*0.12)-(O27*0.07)+(P27*0.1),2) -> 0 | R27: =ROUND((I27*0.16)+(J27*0.2)+(K27*0.12)+(L27*0.1)+((6-M27)*0.08)+((6-N27)*0.08)+(O27*0.06)+(P27*0.14)+(G27*0.06),2) -> 0.96 | S27: =IF(A27="","",IF(AND(G27>=4,H27>=4,K27>=3,P27>=4),"Первый релиз",IF(Q27>=3.7,"Первый релиз",IF(R27>=3.6,"Следующий релиз","Не включать / проверить")))) | T27: =IF(A27="","",IF(S27="Первый релиз","Включить в минимальный рыночный выпуск",IF(S27="Следующий релиз","Запланировать после проверки первого релиза","Оставить как гипотезу / проверить позже")))
Q28: =ROUND((G28*0.18)+(H28*0.15)+(I28*0.12)+(J28*0.08)+(K28*0.13)+(L28*0.1)+(M28*0.12)+(N28*0.12)-(O28*0.07)+(P28*0.1),2) -> 0 | R28: =ROUND((I28*0.16)+(J28*0.2)+(K28*0.12)+(L28*0.1)+((6-M28)*0.08)+((6-N28)*0.08)+(O28*0.06)+(P28*0.14)+(G28*0.06),2) -> 0.96 | S28: =IF(A28="","",IF(AND(G28>=4,H28>=4,K28>=3,P28>=4),"Первый релиз",IF(Q28>=3.7,"Первый релиз",IF(R28>=3.6,"Следующий релиз","Не включать / проверить")))) | T28: =IF(A28="","",IF(S28="Первый релиз","Включить в минимальный рыночный выпуск",IF(S28="Следующий релиз","Запланировать после проверки первого релиза","Оставить как гипотезу / проверить позже")))
Q29: =ROUND((G29*0.18)+(H29*0.15)+(I29*0.12)+(J29*0.08)+(K29*0.13)+(L29*0.1)+(M29*0.12)+(N29*0.12)-(O29*0.07)+(P29*0.1),2) -> 0 | R29: =ROUND((I29*0.16)+(J29*0.2)+(K29*0.12)+(L29*0.1)+((6-M29)*0.08)+((6-N29)*0.08)+(O29*0.06)+(P29*0.14)+(G29*0.06),2) -> 0.96 | S29: =IF(A29="","",IF(AND(G29>=4,H29>=4,K29>=3,P29>=4),"Первый релиз",IF(Q29>=3.7,"Первый релиз",IF(R29>=3.6,"Следующий релиз","Не включать / проверить")))) | T29: =IF(A29="","",IF(S29="Первый релиз","Включить в минимальный рыночный выпуск",IF(S29="Следующий релиз","Запланировать после проверки первого релиза","Оставить как гипотезу / проверить позже")))
Q30: =ROUND((G30*0.18)+(H30*0.15)+(I30*0.12)+(J30*0.08)+(K30*0.13)+(L30*0.1)+(M30*0.12)+(N30*0.12)-(O30*0.07)+(P30*0.1),2) -> 0 | R30: =ROUND((I30*0.16)+(J30*0.2)+(K30*0.12)+(L30*0.1)+((6-M30)*0.08)+((6-N30)*0.08)+(O30*0.06)+(P30*0.14)+(G30*0.06),2) -> 0.96 | S30: =IF(A30="","",IF(AND(G30>=4,H30>=4,K30>=3,P30>=4),"Первый релиз",IF(Q30>=3.7,"Первый релиз",IF(R30>=3.6,"Следующий релиз","Не включать / проверить")))) | T30: =IF(A30="","",IF(S30="Первый релиз","Включить в минимальный рыночный выпуск",IF(S30="Следующий релиз","Запланировать после проверки первого релиза","Оставить как гипотезу / проверить позже")))
Q31: =ROUND((G31*0.18)+(H31*0.15)+(I31*0.12)+(J31*0.08)+(K31*0.13)+(L31*0.1)+(M31*0.12)+(N31*0.12)-(O31*0.07)+(P31*0.1),2) -> 0 | R31: =ROUND((I31*0.16)+(J31*0.2)+(K31*0.12)+(L31*0.1)+((6-M31)*0.08)+((6-N31)*0.08)+(O31*0.06)+(P31*0.14)+(G31*0.06),2) -> 0.96 | S31: =IF(A31="","",IF(AND(G31>=4,H31>=4,K31>=3,P31>=4),"Первый релиз",IF(Q31>=3.7,"Первый релиз",IF(R31>=3.6,"Следующий релиз","Не включать / проверить")))) | T31: =IF(A31="","",IF(S31="Первый релиз","Включить в минимальный рыночный выпуск",IF(S31="Следующий релиз","Запланировать после проверки первого релиза","Оставить как гипотезу / проверить позже")))
Q32: =ROUND((G32*0.18)+(H32*0.15)+(I32*0.12)+(J32*0.08)+(K32*0.13)+(L32*0.1)+(M32*0.12)+(N32*0.12)-(O32*0.07)+(P32*0.1),2) -> 0 | R32: =ROUND((I32*0.16)+(J32*0.2)+(K32*0.12)+(L32*0.1)+((6-M32)*0.08)+((6-N32)*0.08)+(O32*0.06)+(P32*0.14)+(G32*0.06),2) -> 0.96 | S32: =IF(A32="","",IF(AND(G32>=4,H32>=4,K32>=3,P32>=4),"Первый релиз",IF(Q32>=3.7,"Первый релиз",IF(R32>=3.6,"Следующий релиз","Не включать / проверить")))) | T32: =IF(A32="","",IF(S32="Первый релиз","Включить в минимальный рыночный выпуск",IF(S32="Следующий релиз","Запланировать после проверки первого релиза","Оставить как гипотезу / проверить позже")))
Q33: =ROUND((G33*0.18)+(H33*0.15)+(I33*0.12)+(J33*0.08)+(K33*0.13)+(L33*0.1)+(M33*0.12)+(N33*0.12)-(O33*0.07)+(P33*0.1),2) -> 0 | R33: =ROUND((I33*0.16)+(J33*0.2)+(K33*0.12)+(L33*0.1)+((6-M33)*0.08)+((6-N33)*0.08)+(O33*0.06)+(P33*0.14)+(G33*0.06),2) -> 0.96 | S33: =IF(A33="","",IF(AND(G33>=4,H33>=4,K33>=3,P33>=4),"Первый релиз",IF(Q33>=3.7,"Первый релиз",IF(R33>=3.6,"Следующий релиз","Не включать / проверить")))) | T33: =IF(A33="","",IF(S33="Первый релиз","Включить в минимальный рыночный выпуск",IF(S33="Следующий релиз","Запланировать после проверки первого релиза","Оставить как гипотезу / проверить позже")))
... Q101: =ROUND((G101*0.18)+(H101*0.15)+(I101*0.12)+(J101*0.08)+(K101*0.13)+(L101*0.1)+(M101*0.12)+(N101*0.12)-(O101*0.07)+(P101*0.1),2) -> 0 | R101: =ROUND((I101*0.16)+(J101*0.2)+(K101*0.12)+(L101*0.1)+((6-M101)*0.08)+((6-N101)*0.08)+(O101*0.06)+(P101*0.14)+(G101*0.06),2) -> 0.96 | S101: =IF(A101="","",IF(AND(G101>=4,H101>=4,K101>=3,P101>=4),"Первый релиз",IF(Q101>=3.7,"Первый релиз",IF(R101>=3.6,"Следующий релиз","Не включать / проверить")))) | T101: =IF(A101="","",IF(S101="Первый релиз","Включить в минимальный рыночный выпуск",IF(S101="Следующий релиз","Запланировать после проверки первого релиза","Оставить как гипотезу / проверить позже")))

Sheet Оценка_релизов
A1: Сводная оценка состава релизов
A3: Релиз | B3: Количество единиц | C3: Средний балл первого релиза | D3: Средняя доказательность | E3: Средняя связь с ценностью | F3: Средняя критичность дохода | G3: Среднее удержание | H3: Средний рост | I3: Средний технический риск | J3: Интерпретация
A4: Первый релиз | B4: =COUNTIF(Реестр_единиц!$S$2:$S$101,A4) -> 10 | C4: =IFERROR(AVERAGEIF(Реестр_единиц!$S$2:$S$101,A4,Реестр_единиц!$Q$2:$Q$101),0) -> 4.303 | D4: =IFERROR(AVERAGEIF(Реестр_единиц!$S$2:$S$101,A4,Реестр_единиц!$K$2:$K$101),0) -> 4 | E4: =IFERROR(AVERAGEIF(Реестр_единиц!$S$2:$S$101,A4,Реестр_единиц!$G$2:$G$101),0) -> 4.4 | F4: =IFERROR(AVERAGEIF(Реестр_единиц!$S$2:$S$101,A4,Реестр_единиц!$H$2:$H$101),0) -> 3.8 | G4: =IFERROR(AVERAGEIF(Реестр_единиц!$S$2:$S$101,A4,Реестр_единиц!$I$2:$I$101),0) -> 3.2 | H4: =IFERROR(AVERAGEIF(Реестр_единиц!$S$2:$S$101,A4,Реестр_единиц!$J$2:$J$101),0) -> 3.2 | I4: =IFERROR(AVERAGEIF(Реестр_единиц!$S$2:$S$101,A4,Реестр_единиц!$O$2:$O$101),0) -> 1.9 | J4: =IF(B4=0,"Нет выбранных единиц",IF(AND(E4>=4,D4>=3.5),"Состав достаточно обоснован","Требуется дополнительная проверка")) -> Состав достаточно обоснован
A5: Следующий релиз | B5: =COUNTIF(Реестр_единиц!$S$2:$S$101,A5) -> 1 | C5: =IFERROR(AVERAGEIF(Реестр_единиц!$S$2:$S$101,A5,Реестр_единиц!$Q$2:$Q$101),0) -> 2.83 | D5: =IFERROR(AVERAGEIF(Реестр_единиц!$S$2:$S$101,A5,Реестр_единиц!$K$2:$K$101),0) -> 3 | E5: =IFERROR(AVERAGEIF(Реестр_единиц!$S$2:$S$101,A5,Реестр_единиц!$G$2:$G$101),0) -> 4 | F5: =IFERROR(AVERAGEIF(Реестр_единиц!$S$2:$S$101,A5,Реестр_единиц!$H$2:$H$101),0) -> 3 | G5: =IFERROR(AVERAGEIF(Реестр_единиц!$S$2:$S$101,A5,Реестр_единиц!$I$2:$I$101),0) -> 4 | H5: =IFERROR(AVERAGEIF(Реестр_единиц!$S$2:$S$101,A5,Реестр_единиц!$J$2:$J$101),0) -> 5 | I5: =IFERROR(AVERAGEIF(Реестр_единиц!$S$2:$S$101,A5,Реестр_единиц!$O$2:$O$101),0) -> 5 | J5: =IF(B5=0,"Нет выбранных единиц",IF(AND(E5>=4,D5>=3.5),"Состав достаточно обоснован","Требуется дополнительная проверка")) -> Требуется дополнительная проверка
A6: Не включать / проверить | B6: =COUNTIF(Реестр_единиц!$S$2:$S$101,A6) -> 9 | C6: =IFERROR(AVERAGEIF(Реестр_единиц!$S$2:$S$101,A6,Реестр_единиц!$Q$2:$Q$101),0) -> 3.03 | D6: =IFERROR(AVERAGEIF(Реестр_единиц!$S$2:$S$101,A6,Реестр_единиц!$K$2:$K$101),0) -> 2.6666667 | E6: =IFERROR(AVERAGEIF(Реестр_единиц!$S$2:$S$101,A6,Реестр_единиц!$G$2:$G$101),0) -> 3.2222222 | F6: =IFERROR(AVERAGEIF(Реестр_единиц!$S$2:$S$101,A6,Реестр_единиц!$H$2:$H$101),0) -> 2.6666667 | G6: =IFERROR(AVERAGEIF(Реестр_единиц!$S$2:$S$101,A6,Реестр_единиц!$I$2:$I$101),0) -> 3.5555556 | H6: =IFERROR(AVERAGEIF(Реестр_единиц!$S$2:$S$101,A6,Реестр_единиц!$J$2:$J$101),0) -> 3.2222222 | I6: =IFERROR(AVERAGEIF(Реестр_единиц!$S$2:$S$101,A6,Реестр_единиц!$O$2:$O$101),0) -> 3 | J6: =IF(B6=0,"Нет выбранных единиц",IF(AND(E6>=4,D6>=3.5),"Состав достаточно обоснован","Требуется дополнительная проверка")) -> Требуется дополнительная проверка

Sheet Первый_релиз
A1: План первого релиза: быстрый и экономный выход на рынок без разрушения ценности
A3: ID | B3: Единица первого релиза | C3: Зачем нужна в первом релизе | D3: Проверяемая гипотеза | E3: Минимальная реализация | F3: Критерий готовности | G3: Метрика после запуска | H3: Ответственный
A4: FR-001 | B4: Главная страница | C4: Объясняет обещание и ведет к регистрации; поиск - основной канал (ЛР4) | D4: Пользователь использует единицу и достигает цели сценария SC-001 | E4: Минимальная реализация без автоматизации и персонализации | F4: Единица работает в основном сценарии SC-001 и показывает состояния ошибки | G4: Доля завершений сценария SC-001 | H4: Руководитель проекта
A5: FR-002 | B5: Возможности и нотации | C5: Показывает конкурентное отличие: нотации IDEF0, DFD, сети Петри (ЛР5) | D5: Пользователь использует единицу и достигает цели сценария SC-002 | E5: Минимальная реализация без автоматизации и персонализации | F5: Единица работает в основном сценарии SC-002 и показывает состояния ошибки | G5: Доля завершений сценария SC-002 | H5: Руководитель проекта
A6: FR-003 | B6: Тарифы Free и Pro | C6: Открытая страница тарифов у 5 из 8 конкурентов (ЛР5) | D6: Пользователь использует единицу и достигает цели сценария SC-002 | E6: Минимальная реализация без автоматизации и персонализации | F6: Единица работает в основном сценарии SC-002 и показывает состояния ошибки | G6: Доля завершений сценария SC-002 | H6: Руководитель проекта
A7: FR-004 | B7: Регистрация и вход | C7: Вход нужен для сохранения диаграмм и подписки | D7: Пользователь использует единицу и достигает цели сценария SC-003 | E7: Минимальная реализация без автоматизации и персонализации | F7: Единица работает в основном сценарии SC-003 и показывает состояния ошибки | G7: Доля завершений сценария SC-003 | H7: Руководитель проекта
A8: FR-005 | B8: Оплата Pro | C8: Монетизация - граница экономии (6.5, п. 7.5) | D8: Пользователь использует единицу и достигает цели сценария SC-008 | E8: Минимальная реализация без автоматизации и персонализации | F8: Единица работает в основном сценарии SC-008 и показывает состояния ошибки | G8: Доля завершений сценария SC-008 | H8: Руководитель проекта
A9: FR-006 | B9: Выбор нотации и шаблона | C9: Вход в ядро ценности; показывает набор нотаций | D9: Пользователь использует единицу и достигает цели сценария SC-005 | E9: Минимальная реализация без автоматизации и персонализации | F9: Единица работает в основном сценарии SC-005 и показывает состояния ошибки | G9: Доля завершений сценария SC-005 | H9: Руководитель проекта
A10: FR-007 | B10: Рабочая область редактора | C10: Ядро цифрового товара | D10: Пользователь использует единицу и достигает цели сценария SC-004 | E10: Минимальная реализация без автоматизации и персонализации | F10: Единица работает в основном сценарии SC-004 и показывает состояния ошибки | G10: Доля завершений сценария SC-004 | H10: Руководитель проекта
A11: FR-008 | B11: Результат и экспорт | C11: Экспорт у 8 из 8 конкурентов; PNG важен 27 из 27 (опрос) | D11: Пользователь использует единицу и достигает цели сценария SC-006 | E11: Минимальная реализация без автоматизации и персонализации | F11: Единица работает в основном сценарии SC-006 и показывает состояния ошибки | G11: Доля завершений сценария SC-006 | H11: Руководитель проекта
A12: FR-009 | B12: Аналитика событий и обратная связь | C12: События и обратная связь включаются обязательно (6.5, п. 7.6) | D12: Пользователь использует единицу и достигает цели сценария SC-001 | E12: Минимальная реализация без автоматизации и персонализации | F12: Единица работает в основном сценарии SC-001 и показывает состояния ошибки | G12: Доля завершений сценария SC-001 | H12: Руководитель проекта
A13: FR-010 | B13: Правовые тексты и конфиденциальность | C13: Раздел о безопасности у 6 из 8 конкурентов; правовые требования | D13: Пользователь использует единицу и достигает цели сценария SC-003 | E13: Минимальная реализация без автоматизации и персонализации | F13: Единица работает в основном сценарии SC-003 и показывает состояния ошибки | G13: Доля завершений сценария SC-003 | H13: Руководитель проекта

Sheet Следующие_релизы
A1: План последующих релизов: развитие удержания, роста и операционной эффективности
A3: ID | B3: Релиз | C3: Единица развития | D3: Основание переноса | E3: Условие включения | F3: Ожидаемый эффект | G3: Связанная метрика | H3: Зависимости | I3: Комментарий
A4: NR-001 | B4: Релиз 2 | C4: Документация и примеры | D4: Не входит в минимальную цепочку первого релиза; балл следующих релизов 3,32 | E4: Есть данные поведения релиза 1 | F4: Рост удержания или дохода | G4: Метрика единицы U-004 | H4: Стабильное ядро релиза 1 | I4: Документация у 6 из 8 конкурентов (ЛР5)
A5: NR-002 | B5: Релиз 2 | C5: Мои диаграммы | D5: Не входит в минимальную цепочку первого релиза; балл следующих релизов 3,28 | E5: Есть данные поведения релиза 1 | F5: Рост удержания или дохода | G5: Метрика единицы U-010 | H5: Стабильное ядро релиза 1 | I5: Возврат пользователя; история версий у 5 из 8
A6: NR-003 | B6: Релиз 2 | C6: Подсказка об ошибке синтаксиса | D6: Не входит в минимальную цепочку первого релиза; балл следующих релизов 3,22 | E6: Есть данные поведения релиза 1 | F6: Рост удержания или дохода | G6: Метрика единицы U-011 | H6: Стабильное ядро релиза 1 | I6: Данных о реализации у конкурентов нет (гипотеза)
A7: NR-004 | B7: Релиз 2 | C7: Профиль и подписка | D7: Не входит в минимальную цепочку первого релиза; балл следующих релизов 2,84 | E7: Есть данные поведения релиза 1 | F7: Рост удержания или дохода | G7: Метрика единицы U-012 | H7: Стабильное ядро релиза 1 | I7: Продление подписки
A8: NR-005 | B8: Релиз 2 | C8: ИИ-ассистент (заглушка в MVP) | D8: Не входит в минимальную цепочку первого релиза; балл следующих релизов 3,54 | E8: Есть данные поведения релиза 1 | F8: Рост удержания или дохода | G8: Метрика единицы U-013 | H8: Стабильное ядро релиза 1 | I8: ИИ у 5 из 8 конкурентов; лимиты ИИ - тарифный ограничитель
A9: NR-006 | B9: Релиз 4 | C9: Форма обращения в поддержку | D9: Не входит в минимальную цепочку первого релиза; балл следующих релизов 3,12 | E9: Есть данные поведения релиза 1 | F9: Рост удержания или дохода | G9: Метрика единицы U-016 | H9: Стабильное ядро релиза 1 | I9: Базовая поддержка в первом релизе
A10: NR-007 | B10: Релиз 2 | C10: Совместное редактирование | D10: Не входит в минимальную цепочку первого релиза; балл следующих релизов 3,92 | E10: Есть данные поведения релиза 1 | F10: Рост удержания или дохода | G10: Метрика единицы U-017 | H10: Стабильное ядро релиза 1 | I10: Коллаборация у 6 из 8; важна 26 из 27 (опрос)
A11: NR-008 | B11: Релиз 3 | C11: Реферальные механики | D11: Не входит в минимальную цепочку первого релиза; балл следующих релизов 2,62 | E11: Есть данные поведения релиза 1 | F11: Рост удержания или дохода | G11: Метрика единицы U-018 | H11: Стабильное ядро релиза 1 | I11: Рост аудитории переносится
A12: NR-009 | B12: Релиз 4 | C12: API и интеграции | D12: Не входит в минимальную цепочку первого релиза; балл следующих релизов 3,38 | E12: Есть данные поведения релиза 1 | F12: Рост удержания или дохода | G12: Метрика единицы U-019 | H12: Стабильное ядро релиза 1 | I12: Интеграции у 8 из 8, API у 5 из 8 (ЛР5)
A13: NR-010 | B13: Релиз 4 | C13: Командный тариф | D13: Не входит в минимальную цепочку первого релиза; балл следующих релизов 2,9 | E13: Есть данные поведения релиза 1 | F13: Рост удержания или дохода | G13: Метрика единицы U-020 | H13: Стабильное ядро релиза 1 | I13: Enterprise у 4 из 8 конкурентов

Sheet Дорожная_карта
A1: Дорожная карта релизов
A3: Релиз | B3: Цель релиза | C3: Состав | D3: Ключевая гипотеза | E3: Что измеряем | F3: Критерий перехода к следующему релизу | G3: Ограничение бюджета / срока | H3: Риски | I3: Решение по запуску | J3: Дата начала | K3: Дата окончания
A4: Релиз 0 | B4: Прототип, тексты, правовые документы, события аналитики | C4: Прототип страниц и экранов 6.4, правовые тексты, события аналитики, ручные процедуры | D4: Состав первого релиза понятен пользователям | E4: Результаты проверки прототипа | F4: Прототип подтвержден | G4: не собрано: бюджет | H4: Расхождение прототипа и ожиданий | I4: До релиза 1 | J4: не собрано: даты | K4: не собрано: даты
A5: Релиз 1 | B5: Проверить ЦП и готовность платить | C5: Главная, возможности, тарифы, регистрация, выбор нотации, редактор с нотациями волны 1 (UML, ERD, IDEF0, IDEF1X, IDEF3, DFD), экспорт, оплата или заявка Pro, правовые тексты, аналитика, поддержка | D5: Пользователь строит диаграмму и понимает цену Pro | E5: Доля первой диаграммы, конверсия в Pro, повторные заходы | F5: Есть первая диаграмма и признаки спроса на Pro | G5: не собрано: срок и бюджет | H5: Сложность разбора нотаций; нет платежного провайдера | I5: Запустить после контрольного листа первого релиза | J5: не собрано: даты | K5: не собрано: даты
A6: Релиз 2 | B6: Удержание и качество | C6: Расширенное хранение и история версий, подсказки об ошибках, ИИ-ассистент с квотами, документация, нотации BPMN 2.0 (волна 2) | D6: Пользователи возвращаются | E6: Удержание на 7 и 30 дней, число ИИ-запросов | F6: Удержание не ниже целевого (не собрано: порог) | G6: Расходы на ИИ в пределах тарифа | H6: Рост расходов на ИИ | I6: После данных релиза 1 | J6: не собрано: даты | K6: не собрано: даты
A7: Релиз 3 | B7: Рост аудитории | C7: Сети Петри (волна 3), реферальные механики, публичные страницы нотаций, контент, вузы | D7: Аудитория растет без платной рекламы | E7: Новые пользователи по каналам | F7: Подтверждены ценность и удержание | G7: Маркетинговый бюджет | H7: Низкая конверсия страниц | I7: После подтверждения удержания | J7: не собрано: даты | K7: не собрано: даты
A8: Релиз 4 | B8: Расширение продукта | C8: Совместное редактирование, командный тариф, API и интеграции | D8: Командам нужна общая работа | E8: Средний доход, число команд | F8: Понята экономика и спрос команд | G8: Серверная синхронизация | H8: Сложность синхронизации | I8: После расчета экономики | J8: не собрано: даты | K8: не собрано: даты
A9: Релиз 5 | B9: Масштабирование | C9: Автоматизация поддержки, администрирование, производительность, безопасность | D9: Нагрузка стабильно растет | E9: Нагрузка, стоимость поддержки | F9: Повторяемая нагрузка | G9: Инфраструктура | H9: Рост затрат | I9: При росте нагрузки | J9: не собрано: даты | K9: не собрано: даты

Sheet Проверка_ценности
A1: Контрольный лист: первый релиз сохраняет ценностное предложение, монетизацию, удержание и рост
A3: Блок проверки | B3: Контрольный вопрос | C3: Оценка 1–5 | D3: Доказательство | E3: Риск при низкой оценке | F3: Решение | G3: Что добавить / изменить | H3: Ответственный | I3: Статус
A4: Ценность | B4: Может ли пользователь получить диаграмму в выбранной нотации из текста в первом релизе? | C4: 4 | D4: Ядро: U-007, U-008, U-009 | E4: Без ядра нечего проверять | F4: Оставить в первом релизе | G4: – | H4: Руководитель проекта | I4: Готово
A5: Проблема | B5: Закрывает ли первый релиз проблему P-002 (единый набор нотаций)? | C5: 3 | D5: Нотации первого релиза - волна 1 документации NotaCode (UML, ERD, IDEF0, IDEF1X, IDEF3, DFD); BPMN 2.0 - волна 2, сети Петри - волна 3 | E5: Ценностное отличие проявится позже | F5: Показать нотации на странице возможностей | G5: – | H5: Руководитель проекта | I5: В работе
A6: Монетизация | B6: Есть ли в первом релизе способ проверить готовность платить? | C6: 4 | D6: Тарифы U-003 и оплата U-006 (вариант Б) или заявка (вариант А) | E6: Нельзя проверить цену Pro | F6: Включить оплату или заявку | G6: – | H6: Руководитель проекта | I6: Готово
A7: Удержание | B7: Есть ли причина вернуться? | C7: 3 | D7: Мои диаграммы U-010 - во втором релизе; в первом - сохранение через вход | E7: Пользователь не вернется | F7: Минимальное сохранение в первом релизе | G7: – | H7: Руководитель проекта | I7: В работе
A8: Рост | B8: Может ли аудитория расти без платной рекламы? | C8: 3 | D8: Поисковый трафик 47-59 % у текстовых инструментов (ЛР4) | E8: Мало поискового трафика | F8: Страницы нотаций для поиска | G8: – | H8: Руководитель проекта | I8: В работе
A9: Экономичность | B9: Можно ли выпустить первый релиз за короткий срок и малый бюджет? | C9: 3 | D9: Исключены ИИ, коллаборация, API, реферальные механики | E9: Бюджет и сроки не определены | F9: не собрано: срок и бюджет | G9: – | H9: Руководитель проекта | I9: В работе

Sheet Риски_зависимости
A1: Риски, зависимости и условия переноса функций между релизами
A3: ID | B3: Единица / решение | C3: Риск | D3: Тип риска | E3: Вероятность 1–5 | F3: Влияние 1–5 | G3: Индекс риска | H3: Митигирующее действие | I3: Связанный релиз | J3: Ответственный
A4: R-001 | B4: U-008 | C4: Сложность разбора нотаций задерживает ядро | D4: Технический | E4: 4 | F4: 5 | G4: =IF(A4="","",E4*F4) -> 20 | H4: Начать с UML и ERD, остальные нотации - итерациями; ограничить объем первой версии | I4: Первый релиз | J4: Руководитель проекта
A5: R-002 | B5: U-006 | C5: Отсутствие платежного провайдера для Беларуси | D5: Монетизация | E5: 4 | F5: 4 | G5: =IF(A5="","",E5*F5) -> 16 | H5: Вариант А: заявка на Pro без онлайн-оплаты; выбор провайдера до релиза | I5: Первый релиз | J5: Руководитель проекта
A6: R-003 | B6: U-014 | C6: Без аналитики нельзя принять решение о релизе 2 | D6: Данные | E6: 3 | F6: 5 | G6: =IF(A6="","",E6*F6) -> 15 | H6: Оставить минимальный набор событий в релизе 1 | I6: Первый релиз | J6: Руководитель проекта
A7: R-004 | B7: U-007 | C7: BPMN 2.0 (волна 2) и сети Петри (волна 3) не попадут в первый релиз, набор нотаций будет неполным | D7: Ценность | E7: 3 | F7: 4 | G7: =IF(A7="","",E7*F7) -> 12 | H7: Показать полный перечень нотаций на странице возможностей с пометкой о волнах | I7: Релиз 2 | J7: Руководитель проекта
A8: R-005 | B8: U-013 | C8: Расходы на ИИ-вызовы растут быстрее выручки | D8: Экономика | E8: 4 | F8: 4 | G8: =IF(A8="","",E8*F8) -> 16 | H8: Лимиты ИИ по тарифам; отложить до релиза 2 | I8: Релиз 2 | J8: Руководитель проекта
A9: R-006 | B9: U-004 | C9: Мало документации - рост обращений в поддержку | D9: Поддержка | E9: 3 | F9: 3 | G9: =IF(A9="","",E9*F9) -> 9 | H9: Минимальные примеры в первом релизе, база знаний - в релизе 2 | I9: Релиз 2 | J9: Руководитель проекта
A10: R-007 | B10: U-017 | C10: Совместное редактирование требует серверной синхронизации | D10: Технический | E10: 5 | F10: 4 | G10: =IF(A10="","",E10*F10) -> 20 | H10: Отложить до подтвержденного спроса | I10: Релиз 4 | J10: Руководитель проекта
A11: R-008 | B11: U-015 | C11: Правовые тексты не готовы к запуску | D11: Правовой | E11: 3 | F11: 5 | G11: =IF(A11="","",E11*F11) -> 15 | H11: Подготовить политику конфиденциальности и условия до релиза 1 | I11: Первый релиз | J11: Руководитель проекта

Sheet Дашборд
A1: Дашборд готовности релизного плана
A3: Показатель | B3: Значение | C3: Интерпретация | E3: Релиз | F3: Количество
A4: Всего единиц разработки | B4: =COUNTA(Реестр_единиц!$A$2:$A$101) -> 20 | C4: Количество страниц, экранов, функций, интеграций и контентных блоков в реестре | E4: Первый релиз | F4: =COUNTIF(Реестр_единиц!$S$2:$S$101,E4) -> 10
A5: Единиц в первом релизе | B5: =COUNTIF(Реестр_единиц!$S$2:$S$101,"Первый релиз") -> 10 | C5: Объем минимального рыночного выпуска | E5: Следующий релиз | F5: =COUNTIF(Реестр_единиц!$S$2:$S$101,E5) -> 1
A6: Средний балл первого релиза | B6: =IFERROR(AVERAGEIF(Реестр_единиц!$S$2:$S$101,"Первый релиз",Реестр_единиц!$Q$2:$Q$101),0) -> 4.303 | C6: Насколько первый релиз сочетает ценность, скорость и экономичность | E6: Не включать / проверить | F6: =COUNTIF(Реестр_единиц!$S$2:$S$101,E6) -> 9
A7: Средняя связь с ценностным предложением в первом релизе | B7: =IFERROR(AVERAGEIF(Реестр_единиц!$S$2:$S$101,"Первый релиз",Реестр_единиц!$G$2:$G$101),0) -> 4.4 | C7: Должна быть высокой, иначе первый релиз теряет смысл
A8: Средний риск первого релиза | B8: =IFERROR(AVERAGEIF(Реестр_единиц!$S$2:$S$101,"Первый релиз",Реестр_единиц!$O$2:$O$101),0) -> 1.9 | C8: Чем ниже, тем проще старт
A9: Средняя оценка контрольного листа ценности | B9: =IFERROR(AVERAGE(Проверка_ценности!$C$4:$C$9),0) -> 3.3333333 | C9: Показывает, насколько сохранены ценность, монетизация, удержание и рост
A12: Критерий | B12: Средняя оценка первого релиза
A13: Ценность | B13: =IFERROR(AVERAGEIF(Реестр_единиц!$S$2:$S$101,"Первый релиз",Реестр_единиц!$G$2:$G$101),0) -> 4.4
A14: Доход | B14: =IFERROR(AVERAGEIF(Реестр_единиц!$S$2:$S$101,"Первый релиз",Реестр_единиц!$H$2:$H$101),0) -> 3.8
A15: Удержание | B15: =IFERROR(AVERAGEIF(Реестр_единиц!$S$2:$S$101,"Первый релиз",Реестр_единиц!$I$2:$I$101),0) -> 3.2
A16: Рост | B16: =IFERROR(AVERAGEIF(Реестр_единиц!$S$2:$S$101,"Первый релиз",Реестр_единиц!$J$2:$J$101),0) -> 3.2
A17: Доказательность | B17: =IFERROR(AVERAGEIF(Реестр_единиц!$S$2:$S$101,"Первый релиз",Реестр_единиц!$K$2:$K$101),0) -> 4
A18: Быстрота | B18: =IFERROR(AVERAGEIF(Реестр_единиц!$S$2:$S$101,"Первый релиз",Реестр_единиц!$M$2:$M$101),0) -> 4.1
A19: Дешевизна | B19: =IFERROR(AVERAGEIF(Реестр_единиц!$S$2:$S$101,"Первый релиз",Реестр_единиц!$N$2:$N$101),0) -> 4.1

Sheet Справочники
A1: Справочники для выпадающих списков и шкал оценки
A3: Вид анализа | B3: Статус | C3: Тип единицы | D3: Блок Канвас | E3: Рекомендованный релиз | F3: Шкала | G3: Тип риска | H3: Тип метрики
A4: Анализ проблем | B4: Не начато | C4: Страница сайта | D4: Потребительские сегменты | E4: Первый релиз | F4: 1 – очень низко | G4: Ценность | H4: Активация
A5: Анализ отзывов | B5: В работе | C5: Экран приложения | D5: Ценностное предложение | E5: Следующий релиз | F5: 2 – низко | G5: Данные | H5: Конверсия
A6: Анализ конкурентов по сайтам | B6: Готово | C6: Функция | D6: Каналы | E6: Не включать / проверить | F6: 3 – средне | G6: Стоимость | H6: Удержание
A7: Классификация конкурентов | B7: Требует решения | C7: Интеграция | D7: Отношения с клиентами | F7: 4 – высоко | G7: Срок | H7: Повторное использование
A8: Ценностное предложение | C8: Контентный блок | D8: Потоки доходов | F8: 5 – очень высоко | G8: Технология | H8: Рост аудитории
A9: Цифровой товар | C9: Форма | D9: Ключевые ресурсы | G9: Монетизация | H9: Выручка
A10: Канвас | C10: Административная функция | D10: Ключевые виды деятельности | G10: Удержание | H10: Обращения в поддержку
A11: Пользовательские сценарии | C11: Аналитика | D11: Ключевые партнеры | G11: Рост | H11: Стоимость привлечения
A12: Страницы и экраны | D12: Структура затрат | H12: Срок реализации

Sheet Журнал_6_5
A1: Журнал рабочей копии: формулы, варианты релизов, ограничения
A3: Раздел | B3: Код | C3: Содержание
A4: Формула | B4: Ф-1 | C4: Применен расчет шаблона: балл первого релиза и балл следующих релизов (шкала 1-5, 10 критериев), рекомендованный релиз - по правилам шаблона. ИРП по формуле docx (0-5, 9 показателей) не считался
A5: Первый релиз по формуле | B5: Р-1 | C5: Единицы, рекомендованные в первый релиз: U-001, U-002, U-003, U-005, U-006, U-007, U-008, U-009, U-014, U-015 (10 из 20)
A6: Расхождение с формулой | B6: Р-3 | C6: По формуле шаблона документация, мои диаграммы, подсказки об ошибках, профиль, ИИ-ассистент и форма поддержки получают «Не включать / проверить» (кроме совместного редактирования - «Следующий»). В листе «Следующие_релизы» они назначены в релиз 2 (удержание и качество) и далее вручную по методике 6.5 (п. 7.8): форма поддержки и правовые тексты - минимальный состав первого релиза
A7: Вариант А | B7: В-А | C7: Вариант А «Быстрый выход»: Free и заявка на Pro без онлайн-оплаты. Состав релиза 1: главная, возможности, тарифы, регистрация, выбор нотации, редактор, экспорт, правовые тексты, аналитика, форма поддержки. Нотации волны 1 (UML, ERD, IDEF0, IDEF1X, IDEF3, DFD) и заглушка ИИ-ассистента входят. Исключения: онлайн-оплата, реальный ИИ-ассистент, BPMN 2.0 и сети Петри, подсказки об ошибках, совместная работа. Метрики: доля пользователей, построивших первую диаграмму; число заявок на Pro. Риск: платежная готовность проверяется косвенно
A8: Вариант Б | B8: В-Б | C8: Вариант Б «С оплатой»: Free и онлайн-оплата Pro (40 у.е. в год). Состав релиза 1: вариант А плюс оплата Pro и профиль с подпиской. Исключения: реальный ИИ-ассистент (в первом релизе заглушка), BPMN 2.0 и сети Петри, подсказки об ошибках, совместная работа, API. Метрики: доля первой диаграммы, конверсия Free в Pro, повторное использование. Риск: нужен платежный провайдер и срок увеличивается
A9: Рекомендация | B9: Р-2 | C9: Рекомендуется вариант Б, если платежный провайдер выбран до релиза 1: граница экономии - один проверяемый способ монетизации; иначе вариант А как временный
A10: Ограничения | B10: О-1 | C10: Оценки экспертные; сроки, бюджет и пороги метрик не заданы. Планируется собрать: срок и бюджет релиза 1, целевые значения метрик, даты релизов, платежный провайдер
