Workbook

Sheet 00_Инструкция
A1: Excel-шаблон анализа конкурентов по сайтам
A2: Назначение: определить рыночный стандарт цифрового товара, выделить конкурентные преимущества по товару и сформулировать сам цифровой товар через модель Левитта и модель Кано
A4: Раздел | B4: Что делать | C4: Результат
A5: 1. Реестр конкурентов | B5: Заполнить лист «01_Конкуренты»: прямые конкуренты, косвенные конкуренты, эталонные сайты для наблюдения за лучшей практикой | C5: Сформирован сопоставимый контур анализа
A6: 2. Карта сайта | B6: Зафиксировать проверенные страницы: главная, лендинг товара, тарифы, функциональные страницы, личный кабинет, поддержка, вопросы и ответы, блог, документация | C6: Появляется проверяемая база доказательств, а не субъективное впечатление
A7: 3. Модель Левитта | B7: Разложить цифровой товар на уровни: базовая выгода, родовой товар, ожидаемый товар, расширенный товар, потенциальный товар | C7: Понятно, что именно продает конкурент и за счет каких уровней формируется ценность
A8: 4. Модель Кано | B8: Классифицировать функции и признаки товара: обязательные, линейные, привлекательные, безразличные, обратные, неясные | C8: Понятно, какие признаки должны быть обязательно, какие повышают удовлетворенность, а какие создают отличие
A9: 5. Сравнение | B9: Оценить конкурентов по критериям товара, сайта и цифрового сервиса по шкале 0–5 | C9: Получается количественная карта сильных и слабых сторон
A10: 6. Рыночный стандарт | B10: Определить признаки, встречающиеся у большинства конкурентов, особенно если они относятся к обязательным или линейным требованиям Кано | C10: Сформулирован минимально приемлемый состав цифрового товара на рынке
A11: 7. Преимущества | B11: Выделить признаки, которые редки, хорошо реализованы, заметны пользователю и повышают воспринимаемую ценность | C11: Сформирован список конкурентных преимуществ и гипотез дифференциации
A12: 8. Итоговая формулировка товара | B12: На листе «05_Матрица_товара» собрать описание целевого цифрового товара: для кого, какую задачу решает, какие функции включает, где границы продукта | C12: Получено предметное определение цифрового товара и требований к его составу
A14: Шкалы оценки
A15: Шкала | B15: 0 | C15: 1 | D15: 2 | E15: 3 | F15: 4 | G15: 5 | H15: Когда применять | I15: Интерпретация
A16: Наличие признака | B16: Нет | C16: Есть частично | D16: Есть явно | E16: Есть полно | H16: Для бинарных и полуколичественных признаков | I16: 0 – отсутствует; 1–3 – степень проявления
A17: Сила реализации | B17: Нет | C17: Слабая | D17: Средняя | E17: Сильная | H17: Для уровня Левитта и качества функции | I17: 3 означает, что признак хорошо заметен и функционально раскрыт
A18: Пользовательская ценность | B18: Нет | C18: Низкая | D18: Умеренная | E18: Высокая | F18: Очень высокая | G18: Критическая | H18: Для оценки влияния на решение о покупке/регистрации/использовании | I18: 4–5 – признак способен влиять на выбор товара
A19: Сравнение конкурентов | B19: Нет | C19: Очень слабо | D19: Слабо | E19: Средне | F19: Сильно | G19: Лучший уровень | H19: Для листа «06_Сравнение» | I19: Оценки сопоставимы только при одинаковой логике анализа

Sheet 01_Конкуренты
A1: 01. Реестр конкурентов и сайтов
A2: Заполните список конкурентов и базовые параметры. ID конкурента используется в остальных листах для связки данных
A3: ID | B3: Наименование конкурента | C3: Сайт | D3: Страна/рынок | E3: Тип конкурента | F3: Сегмент аудитории | G3: Модель монетизации | H3: Цифровой товар по сайту | I3: Приоритет анализа | J3: Статус | K3: Комментарий
A4: C01 | B4: PlantUML | C4: plantuml.com | D4: Весь мир (английский язык) | E4: Прямой конкурент | F4: Разработчики, студенты, архитекторы ПО | G4: Бесплатно, открытый код | H4: Построение UML-диаграмм из текстового описания, экспорт PNG, LaTeX, EPS, SVG. Главная страница: «Open-source tool that uses simple textual descriptions to draw beautiful UML diagrams» | I4: Высокий | J4: Завершен | K4: Выборка из части A (поле «Переходит в части B и C»); страницы просмотрены 01.10.2026
A5: C02 | B5: Mermaid (библиотека) | C5: mermaid.js.org | D5: Весь мир (английский язык) | E5: Близкий альтернативный конкурент | F5: Разработчики, авторы технической документации | G5: Бесплатно, открытый код (MIT); платные планы у Mermaid Chart | H5: Диаграммы и визуализации из текста и кода (JavaScript-библиотека). Главная страница: «Create diagrams and visualizations using text and code» | I5: Высокий | J5: Завершен | K5: Выборка из части A (поле «Переходит в части B и C»); страницы просмотрены 01.10.2026
A6: C03 | B6: Mermaid Chart | C6: mermaidchart.com | D6: Весь мир (США, Великобритания, Япония в топ-странах) | E6: Близкий альтернативный конкурент | F6: Команды разработки и документации | G6: Условно-бесплатная: Free, Plus 10 у.е., Premium 20 у.е., Enterprise | H6: Облачный редактор диаграмм Mermaid с тарифами Free, Plus, Premium. Главная страница: «Create diagrams, flowcharts, and documentation with Mermaid»; «You already think in systems» | I6: Высокий | J6: Завершен | K6: Выборка из части A (поле «Переходит в части B и C»); страницы просмотрены 01.10.2026
A7: C04 | B7: Storm (StormBPMN) | C7: stormbpmn.com | D7: Россия и СНГ (Россия 62,99 %, Беларусь 2,49 %) | E7: Смежная или потенциальная конкуренция | F7: Процессные аналитики, русскоязычный рынок | G7: Условно-бесплатная: Персональный бесплатно, Команда, Бизнес, Enterprise on-prem (руб.) | H7: Платформа из семи модулей: редактор, реестр, архитектура, оргструктура, опросы, ИИ, симуляция. Главная страница: «Соберите все процессы компании»; «Одна платформа - девять модулей процессного управления» | I7: Средний | J7: Завершен | K7: Выборка из части A (поле «Переходит в части B и C»); страницы просмотрены 01.10.2026
A8: C05 | B8: draw.io (diagrams.net) | C8: app.diagrams.net | D8: Весь мир (США, Индонезия, Индия, Китай, Россия) | E8: Косвенный конкурент / заменитель | F8: Студенты, разработчики, команды | G8: Бесплатно, открытый код (Apache 2.0) | H8: Бесплатный онлайн-редактор блок-схем, UML, ER и других диаграмм. Главная страница: «Security-first diagramming for teams»; «Free, open source diagramming application with 100M+ users» | I8: Высокий | J8: Завершен | K8: Выборка из части A (поле «Переходит в части B и C»); страницы просмотрены 01.10.2026
A9: C06 | B9: Lucidchart | C9: lucidchart.com | D9: Весь мир (США, Мексика, Бразилия в топ-странах) | E9: Косвенный конкурент / заменитель | F9: Команды, бизнес-пользователи | G9: Условно-бесплатная: Free, Individual 9 у.е., Team 10 у.е., Enterprise | H9: Облачный редактор диаграмм с тарифами Free, Individual, Team, Enterprise. Главная страница: «Diagramming powered by intelligence»: диаграммы с ИИ, данными и автоматизацией | I9: Средний | J9: Завершен | K9: Выборка из части A (поле «Переходит в части B и C»); страницы просмотрены 01.10.2026
A10: C07 | B10: Eraser | C10: eraser.io | D10: Весь мир | E10: Косвенный конкурент / заменитель | F10: Инженерные команды, разработчики | G10: Условно-бесплатная: Free, Starter 15 у.е., Business 45 у.е., Enterprise | H10: Создание технических диаграмм с помощью ИИ. Главная страница: «AI for diagrams that matter»; «Create technical diagrams using AI» | I10: Высокий | J10: Завершен | K10: Выборка из части A (поле «Переходит в части B и C»); страницы просмотрены 01.10.2026
A11: C08 | B11: Whimsical | C11: whimsical.com | D11: Весь мир | E11: Смежная или потенциальная конкуренция | F11: Команды продуктов | G11: Условно-бесплатная: Free, Pro 10 у.е., Business 20 у.е. | H11: Редактор диаграмм, схем интерфейсов и документов; тарифы Free, Pro, Business (страница тарифов, 01.10.2026). Главная страница: «The whiteboard for product builders»: диаграммы, схемы интерфейсов, документы | I11: Низкий | J11: Завершен | K11: Выборка из части A (поле «Переходит в части B и C»); страницы просмотрены 01.10.2026

Sheet 02_Карта_сайтов
A1: 02. Карта страниц сайта конкурента
A2: Фиксируйте каждую страницу, которая стала источником вывода. Это повышает воспроизводимость анализа и качество итоговых решений
A3: ID конкурента | B3: Раздел/страница | C3: URL | D3: Тип страницы | E3: Цель анализа | F3: Что извлекаем | G3: Дата просмотра | H3: Скриншот/архив | I3: Достоверность 1–5 | J3: Краткий вывод
A4: C01 | B4: Главная | C4: https://plantuml.com/ | D4: Главная | E4: Определить обещание и состав товара | F4: Заголовок, разделы, тарифы, ключевые признаки | G4: 01.10.2026 | H4: Текст страницы, запрос 01.10.2026 | I4: 4 | J4: Заголовок: Open-source tool that uses simple textual descriptions to draw beautif. Признаки в тексте: integr, export, uml, erd
A5: C01 | B5: Документация | C5: https://plantuml.com/faq | D5: Документация | E5: Глубина документации, поддержка нотаций | F5: Заголовок, разделы, тарифы, ключевые признаки | G5: 01.10.2026 | H5: Текст страницы, запрос 01.10.2026 | I5: 4 | J5: Заголовок: Frequently Asked Questions. Признаки в тексте: free, integr, export, uml
A6: C01 | B6: Документация | C6: https://plantuml.com/running | D6: Документация | E6: Глубина документации, поддержка нотаций | F6: Заголовок, разделы, тарифы, ключевые признаки | G6: 01.10.2026 | H6: Текст страницы, запрос 01.10.2026 | I6: 4 | J6: Заголовок отсутствует. Признаки в тексте: integr, api, export, uml
A7: C01 | B7: Документация | C7: https://plantuml.com/download | D7: Документация | E7: Глубина документации, поддержка нотаций | F7: Заголовок, разделы, тарифы, ключевые признаки | G7: 01.10.2026 | H7: Текст страницы, запрос 01.10.2026 | I7: 4 | J7: Заголовок отсутствует. Признаки в тексте: integr, uml
A8: C01 | B8: Документация | C8: https://plantuml.com/class-diagram | D8: Документация | E8: Глубина документации, поддержка нотаций | F8: Заголовок, разделы, тарифы, ключевые признаки | G8: 01.10.2026 | H8: Текст страницы, запрос 01.10.2026 | I8: 4 | J8: Заголовок: Class Diagram syntax and features. Признаки в тексте: integr, security, uml
A9: C01 | B9: Документация | C9: https://plantuml.com/ie-diagram | D9: Документация | E9: Глубина документации, поддержка нотаций | F9: Заголовок, разделы, тарифы, ключевые признаки | G9: 01.10.2026 | H9: Текст страницы, запрос 01.10.2026 | I9: 4 | J9: Заголовок: Information Engineering diagram syntax and features. Признаки в тексте: integr, erd
A10: C01 | B10: Документация | C10: https://plantuml.com/activity-diagram-beta | D10: Документация | E10: Глубина документации, поддержка нотаций | F10: Заголовок, разделы, тарифы, ключевые признаки | G10: 01.10.2026 | H10: Текст страницы, запрос 01.10.2026 | I10: 4 | J10: Заголовок: New Activity Diagram Beta syntax and features. Признаки в тексте: integr, templates, security, uml
A11: C01 | B11: Репозиторий GitHub | C11: https://github.com/plantuml/plantuml | D11: Сообщество | E11: Открытый код, лицензия, активность | F11: Звезды, форки, дата обновления | G11: 30.09.2026 | H11: GitHub API, ЛР4 | I11: 5 | J11: 13 346 звезд, лицензия LGPL-3.0, обновление 2026-09-30
A12: C02 | B12: Главная | C12: https://mermaid.js.org/ | D12: Главная | E12: Определить обещание и состав товара | F12: Заголовок, разделы, тарифы, ключевые признаки | G12: 01.10.2026 | H12: Текст страницы, запрос 01.10.2026 | I12: 4 | J12: Заголовок: Mermaid | Diagramming and charting tool. Признаки в тексте: ai, integr
A13: C02 | B13: Документация | C13: https://mermaid.js.org/intro/ | D13: Документация | E13: Глубина документации, поддержка нотаций | F13: Заголовок, разделы, тарифы, ключевые признаки | G13: 01.10.2026 | H13: Текст страницы, запрос 01.10.2026 | I13: 4 | J13: Заголовок: About Mermaid | Mermaid. Признаки в тексте: ai, collab, integr, api, security, erd
A14: C02 | B14: Документация | C14: https://mermaid.js.org/intro/getting-started.html | D14: Документация | E14: Глубина документации, поддержка нотаций | F14: Заголовок, разделы, тарифы, ключевые признаки | G14: 01.10.2026 | H14: Текст страницы, запрос 01.10.2026 | I14: 4 | J14: Заголовок: Mermaid User Guide | Mermaid. Признаки в тексте: free, ai, collab, integr, api, export
A15: C02 | B15: Интеграции | C15: https://mermaid.js.org/ecosystem/integrations-community.html | D15: Интеграции | E15: Интеграции и экосистема | F15: Заголовок, разделы, тарифы, ключевые признаки | G15: 01.10.2026 | H15: Текст страницы, запрос 01.10.2026 | I15: 4 | J15: Заголовок: Integrations | Mermaid. Признаки в тексте: ai, integr, api, export, security, uml
... A43: C08 | B43: Документация | C43: https://whimsical.com/diagrams | D43: Документация | E43: Глубина документации, поддержка нотаций | F43: Заголовок, разделы, тарифы, ключевые признаки | G43: 01.10.2026 | H43: Текст страницы, запрос 01.10.2026 | I43: 4 | J43: Заголовок: Whimsical Diagrams, Flowcharts, and Mind Maps. Признаки в тексте: free, pricing, ai, collab, integr, templates

Sheet 03_Левитт
A1: 03. Анализ цифрового товара по модели Левитта
A2: Разложите товар конкурента на уровни: от базовой выгоды до потенциального развития. Оценка признака рассчитывается автоматически
A3: ID конкурента | B3: Товар/предложение | C3: URL/страница | D3: Уровень товара по Левитту | E3: Элемент товара / признак | F3: Как проявлен на сайте | G3: Доказательство | H3: Наличие 0/1 | I3: Сила реализации 0–3 | J3: Понятность 0–3 | K3: Влияние на ценность 1–5 | L3: Оценка признака | M3: Роль признака | N3: Примечание
A4: C01 | B4: PlantUML | C4: https://plantuml.com/ | D4: 1. Базовая выгода | E4: Основное обещание главной страницы | F4: «Open-source tool that uses simple textual descriptions to draw beautiful UML diagrams» | G4: Главная страница, просмотр 01.10.2026 | H4: 1 | I4: 3 | J4: 3 | K4: 5 | L4: =IF(OR(H4="",I4="",J4="",K4=""),"",ROUND(H4*((I4+J4)/6)*K4,2)) -> 5 | M4: =IF(L4="","",IF(AND(L4>=3.5,H4=1),"Сильный признак",IF(AND(L4>=2,H4=1),"Рабочий признак",IF(H4=1,"Слабый признак","Отсутствует")))) -> Сильный признак | N4: Конкурентная норма с высоким влиянием; включить в минимальный состав NotaCode
A5: C01 | B5: PlantUML | C5: https://plantuml.com/ | D5: 2. Родовой товар | E5: Форма поставки товара | F5: Текстовый DSL, открытый код: Построение UML-диаграмм из текстового описания, экспорт PNG, LaTeX, EPS, SVG | G5: Страницы сайта, ЛР1 табл. 42, ЛР4 | H5: 1 | I5: 3 | J5: 3 | K5: 4 | L5: =IF(OR(H5="",I5="",J5="",K5=""),"",ROUND(H5*((I5+J5)/6)*K5,2)) -> 4 | M5: =IF(L5="","",IF(AND(L5>=3.5,H5=1),"Сильный признак",IF(AND(L5>=2,H5=1),"Рабочий признак",IF(H5=1,"Слабый признак","Отсутствует")))) -> Сильный признак | N5: Конкурентная норма с высоким влиянием; включить в минимальный состав NotaCode
A6: C01 | B6: PlantUML | C6: https://plantuml.com/ | D6: 2. Родовой товар | E6: Описание диаграммы текстом (DSL) | F6: Признак найден на просмотренных страницах: описание диаграммы текстом (dsl) | G6: Страницы сайта, просмотр 01.10.2026 | H6: 1 | I6: 3 | J6: 2 | K6: 5 | L6: =IF(OR(H6="",I6="",J6="",K6=""),"",ROUND(H6*((I6+J6)/6)*K6,2)) -> 4.17 | M6: =IF(L6="","",IF(AND(L6>=3.5,H6=1),"Сильный признак",IF(AND(L6>=2,H6=1),"Рабочий признак",IF(H6=1,"Слабый признак","Отсутствует")))) -> Сильный признак | N6: Конкурентная норма с высоким влиянием; включить в минимальный состав NotaCode
A7: C01 | B7: PlantUML | C7: https://plantuml.com/ | D7: 3. Ожидаемый товар | E7: Бесплатный доступ или Free-тариф | F7: Открытый код; раздел лицензирования на странице загрузки | G7: Страницы сайта, просмотр 01.10.2026 | H7: 1 | I7: 3 | J7: 2 | K7: 5 | L7: =IF(OR(H7="",I7="",J7="",K7=""),"",ROUND(H7*((I7+J7)/6)*K7,2)) -> 4.17 | M7: =IF(L7="","",IF(AND(L7>=3.5,H7=1),"Сильный признак",IF(AND(L7>=2,H7=1),"Рабочий признак",IF(H7=1,"Слабый признак","Отсутствует")))) -> Сильный признак | N7: Конкурентная норма с высоким влиянием; включить в минимальный состав NotaCode
A8: C01 | B8: PlantUML | C8: https://plantuml.com/ | D8: 3. Ожидаемый товар | E8: Интеграции с другими сервисами | F8: Признак найден на просмотренных страницах: интеграции с другими сервисами | G8: Страницы сайта, просмотр 01.10.2026 | H8: 1 | I8: 2 | J8: 2 | K8: 4 | L8: =IF(OR(H8="",I8="",J8="",K8=""),"",ROUND(H8*((I8+J8)/6)*K8,2)) -> 2.67 | M8: =IF(L8="","",IF(AND(L8>=3.5,H8=1),"Сильный признак",IF(AND(L8>=2,H8=1),"Рабочий признак",IF(H8=1,"Слабый признак","Отсутствует")))) -> Рабочий признак | N8: Конкурентная норма с высоким влиянием; включить в минимальный состав NotaCode
A9: C01 | B9: PlantUML | C9: https://plantuml.com/ | D9: 4. Расширенный товар | E9: Открытый код и сообщество | F9: Признак найден на просмотренных страницах: открытый код и сообщество | G9: Страницы сайта, просмотр 01.10.2026 | H9: 1 | I9: 2 | J9: 2 | K9: 4 | L9: =IF(OR(H9="",I9="",J9="",K9=""),"",ROUND(H9*((I9+J9)/6)*K9,2)) -> 2.67 | M9: =IF(L9="","",IF(AND(L9>=3.5,H9=1),"Сильный признак",IF(AND(L9>=2,H9=1),"Рабочий признак",IF(H9=1,"Слабый признак","Отсутствует")))) -> Рабочий признак | N9: Конкурентная норма с высоким влиянием; включить в минимальный состав NotaCode
A10: C01 | B10: PlantUML | C10: https://plantuml.com/ | D10: 4. Расширенный товар | E10: Независимые отзывы и оценки | F10: Признак найден на просмотренных страницах: независимые отзывы и оценки | G10: Страницы сайта, просмотр 01.10.2026 | H10: 1 | I10: 2 | J10: 2 | K10: 3 | L10: =IF(OR(H10="",I10="",J10="",K10=""),"",ROUND(H10*((I10+J10)/6)*K10,2)) -> 2 | M10: =IF(L10="","",IF(AND(L10>=3.5,H10=1),"Сильный признак",IF(AND(L10>=2,H10=1),"Рабочий признак",IF(H10=1,"Слабый признак","Отсутствует")))) -> Рабочий признак | N10: Конкурентная норма с высоким влиянием; включить в минимальный состав NotaCode
A11: C01 | B11: PlantUML | C11: https://plantuml.com/ | D11: 3. Ожидаемый товар | E11: Экспорт диаграмм (PNG, SVG, PDF и др.) | F11: Признак найден на просмотренных страницах: экспорт диаграмм (png, svg, pdf и др.) | G11: Страницы сайта, просмотр 01.10.2026 | H11: 1 | I11: 3 | J11: 2 | K11: 5 | L11: =IF(OR(H11="",I11="",J11="",K11=""),"",ROUND(H11*((I11+J11)/6)*K11,2)) -> 4.17 | M11: =IF(L11="","",IF(AND(L11>=3.5,H11=1),"Сильный признак",IF(AND(L11>=2,H11=1),"Рабочий признак",IF(H11=1,"Слабый признак","Отсутствует")))) -> Сильный признак | N11: Конкурентная норма с высоким влиянием; включить в минимальный состав NotaCode
A12: C01 | B12: PlantUML | C12: https://plantuml.com/ | D12: 3. Ожидаемый товар | E12: Документация и руководства | F12: Признак найден на просмотренных страницах: документация и руководства | G12: Страницы сайта, просмотр 01.10.2026 | H12: 1 | I12: 3 | J12: 2 | K12: 4 | L12: =IF(OR(H12="",I12="",J12="",K12=""),"",ROUND(H12*((I12+J12)/6)*K12,2)) -> 3.33 | M12: =IF(L12="","",IF(AND(L12>=3.5,H12=1),"Сильный признак",IF(AND(L12>=2,H12=1),"Рабочий признак",IF(H12=1,"Слабый признак","Отсутствует")))) -> Рабочий признак | N12: Конкурентная норма с высоким влиянием; включить в минимальный состав NotaCode
A13: C01 | B13: PlantUML | C13: https://plantuml.com/ | D13: 3. Ожидаемый товар | E13: Диаграммы UML | F13: Признак найден на просмотренных страницах: диаграммы uml | G13: Страницы сайта, просмотр 01.10.2026 | H13: 1 | I13: 3 | J13: 2 | K13: 5 | L13: =IF(OR(H13="",I13="",J13="",K13=""),"",ROUND(H13*((I13+J13)/6)*K13,2)) -> 4.17 | M13: =IF(L13="","",IF(AND(L13>=3.5,H13=1),"Сильный признак",IF(AND(L13>=2,H13=1),"Рабочий признак",IF(H13=1,"Слабый признак","Отсутствует")))) -> Сильный признак | N13: Конкурентная норма с высоким влиянием; включить в минимальный состав NotaCode
A14: C01 | B14: PlantUML | C14: https://plantuml.com/ | D14: 4. Расширенный товар | E14: Диаграммы ERD | F14: Признак найден на просмотренных страницах: диаграммы erd | G14: Страницы сайта, просмотр 01.10.2026 | H14: 1 | I14: 3 | J14: 2 | K14: 4 | L14: =IF(OR(H14="",I14="",J14="",K14=""),"",ROUND(H14*((I14+J14)/6)*K14,2)) -> 3.33 | M14: =IF(L14="","",IF(AND(L14>=3.5,H14=1),"Сильный признак",IF(AND(L14>=2,H14=1),"Рабочий признак",IF(H14=1,"Слабый признак","Отсутствует")))) -> Рабочий признак | N14: Конкурентная норма с высоким влиянием; включить в минимальный состав NotaCode
A15: C01 | B15: PlantUML | C15: https://plantuml.com/ | D15: 4. Расширенный товар | E15: Развертывание на своем сервере | F15: Признак найден на просмотренных страницах: развертывание на своем сервере | G15: Страницы сайта, просмотр 01.10.2026 | H15: 1 | I15: 2 | J15: 2 | K15: 3 | L15: =IF(OR(H15="",I15="",J15="",K15=""),"",ROUND(H15*((I15+J15)/6)*K15,2)) -> 2 | M15: =IF(L15="","",IF(AND(L15>=3.5,H15=1),"Сильный признак",IF(AND(L15>=2,H15=1),"Рабочий признак",IF(H15=1,"Слабый признак","Отсутствует")))) -> Рабочий признак | N15: Конкурентная норма с высоким влиянием; включить в минимальный состав NotaCode
... A156: C08 | B156: Whimsical | C156: https://whimsical.com/ | D156: 4. Расширенный товар | E156: Настольное приложение | F156: Признак найден на просмотренных страницах: настольное приложение | G156: Страницы сайта, просмотр 01.10.2026 | H156: 1 | I156: 2 | J156: 3 | K156: 2 | L156: =IF(OR(H156="",I156="",J156="",K156=""),"",ROUND(H156*((I156+J156)/6)*K156,2)) -> 1.67 | M156: =IF(L156="","",IF(AND(L156>=3.5,H156=1),"Сильный признак",IF(AND(L156>=2,H156=1),"Рабочий признак",IF(H156=1,"Слабый признак","Отсутствует")))) -> Слабый признак | N156: Конкурентная норма с высоким влиянием; включить в минимальный состав NotaCode

Sheet 04_Кано
A1: 04. Классификация признаков по модели Кано
A2: Классифицируйте требования к цифровому товару: что обязательно, что прямо повышает удовлетворенность, а что создает эффект привлекательности
A3: ID требования | B3: Функция / признак товара | C3: Пользовательская задача | D3: Доказательства с сайтов | E3: Категория Кано | F3: Вес 1–5 | G3: Кол-во конкурентов с признаком | H3: Доля конкурентов | I3: Средняя сила реализации 0–5 | J3: Интерпретация | K3: Решение для своего товара | L3: Ответственный | M3: Примечание
A4: R001 | B4: Описание диаграммы текстом (DSL) | C4: Быстро создавать и версионировать диаграммы как код | D4: Главные страницы PlantUML, Mermaid, Mermaid Chart; «Diagram-as-code» в тарифе Free Eraser; «Diagram as code» на lucid.co/lucidchart. Категория Кано - экспертная классификация по распространенности и роли признака (опрос не проводился) | E4: Обязательное | F4: 5 | G4: 5 | H4: =IF(G4="","",IFERROR(G4/MAX(1,COUNTIF('01_Конкуренты'!$B$4:$B$11,"?*")),"")) -> 0.625 | I4: 5 | J4: =IF(B4="","",IF(E4="Обязательное",IF(H4>=0.6,"Минимальный рыночный стандарт","Потенциальный обязательный разрыв"),IF(E4="Линейное",IF(H4>=0.5,"Конкурентная норма с влиянием на выбор","Зона усиления ценности"),IF(E4="Привлекательное",IF(H4<0.5,"Зона дифференциации","Переходит в ожидаемую норму"),IF(E4="Безразличное","Не делать при дефиците ресурсов",IF(E4="Обратное","Исключить или проверить риск отторжения","Требует проверки")))))) -> Минимальный рыночный стандарт | K4: Включить в минимальный состав NotaCode | L4: К. А. Хаджинова | M4: Отсутствие снижает удовлетворенность; обязательно включить в MVP NotaCode
A5: R002 | B5: Бесплатный доступ или Free-тариф | C5: Начать работу без оплаты | D5: Открытый код или тариф Free на страницах 8 из 8 конкурентов. Категория Кано - экспертная классификация по распространенности и роли признака (опрос не проводился) | E5: Обязательное | F5: 5 | G5: 8 | H5: =IF(G5="","",IFERROR(G5/MAX(1,COUNTIF('01_Конкуренты'!$B$4:$B$11,"?*")),"")) -> 1 | I5: 5 | J5: =IF(B5="","",IF(E5="Обязательное",IF(H5>=0.6,"Минимальный рыночный стандарт","Потенциальный обязательный разрыв"),IF(E5="Линейное",IF(H5>=0.5,"Конкурентная норма с влиянием на выбор","Зона усиления ценности"),IF(E5="Привлекательное",IF(H5<0.5,"Зона дифференциации","Переходит в ожидаемую норму"),IF(E5="Безразличное","Не делать при дефиците ресурсов",IF(E5="Обратное","Исключить или проверить риск отторжения","Требует проверки")))))) -> Минимальный рыночный стандарт | K5: Включить в минимальный состав NotaCode | L5: К. А. Хаджинова | M5: Отсутствие снижает удовлетворенность; обязательно включить в MVP NotaCode
A6: R003 | B6: Платная подписка по тарифным уровням | C6: Получить расширенные возможности за оплату | D6: Страницы тарифов Mermaid Chart, Storm, Lucidchart, Eraser, Whimsical. Категория Кано - экспертная классификация по распространенности и роли признака (опрос не проводился) | E6: Линейное | F6: 4 | G6: 5 | H6: =IF(G6="","",IFERROR(G6/MAX(1,COUNTIF('01_Конкуренты'!$B$4:$B$11,"?*")),"")) -> 0.625 | I6: 5 | J6: =IF(B6="","",IF(E6="Обязательное",IF(H6>=0.6,"Минимальный рыночный стандарт","Потенциальный обязательный разрыв"),IF(E6="Линейное",IF(H6>=0.5,"Конкурентная норма с влиянием на выбор","Зона усиления ценности"),IF(E6="Привлекательное",IF(H6<0.5,"Зона дифференциации","Переходит в ожидаемую норму"),IF(E6="Безразличное","Не делать при дефиците ресурсов",IF(E6="Обратное","Исключить или проверить риск отторжения","Требует проверки")))))) -> Конкурентная норма с влиянием на выбор | K6: Реализовать на уровне рынка | L6: К. А. Хаджинова | M6: Линейное влияние: чем лучше реализовано, тем выше оценка NotaCode
A7: R004 | B7: Открытая страница тарифов | C7: Понять цену и состав тарифа до регистрации | D7: Страницы тарифов (01.10.2026). Категория Кано - экспертная классификация по распространенности и роли признака (опрос не проводился) | E7: Обязательное | F7: 5 | G7: 5 | H7: =IF(G7="","",IFERROR(G7/MAX(1,COUNTIF('01_Конкуренты'!$B$4:$B$11,"?*")),"")) -> 0.625 | I7: 5 | J7: =IF(B7="","",IF(E7="Обязательное",IF(H7>=0.6,"Минимальный рыночный стандарт","Потенциальный обязательный разрыв"),IF(E7="Линейное",IF(H7>=0.5,"Конкурентная норма с влиянием на выбор","Зона усиления ценности"),IF(E7="Привлекательное",IF(H7<0.5,"Зона дифференциации","Переходит в ожидаемую норму"),IF(E7="Безразличное","Не делать при дефиците ресурсов",IF(E7="Обратное","Исключить или проверить риск отторжения","Требует проверки")))))) -> Минимальный рыночный стандарт | K7: Включить в минимальный состав NotaCode | L7: К. А. Хаджинова | M7: Отсутствие снижает удовлетворенность; обязательно включить в MVP NotaCode
A8: R005 | B8: Корпоративный тариф (Enterprise или on-prem) | C8: Подключить организацию целиком | D8: Enterprise по запросу на страницах тарифов; Storm: on-prem от 990 тыс. руб. в год. Категория Кано - экспертная классификация по распространенности и роли признака (опрос не проводился) | E8: Безразличное | F8: 2 | G8: 4 | H8: =IF(G8="","",IFERROR(G8/MAX(1,COUNTIF('01_Конкуренты'!$B$4:$B$11,"?*")),"")) -> 0.5 | I8: 5 | J8: =IF(B8="","",IF(E8="Обязательное",IF(H8>=0.6,"Минимальный рыночный стандарт","Потенциальный обязательный разрыв"),IF(E8="Линейное",IF(H8>=0.5,"Конкурентная норма с влиянием на выбор","Зона усиления ценности"),IF(E8="Привлекательное",IF(H8<0.5,"Зона дифференциации","Переходит в ожидаемую норму"),IF(E8="Безразличное","Не делать при дефиците ресурсов",IF(E8="Обратное","Исключить или проверить риск отторжения","Требует проверки")))))) -> Не делать при дефиците ресурсов | K8: Не приоритет для сегмента студентов и аналитиков | L8: К. А. Хаджинова | M8: Слабое влияние на выбор; исключить из приоритетного плана
A9: R006 | B9: Скидка или цена при годовой оплате | C9: Снизить стоимость при долгом использовании | D9: Цены «billed annually» (Mermaid Chart, Lucidchart, Eraser), скидка 20 % (Storm). Категория Кано - экспертная классификация по распространенности и роли признака (опрос не проводился) | E9: Линейное | F9: 3 | G9: 4 | H9: =IF(G9="","",IFERROR(G9/MAX(1,COUNTIF('01_Конкуренты'!$B$4:$B$11,"?*")),"")) -> 0.5 | I9: 5 | J9: =IF(B9="","",IF(E9="Обязательное",IF(H9>=0.6,"Минимальный рыночный стандарт","Потенциальный обязательный разрыв"),IF(E9="Линейное",IF(H9>=0.5,"Конкурентная норма с влиянием на выбор","Зона усиления ценности"),IF(E9="Привлекательное",IF(H9<0.5,"Зона дифференциации","Переходит в ожидаемую норму"),IF(E9="Безразличное","Не делать при дефиците ресурсов",IF(E9="Обратное","Исключить или проверить риск отторжения","Требует проверки")))))) -> Конкурентная норма с влиянием на выбор | K9: Реализовать на уровне рынка | L9: К. А. Хаджинова | M9: Линейное влияние: чем лучше реализовано, тем выше оценка NotaCode
A10: R007 | B10: Пробный период платного тарифа | C10: Проверить платные функции до оплаты | D10: FAQ Lucidchart: пробный период 7 дней. Категория Кано - экспертная классификация по распространенности и роли признака (опрос не проводился) | E10: Безразличное | F10: 2 | G10: 1 | H10: =IF(G10="","",IFERROR(G10/MAX(1,COUNTIF('01_Конкуренты'!$B$4:$B$11,"?*")),"")) -> 0.125 | I10: 5 | J10: =IF(B10="","",IF(E10="Обязательное",IF(H10>=0.6,"Минимальный рыночный стандарт","Потенциальный обязательный разрыв"),IF(E10="Линейное",IF(H10>=0.5,"Конкурентная норма с влиянием на выбор","Зона усиления ценности"),IF(E10="Привлекательное",IF(H10<0.5,"Зона дифференциации","Переходит в ожидаемую норму"),IF(E10="Безразличное","Не делать при дефиците ресурсов",IF(E10="Обратное","Исключить или проверить риск отторжения","Требует проверки")))))) -> Не делать при дефиците ресурсов | K10: Не приоритет для сегмента студентов и аналитиков | L10: К. А. Хаджинова | M10: Слабое влияние на выбор; исключить из приоритетного плана
A11: R008 | B11: Бесплатные гости или зрители | C11: Показать диаграмму без оплаты за каждого читателя | D11: Unlimited viewer seats (Mermaid Chart Premium); 100 гостей на участника (Storm); unlimited guests (Eraser, Whimsical). Категория Кано - экспертная классификация по распространенности и роли признака (опрос не проводился) | E11: Привлекательное | F11: 3 | G11: 4 | H11: =IF(G11="","",IFERROR(G11/MAX(1,COUNTIF('01_Конкуренты'!$B$4:$B$11,"?*")),"")) -> 0.5 | I11: 5 | J11: =IF(B11="","",IF(E11="Обязательное",IF(H11>=0.6,"Минимальный рыночный стандарт","Потенциальный обязательный разрыв"),IF(E11="Линейное",IF(H11>=0.5,"Конкурентная норма с влиянием на выбор","Зона усиления ценности"),IF(E11="Привлекательное",IF(H11<0.5,"Зона дифференциации","Переходит в ожидаемую норму"),IF(E11="Безразличное","Не делать при дефиците ресурсов",IF(E11="Обратное","Исключить или проверить риск отторжения","Требует проверки")))))) -> Переходит в ожидаемую норму | K11: Рассмотреть как дифференциатор Pro | L11: К. А. Хаджинова | M11: Дифференциатор; добавляет ценность при реализации; кандидат для Pro
A12: R009 | B12: ИИ-генерация или ИИ-помощник | C12: Ускорить создание диаграммы по описанию | D12: ИИ-кредиты (Mermaid Chart); ИИ-ассистент (Storm); Lucid AI; Eraser AI; ИИ в Whimsical. Категория Кано - экспертная классификация по распространенности и роли признака (опрос не проводился) | E12: Привлекательное | F12: 4 | G12: 5 | H12: =IF(G12="","",IFERROR(G12/MAX(1,COUNTIF('01_Конкуренты'!$B$4:$B$11,"?*")),"")) -> 0.625 | I12: 5 | J12: =IF(B12="","",IF(E12="Обязательное",IF(H12>=0.6,"Минимальный рыночный стандарт","Потенциальный обязательный разрыв"),IF(E12="Линейное",IF(H12>=0.5,"Конкурентная норма с влиянием на выбор","Зона усиления ценности"),IF(E12="Привлекательное",IF(H12<0.5,"Зона дифференциации","Переходит в ожидаемую норму"),IF(E12="Безразличное","Не делать при дефиците ресурсов",IF(E12="Обратное","Исключить или проверить риск отторжения","Требует проверки")))))) -> Переходит в ожидаемую норму | K12: Рассмотреть как дифференциатор Pro | L12: К. А. Хаджинова | M12: Дифференциатор; добавляет ценность при реализации; кандидат для Pro
A13: R010 | B13: Интеграции с другими сервисами | C13: Встроить инструмент в рабочие процессы | D13: Разделы и упоминания интеграций на страницах 8 из 8 конкурентов. Категория Кано - экспертная классификация по распространенности и роли признака (опрос не проводился) | E13: Линейное | F13: 4 | G13: 8 | H13: =IF(G13="","",IFERROR(G13/MAX(1,COUNTIF('01_Конкуренты'!$B$4:$B$11,"?*")),"")) -> 1 | I13: 3.33 | J13: =IF(B13="","",IF(E13="Обязательное",IF(H13>=0.6,"Минимальный рыночный стандарт","Потенциальный обязательный разрыв"),IF(E13="Линейное",IF(H13>=0.5,"Конкурентная норма с влиянием на выбор","Зона усиления ценности"),IF(E13="Привлекательное",IF(H13<0.5,"Зона дифференциации","Переходит в ожидаемую норму"),IF(E13="Безразличное","Не делать при дефиците ресурсов",IF(E13="Обратное","Исключить или проверить риск отторжения","Требует проверки")))))) -> Конкурентная норма с влиянием на выбор | K13: Реализовать на уровне рынка | L13: К. А. Хаджинова | M13: Линейное влияние: чем лучше реализовано, тем выше оценка NotaCode
A14: R011 | B14: API или платформа разработчика | C14: Автоматизировать генерацию диаграмм | D14: API Mermaid; пункт API в меню Mermaid Chart; API в Enterprise Storm; Developer platform Lucidchart; API calls Eraser. Категория Кано - экспертная классификация по распространенности и роли признака (опрос не проводился) | E14: Привлекательное | F14: 3 | G14: 5 | H14: =IF(G14="","",IFERROR(G14/MAX(1,COUNTIF('01_Конкуренты'!$B$4:$B$11,"?*")),"")) -> 0.625 | I14: 5 | J14: =IF(B14="","",IF(E14="Обязательное",IF(H14>=0.6,"Минимальный рыночный стандарт","Потенциальный обязательный разрыв"),IF(E14="Линейное",IF(H14>=0.5,"Конкурентная норма с влиянием на выбор","Зона усиления ценности"),IF(E14="Привлекательное",IF(H14<0.5,"Зона дифференциации","Переходит в ожидаемую норму"),IF(E14="Безразличное","Не делать при дефиците ресурсов",IF(E14="Обратное","Исключить или проверить риск отторжения","Требует проверки")))))) -> Переходит в ожидаемую норму | K14: Рассмотреть как дифференциатор Pro | L14: К. А. Хаджинова | M14: Дифференциатор; добавляет ценность при реализации; кандидат для Pro
A15: R012 | B15: Открытый код и сообщество | C15: Доверять инструменту и расширять его | D15: GitHub API, 30.09.2026; лицензия Apache 2.0 у draw.io. Категория Кано - экспертная классификация по распространенности и роли признака (опрос не проводился) | E15: Привлекательное | F15: 4 | G15: 3 | H15: =IF(G15="","",IFERROR(G15/MAX(1,COUNTIF('01_Конкуренты'!$B$4:$B$11,"?*")),"")) -> 0.375 | I15: 3.33 | J15: =IF(B15="","",IF(E15="Обязательное",IF(H15>=0.6,"Минимальный рыночный стандарт","Потенциальный обязательный разрыв"),IF(E15="Линейное",IF(H15>=0.5,"Конкурентная норма с влиянием на выбор","Зона усиления ценности"),IF(E15="Привлекательное",IF(H15<0.5,"Зона дифференциации","Переходит в ожидаемую норму"),IF(E15="Безразличное","Не делать при дефиците ресурсов",IF(E15="Обратное","Исключить или проверить риск отторжения","Требует проверки")))))) -> Зона дифференциации | K15: Рассмотреть как дифференциатор Pro | L15: К. А. Хаджинова | M15: Дифференциатор; добавляет ценность при реализации; кандидат для Pro
... A32: R029 | B32: Признаки развития (ИИ-помощник, MCP, новые функции) | C32: Видеть, что продукт развивается | D32: MCP-интеграция (Storm); метки NEW: Lucid AI, Developer platform (Lucidchart); ИИ-кредиты (Mermaid Chart); AI-first (Eraser). Категория Кано - экспертная классификация по распространенности и роли признака (опрос не проводился) | E32: Привлекательное | F32: 3 | G32: 4 | H32: =IF(G32="","",IFERROR(G32/MAX(1,COUNTIF('01_Конкуренты'!$B$4:$B$11,"?*")),"")) -> 0.5 | I32: 3.33 | J32: =IF(B32="","",IF(E32="Обязательное",IF(H32>=0.6,"Минимальный рыночный стандарт","Потенциальный обязательный разрыв"),IF(E32="Линейное",IF(H32>=0.5,"Конкурентная норма с влиянием на выбор","Зона усиления ценности"),IF(E32="Привлекательное",IF(H32<0.5,"Зона дифференциации","Переходит в ожидаемую норму"),IF(E32="Безразличное","Не делать при дефиците ресурсов",IF(E32="Обратное","Исключить или проверить риск отторжения","Требует проверки")))))) -> Переходит в ожидаемую норму | K32: Рассмотреть как дифференциатор Pro | L32: К. А. Хаджинова | M32: Дифференциатор; добавляет ценность при реализации; кандидат для Pro
A33: R030 | B33: Несколько нотаций (UML, BPMN, ERD) в одном инструменте | C33: Работать с разными нотациями без смены инструмента | D33: Lucidchart: UML-, BPMN-шаблоны и ERD markup (lucid.co/lucidchart) | E33: Привлекательное | F33: 5 | G33: 1 | H33: =IF(G33="","",IFERROR(G33/MAX(1,COUNTIF('01_Конкуренты'!$B$4:$B$11,"?*")),"")) -> 0.125 | I33: – | J33: =IF(B33="","",IF(E33="Обязательное",IF(H33>=0.6,"Минимальный рыночный стандарт","Потенциальный обязательный разрыв"),IF(E33="Линейное",IF(H33>=0.5,"Конкурентная норма с влиянием на выбор","Зона усиления ценности"),IF(E33="Привлекательное",IF(H33<0.5,"Зона дифференциации","Переходит в ожидаемую норму"),IF(E33="Безразличное","Не делать при дефиците ресурсов",IF(E33="Обратное","Исключить или проверить риск отторжения","Требует проверки")))))) -> Зона дифференциации | K33: Рассмотреть как дифференциатор: полный набор нотаций проекта | L33: К. А. Хаджинова | M33: Дифференциатор; добавляет ценность при реализации; кандидат для Pro
A34: R031 | B34: Нотации IDEF0, DFD, сети Петри | C34: Строить диаграммы по учебным и отраслевым стандартам | D34: На просмотренных страницах 8 конкурентов не найдены (IDEF упомянут в блоге Storm) | E34: Привлекательное | F34: 5 | G34: 0 | H34: =IF(G34="","",IFERROR(G34/MAX(1,COUNTIF('01_Конкуренты'!$B$4:$B$11,"?*")),"")) -> 0 | I34: – | J34: =IF(B34="","",IF(E34="Обязательное",IF(H34>=0.6,"Минимальный рыночный стандарт","Потенциальный обязательный разрыв"),IF(E34="Линейное",IF(H34>=0.5,"Конкурентная норма с влиянием на выбор","Зона усиления ценности"),IF(E34="Привлекательное",IF(H34<0.5,"Зона дифференциации","Переходит в ожидаемую норму"),IF(E34="Безразличное","Не делать при дефиците ресурсов",IF(E34="Обратное","Исключить или проверить риск отторжения","Требует проверки")))))) -> Зона дифференциации | K34: Дифференциатор NotaCode: у конкурентов не найден | L34: К. А. Хаджинова | M34: Дифференциатор; добавляет ценность при реализации; кандидат для Pro
A35: R032 | B35: Проверка правил нотации при вводе | C35: Получать подсказки об ошибках в модели | D35: не собрано: проверка работы продуктов (тест редакторов) | E35: Неясное | F35: 4 | G35: – | H35: =IF(G35="","",IFERROR(G35/MAX(1,COUNTIF('01_Конкуренты'!$B$4:$B$11,"?*")),"")) | I35: – | J35: =IF(B35="","",IF(E35="Обязательное",IF(H35>=0.6,"Минимальный рыночный стандарт","Потенциальный обязательный разрыв"),IF(E35="Линейное",IF(H35>=0.5,"Конкурентная норма с влиянием на выбор","Зона усиления ценности"),IF(E35="Привлекательное",IF(H35<0.5,"Зона дифференциации","Переходит в ожидаемую норму"),IF(E35="Безразличное","Не делать при дефиците ресурсов",IF(E35="Обратное","Исключить или проверить риск отторжения","Требует проверки")))))) -> Требует проверки | K35: не собрано: решение после проверки продуктов | L35: К. А. Хаджинова | M35: Недостаточно данных; требует дополнительного исследования
A36: R033 | B36: Импорт форматов PlantUML, Mermaid, D2, draw.io, BPMN XML | C36: Перенести существующие диаграммы | D36: не собрано: проверка работы продуктов (Visio import найден у Lucidchart) | E36: Неясное | F36: 4 | G36: – | H36: =IF(G36="","",IFERROR(G36/MAX(1,COUNTIF('01_Конкуренты'!$B$4:$B$11,"?*")),"")) | I36: – | J36: =IF(B36="","",IF(E36="Обязательное",IF(H36>=0.6,"Минимальный рыночный стандарт","Потенциальный обязательный разрыв"),IF(E36="Линейное",IF(H36>=0.5,"Конкурентная норма с влиянием на выбор","Зона усиления ценности"),IF(E36="Привлекательное",IF(H36<0.5,"Зона дифференциации","Переходит в ожидаемую норму"),IF(E36="Безразличное","Не делать при дефиците ресурсов",IF(E36="Обратное","Исключить или проверить риск отторжения","Требует проверки")))))) -> Требует проверки | K36: не собрано: решение после проверки продуктов | L36: К. А. Хаджинова | M36: Недостаточно данных; требует дополнительного исследования

Sheet 05_Матрица_товара
A1: 05. Определение цифрового товара
A2: Используйте этот лист для итогового синтеза: какие элементы входят в цифровой товар, какие являются обязательными, а какие формируют отличие
A3: Блок определения | B3: Вопрос для анализа | C3: Вывод по рынку | D3: Доказательства | E3: Связь с Левиттом | F3: Связь с Кано | G3: Статус для своего товара | H3: Минимальная реализация | I3: Расширенная реализация | J3: Риск исключения | K3: Решение | L3: Комментарий
A4: Целевая пользовательская задача | B4: Какую основную задачу обещает решить товар? | C4: Рынок обещает три вида задач: диаграммы из текста (PlantUML, Mermaid, Mermaid Chart, Eraser), рисование в редакторе (draw.io, Lucidchart, Whimsical), управление процессами (Storm); ИИ-генерация есть у 5 из 8 | D4: Главные страницы и страницы ИИ (01.10.2026) | E4: 1. Базовая выгода | F4: Обязательное / Линейное | G4: Принять | H4: Построение диаграммы по текстовому описанию | I4: ИИ-генерация диаграммы по описанию | J4: Низкий | K4: Обязательно | L4: Основа продукта
A5: Пользовательский сегмент | B5: Для кого товар явно предназначен по сайту конкурентов? | C5: Явные аудитории: разработчики и технические писатели (PlantUML, Mermaid), команды и бизнес-пользователи (Mermaid Chart, Lucidchart, Whimsical), процессные аналитики (Storm), инженерные команды (Eraser) | D5: Главные страницы, ЛР4 карточки | E5: 1. Базовая выгода | F5: Линейное | G5: Принять | H5: Студенты и аналитики ПО | I5: Преподаватели и команды | J5: Низкий | K5: Обязательно | L5: Сегмент NotaCode: студенты (Free), аналитики и разработчики (Pro)
A6: Родовой товар | B6: Какой минимальный цифровой объект продается: сервис, приложение, платформа, курс, кабинет, база данных, подписка? | C6: Родовой товар: онлайн-редактор с кодом диаграммы (PlantUML server, Mermaid Live), облачный SaaS (Mermaid Chart, Lucidchart, Eraser, Whimsical, Storm) или бесплатное приложение (draw.io) | D6: Страницы продуктов и тарифов | E6: 2. Родовой товар | F6: Обязательное | G6: Принять | H6: Веб-IDE «диаграммы как код» (PWA) | I6: Настольный режим и отдельный сервер | J6: Низкий | K6: Обязательно | L6: Форма поставки NotaCode - PWA
A7: Ожидаемый состав | B7: Какие функции пользователь считает нормой рынка? | C7: Ожидаемый состав: UML (4 из 8), ERD (6 из 8), экспорт (8 из 8), документация (6 из 8), вход (5 из 8), шаблоны (3 из 8) | D7: Страницы документации и продуктов | E7: 3. Ожидаемый товар | F7: Обязательное | G7: Принять | H7: UML, BPMN, ERD, экспорт PNG/SVG/PDF, документация | I7: Шаблоны, история версий | J7: Средний | K7: Включить | L7: IDEF0, DFD, сети Петри у конкурентов не найдены: отличие NotaCode
A8: Интерфейс и доступ | B8: Как организован доступ: сайт, приложение, личный кабинет, мобильная версия, интеграции? | C8: Доступ: открытый код или Free-тариф у 8 из 8; вход и личный кабинет у 5 из 8; совместная работа у 6 из 8 | D8: Главные страницы и тарифы | E8: 3. Ожидаемый товар | F8: Обязательное / Линейное | G8: Принять | H8: Работа в браузере без установки, Free-доступ | I8: Совместное редактирование | J8: Низкий | K8: Включить | L8: Коллаборация - линейное требование
A9: Оплата и тарифы | B9: Какой способ оплаты и представления тарифов является нормой? | C9: Тарифы открыты у 5 из 8: Free плюс подписка 9-20 у.е. за пользователя в месяц (Mermaid Chart 10 и 20, Lucidchart 9 и 10, Eraser 15 и 45, Whimsical 10 и 20); цены при годовой оплате у 4 из 8 | D9: Страницы тарифов (01.10.2026) | E9: 3. Ожидаемый товар | F9: Обязательное | G9: Принять | H9: Free и Pro 40 у.е. в год (48 у.е. при 4 x 12 рядом) | I9: Командный тариф за пользователя | J9: Средний | K9: Включить | L9: Цена Pro ниже минимальных тарифов конкурентов (от 9 у.е. в месяц)
A10: Поддержка и сопровождение | B10: Какой уровень поддержки включен в товар? | C10: Поддержка: документация у 6 из 8, учебный центр у Lucidchart, раздел поддержки у Whimsical; чат поддержки не проверялся | D10: Страницы документации и поддержки | E10: 3. Ожидаемый товар | F10: Линейное | G10: Принять | H10: Документация и примеры | I10: Обучающие материалы для студентов | J10: Средний | K10: Включить | L10: Документация - обязательное требование
A11: Расширение ценности | B11: Какие дополнительные функции повышают ценность: персонализация, аналитика, рекомендации, автоматизация? | C11: Расширение ценности: ИИ у 5 из 8, API у 5 из 8, интеграции у 8 из 8, история версий у 5 из 8 | D11: Страницы тарифов и продуктов | E11: 4. Расширенный товар | F11: Линейное / Привлекательное | G11: Рассмотреть | H11: ИИ-помощник и экспорт | I11: API, интеграции, история версий | J11: Средний | K11: Рассмотреть | L11: ИИ - привлекательное требование
A12: Доверие и доказательства | B12: Какие элементы подтверждают надежность: кейсы, отзывы, сертификаты, политика безопасности, гарантии? | C12: Доверие: независимые отзывы у 7 из 8, данные о числе пользователей на сайте у 4 из 8, раздел о безопасности у 6 из 8, открытый код у 3 из 8 | D12: G2, Capterra, Trustpilot, страницы сайтов | E12: 4. Расширенный товар | F12: Линейное | G12: Принять | H12: Политика конфиденциальности, примеры | I12: Открытый репозиторий, отзывы | J12: Средний | K12: Включить | L12: Пока продукт до MVP: отзывов нет
A13: Потенциальное развитие | B13: Какие будущие возможности видны по дорожной карте, интеграциям, пробным функциям, технологиям? | C13: Потенциал: ИИ-помощник и MCP (Storm), Lucid AI и платформа разработчика (Lucidchart), ИИ-кредиты (Mermaid Chart) | D13: Страницы сайтов | E13: 5. Потенциальный товар | F13: Привлекательное | G13: Рассмотреть | H13: Не требуется в минимальной версии | I13: ИИ-помощник, платформа разработчика | J13: Средний | K13: Рассмотреть | L13: Развитие после MVP
A14: Граница товара | B14: Что входит в товар, а что остается услугой, сопровождением или маркетинговым обещанием? | C14: Граница товара: у всех восьми товар - сервис или библиотека; консультации и обучение не входят в тарифы Free и Pro | D14: Страницы тарифов | E14: Все уровни | F14: Все категории | G14: Принять | H14: Сервис без консультаций | I14: Платное обучение | J14: Низкий | K14: Принять | L14: Консультации вне границы товара
A15: Формулировка товара | B15: Сформулируйте итог: цифровой товар – это… для… который решает… за счет… | C15: Рынок: цифровой товар диаграмм - онлайн-редактор или библиотека с кодом диаграммы для разработчиков и аналитиков, бесплатный доступ и платная подписка, экспорт, документация | D15: Сводка по листам 03, 04, 07 | E15: Синтез | F15: Синтез | G15: Принять | H15: Цифровой товар NotaCode - это веб-IDE «диаграммы как код» для студентов и аналитиков ПО, который решает задачу построения и проверки диаграмм UML, BPMN, ERD, IDEF0 и DFD по текстовому описанию за счет онлайн-редактора с экспортом, бесплатного уровня Free и подписки Pro 40 у.е. в год | I15: – | J15: – | K15: Принять | L15: –

Sheet 06_Сравнение
A1: 06. Сравнительная оценка конкурентов
A2: Оцените каждый критерий по шкале 0–5. Вес показывает влияние критерия на товарную конкурентоспособность
A3: ID критерия | B3: Группа | C3: Критерий | D3: Вес | E3: C01 | F3: C02 | G3: C03 | H3: C04 | I3: C05 | J3: C06 | K3: C07 | L3: C08 | M3: Среднее | N3: Лучший балл | O3: Лидер
A4: P01 | B4: Сущность товара | C4: На сайте ясно понятно, какой цифровой товар предлагается | D4: 5 | E4: 5 | F4: 5 | G4: 5 | H4: 5 | I4: 5 | J4: 5 | K4: 5 | L4: 5 | M4: =IFERROR(AVERAGE(E4:L4),"") -> 5 | N4: =IFERROR(MAX(E4:L4),"") -> 5 | O4: =IF(N4="","",IFERROR(INDEX($E$3:$L$3,1,MATCH(N4,E4:L4,0)),"")) -> C01
A5: P02 | B5: Сущность товара | C5: Целевая пользовательская задача сформулирована конкретно | D5: 5 | E5: 4 | F5: 4 | G5: 5 | H5: 4 | I5: 4 | J5: 4 | K5: 5 | L5: 4 | M5: =IFERROR(AVERAGE(E5:L5),"") -> 4.25 | N5: =IFERROR(MAX(E5:L5),"") -> 5 | O5: =IF(N5="","",IFERROR(INDEX($E$3:$L$3,1,MATCH(N5,E5:L5,0)),"")) -> C03
A6: P03 | B6: Сущность товара | C6: Граница товара отделена от консультаций, сопровождения и маркетинговых обещаний | D6: 4 | E6: 4 | F6: 4 | G6: 4 | H6: 4 | I6: 4 | J6: 4 | K6: 4 | L6: 3 | M6: =IFERROR(AVERAGE(E6:L6),"") -> 3.875 | N6: =IFERROR(MAX(E6:L6),"") -> 4 | O6: =IF(N6="","",IFERROR(INDEX($E$3:$L$3,1,MATCH(N6,E6:L6,0)),"")) -> C01
A7: P04 | B7: Функциональность | C7: Ключевые функции товара раскрыты через сценарии использования | D7: 5 | E7: 4 | F7: 4 | G7: 5 | H7: 5 | I7: 4 | J7: 5 | K7: 5 | L7: 4 | M7: =IFERROR(AVERAGE(E7:L7),"") -> 4.5 | N7: =IFERROR(MAX(E7:L7),"") -> 5 | O7: =IF(N7="","",IFERROR(INDEX($E$3:$L$3,1,MATCH(N7,E7:L7,0)),"")) -> C03
A8: P05 | B8: Функциональность | C8: Есть демонстрация интерфейса, личного кабинета или результата работы | D8: 4 | E8: 4 | F8: 4 | G8: 4 | H8: – | I8: 4 | J8: 5 | K8: 4 | L8: 4 | M8: =IFERROR(AVERAGE(E8:L8),"") -> 4.1428571 | N8: =IFERROR(MAX(E8:L8),"") -> 5 | O8: =IF(N8="","",IFERROR(INDEX($E$3:$L$3,1,MATCH(N8,E8:L8,0)),"")) -> C06
A9: P06 | B9: Функциональность | C9: Есть пробный доступ, демоверсия, бесплатный фрагмент или понятный вход в использование | D9: 4 | E9: 5 | F9: 5 | G9: 5 | H9: 5 | I9: 5 | J9: 5 | K9: 5 | L9: 5 | M9: =IFERROR(AVERAGE(E9:L9),"") -> 5 | N9: =IFERROR(MAX(E9:L9),"") -> 5 | O9: =IF(N9="","",IFERROR(INDEX($E$3:$L$3,1,MATCH(N9,E9:L9,0)),"")) -> C01
A10: P07 | B10: Ценность | C10: Показана измеримая выгода: экономия времени, денег, снижение риска, рост результата | D10: 5 | E10: 2 | F10: 2 | G10: 4 | H10: 3 | I10: 3 | J10: 4 | K10: 4 | L10: 3 | M10: =IFERROR(AVERAGE(E10:L10),"") -> 3.125 | N10: =IFERROR(MAX(E10:L10),"") -> 4 | O10: =IF(N10="","",IFERROR(INDEX($E$3:$L$3,1,MATCH(N10,E10:L10,0)),"")) -> C03
A11: P08 | B11: Ценность | C11: Преимущества связаны с функциями товара, а не только с рекламными обещаниями | D11: 5 | E11: 3 | F11: 3 | G11: 4 | H11: 4 | I11: 4 | J11: 5 | K11: 5 | L11: 4 | M11: =IFERROR(AVERAGE(E11:L11),"") -> 4 | N11: =IFERROR(MAX(E11:L11),"") -> 5 | O11: =IF(N11="","",IFERROR(INDEX($E$3:$L$3,1,MATCH(N11,E11:L11,0)),"")) -> C06
A12: P09 | B12: Ценность | C12: Есть сравнение тарифов, комплектаций или уровней доступа | D12: 4 | E12: 2 | F12: 1 | G12: 5 | H12: 5 | I12: 2 | J12: 5 | K12: 5 | L12: 5 | M12: =IFERROR(AVERAGE(E12:L12),"") -> 3.75 | N12: =IFERROR(MAX(E12:L12),"") -> 5 | O12: =IF(N12="","",IFERROR(INDEX($E$3:$L$3,1,MATCH(N12,E12:L12,0)),"")) -> C03
A13: P10 | B13: Доверие | C13: Есть отзывы, кейсы, примеры клиентов или подтверждения результата | D13: 4 | E13: 1 | F13: 2 | G13: 4 | H13: 4 | I13: 3 | J13: 5 | K13: 4 | L13: 4 | M13: =IFERROR(AVERAGE(E13:L13),"") -> 3.375 | N13: =IFERROR(MAX(E13:L13),"") -> 5 | O13: =IF(N13="","",IFERROR(INDEX($E$3:$L$3,1,MATCH(N13,E13:L13,0)),"")) -> C06
A14: P11 | B14: Доверие | C14: Раскрыты безопасность, обработка данных, юридические условия, гарантии | D14: 4 | E14: 2 | F14: 2 | G14: 4 | H14: 4 | I14: 5 | J14: 5 | K14: 4 | L14: 5 | M14: =IFERROR(AVERAGE(E14:L14),"") -> 3.875 | N14: =IFERROR(MAX(E14:L14),"") -> 5 | O14: =IF(N14="","",IFERROR(INDEX($E$3:$L$3,1,MATCH(N14,E14:L14,0)),"")) -> C05
A15: P12 | B15: Доверие | C15: Есть прозрачные контакты, реквизиты, команда или сведения о поставщике | D15: 3 | E15: 2 | F15: 3 | G15: 3 | H15: – | I15: 3 | J15: – | K15: – | L15: – | M15: =IFERROR(AVERAGE(E15:L15),"") -> 2.75 | N15: =IFERROR(MAX(E15:L15),"") -> 3 | O15: =IF(N15="","",IFERROR(INDEX($E$3:$L$3,1,MATCH(N15,E15:L15,0)),"")) -> C02
A16: P13 | B16: Интерфейс | C16: Путь пользователя к покупке/регистрации короткий и понятный | D16: 5 | E16: 4 | F16: 5 | G16: 5 | H16: 5 | I16: 5 | J16: 5 | K16: 5 | L16: 5 | M16: =IFERROR(AVERAGE(E16:L16),"") -> 4.875 | N16: =IFERROR(MAX(E16:L16),"") -> 5 | O16: =IF(N16="","",IFERROR(INDEX($E$3:$L$3,1,MATCH(N16,E16:L16,0)),"")) -> C02
A17: P14 | B17: Интерфейс | C17: Призыв к действию соответствует стадии выбора: узнать, попробовать, купить, запросить демо | D17: 4 | E17: 3 | F17: 3 | G17: 5 | H17: 5 | I17: 4 | J17: 5 | K17: 5 | L17: 4 | M17: =IFERROR(AVERAGE(E17:L17),"") -> 4.25 | N17: =IFERROR(MAX(E17:L17),"") -> 5 | O17: =IF(N17="","",IFERROR(INDEX($E$3:$L$3,1,MATCH(N17,E17:L17,0)),"")) -> C03
A18: P15 | B18: Интерфейс | C18: Навигация помогает понять состав товара без лишнего поиска | D18: 4 | E18: 3 | F18: 4 | G18: 4 | H18: 4 | I18: 4 | J18: 4 | K18: 4 | L18: 4 | M18: =IFERROR(AVERAGE(E18:L18),"") -> 3.875 | N18: =IFERROR(MAX(E18:L18),"") -> 4 | O18: =IF(N18="","",IFERROR(INDEX($E$3:$L$3,1,MATCH(N18,E18:L18,0)),"")) -> C02
A19: P16 | B19: Тарифы и оплата | C19: Цена, состав тарифа и ограничения раскрыты ясно | D19: 5 | E19: 4 | F19: 3 | G19: 5 | H19: 5 | I19: 4 | J19: 5 | K19: 5 | L19: 5 | M19: =IFERROR(AVERAGE(E19:L19),"") -> 4.5 | N19: =IFERROR(MAX(E19:L19),"") -> 5 | O19: =IF(N19="","",IFERROR(INDEX($E$3:$L$3,1,MATCH(N19,E19:L19,0)),"")) -> C03
A20: P17 | B20: Тарифы и оплата | C20: Оплата, возврат, пробный период или условия подключения объяснены без неопределенности | D20: 4 | E20: 2 | F20: 1 | G20: 4 | H20: 4 | I20: 2 | J20: 5 | K20: 4 | L20: 4 | M20: =IFERROR(AVERAGE(E20:L20),"") -> 3.25 | N20: =IFERROR(MAX(E20:L20),"") -> 5 | O20: =IF(N20="","",IFERROR(INDEX($E$3:$L$3,1,MATCH(N20,E20:L20,0)),"")) -> C06
A21: P18 | B21: Сопровождение | C21: Поддержка и обучение встроены в товарное предложение | D21: 3 | E21: 2 | F21: 2 | G21: 4 | H21: 3 | I21: 3 | J21: 4 | K21: 3 | L21: 4 | M21: =IFERROR(AVERAGE(E21:L21),"") -> 3.125 | N21: =IFERROR(MAX(E21:L21),"") -> 4 | O21: =IF(N21="","",IFERROR(INDEX($E$3:$L$3,1,MATCH(N21,E21:L21,0)),"")) -> C03
A22: P19 | B22: Сопровождение | C22: Есть база знаний, вопросы и ответы, инструкции или документация | D22: 3 | E22: 5 | F22: 5 | G22: 5 | H22: – | I22: 4 | J22: 4 | K22: 4 | L22: – | M22: =IFERROR(AVERAGE(E22:L22),"") -> 4.5 | N22: =IFERROR(MAX(E22:L22),"") -> 5 | O22: =IF(N22="","",IFERROR(INDEX($E$3:$L$3,1,MATCH(N22,E22:L22,0)),"")) -> C01
A23: P20 | B23: Расширение товара | C23: Есть персонализация, рекомендации, интеграции, автоматизация или аналитика | D23: 4 | E23: 4 | F23: 5 | G23: 5 | H23: 5 | I23: 5 | J23: 5 | K23: 5 | L23: 4 | M23: =IFERROR(AVERAGE(E23:L23),"") -> 4.75 | N23: =IFERROR(MAX(E23:L23),"") -> 5 | O23: =IF(N23="","",IFERROR(INDEX($E$3:$L$3,1,MATCH(N23,E23:L23,0)),"")) -> C02
A24: P21 | B24: Расширение товара | C24: Есть признаки будущего развития товара: дорожная карта, обновления, новые функции | D24: 3 | E24: 3 | F24: 3 | G24: 4 | H24: 3 | I24: – | J24: 4 | K24: 4 | L24: 3 | M24: =IFERROR(AVERAGE(E24:L24),"") -> 3.4285714 | N24: =IFERROR(MAX(E24:L24),"") -> 4 | O24: =IF(N24="","",IFERROR(INDEX($E$3:$L$3,1,MATCH(N24,E24:L24,0)),"")) -> C03
A25: P22 | B25: Дифференциация | C25: Есть уникальные или редкие товарные признаки | D25: 5 | E25: 3 | F25: 3 | G25: 4 | H25: 4 | I25: 4 | J25: 4 | K25: 5 | L25: 3 | M25: =IFERROR(AVERAGE(E25:L25),"") -> 3.75 | N25: =IFERROR(MAX(E25:L25),"") -> 5 | O25: =IF(N25="","",IFERROR(INDEX($E$3:$L$3,1,MATCH(N25,E25:L25,0)),"")) -> C07
A26: P23 | B26: Дифференциация | C26: Отличия хорошо объяснены через пользовательскую ценность | D26: 5 | E26: 2 | F26: 2 | G26: 4 | H26: 4 | I26: 4 | J26: 4 | K26: 4 | L26: 4 | M26: =IFERROR(AVERAGE(E26:L26),"") -> 3.5 | N26: =IFERROR(MAX(E26:L26),"") -> 4 | O26: =IF(N26="","",IFERROR(INDEX($E$3:$L$3,1,MATCH(N26,E26:L26,0)),"")) -> C03
A27: P24 | B27: Рыночный стандарт | C27: На сайте закрыты обязательные требования категории | D27: 5 | E27: 4 | F27: 4 | G27: 5 | H27: 4 | I27: 5 | J27: 5 | K27: 4 | L27: 3 | M27: =IFERROR(AVERAGE(E27:L27),"") -> 4.25 | N27: =IFERROR(MAX(E27:L27),"") -> 5 | O27: =IF(N27="","",IFERROR(INDEX($E$3:$L$3,1,MATCH(N27,E27:L27,0)),"")) -> C03
A28: P25 | B28: Рыночный стандарт | C28: Предложение не уступает большинству конкурентов по базовым ожиданиям | D28: 5 | E28: 4 | F28: 4 | G28: 5 | H28: 4 | I28: 5 | J28: 5 | K28: 4 | L28: 4 | M28: =IFERROR(AVERAGE(E28:L28),"") -> 4.375 | N28: =IFERROR(MAX(E28:L28),"") -> 5 | O28: =IF(N28="","",IFERROR(INDEX($E$3:$L$3,1,MATCH(N28,E28:L28,0)),"")) -> C03
A29: Итоговый взвешенный балл | E29: =IFERROR(ROUND(SUMPRODUCT($D$4:$D$28,E$4:E$28)/SUMIF(E$4:E$28,">=0",$D$4:$D$28),2),"") -> 3.28 | F29: =IFERROR(ROUND(SUMPRODUCT($D$4:$D$28,F$4:F$28)/SUMIF(F$4:F$28,">=0",$D$4:$D$28),2),"") -> 3.35 | G29: =IFERROR(ROUND(SUMPRODUCT($D$4:$D$28,G$4:G$28)/SUMIF(G$4:G$28,">=0",$D$4:$D$28),2),"") -> 4.48 | H29: =IFERROR(ROUND(SUMPRODUCT($D$4:$D$28,H$4:H$28)/SUMIF(H$4:H$28,">=0",$D$4:$D$28),2),"") -> 4.26 | I29: =IFERROR(ROUND(SUMPRODUCT($D$4:$D$28,I$4:I$28)/SUMIF(I$4:I$28,">=0",$D$4:$D$28),2),"") -> 4.01 | J29: =IFERROR(ROUND(SUMPRODUCT($D$4:$D$28,J$4:J$28)/SUMIF(J$4:J$28,">=0",$D$4:$D$28),2),"") -> 4.64 | K29: =IFERROR(ROUND(SUMPRODUCT($D$4:$D$28,K$4:K$28)/SUMIF(K$4:K$28,">=0",$D$4:$D$28),2),"") -> 4.46 | L29: =IFERROR(ROUND(SUMPRODUCT($D$4:$D$28,L$4:L$28)/SUMIF(L$4:L$28,">=0",$D$4:$D$28),2),"") -> 4.05
A30: Интерпретация | E30: =IF(E29="","",IF(E29>=4.2,"Лидерский уровень",IF(E29>=3.5,"Сильный уровень",IF(E29>=2.5,"Средний уровень","Слабый уровень")))) -> Средний уровень | F30: =IF(F29="","",IF(F29>=4.2,"Лидерский уровень",IF(F29>=3.5,"Сильный уровень",IF(F29>=2.5,"Средний уровень","Слабый уровень")))) -> Средний уровень | G30: =IF(G29="","",IF(G29>=4.2,"Лидерский уровень",IF(G29>=3.5,"Сильный уровень",IF(G29>=2.5,"Средний уровень","Слабый уровень")))) -> Лидерский уровень | H30: =IF(H29="","",IF(H29>=4.2,"Лидерский уровень",IF(H29>=3.5,"Сильный уровень",IF(H29>=2.5,"Средний уровень","Слабый уровень")))) -> Лидерский уровень | I30: =IF(I29="","",IF(I29>=4.2,"Лидерский уровень",IF(I29>=3.5,"Сильный уровень",IF(I29>=2.5,"Средний уровень","Слабый уровень")))) -> Сильный уровень | J30: =IF(J29="","",IF(J29>=4.2,"Лидерский уровень",IF(J29>=3.5,"Сильный уровень",IF(J29>=2.5,"Средний уровень","Слабый уровень")))) -> Лидерский уровень | K30: =IF(K29="","",IF(K29>=4.2,"Лидерский уровень",IF(K29>=3.5,"Сильный уровень",IF(K29>=2.5,"Средний уровень","Слабый уровень")))) -> Лидерский уровень | L30: =IF(L29="","",IF(L29>=4.2,"Лидерский уровень",IF(L29>=3.5,"Сильный уровень",IF(L29>=2.5,"Средний уровень","Слабый уровень")))) -> Сильный уровень

Sheet 07_Стандарт_рынка
A1: 07. Определение рыночного стандарта
A2: Лист позволяет отделить обязательную норму рынка от зон дифференциации и спорных признаков
A3: ID признака | B3: Признак / требование | C3: Источник | D3: Уровень Левитта | E3: Категория Кано | F3: Кол-во конкурентов | G3: Доля конкурентов | H3: Средняя сила 0–5 | I3: Статус | J3: Минимальная формулировка стандарта | K3: Что проверить дополнительно | L3: Комментарий
A4: S001 | B4: Описание диаграммы текстом (DSL) | C4: Главные страницы PlantUML, Mermaid, Mermaid Chart; «Diagram-as-code» в тарифе Free Eraser; «Diagram as code» на lucid.co/lucidchart | D4: 2. Родовой товар | E4: Обязательное | F4: 5 | G4: =IF(F4="","",IFERROR(F4/MAX(1,COUNTIF('01_Конкуренты'!$B$4:$B$11,"?*")),"")) -> 0.625 | H4: 5 | I4: =IF(B4="","",IF(OR(E4="Обязательное",E4="Линейное"),IF(G4>=0.6,"Рыночный стандарт",IF(G4>=0.35,"Формирующаяся норма","Проверить необходимость")),IF(E4="Привлекательное",IF(G4<0.5,"Зона дифференциации","Переходит в ожидаемое"),IF(E4="Безразличное","Низкий приоритет",IF(E4="Обратное","Риск отторжения","Требует проверки"))))) -> Рыночный стандарт | J4: Признак есть у 5 из 8 конкурентов; входит в минимальный состав товара | K4: Подтвердить реализацию в продуктах конкурентов, а не только на сайтах | L4: Признак есть у 5 из 8 конкурентов (просмотр 01.10.2026)
A5: S002 | B5: Бесплатный доступ или Free-тариф | C5: Открытый код или тариф Free на страницах 8 из 8 конкурентов | D5: 3. Ожидаемый товар | E5: Обязательное | F5: 8 | G5: =IF(F5="","",IFERROR(F5/MAX(1,COUNTIF('01_Конкуренты'!$B$4:$B$11,"?*")),"")) -> 1 | H5: 5 | I5: =IF(B5="","",IF(OR(E5="Обязательное",E5="Линейное"),IF(G5>=0.6,"Рыночный стандарт",IF(G5>=0.35,"Формирующаяся норма","Проверить необходимость")),IF(E5="Привлекательное",IF(G5<0.5,"Зона дифференциации","Переходит в ожидаемое"),IF(E5="Безразличное","Низкий приоритет",IF(E5="Обратное","Риск отторжения","Требует проверки"))))) -> Рыночный стандарт | J5: Признак есть у 8 из 8 конкурентов; входит в минимальный состав товара | K5: Подтвердить реализацию в продуктах конкурентов, а не только на сайтах | L5: Признак есть у 8 из 8 конкурентов (просмотр 01.10.2026)
A6: S003 | B6: Платная подписка по тарифным уровням | C6: Страницы тарифов Mermaid Chart, Storm, Lucidchart, Eraser, Whimsical | D6: 3. Ожидаемый товар | E6: Линейное | F6: 5 | G6: =IF(F6="","",IFERROR(F6/MAX(1,COUNTIF('01_Конкуренты'!$B$4:$B$11,"?*")),"")) -> 0.625 | H6: 5 | I6: =IF(B6="","",IF(OR(E6="Обязательное",E6="Линейное"),IF(G6>=0.6,"Рыночный стандарт",IF(G6>=0.35,"Формирующаяся норма","Проверить необходимость")),IF(E6="Привлекательное",IF(G6<0.5,"Зона дифференциации","Переходит в ожидаемое"),IF(E6="Безразличное","Низкий приоритет",IF(E6="Обратное","Риск отторжения","Требует проверки"))))) -> Рыночный стандарт | J6: Признак есть у 5 из 8 конкурентов; реализовать на уровне рынка | K6: Подтвердить реализацию в продуктах конкурентов, а не только на сайтах | L6: Признак есть у 5 из 8 конкурентов (просмотр 01.10.2026)
A7: S004 | B7: Открытая страница тарифов | C7: Страницы тарифов (01.10.2026) | D7: 3. Ожидаемый товар | E7: Обязательное | F7: 5 | G7: =IF(F7="","",IFERROR(F7/MAX(1,COUNTIF('01_Конкуренты'!$B$4:$B$11,"?*")),"")) -> 0.625 | H7: 5 | I7: =IF(B7="","",IF(OR(E7="Обязательное",E7="Линейное"),IF(G7>=0.6,"Рыночный стандарт",IF(G7>=0.35,"Формирующаяся норма","Проверить необходимость")),IF(E7="Привлекательное",IF(G7<0.5,"Зона дифференциации","Переходит в ожидаемое"),IF(E7="Безразличное","Низкий приоритет",IF(E7="Обратное","Риск отторжения","Требует проверки"))))) -> Рыночный стандарт | J7: Признак есть у 5 из 8 конкурентов; входит в минимальный состав товара | K7: Подтвердить реализацию в продуктах конкурентов, а не только на сайтах | L7: Признак есть у 5 из 8 конкурентов (просмотр 01.10.2026)
A8: S005 | B8: Корпоративный тариф (Enterprise или on-prem) | C8: Enterprise по запросу на страницах тарифов; Storm: on-prem от 990 тыс. руб. в год | D8: 4. Расширенный товар | E8: Безразличное | F8: 4 | G8: =IF(F8="","",IFERROR(F8/MAX(1,COUNTIF('01_Конкуренты'!$B$4:$B$11,"?*")),"")) -> 0.5 | H8: 5 | I8: =IF(B8="","",IF(OR(E8="Обязательное",E8="Линейное"),IF(G8>=0.6,"Рыночный стандарт",IF(G8>=0.35,"Формирующаяся норма","Проверить необходимость")),IF(E8="Привлекательное",IF(G8<0.5,"Зона дифференциации","Переходит в ожидаемое"),IF(E8="Безразличное","Низкий приоритет",IF(E8="Обратное","Риск отторжения","Требует проверки"))))) -> Низкий приоритет | J8: Признак есть у 4 из 8 конкурентов; не приоритет | K8: Пересмотреть при росте распространенности признака | L8: Признак есть у 4 из 8 конкурентов (просмотр 01.10.2026)
A9: S006 | B9: Скидка или цена при годовой оплате | C9: Цены «billed annually» (Mermaid Chart, Lucidchart, Eraser), скидка 20 % (Storm) | D9: 3. Ожидаемый товар | E9: Линейное | F9: 4 | G9: =IF(F9="","",IFERROR(F9/MAX(1,COUNTIF('01_Конкуренты'!$B$4:$B$11,"?*")),"")) -> 0.5 | H9: 5 | I9: =IF(B9="","",IF(OR(E9="Обязательное",E9="Линейное"),IF(G9>=0.6,"Рыночный стандарт",IF(G9>=0.35,"Формирующаяся норма","Проверить необходимость")),IF(E9="Привлекательное",IF(G9<0.5,"Зона дифференциации","Переходит в ожидаемое"),IF(E9="Безразличное","Низкий приоритет",IF(E9="Обратное","Риск отторжения","Требует проверки"))))) -> Формирующаяся норма | J9: Признак есть у 4 из 8 конкурентов; реализовать на уровне рынка | K9: Отследить динамику распространенности признака | L9: Признак есть у 4 из 8 конкурентов (просмотр 01.10.2026)
A10: S007 | B10: Пробный период платного тарифа | C10: FAQ Lucidchart: пробный период 7 дней | D10: 3. Ожидаемый товар | E10: Безразличное | F10: 1 | G10: =IF(F10="","",IFERROR(F10/MAX(1,COUNTIF('01_Конкуренты'!$B$4:$B$11,"?*")),"")) -> 0.125 | H10: 5 | I10: =IF(B10="","",IF(OR(E10="Обязательное",E10="Линейное"),IF(G10>=0.6,"Рыночный стандарт",IF(G10>=0.35,"Формирующаяся норма","Проверить необходимость")),IF(E10="Привлекательное",IF(G10<0.5,"Зона дифференциации","Переходит в ожидаемое"),IF(E10="Безразличное","Низкий приоритет",IF(E10="Обратное","Риск отторжения","Требует проверки"))))) -> Низкий приоритет | J10: Признак есть у 1 из 8 конкурентов; не приоритет | K10: Пересмотреть при росте распространенности признака | L10: Признак есть у 1 из 8 конкурентов (просмотр 01.10.2026)
A11: S008 | B11: Бесплатные гости или зрители | C11: Unlimited viewer seats (Mermaid Chart Premium); 100 гостей на участника (Storm); unlimited guests (Eraser, Whimsical) | D11: 4. Расширенный товар | E11: Привлекательное | F11: 4 | G11: =IF(F11="","",IFERROR(F11/MAX(1,COUNTIF('01_Конкуренты'!$B$4:$B$11,"?*")),"")) -> 0.5 | H11: 5 | I11: =IF(B11="","",IF(OR(E11="Обязательное",E11="Линейное"),IF(G11>=0.6,"Рыночный стандарт",IF(G11>=0.35,"Формирующаяся норма","Проверить необходимость")),IF(E11="Привлекательное",IF(G11<0.5,"Зона дифференциации","Переходит в ожидаемое"),IF(E11="Безразличное","Низкий приоритет",IF(E11="Обратное","Риск отторжения","Требует проверки"))))) -> Переходит в ожидаемое | J11: Признак есть у 4 из 8 конкурентов; кандидат на дифференциацию | K11: Оценить готовность пользователей платить за признак | L11: Признак есть у 4 из 8 конкурентов (просмотр 01.10.2026)
A12: S009 | B12: ИИ-генерация или ИИ-помощник | C12: ИИ-кредиты (Mermaid Chart); ИИ-ассистент (Storm); Lucid AI; Eraser AI; ИИ в Whimsical | D12: 4. Расширенный товар | E12: Привлекательное | F12: 5 | G12: =IF(F12="","",IFERROR(F12/MAX(1,COUNTIF('01_Конкуренты'!$B$4:$B$11,"?*")),"")) -> 0.625 | H12: 5 | I12: =IF(B12="","",IF(OR(E12="Обязательное",E12="Линейное"),IF(G12>=0.6,"Рыночный стандарт",IF(G12>=0.35,"Формирующаяся норма","Проверить необходимость")),IF(E12="Привлекательное",IF(G12<0.5,"Зона дифференциации","Переходит в ожидаемое"),IF(E12="Безразличное","Низкий приоритет",IF(E12="Обратное","Риск отторжения","Требует проверки"))))) -> Переходит в ожидаемое | J12: Признак есть у 5 из 8 конкурентов; кандидат на дифференциацию | K12: Оценить готовность пользователей платить за признак | L12: Признак есть у 5 из 8 конкурентов (просмотр 01.10.2026)
A13: S010 | B13: Интеграции с другими сервисами | C13: Разделы и упоминания интеграций на страницах 8 из 8 конкурентов | D13: 3. Ожидаемый товар | E13: Линейное | F13: 8 | G13: =IF(F13="","",IFERROR(F13/MAX(1,COUNTIF('01_Конкуренты'!$B$4:$B$11,"?*")),"")) -> 1 | H13: 3.33 | I13: =IF(B13="","",IF(OR(E13="Обязательное",E13="Линейное"),IF(G13>=0.6,"Рыночный стандарт",IF(G13>=0.35,"Формирующаяся норма","Проверить необходимость")),IF(E13="Привлекательное",IF(G13<0.5,"Зона дифференциации","Переходит в ожидаемое"),IF(E13="Безразличное","Низкий приоритет",IF(E13="Обратное","Риск отторжения","Требует проверки"))))) -> Рыночный стандарт | J13: Признак есть у 8 из 8 конкурентов; реализовать на уровне рынка | K13: Подтвердить реализацию в продуктах конкурентов, а не только на сайтах | L13: Признак есть у 8 из 8 конкурентов (просмотр 01.10.2026)
A14: S011 | B14: API или платформа разработчика | C14: API Mermaid; пункт API в меню Mermaid Chart; API в Enterprise Storm; Developer platform Lucidchart; API calls Eraser | D14: 4. Расширенный товар | E14: Привлекательное | F14: 5 | G14: =IF(F14="","",IFERROR(F14/MAX(1,COUNTIF('01_Конкуренты'!$B$4:$B$11,"?*")),"")) -> 0.625 | H14: 5 | I14: =IF(B14="","",IF(OR(E14="Обязательное",E14="Линейное"),IF(G14>=0.6,"Рыночный стандарт",IF(G14>=0.35,"Формирующаяся норма","Проверить необходимость")),IF(E14="Привлекательное",IF(G14<0.5,"Зона дифференциации","Переходит в ожидаемое"),IF(E14="Безразличное","Низкий приоритет",IF(E14="Обратное","Риск отторжения","Требует проверки"))))) -> Переходит в ожидаемое | J14: Признак есть у 5 из 8 конкурентов; кандидат на дифференциацию | K14: Оценить готовность пользователей платить за признак | L14: Признак есть у 5 из 8 конкурентов (просмотр 01.10.2026)
A15: S012 | B15: Открытый код и сообщество | C15: GitHub API, 30.09.2026; лицензия Apache 2.0 у draw.io | D15: 4. Расширенный товар | E15: Привлекательное | F15: 3 | G15: =IF(F15="","",IFERROR(F15/MAX(1,COUNTIF('01_Конкуренты'!$B$4:$B$11,"?*")),"")) -> 0.375 | H15: 3.33 | I15: =IF(B15="","",IF(OR(E15="Обязательное",E15="Линейное"),IF(G15>=0.6,"Рыночный стандарт",IF(G15>=0.35,"Формирующаяся норма","Проверить необходимость")),IF(E15="Привлекательное",IF(G15<0.5,"Зона дифференциации","Переходит в ожидаемое"),IF(E15="Безразличное","Низкий приоритет",IF(E15="Обратное","Риск отторжения","Требует проверки"))))) -> Зона дифференциации | J15: Признак есть у 3 из 8 конкурентов; кандидат на дифференциацию | K15: Проверить спрос и стоимость реализации признака | L15: Признак есть у 3 из 8 конкурентов (просмотр 01.10.2026)
... A32: S029 | B32: Признаки развития (ИИ-помощник, MCP, новые функции) | C32: MCP-интеграция (Storm); метки NEW: Lucid AI, Developer platform (Lucidchart); ИИ-кредиты (Mermaid Chart); AI-first (Eraser) | D32: 5. Потенциальный товар | E32: Привлекательное | F32: 4 | G32: =IF(F32="","",IFERROR(F32/MAX(1,COUNTIF('01_Конкуренты'!$B$4:$B$11,"?*")),"")) -> 0.5 | H32: 3.33 | I32: =IF(B32="","",IF(OR(E32="Обязательное",E32="Линейное"),IF(G32>=0.6,"Рыночный стандарт",IF(G32>=0.35,"Формирующаяся норма","Проверить необходимость")),IF(E32="Привлекательное",IF(G32<0.5,"Зона дифференциации","Переходит в ожидаемое"),IF(E32="Безразличное","Низкий приоритет",IF(E32="Обратное","Риск отторжения","Требует проверки"))))) -> Переходит в ожидаемое | J32: Признак есть у 4 из 8 конкурентов; кандидат на дифференциацию | K32: Оценить готовность пользователей платить за признак | L32: Признак есть у 4 из 8 конкурентов (просмотр 01.10.2026)

Sheet 08_Преимущества
A1: 08. Выявление конкурентных преимуществ по товару
A2: Преимущество фиксируется только при наличии доказательства с сайта, пользовательской ценности и отличия от среднего рынка
A3: ID | B3: ID конкурента | C3: Признак преимущества | D3: Доказательство / URL | E3: Уровень Левитта | F3: Категория Кано | G3: Тип преимущества | H3: Редкость 1–5 | I3: Сила 1–5 | J3: Пользовательская ценность 1–5 | K3: Качество доказательства 1–5 | L3: Индекс преимущества | M3: Вывод | N3: Как использовать для своего товара
A4: A001 | B4: C07 | C4: ИИ-генерация и diagram-as-code в одном продукте | D4: «AI for diagrams that matter»; тариф Free включает diagram-as-code и 3 ИИ-диаграммы (eraser.io, 01.10.2026) | E4: 4. Расширенный товар | F4: Привлекательное | G4: Функциональное | H4: 4 | I4: 5 | J4: 4 | K4: 5 | L4: =IF(OR(H4="",I4="",J4="",K4=""),"",ROUND(H4*0.25+I4*0.25+J4*0.3+K4*0.2,2)) -> 4.45 | M4: =IF(L4="","",IF(L4>=4.2,"Сильное преимущество",IF(L4>=3.4,"Потенциальное преимущество",IF(L4>=2.5,"Слабое преимущество","Не считать преимуществом")))) -> Сильное преимущество | N4: Использовать как ориентир при формулировании ценностного предложения
A5: A002 | B5: C04 | C5: Девять модулей процессного управления и русскоязычный рынок с тарифами в рублях | D5: stormbpmn.com и /pricing, 01.10.2026; Россия 62,99 % трафика | E5: 4. Расширенный товар | F5: Привлекательное | G5: Интеграционное | H5: 5 | I5: 4 | J5: 4 | K5: 5 | L5: =IF(OR(H5="",I5="",J5="",K5=""),"",ROUND(H5*0.25+I5*0.25+J5*0.3+K5*0.2,2)) -> 4.45 | M5: =IF(L5="","",IF(L5>=4.2,"Сильное преимущество",IF(L5>=3.4,"Потенциальное преимущество",IF(L5>=2.5,"Слабое преимущество","Не считать преимуществом")))) -> Сильное преимущество | N5: Использовать как ориентир при формулировании ценностного предложения
A6: A003 | B6: C06 | C6: Глубина товара и масштаб: 100 шаблонов в Free, Visio import, SAML, Fortune 500 | D6: lucid.app/pricing/lucidchart и lucid.co/lucidchart, 01.10.2026 | E6: 4. Расширенный товар | F6: Линейное | G6: Доверительное | H6: 2 | I6: 5 | J6: 4 | K6: 5 | L6: =IF(OR(H6="",I6="",J6="",K6=""),"",ROUND(H6*0.25+I6*0.25+J6*0.3+K6*0.2,2)) -> 3.95 | M6: =IF(L6="","",IF(L6>=4.2,"Сильное преимущество",IF(L6>=3.4,"Потенциальное преимущество",IF(L6>=2.5,"Слабое преимущество","Не считать преимуществом")))) -> Потенциальное преимущество | N6: Учесть при развитии продукта после выпуска минимальной версии
A7: A004 | B7: C05 | C7: Бесплатное приложение без enterprise-тарифа, privacy-first, 100M+ пользователей | D7: drawio.com, 01.10.2026; GitHub (ЛР4) | E7: 3. Ожидаемый товар | F7: Привлекательное | G7: Экономическое | H7: 3 | I7: 5 | J7: 5 | K7: 4 | L7: =IF(OR(H7="",I7="",J7="",K7=""),"",ROUND(H7*0.25+I7*0.25+J7*0.3+K7*0.2,2)) -> 4.3 | M7: =IF(L7="","",IF(L7>=4.2,"Сильное преимущество",IF(L7>=3.4,"Потенциальное преимущество",IF(L7>=2.5,"Слабое преимущество","Не считать преимуществом")))) -> Сильное преимущество | N7: Использовать как ориентир при формулировании ценностного предложения
A8: A005 | B8: C02 | C8: Открытая экосистема интеграций и крупнейшее сообщество (90 489 звезд) | D8: mermaid.js.org/ecosystem; GitHub (ЛР4) | E8: 4. Расширенный товар | F8: Привлекательное | G8: Сетевой эффект | H8: 3 | I8: 5 | J8: 4 | K8: 5 | L8: =IF(OR(H8="",I8="",J8="",K8=""),"",ROUND(H8*0.25+I8*0.25+J8*0.3+K8*0.2,2)) -> 4.2 | M8: =IF(L8="","",IF(L8>=4.2,"Сильное преимущество",IF(L8>=3.4,"Потенциальное преимущество",IF(L8>=2.5,"Слабое преимущество","Не считать преимуществом")))) -> Сильное преимущество | N8: Использовать как ориентир при формулировании ценностного предложения
A9: A006 | B9: C01 | C9: Широкий набор UML-диаграмм и запуск на собственном сервере | D9: plantuml.com/running и /class-diagram, 01.10.2026 | E9: 2. Родовой товар | F9: Обязательное | G9: Функциональное | H9: 3 | I9: 4 | J9: 4 | K9: 4 | L9: =IF(OR(H9="",I9="",J9="",K9=""),"",ROUND(H9*0.25+I9*0.25+J9*0.3+K9*0.2,2)) -> 3.75 | M9: =IF(L9="","",IF(L9>=4.2,"Сильное преимущество",IF(L9>=3.4,"Потенциальное преимущество",IF(L9>=2.5,"Слабое преимущество","Не считать преимуществом")))) -> Потенциальное преимущество | N9: Учесть при развитии продукта после выпуска минимальной версии
A10: A007 | B10: C03 | C10: Прозрачные тарифы и зрители без оплаты в Premium | D10: mermaid.ai/pricing, 01.10.2026 | E10: 3. Ожидаемый товар | F10: Привлекательное | G10: Экономическое | H10: 3 | I10: 4 | J10: 4 | K10: 5 | L10: =IF(OR(H10="",I10="",J10="",K10=""),"",ROUND(H10*0.25+I10*0.25+J10*0.3+K10*0.2,2)) -> 3.95 | M10: =IF(L10="","",IF(L10>=4.2,"Сильное преимущество",IF(L10>=3.4,"Потенциальное преимущество",IF(L10>=2.5,"Слабое преимущество","Не считать преимуществом")))) -> Потенциальное преимущество | N10: Учесть при развитии продукта после выпуска минимальной версии
A11: A008 | B11: C08 | C11: Неограниченные гости и зрители на всех тарифах | D11: whimsical.com/pricing, 01.10.2026 | E11: 4. Расширенный товар | F11: Привлекательное | G11: Экономическое | H11: 3 | I11: 3 | J11: 3 | K11: 5 | L11: =IF(OR(H11="",I11="",J11="",K11=""),"",ROUND(H11*0.25+I11*0.25+J11*0.3+K11*0.2,2)) -> 3.4 | M11: =IF(L11="","",IF(L11>=4.2,"Сильное преимущество",IF(L11>=3.4,"Потенциальное преимущество",IF(L11>=2.5,"Слабое преимущество","Не считать преимуществом")))) -> Потенциальное преимущество | N11: Учесть при развитии продукта после выпуска минимальной версии

Sheet 09_Дашборд
A1: 09. Дашборд анализа цифрового товара
A2: Сводные показатели обновляются после заполнения листов. Используйте лист для контроля полноты анализа и обсуждения итоговых выводов
A4: Показатель | B4: Значение | C4: Норма контроля | D4: Комментарий | F4: Категория Кано | G4: Количество | H4: Доля | J4: Уровень Левитта | K4: Кол-во признаков | L4: Средняя оценка
A5: Конкурентов в анализе | B5: =COUNTIF('01_Конкуренты'!$B$4:$B$11,"?*") -> 8 | C5: 5–12 | D5: Меньше 5 – риск случайных выводов | F5: Обязательное | G5: =COUNTIF('04_Кано'!$E$4:$E$36,F5) -> 7 | H5: =IFERROR(G5/SUM($G$5:$G$10),"") -> 0.21212121 | J5: 1. Базовая выгода | K5: =COUNTIF('03_Левитт'!$D$4:$D$156,J5) -> 8 | L5: =IFERROR(AVERAGEIF('03_Левитт'!$D$4:$D$156,J5,'03_Левитт'!$L$4:$L$156),"") -> 5
A6: Проверенных страниц | B6: =COUNTIF('02_Карта_сайтов'!$C$4:$C$43,"?*") -> 40 | C6: 30+ | D6: Желательно несколько типов страниц по каждому конкуренту | F6: Линейное | G6: =COUNTIF('04_Кано'!$E$4:$E$36,F6) -> 11 | H6: =IFERROR(G6/SUM($G$5:$G$10),"") -> 0.33333333 | J6: 2. Родовой товар | K6: =COUNTIF('03_Левитт'!$D$4:$D$156,J6) -> 13 | L6: =IFERROR(AVERAGEIF('03_Левитт'!$D$4:$D$156,J6,'03_Левитт'!$L$4:$L$156),"") -> 4.2569231
A7: Признаков по Левитту | B7: =COUNTIF('03_Левитт'!$E$4:$E$156,"?*") -> 153 | C7: 40+ | D7: Нужны признаки по всем уровням товара | F7: Привлекательное | G7: =COUNTIF('04_Кано'!$E$4:$E$36,F7) -> 9 | H7: =IFERROR(G7/SUM($G$5:$G$10),"") -> 0.27272727 | J7: 3. Ожидаемый товар | K7: =COUNTIF('03_Левитт'!$D$4:$D$156,J7) -> 63 | L7: =IFERROR(AVERAGEIF('03_Левитт'!$D$4:$D$156,J7,'03_Левитт'!$L$4:$L$156),"") -> 3.8969841
A8: Требований по Кано | B8: =COUNTIF('04_Кано'!$B$4:$B$36,"?*") -> 33 | C8: 25+ | D8: Обязательные и привлекательные признаки должны быть разделены | F8: Безразличное | G8: =COUNTIF('04_Кано'!$E$4:$E$36,F8) -> 4 | H8: =IFERROR(G8/SUM($G$5:$G$10),"") -> 0.12121212 | J8: 4. Расширенный товар | K8: =COUNTIF('03_Левитт'!$D$4:$D$156,J8) -> 65 | L8: =IFERROR(AVERAGEIF('03_Левитт'!$D$4:$D$156,J8,'03_Левитт'!$L$4:$L$156),"") -> 2.7409231
A9: Рыночных стандартов | B9: =COUNTIF('07_Стандарт_рынка'!$I$4:$I$32,"Рыночный стандарт") -> 13 | C9: по факту | D9: Это минимальная планка цифрового товара | F9: Обратное | G9: =COUNTIF('04_Кано'!$E$4:$E$36,F9) -> 0 | H9: =IFERROR(G9/SUM($G$5:$G$10),"") -> 0 | J9: 5. Потенциальный товар | K9: =COUNTIF('03_Левитт'!$D$4:$D$156,J9) -> 4 | L9: =IFERROR(AVERAGEIF('03_Левитт'!$D$4:$D$156,J9,'03_Левитт'!$L$4:$L$156),"") -> 2.5
A10: Зон дифференциации | B10: =COUNTIF('07_Стандарт_рынка'!$I$4:$I$32,"Зона дифференциации") -> 2 | C10: по факту | D10: Это пространство для конкурентного отличия | F10: Неясное | G10: =COUNTIF('04_Кано'!$E$4:$E$36,F10) -> 2 | H10: =IFERROR(G10/SUM($G$5:$G$10),"") -> 0.060606061
A11: Сильных преимуществ | B11: =COUNTIF('08_Преимущества'!$M$4:$M$11,"Сильное преимущество") -> 4 | C11: по факту | D11: Проверять доказательства и воспроизводимость
A14: Итоговые баллы конкурентов
A15: C01 | B15: C02 | C15: C03 | D15: C04 | E15: C05 | F15: C06 | G15: C07 | H15: C08
A16: ='06_Сравнение'!E29 -> 3.28 | B16: ='06_Сравнение'!F29 -> 3.35 | C16: ='06_Сравнение'!G29 -> 4.48 | D16: ='06_Сравнение'!H29 -> 4.26 | E16: ='06_Сравнение'!I29 -> 4.01 | F16: ='06_Сравнение'!J29 -> 4.64 | G16: ='06_Сравнение'!K29 -> 4.46 | H16: ='06_Сравнение'!L29 -> 4.05
A17: ='06_Сравнение'!E30 -> Средний уровень | B17: ='06_Сравнение'!F30 -> Средний уровень | C17: ='06_Сравнение'!G30 -> Лидерский уровень | D17: ='06_Сравнение'!H30 -> Лидерский уровень | E17: ='06_Сравнение'!I30 -> Сильный уровень | F17: ='06_Сравнение'!J30 -> Лидерский уровень | G17: ='06_Сравнение'!K30 -> Лидерский уровень | H17: ='06_Сравнение'!L30 -> Сильный уровень
A20: Итоговые управленческие выводы
A21: 1. Минимальный состав цифрового товара | B21: Минимальный состав: бесплатный доступ (8 из 8), экспорт (8 из 8), интеграции (8 из 8), UML (4 из 8), ERD (6 из 8), документация (6 из 8), открытая страница тарифов (5 из 8)
A22: 2. Признаки, которые нельзя игнорировать | B22: Нельзя игнорировать: Free-тариф, экспорт, понятные тарифы с ценой за пользователя в месяц, документация, ИИ-генерация (5 из 8) и интеграции
A23: 3. Главные зоны дифференциации | B23: Зоны дифференциации NotaCode: IDEF0, DFD и сети Петри на просмотренных сайтах не найдены; полный набор UML, BPMN, ERD найден только у Lucidchart; тарифы в рублях - только у Storm
A24: 4. Лучшие практики конкурентов | B24: Лучшие практики: прозрачные тарифы с ИИ-лимитами (Eraser, Mermaid Chart), шаблоны в бесплатном тарифе (Lucidchart), зрители без оплаты (Whimsical, Mermaid Chart), открытая экосистема (Mermaid)
A25: 5. Риски копирования конкурентов без проверки спроса | B25: Риск: копировать тарифы за пользователя без проверки спроса студентов; цена Pro 40 у.е. в год ниже минимальных тарифов конкурентов (от 9 у.е. в месяц), ее нужно подтвердить опросом

Sheet 99_Справочники
A1: 99. Справочники для заполнения
A2: Лист содержит подсказки по классификациям, используемым в шаблоне
A4: Справочник | B4: Значение | C4: Пояснение
A5: Уровни Левитта | B5: 1. Базовая выгода | C5: Главная задача и ценность для пользователя
A6: Уровни Левитта | B6: 2. Родовой товар | C6: Минимальная форма товара: сервис, приложение, кабинет, база, подписка
A7: Уровни Левитта | B7: 3. Ожидаемый товар | C7: То, что пользователь считает нормой категории
A8: Уровни Левитта | B8: 4. Расширенный товар | C8: Дополнительные элементы, повышающие ценность и доверие
A9: Уровни Левитта | B9: 5. Потенциальный товар | C9: Будущие функции, развитие, интеграции, персонализация, данные
A10: Категории Кано | B10: Обязательное | C10: Отсутствие вызывает неудовлетворенность; наличие обычно воспринимается как норма
A11: Категории Кано | B11: Линейное | C11: Чем лучше реализовано, тем выше удовлетворенность и готовность выбрать товар
A12: Категории Кано | B12: Привлекательное | C12: Не ожидается большинством, но создает положительное отличие
A13: Категории Кано | B13: Безразличное | C13: Слабо влияет на выбор и удовлетворенность
A14: Категории Кано | B14: Обратное | C14: Может снижать удовлетворенность или создавать отторжение
A15: Категории Кано | B15: Неясное | C15: Недостаточно данных для классификации
... A24: Типы преимуществ | B24: Контентное | C24: Качество, глубина, эксклюзивность или регулярность материалов

Sheet 98_Журнал
A1: Журнал рабочей копии: источники, правила, ограничения
A3: Раздел | B3: Код | C3: Содержание
A4: Исправление шаблона | B4: Д-1 | C4: Лист 06_Сравнение, строки 90 и 91 (итоговый балл и интерпретация): формулы столбцов F-L ссылались на столбец E (баллы C01), поэтому итог был одинаковым (3,28) у всех конкурентов. Ссылки заменены на собственные столбцы (E-L); логика формулы сохранена
A5: Исправление шаблона | B5: Д-2 | C5: Лист 06_Сравнение, столбец O (Лидер) в пустых строках P26-P80: MAX пустого диапазона дает 0, MATCH не находит значение, результат #Н/Д. Формула обернута в IFERROR (при пустых баллах - пустая ячейка)
A6: Источники | B6: И-1 | C6: Страницы 8 конкурентов (главные, тарифы, документация, интеграции, шаблоны, безопасность, блог): автоматическое извлечение текста 01.10.2026 (Материалы_собранные/sajty_konkurentov_stranicy_2026-10-01.json) и чтение во встроенном браузере (Lucidchart, тарифы Mermaid Chart); данные ЛР1-ЛР4 от 30.09.2026
A7: Выборка | B7: В-1 | C7: 8 компаний из 22 части A (поле «Переходит в части B и C»). Тип конкурента - итоговый уровень из части A
A8: Правило | B8: П-1 | C8: Признак засчитывается, если он найден на просмотренных страницах; отсутствие на просмотренных страницах не доказывает отсутствия у продукта (значения занижают долю)
A9: Правило | B9: П-2 | C9: Достоверность в 02_Карта_сайтов: 5 - страница прочитана целиком (тарифы, Lucidchart, Mermaid Chart) или данные GitHub API; 4 - автоматическое извлечение текста
A10: Правило | B10: П-3 | C10: 03_Левитт: сила реализации 3, если признак явно описан на странице (цена, тариф, функция), 2 - найден по ключевым словам; понятность 3 для SaaS-сайтов с отдельными разделами, 2 для остальных; влияние на ценность 1-5 - по типу признака
A11: Правило | B11: П-4 | C11: Категории Кано присвоены экспертно (по распространенности и роли признака для студентов и аналитиков ПО); опрос по методу Кано не проводился. Требования без данных помечены «Неясное»
A12: Правило | B12: П-5 | C12: 06_Сравнение: баллы 0-5 по 25 критериям поставлены по просмотренным страницам; пусто - критерий не подтвержден страницами. Итог - взвешенный балл шаблона
A13: Правило | B13: П-6 | C13: 08_Преимущества: редкость, сила, ценность и качество доказательства - экспертные оценки 1-5 по просмотренным страницам и данным ЛР4
A14: Нормы дашборда | B14: К-1 | C14: Страниц: 40 (норма 30+); признаков по Левитту: 153 (норма 40+); требований по Кано: 33 (норма 25+)
... A16: Ограничения | B16: О-1 | C16: Оценки экспертные; страницы просмотрены с одного устройства. Планируется собрать: проверка работы продуктов (проверка правил нотации, импорт форматов), опрос для категорий Кано
