Workbook

Sheet 00_Инструкция
A1: Методика работы с Excel-шаблоном классификации компаний по уровням конкуренции | B1: Методика работы с Excel-шаблоном классификации компаний по уровням конкуренции | C1: Методика работы с Excel-шаблоном классификации компаний по уровням конкуренции | D1: Методика работы с Excel-шаблоном классификации компаний по уровням конкуренции | E1: Методика работы с Excel-шаблоном классификации компаний по уровням конкуренции | F1: Методика работы с Excel-шаблоном классификации компаний по уровням конкуренции | G1: Методика работы с Excel-шаблоном классификации компаний по уровням конкуренции | H1: Методика работы с Excel-шаблоном классификации компаний по уровням конкуренции
A3: Блок | B3: Что делает аналитик | C3: Где заполнять | D3: Результат | E3: Контроль качества | F3: Тип ошибки | G3: Как исправлять | H3: Итог
A4: 1. Формирование списка | B4: Собрать первичный перечень компаний из поиска, отраслевых обзоров, каталогов, рекламы, рекомендаций и найденных на сайтах ссылок | C4: 01_Компании | D4: Единый реестр компаний | E4: У каждой компании есть сайт и краткое описание товара | F4: В список попали нерелевантные компании без объяснения | G4: Оставлять только с пометкой «объект наблюдения» или исключать | H4: Сформирован массив для проверки
A5: 2. Сбор доказательств | B5: По каждой компании фиксировать факты с сайта: продукт, аудитория, цена, сценарии, каналы, доверие, география | C5: 02_Доказательства | D5: Набор проверяемых сигналов | E5: Каждый вывод имеет URL и наблюдаемый факт | F5: Аналитик записывает мнение без факта | G5: Разделять факт и вывод; добавлять ссылку | H5: Создана доказательная база
A6: 3. Оценка по критериям | B6: Присвоить баллы 0–5 по каждому критерию согласно листу 03 | C6: 04_Оценка | D6: Взвешенный балл близости | E6: Оценка не ставится без доказательств | F6: Завышение баллов из-за общего отраслевого сходства | G6: Проверять заменяемость товара и потребительскую задачу | H6: Получена расчетная классификация
A7: 4. Проверка ограничителей | B7: Проверить, не мешает ли низкое совпадение задачи или заменяемости присвоить прямую конкуренцию | C7: 04_Оценка | D7: Автоматическое ограничение уровня | E7: Прямой конкурент невозможен без совпадения задачи и заменяемости | F7: Компания названа прямым конкурентом только из-за известности | G7: Снизить уровень до альтернативы или заменителя | H7: Классификация становится строгой
A8: 5. Экспертная корректировка | B8: При необходимости изменить уровень, но только с письменным обоснованием | C8: 04_Оценка | D8: Итоговый уровень | E8: У корректировки есть причина и ссылка | F8: Корректировка без объяснения | G8: Заполнить обоснование и ключевые ссылки | H8: Получена финальная классификация
A9: 6. Сводный анализ | B9: Оценить распределение компаний по уровням, выделить прямых конкурентов и ближайшие альтернативы | C9: 06_Сводка, 07_Карта | D9: Карта конкурентного окружения | E9: Прямые конкуренты отделены от заменителей и смежных компаний | F9: Все компании смешаны в одну группу | G9: Использовать уровни и зоны карты отдельно | H9: Сформирован список для последующего анализа сайтов, товара и бизнес-модели
A11: Правило | B11: Содержание
A12: Факт важнее предположения | B12: Уровень конкуренции нельзя назначать только по общему впечатлению от компании. Минимальное основание – сайт, страница товара, тарифы, описание сегмента или иной публичный сигнал
A13: Прямой конкурент – это не просто похожая компания | B13: Прямым конкурентом считается только тот, кто решает ту же задачу для близкой аудитории с функционально заменяемым цифровым товаром
A14: Заменитель не равен прямому конкуренту | B14: Если конечная потребность похожа, но способ решения другой, компания относится к косвенной конкуренции или заменителям
A15: Потенциальный конкурент требует сигнала | B15: Недостаточно предположить, что компания может войти в рынок. Нужны признаки: смежные продукты, новые разделы, вакансии, партнерства, дорожная карта, объявления
A16: Экспертная корректировка допустима | B16: Она нужна для спорных случаев, но всегда должна сопровождаться обоснованием и ссылками на доказательства

Sheet 01_Компании
A1: Реестр компаний для классификации по уровням конкуренции | B1: Реестр компаний для классификации по уровням конкуренции | C1: Реестр компаний для классификации по уровням конкуренции | D1: Реестр компаний для классификации по уровням конкуренции | E1: Реестр компаний для классификации по уровням конкуренции | F1: Реестр компаний для классификации по уровням конкуренции | G1: Реестр компаний для классификации по уровням конкуренции | H1: Реестр компаний для классификации по уровням конкуренции | I1: Реестр компаний для классификации по уровням конкуренции | J1: Реестр компаний для классификации по уровням конкуренции | K1: Реестр компаний для классификации по уровням конкуренции | L1: Реестр компаний для классификации по уровням конкуренции | M1: Реестр компаний для классификации по уровням конкуренции
A3: ID | B3: Компания | C3: Сайт | D3: Рынок / страна | E3: Тип компании | F3: Основной цифровой товар | G3: Целевой сегмент | H3: Предварительная гипотеза | I3: Приоритет | J3: Ответственный | K3: Статус | L3: Дата обновления | M3: Комментарий
A4: K001 | B4: PlantUML | C4: plantuml.com | D4: Весь мир (английский язык) | E4: Текстовый DSL, открытый код | F4: Построение UML-диаграмм из текстового описания, экспорт PNG, LaTeX, EPS, SVG | G4: Разработчики, студенты, архитекторы ПО | H4: Прямой конкурент | I4: Высокий | J4: К. А. Хаджинова | K4: В работе | L4: 30.09.2026 | M4: Источник обнаружения: ЛР4 табл. 3 (кандидат 1); ЛР1 табл. 44 (прямой конкурент); Вордстат «plantuml». Переходит в части B и C (одна из семи компаний анализа цифрового товара и бизнес-модели)
A5: K002 | B5: Mermaid (библиотека) | C5: mermaid.js.org | D5: Весь мир (английский язык) | E5: Текстовый DSL, открытый код | F5: Диаграммы и визуализации из текста и кода (JavaScript-библиотека) | G5: Разработчики, авторы технической документации | H5: Прямой конкурент | I5: Высокий | J5: К. А. Хаджинова | K5: В работе | L5: 30.09.2026 | M5: Источник обнаружения: ЛР4 табл. 3 (кандидат 2); ЛР1 табл. 44 (прямой конкурент). Переходит в части B и C (одна из семи компаний анализа цифрового товара и бизнес-модели)
A6: K003 | B6: Mermaid Chart | C6: mermaidchart.com | D6: Весь мир (США, Великобритания, Япония в топ-странах) | E6: Облачный сервис на основе Mermaid | F6: Облачный редактор диаграмм Mermaid с тарифами Free, Plus, Premium | G6: Команды разработки и документации | H6: Прямой конкурент | I6: Высокий | J6: К. А. Хаджинова | K6: В работе | L6: 30.09.2026 | M6: Источник обнаружения: ЛР4 табл. 3 (кандидат 3); ЛР1 табл. 42 (тарифы). Переходит в части B и C (одна из семи компаний анализа цифрового товара и бизнес-модели)
A7: K004 | B7: D2 (Terrastruct) | C7: d2lang.com | D7: Весь мир | E7: Текстовый DSL, открытый код | F7: Язык описания диаграмм D2 и документация | G7: Разработчики, архитекторы ПО | H7: Прямой конкурент | I7: Средний | J7: К. А. Хаджинова | K7: В работе | L7: 30.09.2026 | M7: Источник обнаружения: ЛР4 табл. 3 (кандидат 4)
A8: K005 | B8: Kroki | C8: kroki.io | D8: Весь мир | E8: API отрисовки текстовых диаграмм | F8: Единый API для отрисовки диаграмм из текста (PlantUML, Mermaid, D2 и др.) | G8: Разработчики, интеграторы | H8: Прямой конкурент | I8: Низкий | J8: К. А. Хаджинова | K8: В работе | L8: 30.09.2026 | M8: Источник обнаружения: ЛР4 табл. 3 (кандидат 5); ЛР2-3 (движки рендеринга)
A9: K006 | B9: PlantText | C9: planttext.com | D9: Весь мир (Индонезия, Боливия, Вьетнам в топ-странах) | E9: Онлайн-редактор PlantUML | F9: Онлайн-редактор PlantUML: классовые, последовательностные, деятельностные диаграммы | G9: Студенты, разработчики | H9: Прямой конкурент | I9: Средний | J9: К. А. Хаджинова | K9: В работе | L9: 30.09.2026 | M9: Источник обнаружения: ЛР4 табл. 3 (кандидат 6)
A10: K007 | B10: StarUML | C10: staruml.io | D10: Весь мир | E10: Программа для моделирования UML | F10: Программа визуального моделирования UML | G10: Разработчики, архитекторы ПО | H10: Прямой конкурент | I10: Средний | J10: К. А. Хаджинова | K10: В работе | L10: 30.09.2026 | M10: Источник обнаружения: ЛР4 табл. 3 (кандидат 7); Вордстат «staruml» (16)
A11: K008 | B11: Visual Paradigm | C11: visual-paradigm.com | D11: Весь мир (Индия, Индонезия, Россия в топ-странах) | E11: Платформа UML, BPMN, архитектуры | F11: Универсальная платформа моделирования UML, BPMN, Enterprise Architecture с генеративным ИИ | G11: Аналитики, архитекторы ПО, студенты | H11: Прямой конкурент | I11: Высокий | J11: К. А. Хаджинова | K11: В работе | L11: 30.09.2026 | M11: Источник обнаружения: ЛР4 табл. 3 (кандидат 8); ЛР1 табл. 42, 44
A12: K009 | B12: Sparx Systems (Enterprise Architect) | C12: sparxsystems.com | D12: Весь мир | E12: Корпоративная платформа моделирования | F12: Enterprise Architect (UML, BPMN) | G12: Корпоративные архитекторы | H12: Прямой конкурент | I12: Низкий | J12: К. А. Хаджинова | K12: Требует уточнения | L12: 30.09.2026 | M12: Источник обнаружения: ЛР4 табл. 3 (кандидат 9); ЛР1 табл. 44
A13: K010 | B13: bpmn.io | C13: bpmn.io | D13: Весь мир | E13: Редактор BPMN, открытый код | F13: Веб-инструменты для BPMN, DMN, CMMN и форм (встраиваемые) | G13: Разработчики, аналитики процессов | H13: Косвенный конкурент / заменитель | I13: Средний | J13: К. А. Хаджинова | K13: В работе | L13: 30.09.2026 | M13: Источник обнаружения: ЛР4 табл. 3 (кандидат 10); ЛР1 табл. 44 (частичный заменитель)
... A25: K022 | B25: Microsoft Visio | C25: microsoft.com/visio | D25: Весь мир | E25: Универсальный редактор (подписка) | F25: Редактор диаграмм Microsoft Visio (Plan 1, Plan 2) | G25: Корпоративные аналитики | H25: Косвенный конкурент / заменитель | I25: Средний | J25: К. А. Хаджинова | K25: В работе | L25: 30.09.2026 | M25: Источник обнаружения: ЛР4 табл. 3 (кандидат 21); ЛР1 табл. 42, 44; Вордстат «visio» (1501)

Sheet 02_Доказательства
A1: Доказательства и сигналы с сайтов конкурентов | B1: Доказательства и сигналы с сайтов конкурентов | C1: Доказательства и сигналы с сайтов конкурентов | D1: Доказательства и сигналы с сайтов конкурентов | E1: Доказательства и сигналы с сайтов конкурентов | F1: Доказательства и сигналы с сайтов конкурентов | G1: Доказательства и сигналы с сайтов конкурентов | H1: Доказательства и сигналы с сайтов конкурентов | I1: Доказательства и сигналы с сайтов конкурентов | J1: Доказательства и сигналы с сайтов конкурентов | K1: Доказательства и сигналы с сайтов конкурентов | L1: Доказательства и сигналы с сайтов конкурентов
A3: ID компании | B3: Компания | C3: Раздел сайта | D3: URL | E3: Наблюдаемый факт | F3: Тип сигнала | G3: Сила сигнала 1–5 | H3: Дата фиксации | I3: Вывод для классификации | J3: Достоверность 1–5 | K3: Скриншот / архив | L3: Комментарий
A4: K001 | B4: =IFERROR(INDEX('01_Компании'!$B$4:$B$25,MATCH(A4,'01_Компании'!$A$4:$A$25,0)),"") -> PlantUML | C4: Главная страница (title, description) | D4: https://plantuml.com/ | E4: title: «Open-source tool that uses simple textual descriptions to draw beautiful UML diagrams.»; description: «Easily create beautiful UML Diagrams from simple textual description. There are also numerous kind of available diagrams. It's also possible to export images in PNG, LaTeX, EPS, SVG.» | F4: Цифровой товар | G4: 4 | H4: 30.09.2026 | I4: Главное обещание совпадает с задачей NotaCode: диаграммы UML из текста | J4: 4 | K4: sajty_konkurentov_title_description_2026-09-30.json | L4: метаданные главной страницы, curl 30.09.2026
A5: K001 | B5: =IFERROR(INDEX('01_Компании'!$B$4:$B$25,MATCH(A5,'01_Компании'!$A$4:$A$25,0)),"") -> PlantUML | C5: Similarweb Pro, Website performance | D5: https://pro.similarweb.com/ | E5: 739 657 визитов в месяц; уникальных 325 279; длительность 00:04:00; 3,32 стр. за визит; отказы 45,61 %; окно июнь-август 2026, весь мир | F5: Доверие и зрелость | G5: 3 | H5: 30.09.2026 | I5: Масштаб видимости (оценочная модель, не измерение) | J5: 3 | K5: similarweb_pro_obzor_2026-09-30.csv | L5: пробный доступ Similarweb Pro, снимок 30.09.2026
A6: K001 | B6: =IFERROR(INDEX('01_Компании'!$B$4:$B$25,MATCH(A6,'01_Компании'!$A$4:$A$25,0)),"") -> PlantUML | C6: Similarweb Pro, Marketing channels | D6: https://pro.similarweb.com/ | E6: Прямой 38,11 %; органический поиск 47,25 %; платный поиск нет данных; реферальный 5,91 %; соцсети (орг.) 3,62 % | F6: Каналы продаж | G6: 3 | H6: 30.09.2026 | I6: Структура привлечения; сравнивается с каналами NotaCode (поиск, сообщества, каталоги расширений) | J6: 3 | K6: similarweb_pro_obzor_2026-09-30.csv | L6: Similarweb Pro, 30.09.2026
A7: K001 | B7: =IFERROR(INDEX('01_Компании'!$B$4:$B$25,MATCH(A7,'01_Компании'!$A$4:$A$25,0)),"") -> PlantUML | C7: Similarweb Pro, Geography | D7: https://pro.similarweb.com/ | E7: Топ-5 стран: RU 9.21/ID 6.08/DE 5.61/JP 5.43/US 3.66 | F7: География и язык | G7: 3 | H7: 30.09.2026 | I7: Пересечение с рынком РБ и РФ/СНГ оценивается по наличию RU и BY среди стран | J7: 3 | K7: similarweb_pro_obzor_2026-09-30.csv | L7: Similarweb Pro, 30.09.2026; доля Беларуси недоступна (пробный доступ)
A8: K001 | B8: =IFERROR(INDEX('01_Компании'!$B$4:$B$25,MATCH(A8,'01_Компании'!$A$4:$A$25,0)),"") -> PlantUML | C8: Яндекс Вордстат, Беларусь | D8: https://wordstat.yandex.ru/ | E8: Запрос «plantuml»: 200 запросов в месяц (регион Беларусь, все устройства) | F8: География и язык | G8: 3 | H8: 30.09.2026 | I8: Спрос в РБ по бренду как признак пересечения по каналу выбора | J8: 4 | K8: wordstat_zaprosy_RB_2026-09-30.csv | L8: Вордстат, 30.09.2026
A9: K001 | B9: =IFERROR(INDEX('01_Компании'!$B$4:$B$25,MATCH(A9,'01_Компании'!$A$4:$A$25,0)),"") -> PlantUML | C9: Тарифы и цена | D9: https://plantuml.com/ | E9: открытый код, бесплатно (ЛР1, табл. 42) | F9: Цена и тарифы | G9: 5 | H9: 30.09.2026 | I9: Ценовая логика сопоставляется с Free и Pro 40 у.е. в год (4 у.е. в месяц) у NotaCode | J9: 4 | K9: ЛР1 табл. 42; ЛР2-3 табл. 70 | L9: значения считаны с официальных страниц 30.09.2026 (ЛР1, ЛР2-3)
A10: K001 | B10: =IFERROR(INDEX('01_Компании'!$B$4:$B$25,MATCH(A10,'01_Компании'!$A$4:$A$25,0)),"") -> PlantUML | C10: Отзывы и рейтинги (каталоги) | D10: https://www.g2.com/ ; https://www.capterra.com/ ; https://www.trustpilot.com/review/plantuml.com | E10: оценки расширений: VS Marketplace jebbs.plantuml 4,72 (105), JetBrains plantuml4idea 4,63 (102); G2 и Trustpilot: карточка не найдена | F10: Доверие и зрелость | G10: 3 | H10: 30.09.2026 | I10: Независимые отзывы; тональность может быть смещена | J10: 3 | K10: rev05.csv; trustpilot_reviews_2026-09-30.json; marketplaces.csv | L10: значения считаны 30.09.2026
A11: K001 | B11: =IFERROR(INDEX('01_Компании'!$B$4:$B$25,MATCH(A11,'01_Компании'!$A$4:$A$25,0)),"") -> PlantUML | C11: GitHub (репозиторий) | D11: https://github.com/plantuml/plantuml | E11: plantuml/plantuml: 13 346 звезд, 1 238 форков, лицензия LGPL-3.0, последнее обновление 2026-09-30 | F11: Доверие и зрелость | G11: 3 | H11: 30.09.2026 | I11: Активность сообщества и открытость кода | J11: 5 | K11: github_repos_2026-09-30.json | L11: GitHub REST API, 30.09.2026
A12: K001 | B12: =IFERROR(INDEX('01_Компании'!$B$4:$B$25,MATCH(A12,'01_Компании'!$A$4:$A$25,0)),"") -> PlantUML | C12: Регистрационные данные домена (RDAP) | D12: https://rdap.org/domain/plantuml.com | E12: Возраст домена или репозитория около 15,8 лет (верхняя оценка возраста бренда) | F12: Доверие и зрелость | G12: 2 | H12: 30.09.2026 | I12: Историю продукта подтверждает косвенно | J12: 4 | K12: vozrast_domenov_raschet_2026-09-30.json | L12: RDAP, 30.09.2026
A13: K001 | B13: =IFERROR(INDEX('01_Компании'!$B$4:$B$25,MATCH(A13,'01_Компании'!$A$4:$A$25,0)),"") -> PlantUML | C13: Признаки на главной странице (HTML) | D13: https://plantuml.com/ | E13: Совпадения шаблонов в HTML: вход - 0, тарифы - 0, интеграции - 0, вакансии - 0, магазин приложений - 0, GitHub - 4 | F13: Функциональность | G13: 2 | H13: 30.09.2026 | I13: Косвенный признак (автоматический подсчет, не просмотр страницы человеком) | J13: 3 | K13: sajty_konkurentov_priznaki_2026-09-30.json | L13: curl главной страницы, 30.09.2026
A14: K001 | B14: =IFERROR(INDEX('01_Компании'!$B$4:$B$25,MATCH(A14,'01_Компании'!$A$4:$A$25,0)),"") -> PlantUML | C14: Совместимость форматов NotaCode | D14: docs/business/01-project-concept.md, разделы 2 и 5 | E14: В документации проекта предусмотрены экспорт и импорт форматов PlantUML, Mermaid, D2, BPMN XML, draw.io | F14: Замена и переключение | G14: 2 | H14: 30.09.2026 | I14: Переключение с формата этого инструмента на NotaCode возможно при реализации импорта (план) | J14: 3 | K14: NotaCode/docs/business/01-project-concept.md | L14: импорт - не в MVP
A15: K002 | B15: =IFERROR(INDEX('01_Компании'!$B$4:$B$25,MATCH(A15,'01_Компании'!$A$4:$A$25,0)),"") -> Mermaid (библиотека) | C15: Главная страница (title, description) | D15: https://mermaid.js.org/ | E15: title: «Mermaid | Diagramming and charting tool»; description: «Create diagrams and visualizations using text and code.» | F15: Цифровой товар | G15: 4 | H15: 30.09.2026 | I15: Задача та же (диаграммы из текста и кода), нотаций UML/BPMN/IDEF как набора с проверкой правил в описании нет | J15: 4 | K15: sajty_konkurentov_title_description_2026-09-30.json | L15: метаданные главной страницы, curl 30.09.2026
... A180: K022 | B180: =IFERROR(INDEX('01_Компании'!$B$4:$B$25,MATCH(A180,'01_Компании'!$A$4:$A$25,0)),"") -> Microsoft Visio | C180: Тарифы и цена | D180: https://www.microsoft.com/ru-ru/microsoft-365/visio/flowchart-software | E180: Plan 1 - 5 у.е., Plan 2 - 15 у.е. за пользователя в месяц при оплате за год; бесплатного тарифа нет (пробный месяц) | F180: Цена и тарифы | G180: 5 | H180: 30.09.2026 | I180: Ценовая логика сопоставляется с Free и Pro 40 у.е. в год (4 у.е. в месяц) у NotaCode | J180: 4 | K180: ЛР1 табл. 42; ЛР2-3 табл. 70 | L180: значения считаны с официальных страниц 30.09.2026 (ЛР1, ЛР2-3)

Sheet 03_Критерии
A1: Критерии оценки уровня конкуренции | B1: Критерии оценки уровня конкуренции | C1: Критерии оценки уровня конкуренции | D1: Критерии оценки уровня конкуренции | E1: Критерии оценки уровня конкуренции | F1: Критерии оценки уровня конкуренции | G1: Критерии оценки уровня конкуренции | H1: Критерии оценки уровня конкуренции | I1: Критерии оценки уровня конкуренции | J1: Критерии оценки уровня конкуренции
A3: Код | B3: Критерий | C3: Что проверяется по сайту | D3: Индикаторы | E3: Вес | F3: 0 баллов | G3: 1 балл | H3: 3 балла | I3: 5 баллов | J3: Обязателен для прямого конкурента
A4: C1 | B4: Потребительская задача | C4: Какую проблему клиента компания обещает решить | D4: Формулировки на главной странице, страницы продукта, выгоды, результаты, случаи применения | E4: 20 | F4: Задача не совпадает | G4: Есть общее отраслевое сходство | H4: Задача в значительной степени совпадает | I4: Та же задача и тот же ожидаемый результат | J4: Да
A5: C2 | B5: Целевая аудитория | C5: Для кого предназначен товар | D5: Сегменты, отрасли, роли пользователей, размер клиента, B2B/B2C/B2G | E5: 15 | F5: Иная аудитория | G5: Частичное пересечение | H5: Существенное пересечение | I5: Та же целевая аудитория | J5: Да
A6: C3 | B6: Функциональная заменяемость товара | C6: Может ли товар заменить анализируемое решение | D6: Функции, модули, демонстрации, страницы возможностей, интеграции | E6: 18 | F6: Не заменяет | G6: Заменяет отдельный участок | H6: Заменяет значимую часть задачи | I6: Может полностью заменить товар | J6: Да
A7: C4 | B7: Сценарий использования | C7: В каком процессе и в какой ситуации используется товар | D7: Путь пользователя, описания внедрения, варианты использования, инструкции | E7: 10 | F7: Иной сценарий | G7: Слабое совпадение сценария | H7: Сценарии близки | I7: Сценарии практически одинаковы | J7: Нет
A8: C5 | B8: Ценовой уровень и форма оплаты | C8: Сопоставима ли экономическая логика покупки | D8: Тарифы, подписка, комиссия, пакет, бесплатный период, корпоративный расчет | E8: 8 | F8: Нет данных/иная экономика | G8: Частично сопоставимо | H8: Сопоставимый диапазон | I8: Почти тот же диапазон и форма оплаты | J8: Нет
A9: C6 | B9: Каналы продаж и привлечения | C9: Как клиент приходит к покупке и получает доступ | D9: Сайт, приложение, маркетплейсы, партнеры, личные продажи, демонстрация, пробный доступ | E9: 8 | F9: Каналы не совпадают | G9: Есть один общий канал | H9: Несколько общих каналов | I9: Путь к покупке почти одинаков | J9: Нет
A10: C7 | B10: География, язык, регулирование | C10: Работает ли компания на том же рынке в сопоставимых условиях | D10: Страны, языки, валюта, юридическая информация, требования отрасли | E10: 7 | F10: Иной рынок | G10: Потенциально релевантно | H10: Рынки частично совпадают | I10: Тот же рынок и условия | J10: Нет
A11: C8 | B11: Модель монетизации | C11: Как компания получает выручку | D11: Тарифные планы, комиссия, freemium, лицензия, платные модули, реклама | E11: 7 | F11: Иная логика выручки | G11: Есть отдельные сходства | H11: Модель близка | I11: Модель практически совпадает | J11: Нет
A12: C9 | B12: Уровень зрелости и доверия | C12: Способна ли компания реально конкурировать за выбор клиента | D12: Кейсы, клиенты, отзывы, сертификаты, партнеры, история, служба поддержки | E12: 4 | F12: Слабые признаки зрелости | G12: Единичные признаки | H12: Достаточные признаки надежности | I12: Сильная доказанная рыночная позиция | J12: Нет
A13: C10 | B13: Вероятность переключения клиента | C13: Насколько реалистично, что клиент заменит одно решение другим | D13: Миграция, импорт данных, интеграции, поддержка перехода, сравнения, обещания простого старта | E13: 3 | F13: Переключение маловероятно | G13: Требует значительных усилий | H13: Переключение возможно | I13: Переключение явно поддерживается | J13: Нет
A15: Примечание | B15: Вес можно изменять под отрасль. Итоговая оценка на листе 04 автоматически пересчитывается по измененным весам

Sheet 04_Оценка
A1: Матрица оценки и автоматическая классификация уровня конкуренции | B1: Матрица оценки и автоматическая классификация уровня конкуренции | C1: Матрица оценки и автоматическая классификация уровня конкуренции | D1: Матрица оценки и автоматическая классификация уровня конкуренции | E1: Матрица оценки и автоматическая классификация уровня конкуренции | F1: Матрица оценки и автоматическая классификация уровня конкуренции | G1: Матрица оценки и автоматическая классификация уровня конкуренции | H1: Матрица оценки и автоматическая классификация уровня конкуренции | I1: Матрица оценки и автоматическая классификация уровня конкуренции | J1: Матрица оценки и автоматическая классификация уровня конкуренции | K1: Матрица оценки и автоматическая классификация уровня конкуренции | L1: Матрица оценки и автоматическая классификация уровня конкуренции | M1: Матрица оценки и автоматическая классификация уровня конкуренции | N1: Матрица оценки и автоматическая классификация уровня конкуренции | O1: Матрица оценки и автоматическая классификация уровня конкуренции | P1: Матрица оценки и автоматическая классификация уровня конкуренции | Q1: Матрица оценки и автоматическая классификация уровня конкуренции | R1: Матрица оценки и автоматическая классификация уровня конкуренции | S1: Матрица оценки и автоматическая классификация уровня конкуренции | T1: Матрица оценки и автоматическая классификация уровня конкуренции | U1: Матрица оценки и автоматическая классификация уровня конкуренции | V1: Матрица оценки и автоматическая классификация уровня конкуренции
A3: ID | B3: Компания | C3: Сайт | D3: C1 задача | E3: C2 аудитория | F3: C3 заменяемость | G3: C4 сценарий | H3: C5 цена | I3: C6 каналы | J3: C7 география | K3: C8 монетизация | L3: C9 зрелость | M3: C10 переключение | N3: Взвешенный балл | O3: Ограничитель | P3: Расчетный уровень | Q3: Экспертная корректировка | R3: Итоговый уровень | S3: Статус решения | T3: Ключевое обоснование | U3: Ключевые ссылки | V3: Дата проверки
A4: K001 | B4: =IFERROR(IF(INDEX('01_Компании'!$B$4:$B$25,MATCH(A4,'01_Компании'!$A$4:$A$25,0))="","",INDEX('01_Компании'!$B$4:$B$25,MATCH(A4,'01_Компании'!$A$4:$A$25,0))),"") -> PlantUML | C4: =IFERROR(IF(INDEX('01_Компании'!$C$4:$C$25,MATCH(A4,'01_Компании'!$A$4:$A$25,0))="","",INDEX('01_Компании'!$C$4:$C$25,MATCH(A4,'01_Компании'!$A$4:$A$25,0))),"") -> plantuml.com | D4: 5 | E4: 4 | F4: 4 | G4: 5 | H4: 4 | I4: 4 | J4: 4 | K4: 1 | L4: 5 | M4: 3 | N4: =IF(COUNTA(D4:M4)=0,"",(D4*'03_Критерии'!$E$4+E4*'03_Критерии'!$E$5+F4*'03_Критерии'!$E$6+G4*'03_Критерии'!$E$7+H4*'03_Критерии'!$E$8+I4*'03_Критерии'!$E$9+J4*'03_Критерии'!$E$10+K4*'03_Критерии'!$E$11+L4*'03_Критерии'!$E$12+M4*'03_Критерии'!$E$13)/SUM('03_Критерии'!$E$4:$E$13)) -> 4.1 | O4: =IF(N4="","",IF(COUNTA(D4:M4)<6,"Недостаточно данных",IF(D4<3,"Низкое совпадение задачи",IF(F4<3,"Низкая товарная заменяемость","Нет")))) -> Нет | P4: =IF(N4="","",IF(O4="Недостаточно данных","Недостаточно данных",IF(OR(D4<3,F4<3),IF(N4>=2.5,"Косвенный конкурент / заменитель",IF(N4>=1.6,"Смежная или потенциальная конкуренция","Не конкурент / объект наблюдения")),IF(N4>=4.2,"Прямой конкурент",IF(N4>=3.4,"Близкий альтернативный конкурент",IF(N4>=2.5,"Косвенный конкурент / заменитель",IF(N4>=1.6,"Смежная или потенциальная конкуренция","Не конкурент / объект наблюдения"))))))) -> Близкий альтернативный конкурент | Q4: Прямой конкурент | R4: =IF(Q4="",P4,Q4) -> Прямой конкурент | S4: В работе | T4: Экспертная корректировка: Расчетный балл 4,10 лишь на 0,10 ниже порога 4,20; по правилу методики (индекс 65-79 и постоянное присутствие в тех же запросах) допускается повышение до прямого. Подтверждения: (1) запрос «plantuml» - 200 запросов в месяц в Беларуси (Вордстат, 29.08-27.09.2026), максимум среди брендов текстовых DSL; (2) страница товара и описание совпадают с задачей NotaCode (title/description 30.09.2026); (3) ЛР1 табл. 44 относит PlantUML к прямым конкурентам; (4) плагины IDE: 3 712 111 установок VS Marketplace и 5 014 362 загрузки JetBrains (ЛР2-3). Уверенность: средняя. Similarweb Pro: 739 657 визитов в месяц (июнь-август 2026). Вордстат, Беларусь: 200 запр. в месяц. Цена: открытый код, бесплатно (ЛР1, табл. 42). Главное обещание совпадает с задачей NotaCode: диаграммы UML из текста | U4: 02_Доказательства: 11 строк (ID K001); ЛР1 табл. 44; ЛР2-3 (маркетплейсы); Вордстат 29.08-27.09.2026 | V4: 30.09.2026
A5: K002 | B5: =IFERROR(IF(INDEX('01_Компании'!$B$4:$B$25,MATCH(A5,'01_Компании'!$A$4:$A$25,0))="","",INDEX('01_Компании'!$B$4:$B$25,MATCH(A5,'01_Компании'!$A$4:$A$25,0))),"") -> Mermaid (библиотека) | C5: =IFERROR(IF(INDEX('01_Компании'!$C$4:$C$25,MATCH(A5,'01_Компании'!$A$4:$A$25,0))="","",INDEX('01_Компании'!$C$4:$C$25,MATCH(A5,'01_Компании'!$A$4:$A$25,0))),"") -> mermaid.js.org | D5: 5 | E5: 4 | F5: 4 | G5: 5 | H5: 4 | I5: 5 | J5: 3 | K5: 1 | L5: 4 | M5: 3 | N5: =IF(COUNTA(D5:M5)=0,"",(D5*'03_Критерии'!$E$4+E5*'03_Критерии'!$E$5+F5*'03_Критерии'!$E$6+G5*'03_Критерии'!$E$7+H5*'03_Критерии'!$E$8+I5*'03_Критерии'!$E$9+J5*'03_Критерии'!$E$10+K5*'03_Критерии'!$E$11+L5*'03_Критерии'!$E$12+M5*'03_Критерии'!$E$13)/SUM('03_Критерии'!$E$4:$E$13)) -> 4.07 | O5: =IF(N5="","",IF(COUNTA(D5:M5)<6,"Недостаточно данных",IF(D5<3,"Низкое совпадение задачи",IF(F5<3,"Низкая товарная заменяемость","Нет")))) -> Нет | P5: =IF(N5="","",IF(O5="Недостаточно данных","Недостаточно данных",IF(OR(D5<3,F5<3),IF(N5>=2.5,"Косвенный конкурент / заменитель",IF(N5>=1.6,"Смежная или потенциальная конкуренция","Не конкурент / объект наблюдения")),IF(N5>=4.2,"Прямой конкурент",IF(N5>=3.4,"Близкий альтернативный конкурент",IF(N5>=2.5,"Косвенный конкурент / заменитель",IF(N5>=1.6,"Смежная или потенциальная конкуренция","Не конкурент / объект наблюдения"))))))) -> Близкий альтернативный конкурент | R5: =IF(Q5="",P5,Q5) -> Близкий альтернативный конкурент | S5: В работе | T5: Уверенность: средняя. Similarweb Pro: 442 646 визитов в месяц (июнь-август 2026). Вордстат, Беларусь: 19 запр. в месяц. Цена: открытый код (MIT); платные планы у Mermaid Chart. Задача та же (диаграммы из текста и кода), нотаций UML/BPMN/IDEF как набора с проверкой правил в описании нет | U5: 02_Доказательства: 11 строк (ID K002) | V5: 30.09.2026
A6: K003 | B6: =IFERROR(IF(INDEX('01_Компании'!$B$4:$B$25,MATCH(A6,'01_Компании'!$A$4:$A$25,0))="","",INDEX('01_Компании'!$B$4:$B$25,MATCH(A6,'01_Компании'!$A$4:$A$25,0))),"") -> Mermaid Chart | C6: =IFERROR(IF(INDEX('01_Компании'!$C$4:$C$25,MATCH(A6,'01_Компании'!$A$4:$A$25,0))="","",INDEX('01_Компании'!$C$4:$C$25,MATCH(A6,'01_Компании'!$A$4:$A$25,0))),"") -> mermaidchart.com | D6: 5 | E6: 3 | F6: 4 | G6: 4 | H6: 3 | I6: 3 | J6: 2 | K6: 5 | L6: 2 | M6: 3 | N6: =IF(COUNTA(D6:M6)=0,"",(D6*'03_Критерии'!$E$4+E6*'03_Критерии'!$E$5+F6*'03_Критерии'!$E$6+G6*'03_Критерии'!$E$7+H6*'03_Критерии'!$E$8+I6*'03_Критерии'!$E$9+J6*'03_Критерии'!$E$10+K6*'03_Критерии'!$E$11+L6*'03_Критерии'!$E$12+M6*'03_Критерии'!$E$13)/SUM('03_Критерии'!$E$4:$E$13)) -> 3.71 | O6: =IF(N6="","",IF(COUNTA(D6:M6)<6,"Недостаточно данных",IF(D6<3,"Низкое совпадение задачи",IF(F6<3,"Низкая товарная заменяемость","Нет")))) -> Нет | P6: =IF(N6="","",IF(O6="Недостаточно данных","Недостаточно данных",IF(OR(D6<3,F6<3),IF(N6>=2.5,"Косвенный конкурент / заменитель",IF(N6>=1.6,"Смежная или потенциальная конкуренция","Не конкурент / объект наблюдения")),IF(N6>=4.2,"Прямой конкурент",IF(N6>=3.4,"Близкий альтернативный конкурент",IF(N6>=2.5,"Косвенный конкурент / заменитель",IF(N6>=1.6,"Смежная или потенциальная конкуренция","Не конкурент / объект наблюдения"))))))) -> Близкий альтернативный конкурент | R6: =IF(Q6="",P6,Q6) -> Близкий альтернативный конкурент | S6: В работе | T6: Уверенность: средняя. Similarweb Pro: 2 535 визитов в месяц (июнь-август 2026). Вордстат, Беларусь: 0 запр. в месяц. Тарифы: Free (до 6 диаграмм, 15 AI-кредитов). Платная надстройка над Mermaid; домен, вероятно, перенесен на mermaid.ai (трафик mermaidchart.com -82,22 %) | U6: 02_Доказательства: 10 строк (ID K003) | V6: 30.09.2026
A7: K004 | B7: =IFERROR(IF(INDEX('01_Компании'!$B$4:$B$25,MATCH(A7,'01_Компании'!$A$4:$A$25,0))="","",INDEX('01_Компании'!$B$4:$B$25,MATCH(A7,'01_Компании'!$A$4:$A$25,0))),"") -> D2 (Terrastruct) | C7: =IFERROR(IF(INDEX('01_Компании'!$C$4:$C$25,MATCH(A7,'01_Компании'!$A$4:$A$25,0))="","",INDEX('01_Компании'!$C$4:$C$25,MATCH(A7,'01_Компании'!$A$4:$A$25,0))),"") -> d2lang.com | D7: 4 | E7: 3 | F7: 3 | G7: 4 | I7: 4 | J7: 2 | L7: 2 | M7: 3 | N7: =IF(COUNTA(D7:M7)=0,"",(D7*'03_Критерии'!$E$4+E7*'03_Критерии'!$E$5+F7*'03_Критерии'!$E$6+G7*'03_Критерии'!$E$7+H7*'03_Критерии'!$E$8+I7*'03_Критерии'!$E$9+J7*'03_Критерии'!$E$10+K7*'03_Критерии'!$E$11+L7*'03_Критерии'!$E$12+M7*'03_Критерии'!$E$13)/SUM('03_Критерии'!$E$4:$E$13)) -> 2.82 | O7: =IF(N7="","",IF(COUNTA(D7:M7)<6,"Недостаточно данных",IF(D7<3,"Низкое совпадение задачи",IF(F7<3,"Низкая товарная заменяемость","Нет")))) -> Нет | P7: =IF(N7="","",IF(O7="Недостаточно данных","Недостаточно данных",IF(OR(D7<3,F7<3),IF(N7>=2.5,"Косвенный конкурент / заменитель",IF(N7>=1.6,"Смежная или потенциальная конкуренция","Не конкурент / объект наблюдения")),IF(N7>=4.2,"Прямой конкурент",IF(N7>=3.4,"Близкий альтернативный конкурент",IF(N7>=2.5,"Косвенный конкурент / заменитель",IF(N7>=1.6,"Смежная или потенциальная конкуренция","Не конкурент / объект наблюдения"))))))) -> Косвенный конкурент / заменитель | R7: =IF(Q7="",P7,Q7) -> Косвенный конкурент / заменитель | S7: В работе | T7: Уверенность: средняя. Similarweb Pro: 61 003 визитов в месяц (июнь-август 2026). Вордстат, Беларусь: 0 запр. в месяц. Описание на главной отсутствует (meta description пуста); отнесение по ЛР4 (язык диаграмм D2) | U7: 02_Доказательства: 9 строк (ID K004) | V7: 30.09.2026
A8: K005 | B8: =IFERROR(IF(INDEX('01_Компании'!$B$4:$B$25,MATCH(A8,'01_Компании'!$A$4:$A$25,0))="","",INDEX('01_Компании'!$B$4:$B$25,MATCH(A8,'01_Компании'!$A$4:$A$25,0))),"") -> Kroki | C8: =IFERROR(IF(INDEX('01_Компании'!$C$4:$C$25,MATCH(A8,'01_Компании'!$A$4:$A$25,0))="","",INDEX('01_Компании'!$C$4:$C$25,MATCH(A8,'01_Компании'!$A$4:$A$25,0))),"") -> kroki.io | D8: 3 | E8: 3 | F8: 2 | G8: 2 | I8: 3 | J8: 2 | L8: 2 | N8: =IF(COUNTA(D8:M8)=0,"",(D8*'03_Критерии'!$E$4+E8*'03_Критерии'!$E$5+F8*'03_Критерии'!$E$6+G8*'03_Критерии'!$E$7+H8*'03_Критерии'!$E$8+I8*'03_Критерии'!$E$9+J8*'03_Критерии'!$E$10+K8*'03_Критерии'!$E$11+L8*'03_Критерии'!$E$12+M8*'03_Критерии'!$E$13)/SUM('03_Критерии'!$E$4:$E$13)) -> 2.07 | O8: =IF(N8="","",IF(COUNTA(D8:M8)<6,"Недостаточно данных",IF(D8<3,"Низкое совпадение задачи",IF(F8<3,"Низкая товарная заменяемость","Нет")))) -> Низкая товарная заменяемость | P8: =IF(N8="","",IF(O8="Недостаточно данных","Недостаточно данных",IF(OR(D8<3,F8<3),IF(N8>=2.5,"Косвенный конкурент / заменитель",IF(N8>=1.6,"Смежная или потенциальная конкуренция","Не конкурент / объект наблюдения")),IF(N8>=4.2,"Прямой конкурент",IF(N8>=3.4,"Близкий альтернативный конкурент",IF(N8>=2.5,"Косвенный конкурент / заменитель",IF(N8>=1.6,"Смежная или потенциальная конкуренция","Не конкурент / объект наблюдения"))))))) -> Смежная или потенциальная конкуренция | R8: =IF(Q8="",P8,Q8) -> Смежная или потенциальная конкуренция | S8: В работе | T8: Уверенность: средняя. Similarweb Pro: 33 398 визитов в месяц (июнь-август 2026). Вордстат, Беларусь: 12 запр. в месяц. Отрисовка через API без самостоятельного редактора; NotaCode планирует Kroki как альтернативный движок (документация проекта) | U8: 02_Доказательства: 8 строк (ID K005) | V8: 30.09.2026
A9: K006 | B9: =IFERROR(IF(INDEX('01_Компании'!$B$4:$B$25,MATCH(A9,'01_Компании'!$A$4:$A$25,0))="","",INDEX('01_Компании'!$B$4:$B$25,MATCH(A9,'01_Компании'!$A$4:$A$25,0))),"") -> PlantText | C9: =IFERROR(IF(INDEX('01_Компании'!$C$4:$C$25,MATCH(A9,'01_Компании'!$A$4:$A$25,0))="","",INDEX('01_Компании'!$C$4:$C$25,MATCH(A9,'01_Компании'!$A$4:$A$25,0))),"") -> planttext.com | D9: 5 | E9: 4 | F9: 4 | G9: 5 | H9: 4 | I9: 2 | J9: 2 | K9: 1 | L9: 3 | M9: 3 | N9: =IF(COUNTA(D9:M9)=0,"",(D9*'03_Критерии'!$E$4+E9*'03_Критерии'!$E$5+F9*'03_Критерии'!$E$6+G9*'03_Критерии'!$E$7+H9*'03_Критерии'!$E$8+I9*'03_Критерии'!$E$9+J9*'03_Критерии'!$E$10+K9*'03_Критерии'!$E$11+L9*'03_Критерии'!$E$12+M9*'03_Критерии'!$E$13)/SUM('03_Критерии'!$E$4:$E$13)) -> 3.72 | O9: =IF(N9="","",IF(COUNTA(D9:M9)<6,"Недостаточно данных",IF(D9<3,"Низкое совпадение задачи",IF(F9<3,"Низкая товарная заменяемость","Нет")))) -> Нет | P9: =IF(N9="","",IF(O9="Недостаточно данных","Недостаточно данных",IF(OR(D9<3,F9<3),IF(N9>=2.5,"Косвенный конкурент / заменитель",IF(N9>=1.6,"Смежная или потенциальная конкуренция","Не конкурент / объект наблюдения")),IF(N9>=4.2,"Прямой конкурент",IF(N9>=3.4,"Близкий альтернативный конкурент",IF(N9>=2.5,"Косвенный конкурент / заменитель",IF(N9>=1.6,"Смежная или потенциальная конкуренция","Не конкурент / объект наблюдения"))))))) -> Близкий альтернативный конкурент | R9: =IF(Q9="",P9,Q9) -> Близкий альтернативный конкурент | S9: В работе | T9: Уверенность: средняя. Similarweb Pro: 339 451 визитов в месяц (июнь-август 2026). Вордстат, Беларусь: 9 запр. в месяц. Цена: заголовок страницы: Free & Fast. В заголовке заявлены бесплатность и онлайн-доступ; редактор поверх PlantUML | U9: 02_Доказательства: 9 строк (ID K006) | V9: 30.09.2026
A10: K007 | B10: =IFERROR(IF(INDEX('01_Компании'!$B$4:$B$25,MATCH(A10,'01_Компании'!$A$4:$A$25,0))="","",INDEX('01_Компании'!$B$4:$B$25,MATCH(A10,'01_Компании'!$A$4:$A$25,0))),"") -> StarUML | C10: =IFERROR(IF(INDEX('01_Компании'!$C$4:$C$25,MATCH(A10,'01_Компании'!$A$4:$A$25,0))="","",INDEX('01_Компании'!$C$4:$C$25,MATCH(A10,'01_Компании'!$A$4:$A$25,0))),"") -> staruml.io | D10: 4 | E10: 4 | F10: 3 | G10: 3 | I10: 3 | J10: 3 | L10: 3 | N10: =IF(COUNTA(D10:M10)=0,"",(D10*'03_Критерии'!$E$4+E10*'03_Критерии'!$E$5+F10*'03_Критерии'!$E$6+G10*'03_Критерии'!$E$7+H10*'03_Критерии'!$E$8+I10*'03_Критерии'!$E$9+J10*'03_Критерии'!$E$10+K10*'03_Критерии'!$E$11+L10*'03_Критерии'!$E$12+M10*'03_Критерии'!$E$13)/SUM('03_Критерии'!$E$4:$E$13)) -> 2.81 | O10: =IF(N10="","",IF(COUNTA(D10:M10)<6,"Недостаточно данных",IF(D10<3,"Низкое совпадение задачи",IF(F10<3,"Низкая товарная заменяемость","Нет")))) -> Нет | P10: =IF(N10="","",IF(O10="Недостаточно данных","Недостаточно данных",IF(OR(D10<3,F10<3),IF(N10>=2.5,"Косвенный конкурент / заменитель",IF(N10>=1.6,"Смежная или потенциальная конкуренция","Не конкурент / объект наблюдения")),IF(N10>=4.2,"Прямой конкурент",IF(N10>=3.4,"Близкий альтернативный конкурент",IF(N10>=2.5,"Косвенный конкурент / заменитель",IF(N10>=1.6,"Смежная или потенциальная конкуренция","Не конкурент / объект наблюдения"))))))) -> Косвенный конкурент / заменитель | R10: =IF(Q10="",P10,Q10) -> Косвенный конкурент / заменитель | S10: В работе | T10: Уверенность: средняя. Similarweb Pro: 107 631 визитов в месяц (июнь-август 2026). Вордстат, Беларусь: 16 запр. в месяц. Графический моделер UML; страница тарифов в HTML упомянута 2 раза, цены не получены | U10: 02_Доказательства: 7 строк (ID K007) | V10: 30.09.2026
A11: K008 | B11: =IFERROR(IF(INDEX('01_Компании'!$B$4:$B$25,MATCH(A11,'01_Компании'!$A$4:$A$25,0))="","",INDEX('01_Компании'!$B$4:$B$25,MATCH(A11,'01_Компании'!$A$4:$A$25,0))),"") -> Visual Paradigm | C11: =IFERROR(IF(INDEX('01_Компании'!$C$4:$C$25,MATCH(A11,'01_Компании'!$A$4:$A$25,0))="","",INDEX('01_Компании'!$C$4:$C$25,MATCH(A11,'01_Компании'!$A$4:$A$25,0))),"") -> visual-paradigm.com | D11: 4 | E11: 4 | F11: 4 | G11: 3 | H11: 4 | I11: 3 | J11: 4 | K11: 3 | L11: 4 | N11: =IF(COUNTA(D11:M11)=0,"",(D11*'03_Критерии'!$E$4+E11*'03_Критерии'!$E$5+F11*'03_Критерии'!$E$6+G11*'03_Критерии'!$E$7+H11*'03_Критерии'!$E$8+I11*'03_Критерии'!$E$9+J11*'03_Критерии'!$E$10+K11*'03_Критерии'!$E$11+L11*'03_Критерии'!$E$12+M11*'03_Критерии'!$E$13)/SUM('03_Критерии'!$E$4:$E$13)) -> 3.63 | O11: =IF(N11="","",IF(COUNTA(D11:M11)<6,"Недостаточно данных",IF(D11<3,"Низкое совпадение задачи",IF(F11<3,"Низкая товарная заменяемость","Нет")))) -> Нет | P11: =IF(N11="","",IF(O11="Недостаточно данных","Недостаточно данных",IF(OR(D11<3,F11<3),IF(N11>=2.5,"Косвенный конкурент / заменитель",IF(N11>=1.6,"Смежная или потенциальная конкуренция","Не конкурент / объект наблюдения")),IF(N11>=4.2,"Прямой конкурент",IF(N11>=3.4,"Близкий альтернативный конкурент",IF(N11>=2.5,"Косвенный конкурент / заменитель",IF(N11>=1.6,"Смежная или потенциальная конкуренция","Не конкурент / объект наблюдения"))))))) -> Близкий альтернативный конкурент | R11: =IF(Q11="",P11,Q11) -> Близкий альтернативный конкурент | S11: В работе | T11: Уверенность: средняя. Similarweb Pro: 1 516 000 визитов в месяц (июнь-август 2026). Вордстат, Беларусь: 46 запр. в месяц. Тарифы: Подписка: Modeler 6, Standard 19, Professional 35, Enterprise 89 у.е. в месяц. Широкий набор нотаций и ИИ; графический ввод, ценовой уровень выше NotaCode | U11: 02_Доказательства: 9 строк (ID K008) | V11: 30.09.2026
A12: K009 | B12: =IFERROR(IF(INDEX('01_Компании'!$B$4:$B$25,MATCH(A12,'01_Компании'!$A$4:$A$25,0))="","",INDEX('01_Компании'!$B$4:$B$25,MATCH(A12,'01_Компании'!$A$4:$A$25,0))),"") -> Sparx Systems (Enterprise Architect) | C12: =IFERROR(IF(INDEX('01_Компании'!$C$4:$C$25,MATCH(A12,'01_Компании'!$A$4:$A$25,0))="","",INDEX('01_Компании'!$C$4:$C$25,MATCH(A12,'01_Компании'!$A$4:$A$25,0))),"") -> sparxsystems.com | D12: 4 | F12: 3 | I12: 2 | J12: 4 | L12: 3 | N12: =IF(COUNTA(D12:M12)=0,"",(D12*'03_Критерии'!$E$4+E12*'03_Критерии'!$E$5+F12*'03_Критерии'!$E$6+G12*'03_Критерии'!$E$7+H12*'03_Критерии'!$E$8+I12*'03_Критерии'!$E$9+J12*'03_Критерии'!$E$10+K12*'03_Критерии'!$E$11+L12*'03_Критерии'!$E$12+M12*'03_Критерии'!$E$13)/SUM('03_Критерии'!$E$4:$E$13)) -> 1.9 | O12: =IF(N12="","",IF(COUNTA(D12:M12)<6,"Недостаточно данных",IF(D12<3,"Низкое совпадение задачи",IF(F12<3,"Низкая товарная заменяемость","Нет")))) -> Недостаточно данных | P12: =IF(N12="","",IF(O12="Недостаточно данных","Недостаточно данных",IF(OR(D12<3,F12<3),IF(N12>=2.5,"Косвенный конкурент / заменитель",IF(N12>=1.6,"Смежная или потенциальная конкуренция","Не конкурент / объект наблюдения")),IF(N12>=4.2,"Прямой конкурент",IF(N12>=3.4,"Близкий альтернативный конкурент",IF(N12>=2.5,"Косвенный конкурент / заменитель",IF(N12>=1.6,"Смежная или потенциальная конкуренция","Не конкурент / объект наблюдения"))))))) -> Недостаточно данных | R12: =IF(Q12="",P12,Q12) -> Недостаточно данных | S12: Требует уточнения | T12: Уверенность: низкая. Similarweb Pro: 149 507 визитов в месяц (июнь-август 2026). Вордстат, Беларусь: 9 запр. в месяц. Главная страница вернула HTTP 403 автоматическому запросу; отнесение по ЛР1 (табл. 44) | U12: 02_Доказательства: 7 строк (ID K009) | V12: 30.09.2026
A13: K010 | B13: =IFERROR(IF(INDEX('01_Компании'!$B$4:$B$25,MATCH(A13,'01_Компании'!$A$4:$A$25,0))="","",INDEX('01_Компании'!$B$4:$B$25,MATCH(A13,'01_Компании'!$A$4:$A$25,0))),"") -> bpmn.io | C13: =IFERROR(IF(INDEX('01_Компании'!$C$4:$C$25,MATCH(A13,'01_Компании'!$A$4:$A$25,0))="","",INDEX('01_Компании'!$C$4:$C$25,MATCH(A13,'01_Компании'!$A$4:$A$25,0))),"") -> bpmn.io | D13: 3 | E13: 3 | F13: 2 | G13: 3 | I13: 3 | J13: 4 | L13: 3 | M13: 3 | N13: =IF(COUNTA(D13:M13)=0,"",(D13*'03_Критерии'!$E$4+E13*'03_Критерии'!$E$5+F13*'03_Критерии'!$E$6+G13*'03_Критерии'!$E$7+H13*'03_Критерии'!$E$8+I13*'03_Критерии'!$E$9+J13*'03_Критерии'!$E$10+K13*'03_Критерии'!$E$11+L13*'03_Критерии'!$E$12+M13*'03_Критерии'!$E$13)/SUM('03_Критерии'!$E$4:$E$13)) -> 2.44 | O13: =IF(N13="","",IF(COUNTA(D13:M13)<6,"Недостаточно данных",IF(D13<3,"Низкое совпадение задачи",IF(F13<3,"Низкая товарная заменяемость","Нет")))) -> Низкая товарная заменяемость | P13: =IF(N13="","",IF(O13="Недостаточно данных","Недостаточно данных",IF(OR(D13<3,F13<3),IF(N13>=2.5,"Косвенный конкурент / заменитель",IF(N13>=1.6,"Смежная или потенциальная конкуренция","Не конкурент / объект наблюдения")),IF(N13>=4.2,"Прямой конкурент",IF(N13>=3.4,"Близкий альтернативный конкурент",IF(N13>=2.5,"Косвенный конкурент / заменитель",IF(N13>=1.6,"Смежная или потенциальная конкуренция","Не конкурент / объект наблюдения"))))))) -> Смежная или потенциальная конкуренция | R13: =IF(Q13="",P13,Q13) -> Смежная или потенциальная конкуренция | S13: В работе | T13: Уверенность: средняя. Similarweb Pro: 199 080 визитов в месяц (июнь-август 2026). Вордстат, Беларусь: 37 запр. в месяц. Только BPMN-семейство; в NotaCode BPMN относится ко второй волне нотаций | U13: 02_Доказательства: 9 строк (ID K010) | V13: 30.09.2026
A14: K011 | B14: =IFERROR(IF(INDEX('01_Компании'!$B$4:$B$25,MATCH(A14,'01_Компании'!$A$4:$A$25,0))="","",INDEX('01_Компании'!$B$4:$B$25,MATCH(A14,'01_Компании'!$A$4:$A$25,0))),"") -> Camunda (Modeler) | C14: =IFERROR(IF(INDEX('01_Компании'!$C$4:$C$25,MATCH(A14,'01_Компании'!$A$4:$A$25,0))="","",INDEX('01_Компании'!$C$4:$C$25,MATCH(A14,'01_Компании'!$A$4:$A$25,0))),"") -> camunda.com | D14: 2 | E14: 2 | F14: 2 | G14: 2 | I14: 3 | J14: 3 | L14: 3 | M14: 3 | N14: =IF(COUNTA(D14:M14)=0,"",(D14*'03_Критерии'!$E$4+E14*'03_Критерии'!$E$5+F14*'03_Критерии'!$E$6+G14*'03_Критерии'!$E$7+H14*'03_Критерии'!$E$8+I14*'03_Критерии'!$E$9+J14*'03_Критерии'!$E$10+K14*'03_Критерии'!$E$11+L14*'03_Критерии'!$E$12+M14*'03_Критерии'!$E$13)/SUM('03_Критерии'!$E$4:$E$13)) -> 1.92 | O14: =IF(N14="","",IF(COUNTA(D14:M14)<6,"Недостаточно данных",IF(D14<3,"Низкое совпадение задачи",IF(F14<3,"Низкая товарная заменяемость","Нет")))) -> Низкое совпадение задачи | P14: =IF(N14="","",IF(O14="Недостаточно данных","Недостаточно данных",IF(OR(D14<3,F14<3),IF(N14>=2.5,"Косвенный конкурент / заменитель",IF(N14>=1.6,"Смежная или потенциальная конкуренция","Не конкурент / объект наблюдения")),IF(N14>=4.2,"Прямой конкурент",IF(N14>=3.4,"Близкий альтернативный конкурент",IF(N14>=2.5,"Косвенный конкурент / заменитель",IF(N14>=1.6,"Смежная или потенциальная конкуренция","Не конкурент / объект наблюдения"))))))) -> Смежная или потенциальная конкуренция | R14: =IF(Q14="",P14,Q14) -> Смежная или потенциальная конкуренция | S14: В работе | T14: Уверенность: средняя. Вордстат, Беларусь: 17 запр. в месяц. Классифицируется Modeler, а не вся компания; главная страница описывает платформу оркестрации | U14: 02_Доказательства: 7 строк (ID K011) | V14: 30.09.2026
A15: K012 | B15: =IFERROR(IF(INDEX('01_Компании'!$B$4:$B$25,MATCH(A15,'01_Компании'!$A$4:$A$25,0))="","",INDEX('01_Компании'!$B$4:$B$25,MATCH(A15,'01_Компании'!$A$4:$A$25,0))),"") -> Storm (StormBPMN) | C15: =IFERROR(IF(INDEX('01_Компании'!$C$4:$C$25,MATCH(A15,'01_Компании'!$A$4:$A$25,0))="","",INDEX('01_Компании'!$C$4:$C$25,MATCH(A15,'01_Компании'!$A$4:$A$25,0))),"") -> stormbpmn.com | D15: 3 | E15: 3 | F15: 2 | G15: 3 | I15: 2 | J15: 5 | L15: 1 | N15: =IF(COUNTA(D15:M15)=0,"",(D15*'03_Критерии'!$E$4+E15*'03_Критерии'!$E$5+F15*'03_Критерии'!$E$6+G15*'03_Критерии'!$E$7+H15*'03_Критерии'!$E$8+I15*'03_Критерии'!$E$9+J15*'03_Критерии'!$E$10+K15*'03_Критерии'!$E$11+L15*'03_Критерии'!$E$12+M15*'03_Критерии'!$E$13)/SUM('03_Критерии'!$E$4:$E$13)) -> 2.26 | O15: =IF(N15="","",IF(COUNTA(D15:M15)<6,"Недостаточно данных",IF(D15<3,"Низкое совпадение задачи",IF(F15<3,"Низкая товарная заменяемость","Нет")))) -> Низкая товарная заменяемость | P15: =IF(N15="","",IF(O15="Недостаточно данных","Недостаточно данных",IF(OR(D15<3,F15<3),IF(N15>=2.5,"Косвенный конкурент / заменитель",IF(N15>=1.6,"Смежная или потенциальная конкуренция","Не конкурент / объект наблюдения")),IF(N15>=4.2,"Прямой конкурент",IF(N15>=3.4,"Близкий альтернативный конкурент",IF(N15>=2.5,"Косвенный конкурент / заменитель",IF(N15>=1.6,"Смежная или потенциальная конкуренция","Не конкурент / объект наблюдения"))))))) -> Смежная или потенциальная конкуренция | R15: =IF(Q15="",P15,Q15) -> Смежная или потенциальная конкуренция | S15: В работе | T15: Уверенность: средняя. Similarweb Pro: 92 936 визитов в месяц (июнь-август 2026). Вордстат, Беларусь: 2 запр. в месяц. Русскоязычная платформа; BPMN-редактор входит в состав платформы процессного управления | U15: 02_Доказательства: 7 строк (ID K012) | V15: 30.09.2026
A16: K013 | B16: =IFERROR(IF(INDEX('01_Компании'!$B$4:$B$25,MATCH(A16,'01_Компании'!$A$4:$A$25,0))="","",INDEX('01_Компании'!$B$4:$B$25,MATCH(A16,'01_Компании'!$A$4:$A$25,0))),"") -> draw.io (diagrams.net) | C16: =IFERROR(IF(INDEX('01_Компании'!$C$4:$C$25,MATCH(A16,'01_Компании'!$A$4:$A$25,0))="","",INDEX('01_Компании'!$C$4:$C$25,MATCH(A16,'01_Компании'!$A$4:$A$25,0))),"") -> app.diagrams.net | D16: 3 | E16: 4 | F16: 3 | G16: 3 | H16: 4 | I16: 3 | J16: 4 | K16: 1 | L16: 5 | M16: 3 | N16: =IF(COUNTA(D16:M16)=0,"",(D16*'03_Критерии'!$E$4+E16*'03_Критерии'!$E$5+F16*'03_Критерии'!$E$6+G16*'03_Критерии'!$E$7+H16*'03_Критерии'!$E$8+I16*'03_Критерии'!$E$9+J16*'03_Критерии'!$E$10+K16*'03_Критерии'!$E$11+L16*'03_Критерии'!$E$12+M16*'03_Критерии'!$E$13)/SUM('03_Критерии'!$E$4:$E$13)) -> 3.24 | O16: =IF(N16="","",IF(COUNTA(D16:M16)<6,"Недостаточно данных",IF(D16<3,"Низкое совпадение задачи",IF(F16<3,"Низкая товарная заменяемость","Нет")))) -> Нет | P16: =IF(N16="","",IF(O16="Недостаточно данных","Недостаточно данных",IF(OR(D16<3,F16<3),IF(N16>=2.5,"Косвенный конкурент / заменитель",IF(N16>=1.6,"Смежная или потенциальная конкуренция","Не конкурент / объект наблюдения")),IF(N16>=4.2,"Прямой конкурент",IF(N16>=3.4,"Близкий альтернативный конкурент",IF(N16>=2.5,"Косвенный конкурент / заменитель",IF(N16>=1.6,"Смежная или потенциальная конкуренция","Не конкурент / объект наблюдения"))))))) -> Косвенный конкурент / заменитель | R16: =IF(Q16="",P16,Q16) -> Косвенный конкурент / заменитель | S16: В работе | T16: Уверенность: средняя. Similarweb Pro: 8 497 000 визитов в месяц (июнь-август 2026). Вордстат, Беларусь: 1072 запр. в месяц. Цена: полностью бесплатный, открытый код (Apache 2.0) (ЛР1, табл. 42). Универсальный графический редактор; бесплатный, открытый код, заявлено более 100 млн пользователей | U16: 02_Доказательства: 12 строк (ID K013) | V16: 30.09.2026
A17: K014 | B17: =IFERROR(IF(INDEX('01_Компании'!$B$4:$B$25,MATCH(A17,'01_Компании'!$A$4:$A$25,0))="","",INDEX('01_Компании'!$B$4:$B$25,MATCH(A17,'01_Компании'!$A$4:$A$25,0))),"") -> Lucidchart | C17: =IFERROR(IF(INDEX('01_Компании'!$C$4:$C$25,MATCH(A17,'01_Компании'!$A$4:$A$25,0))="","",INDEX('01_Компании'!$C$4:$C$25,MATCH(A17,'01_Компании'!$A$4:$A$25,0))),"") -> lucidchart.com | D17: 3 | E17: 3 | F17: 3 | G17: 3 | H17: 3 | I17: 3 | J17: 3 | K17: 5 | L17: 5 | N17: =IF(COUNTA(D17:M17)=0,"",(D17*'03_Критерии'!$E$4+E17*'03_Критерии'!$E$5+F17*'03_Критерии'!$E$6+G17*'03_Критерии'!$E$7+H17*'03_Критерии'!$E$8+I17*'03_Критерии'!$E$9+J17*'03_Критерии'!$E$10+K17*'03_Критерии'!$E$11+L17*'03_Критерии'!$E$12+M17*'03_Критерии'!$E$13)/SUM('03_Критерии'!$E$4:$E$13)) -> 3.13 | O17: =IF(N17="","",IF(COUNTA(D17:M17)<6,"Недостаточно данных",IF(D17<3,"Низкое совпадение задачи",IF(F17<3,"Низкая товарная заменяемость","Нет")))) -> Нет | P17: =IF(N17="","",IF(O17="Недостаточно данных","Недостаточно данных",IF(OR(D17<3,F17<3),IF(N17>=2.5,"Косвенный конкурент / заменитель",IF(N17>=1.6,"Смежная или потенциальная конкуренция","Не конкурент / объект наблюдения")),IF(N17>=4.2,"Прямой конкурент",IF(N17>=3.4,"Близкий альтернативный конкурент",IF(N17>=2.5,"Косвенный конкурент / заменитель",IF(N17>=1.6,"Смежная или потенциальная конкуренция","Не конкурент / объект наблюдения"))))))) -> Косвенный конкурент / заменитель | R17: =IF(Q17="",P17,Q17) -> Косвенный конкурент / заменитель | S17: В работе | T17: Уверенность: средняя. Similarweb Pro: 703 574 визитов в месяц (июнь-август 2026). Вордстат, Беларусь: 24 запр. в месяц. Тарифы: Free (3 редактируемых документа, 75 фигур на документ). Главная страница вернула HTTP 403; описание продукта не получено, оценка по ЛР1, ЛР2-3, G2, Capterra | U17: 02_Доказательства: 9 строк (ID K014) | V17: 30.09.2026
A18: K015 | B18: =IFERROR(IF(INDEX('01_Компании'!$B$4:$B$25,MATCH(A18,'01_Компании'!$A$4:$A$25,0))="","",INDEX('01_Компании'!$B$4:$B$25,MATCH(A18,'01_Компании'!$A$4:$A$25,0))),"") -> Creately | C18: =IFERROR(IF(INDEX('01_Компании'!$C$4:$C$25,MATCH(A18,'01_Компании'!$A$4:$A$25,0))="","",INDEX('01_Компании'!$C$4:$C$25,MATCH(A18,'01_Компании'!$A$4:$A$25,0))),"") -> creately.com | D18: 3 | E18: 3 | F18: 3 | G18: 3 | H18: 4 | I18: 2 | J18: 2 | K18: 4 | L18: 5 | N18: =IF(COUNTA(D18:M18)=0,"",(D18*'03_Критерии'!$E$4+E18*'03_Критерии'!$E$5+F18*'03_Критерии'!$E$6+G18*'03_Критерии'!$E$7+H18*'03_Критерии'!$E$8+I18*'03_Критерии'!$E$9+J18*'03_Критерии'!$E$10+K18*'03_Критерии'!$E$11+L18*'03_Критерии'!$E$12+M18*'03_Критерии'!$E$13)/SUM('03_Критерии'!$E$4:$E$13)) -> 2.99 | O18: =IF(N18="","",IF(COUNTA(D18:M18)<6,"Недостаточно данных",IF(D18<3,"Низкое совпадение задачи",IF(F18<3,"Низкая товарная заменяемость","Нет")))) -> Нет | P18: =IF(N18="","",IF(O18="Недостаточно данных","Недостаточно данных",IF(OR(D18<3,F18<3),IF(N18>=2.5,"Косвенный конкурент / заменитель",IF(N18>=1.6,"Смежная или потенциальная конкуренция","Не конкурент / объект наблюдения")),IF(N18>=4.2,"Прямой конкурент",IF(N18>=3.4,"Близкий альтернативный конкурент",IF(N18>=2.5,"Косвенный конкурент / заменитель",IF(N18>=1.6,"Смежная или потенциальная конкуренция","Не конкурент / объект наблюдения"))))))) -> Косвенный конкурент / заменитель | R18: =IF(Q18="",P18,Q18) -> Косвенный конкурент / заменитель | S18: В работе | T18: Уверенность: средняя. Similarweb Pro: 784 067 визитов в месяц (июнь-август 2026). Вордстат, Беларусь: 4 запр. в месяц. Тарифы: Платные тарифы от 5 до 89 у.е. в месяц (ЛР2-3, табл. 70: 15,14 - 269,54 BYN). Универсальный редактор; отзывы на Trustpilot низкие (1,9 из 5 при 58 отзывах) | U18: 02_Доказательства: 9 строк (ID K015) | V18: 30.09.2026
A19: K016 | B19: =IFERROR(IF(INDEX('01_Компании'!$B$4:$B$25,MATCH(A19,'01_Компании'!$A$4:$A$25,0))="","",INDEX('01_Компании'!$B$4:$B$25,MATCH(A19,'01_Компании'!$A$4:$A$25,0))),"") -> Miro | C19: =IFERROR(IF(INDEX('01_Компании'!$C$4:$C$25,MATCH(A19,'01_Компании'!$A$4:$A$25,0))="","",INDEX('01_Компании'!$C$4:$C$25,MATCH(A19,'01_Компании'!$A$4:$A$25,0))),"") -> miro.com | D19: 2 | E19: 2 | F19: 2 | G19: 2 | H19: 3 | I19: 3 | J19: 4 | K19: 5 | L19: 5 | N19: =IF(COUNTA(D19:M19)=0,"",(D19*'03_Критерии'!$E$4+E19*'03_Критерии'!$E$5+F19*'03_Критерии'!$E$6+G19*'03_Критерии'!$E$7+H19*'03_Критерии'!$E$8+I19*'03_Критерии'!$E$9+J19*'03_Критерии'!$E$10+K19*'03_Критерии'!$E$11+L19*'03_Критерии'!$E$12+M19*'03_Критерии'!$E$13)/SUM('03_Критерии'!$E$4:$E$13)) -> 2.57 | O19: =IF(N19="","",IF(COUNTA(D19:M19)<6,"Недостаточно данных",IF(D19<3,"Низкое совпадение задачи",IF(F19<3,"Низкая товарная заменяемость","Нет")))) -> Низкое совпадение задачи | P19: =IF(N19="","",IF(O19="Недостаточно данных","Недостаточно данных",IF(OR(D19<3,F19<3),IF(N19>=2.5,"Косвенный конкурент / заменитель",IF(N19>=1.6,"Смежная или потенциальная конкуренция","Не конкурент / объект наблюдения")),IF(N19>=4.2,"Прямой конкурент",IF(N19>=3.4,"Близкий альтернативный конкурент",IF(N19>=2.5,"Косвенный конкурент / заменитель",IF(N19>=1.6,"Смежная или потенциальная конкуренция","Не конкурент / объект наблюдения"))))))) -> Косвенный конкурент / заменитель | R19: =IF(Q19="",P19,Q19) -> Косвенный конкурент / заменитель | S19: В работе | T19: Уверенность: средняя. Similarweb Pro: 27 510 000 визитов в месяц (июнь-август 2026). Вордстат, Беларусь: 1660 запр. в месяц. Тарифы: Free (3 редактируемые доски). Доска для совместной работы; в продуктовые границы ЛР1 как самостоятельный рынок не входит | U19: 02_Доказательства: 9 строк (ID K016) | V19: 30.09.2026
A20: K017 | B20: =IFERROR(IF(INDEX('01_Компании'!$B$4:$B$25,MATCH(A20,'01_Компании'!$A$4:$A$25,0))="","",INDEX('01_Компании'!$B$4:$B$25,MATCH(A20,'01_Компании'!$A$4:$A$25,0))),"") -> Excalidraw | C20: =IFERROR(IF(INDEX('01_Компании'!$C$4:$C$25,MATCH(A20,'01_Компании'!$A$4:$A$25,0))="","",INDEX('01_Компании'!$C$4:$C$25,MATCH(A20,'01_Компании'!$A$4:$A$25,0))),"") -> excalidraw.com | D20: 2 | E20: 3 | F20: 2 | G20: 2 | I20: 3 | J20: 3 | L20: 3 | N20: =IF(COUNTA(D20:M20)=0,"",(D20*'03_Критерии'!$E$4+E20*'03_Критерии'!$E$5+F20*'03_Критерии'!$E$6+G20*'03_Критерии'!$E$7+H20*'03_Критерии'!$E$8+I20*'03_Критерии'!$E$9+J20*'03_Критерии'!$E$10+K20*'03_Критерии'!$E$11+L20*'03_Критерии'!$E$12+M20*'03_Критерии'!$E$13)/SUM('03_Критерии'!$E$4:$E$13)) -> 1.98 | O20: =IF(N20="","",IF(COUNTA(D20:M20)<6,"Недостаточно данных",IF(D20<3,"Низкое совпадение задачи",IF(F20<3,"Низкая товарная заменяемость","Нет")))) -> Низкое совпадение задачи | P20: =IF(N20="","",IF(O20="Недостаточно данных","Недостаточно данных",IF(OR(D20<3,F20<3),IF(N20>=2.5,"Косвенный конкурент / заменитель",IF(N20>=1.6,"Смежная или потенциальная конкуренция","Не конкурент / объект наблюдения")),IF(N20>=4.2,"Прямой конкурент",IF(N20>=3.4,"Близкий альтернативный конкурент",IF(N20>=2.5,"Косвенный конкурент / заменитель",IF(N20>=1.6,"Смежная или потенциальная конкуренция","Не конкурент / объект наблюдения"))))))) -> Смежная или потенциальная конкуренция | R20: =IF(Q20="",P20,Q20) -> Смежная или потенциальная конкуренция | S20: В работе | T20: Уверенность: средняя. Similarweb Pro: 4 253 000 визитов в месяц (июнь-август 2026). Вордстат, Беларусь: 70 запр. в месяц. Наброски вместо нотационных диаграмм; репозиторий с 133 301 звездой | U20: 02_Доказательства: 8 строк (ID K017) | V20: 30.09.2026
A21: K018 | B21: =IFERROR(IF(INDEX('01_Компании'!$B$4:$B$25,MATCH(A21,'01_Компании'!$A$4:$A$25,0))="","",INDEX('01_Компании'!$B$4:$B$25,MATCH(A21,'01_Компании'!$A$4:$A$25,0))),"") -> dbdiagram.io | C21: =IFERROR(IF(INDEX('01_Компании'!$C$4:$C$25,MATCH(A21,'01_Компании'!$A$4:$A$25,0))="","",INDEX('01_Компании'!$C$4:$C$25,MATCH(A21,'01_Компании'!$A$4:$A$25,0))),"") -> dbdiagram.io | D21: 3 | E21: 3 | F21: 2 | G21: 4 | H21: 3 | I21: 3 | J21: 2 | K21: 5 | L21: 3 | N21: =IF(COUNTA(D21:M21)=0,"",(D21*'03_Критерии'!$E$4+E21*'03_Критерии'!$E$5+F21*'03_Критерии'!$E$6+G21*'03_Критерии'!$E$7+H21*'03_Критерии'!$E$8+I21*'03_Критерии'!$E$9+J21*'03_Критерии'!$E$10+K21*'03_Критерии'!$E$11+L21*'03_Критерии'!$E$12+M21*'03_Критерии'!$E$13)/SUM('03_Критерии'!$E$4:$E$13)) -> 2.9 | O21: =IF(N21="","",IF(COUNTA(D21:M21)<6,"Недостаточно данных",IF(D21<3,"Низкое совпадение задачи",IF(F21<3,"Низкая товарная заменяемость","Нет")))) -> Низкая товарная заменяемость | P21: =IF(N21="","",IF(O21="Недостаточно данных","Недостаточно данных",IF(OR(D21<3,F21<3),IF(N21>=2.5,"Косвенный конкурент / заменитель",IF(N21>=1.6,"Смежная или потенциальная конкуренция","Не конкурент / объект наблюдения")),IF(N21>=4.2,"Прямой конкурент",IF(N21>=3.4,"Близкий альтернативный конкурент",IF(N21>=2.5,"Косвенный конкурент / заменитель",IF(N21>=1.6,"Смежная или потенциальная конкуренция","Не конкурент / объект наблюдения"))))))) -> Косвенный конкурент / заменитель | R21: =IF(Q21="",P21,Q21) -> Косвенный конкурент / заменитель | S21: В работе | T21: Уверенность: средняя. Similarweb Pro: 655 207 визитов в месяц (июнь-август 2026). Вордстат, Беларусь: 2 запр. в месяц. Цена: описание: free tool; платный тариф около 8 у.е. (ЛР2-3). Одна нотация (ERD) с вводом текстом; ERD входит в первую волну нотаций NotaCode | U21: 02_Доказательства: 9 строк (ID K018) | V21: 30.09.2026
A22: K019 | B22: =IFERROR(IF(INDEX('01_Компании'!$B$4:$B$25,MATCH(A22,'01_Компании'!$A$4:$A$25,0))="","",INDEX('01_Компании'!$B$4:$B$25,MATCH(A22,'01_Компании'!$A$4:$A$25,0))),"") -> DrawSQL | C22: =IFERROR(IF(INDEX('01_Компании'!$C$4:$C$25,MATCH(A22,'01_Компании'!$A$4:$A$25,0))="","",INDEX('01_Компании'!$C$4:$C$25,MATCH(A22,'01_Компании'!$A$4:$A$25,0))),"") -> drawsql.app | D22: 3 | E22: 3 | F22: 2 | G22: 3 | J22: 2 | L22: 2 | N22: =IF(COUNTA(D22:M22)=0,"",(D22*'03_Критерии'!$E$4+E22*'03_Критерии'!$E$5+F22*'03_Критерии'!$E$6+G22*'03_Критерии'!$E$7+H22*'03_Критерии'!$E$8+I22*'03_Критерии'!$E$9+J22*'03_Критерии'!$E$10+K22*'03_Критерии'!$E$11+L22*'03_Критерии'!$E$12+M22*'03_Критерии'!$E$13)/SUM('03_Критерии'!$E$4:$E$13)) -> 1.93 | O22: =IF(N22="","",IF(COUNTA(D22:M22)<6,"Недостаточно данных",IF(D22<3,"Низкое совпадение задачи",IF(F22<3,"Низкая товарная заменяемость","Нет")))) -> Низкая товарная заменяемость | P22: =IF(N22="","",IF(O22="Недостаточно данных","Недостаточно данных",IF(OR(D22<3,F22<3),IF(N22>=2.5,"Косвенный конкурент / заменитель",IF(N22>=1.6,"Смежная или потенциальная конкуренция","Не конкурент / объект наблюдения")),IF(N22>=4.2,"Прямой конкурент",IF(N22>=3.4,"Близкий альтернативный конкурент",IF(N22>=2.5,"Косвенный конкурент / заменитель",IF(N22>=1.6,"Смежная или потенциальная конкуренция","Не конкурент / объект наблюдения"))))))) -> Смежная или потенциальная конкуренция | R22: =IF(Q22="",P22,Q22) -> Смежная или потенциальная конкуренция | S22: В работе | T22: Уверенность: средняя. Similarweb Pro: 123 677 визитов в месяц (июнь-август 2026). Вордстат, Беларусь: 2 запр. в месяц. Одна нотация (ERD); данные по каналам и географии в Similarweb недоступны | U22: 02_Доказательства: 5 строк (ID K019) | V22: 30.09.2026
A23: K020 | B23: =IFERROR(IF(INDEX('01_Компании'!$B$4:$B$25,MATCH(A23,'01_Компании'!$A$4:$A$25,0))="","",INDEX('01_Компании'!$B$4:$B$25,MATCH(A23,'01_Компании'!$A$4:$A$25,0))),"") -> Eraser | C23: =IFERROR(IF(INDEX('01_Компании'!$C$4:$C$25,MATCH(A23,'01_Компании'!$A$4:$A$25,0))="","",INDEX('01_Компании'!$C$4:$C$25,MATCH(A23,'01_Компании'!$A$4:$A$25,0))),"") -> eraser.io | D23: 4 | E23: 3 | F23: 3 | G23: 4 | H23: 2 | J23: 2 | K23: 5 | L23: 3 | N23: =IF(COUNTA(D23:M23)=0,"",(D23*'03_Критерии'!$E$4+E23*'03_Критерии'!$E$5+F23*'03_Критерии'!$E$6+G23*'03_Критерии'!$E$7+H23*'03_Критерии'!$E$8+I23*'03_Критерии'!$E$9+J23*'03_Критерии'!$E$10+K23*'03_Критерии'!$E$11+L23*'03_Критерии'!$E$12+M23*'03_Критерии'!$E$13)/SUM('03_Критерии'!$E$4:$E$13)) -> 2.96 | O23: =IF(N23="","",IF(COUNTA(D23:M23)<6,"Недостаточно данных",IF(D23<3,"Низкое совпадение задачи",IF(F23<3,"Низкая товарная заменяемость","Нет")))) -> Нет | P23: =IF(N23="","",IF(O23="Недостаточно данных","Недостаточно данных",IF(OR(D23<3,F23<3),IF(N23>=2.5,"Косвенный конкурент / заменитель",IF(N23>=1.6,"Смежная или потенциальная конкуренция","Не конкурент / объект наблюдения")),IF(N23>=4.2,"Прямой конкурент",IF(N23>=3.4,"Близкий альтернативный конкурент",IF(N23>=2.5,"Косвенный конкурент / заменитель",IF(N23>=1.6,"Смежная или потенциальная конкуренция","Не конкурент / объект наблюдения"))))))) -> Косвенный конкурент / заменитель | R23: =IF(Q23="",P23,Q23) -> Косвенный конкурент / заменитель | S23: В работе | T23: Уверенность: средняя. Вордстат, Беларусь: 2 запр. в месяц. Тарифы: Free (0 у.е.. ИИ-режим сопоставим с режимами ИИ-ассистента NotaCode; раздел обзора Similarweb данных не показал | U23: 02_Доказательства: 6 строк (ID K020) | V23: 30.09.2026
A24: K021 | B24: =IFERROR(IF(INDEX('01_Компании'!$B$4:$B$25,MATCH(A24,'01_Компании'!$A$4:$A$25,0))="","",INDEX('01_Компании'!$B$4:$B$25,MATCH(A24,'01_Компании'!$A$4:$A$25,0))),"") -> Whimsical | C24: =IFERROR(IF(INDEX('01_Компании'!$C$4:$C$25,MATCH(A24,'01_Компании'!$A$4:$A$25,0))="","",INDEX('01_Компании'!$C$4:$C$25,MATCH(A24,'01_Компании'!$A$4:$A$25,0))),"") -> whimsical.com | D24: 3 | E24: 3 | F24: 2 | G24: 3 | H24: 3 | K24: 5 | L24: 2 | N24: =IF(COUNTA(D24:M24)=0,"",(D24*'03_Критерии'!$E$4+E24*'03_Критерии'!$E$5+F24*'03_Критерии'!$E$6+G24*'03_Критерии'!$E$7+H24*'03_Критерии'!$E$8+I24*'03_Критерии'!$E$9+J24*'03_Критерии'!$E$10+K24*'03_Критерии'!$E$11+L24*'03_Критерии'!$E$12+M24*'03_Критерии'!$E$13)/SUM('03_Критерии'!$E$4:$E$13)) -> 2.38 | O24: =IF(N24="","",IF(COUNTA(D24:M24)<6,"Недостаточно данных",IF(D24<3,"Низкое совпадение задачи",IF(F24<3,"Низкая товарная заменяемость","Нет")))) -> Низкая товарная заменяемость | P24: =IF(N24="","",IF(O24="Недостаточно данных","Недостаточно данных",IF(OR(D24<3,F24<3),IF(N24>=2.5,"Косвенный конкурент / заменитель",IF(N24>=1.6,"Смежная или потенциальная конкуренция","Не конкурент / объект наблюдения")),IF(N24>=4.2,"Прямой конкурент",IF(N24>=3.4,"Близкий альтернативный конкурент",IF(N24>=2.5,"Косвенный конкурент / заменитель",IF(N24>=1.6,"Смежная или потенциальная конкуренция","Не конкурент / объект наблюдения"))))))) -> Смежная или потенциальная конкуренция | R24: =IF(Q24="",P24,Q24) -> Смежная или потенциальная конкуренция | S24: В работе | T24: Уверенность: средняя. Вордстат, Беларусь: 59 запр. в месяц. Тарифы: Free (0 у.е.. Главная страница и тарифы просмотрены 01.10.2026: диаграммы и схемы интерфейсов для команд продуктов, формальных нотаций UML и BPMN как набора нет; Similarweb не собирался; запрос «whimsical» в Вордстате - омоним | U24: 02_Доказательства: 4 строк (ID K021) | V24: 30.09.2026
A25: K022 | B25: =IFERROR(IF(INDEX('01_Компании'!$B$4:$B$25,MATCH(A25,'01_Компании'!$A$4:$A$25,0))="","",INDEX('01_Компании'!$B$4:$B$25,MATCH(A25,'01_Компании'!$A$4:$A$25,0))),"") -> Microsoft Visio | C25: =IFERROR(IF(INDEX('01_Компании'!$C$4:$C$25,MATCH(A25,'01_Компании'!$A$4:$A$25,0))="","",INDEX('01_Компании'!$C$4:$C$25,MATCH(A25,'01_Компании'!$A$4:$A$25,0))),"") -> microsoft.com/visio | D25: 3 | E25: 3 | F25: 2 | G25: 2 | H25: 4 | I25: 2 | J25: 4 | K25: 4 | N25: =IF(COUNTA(D25:M25)=0,"",(D25*'03_Критерии'!$E$4+E25*'03_Критерии'!$E$5+F25*'03_Критерии'!$E$6+G25*'03_Критерии'!$E$7+H25*'03_Критерии'!$E$8+I25*'03_Критерии'!$E$9+J25*'03_Критерии'!$E$10+K25*'03_Критерии'!$E$11+L25*'03_Критерии'!$E$12+M25*'03_Критерии'!$E$13)/SUM('03_Критерии'!$E$4:$E$13)) -> 2.65 | O25: =IF(N25="","",IF(COUNTA(D25:M25)<6,"Недостаточно данных",IF(D25<3,"Низкое совпадение задачи",IF(F25<3,"Низкая товарная заменяемость","Нет")))) -> Низкая товарная заменяемость | P25: =IF(N25="","",IF(O25="Недостаточно данных","Недостаточно данных",IF(OR(D25<3,F25<3),IF(N25>=2.5,"Косвенный конкурент / заменитель",IF(N25>=1.6,"Смежная или потенциальная конкуренция","Не конкурент / объект наблюдения")),IF(N25>=4.2,"Прямой конкурент",IF(N25>=3.4,"Близкий альтернативный конкурент",IF(N25>=2.5,"Косвенный конкурент / заменитель",IF(N25>=1.6,"Смежная или потенциальная конкуренция","Не конкурент / объект наблюдения"))))))) -> Косвенный конкурент / заменитель | R25: =IF(Q25="",P25,Q25) -> Косвенный конкурент / заменитель | S25: В работе | T25: Уверенность: низкая. Вордстат, Беларусь: 1501 запр. в месяц. Тарифы: Plan 1 - 5 у.е., Plan 2 - 15 у.е. за пользователя в месяц при оплате за год. Домен-раздел без отдельного трафика (ЛР4); использованы тарифы ЛР1 и частота запроса «visio» (1501) | U25: 02_Доказательства: 2 строк (ID K022) | V25: 30.09.2026

Sheet 05_Уровни
A1: Классификация компаний по уровням конкуренции | B1: Классификация компаний по уровням конкуренции | C1: Классификация компаний по уровням конкуренции | D1: Классификация компаний по уровням конкуренции | E1: Классификация компаний по уровням конкуренции | F1: Классификация компаний по уровням конкуренции | G1: Классификация компаний по уровням конкуренции
A3: Уровень | B3: Определение | C3: Ключевой критерий | D3: Порог по баллу | E3: Обязательные условия | F3: Типовые признаки на сайте | G3: Решение аналитика
A4: Прямой конкурент | B4: Компания удовлетворяет ту же потребительскую задачу для той же или близкой аудитории сопоставимым цифровым товаром | C4: Высокая заменяемость товара и совпадение целевого сегмента | D4: 4,20–5,00 | E4: Потребительская задача ≥ 3; функциональная заменяемость ≥ 3 | F4: Сходные тарифы, сценарии использования, обещания результата, демонстрации товара, одинаковые категории клиентов | G4: Включить в постоянный конкурентный мониторинг
A5: Близкий альтернативный конкурент | B5: Компания решает ту же или близкую задачу, но делает это через иной формат товара, канал, сегмент или модель оплаты | C5: Клиент может рассматривать решение как практическую альтернативу | D5: 3,40–4,19 | E5: Нет критического расхождения по потребительской задаче | F5: Похожие выгоды, частично отличающаяся функциональность, иной формат доступа, другая тарифная логика | G5: Сравнивать по ценностному предложению и причинам выбора
A6: Косвенный конкурент / заменитель | B6: Компания закрывает ту же потребность и может заменить покупку, но товарная категория или способ решения заметно отличаются | C6: Есть конкуренция за бюджет, внимание или способ выполнения задачи | D6: 2,50–3,39 | E6: Достаточно доказательств заменяемости | F6: Иные продукты, услуги или платформы, которые дают сходный конечный результат | G6: Анализировать как угрозу замещения
A7: Смежная или потенциальная конкуренция | B7: Компания пока не является прямым конкурентом, но имеет близкую аудиторию, смежный товар, инфраструктуру или возможность расшириться в рассматриваемый рынок | C7: Вероятность входа в рынок или расширения товарной линейки | D7: 1,60–2,49 | E7: Наличие хотя бы одного сильного сигнала пересечения | F7: Смежные разделы сайта, близкие категории клиентов, партнерства, вакансии, дорожная карта, упоминания планов развития | G7: Наблюдать периодически; не смешивать с прямыми конкурентами
A8: Не конкурент / объект наблюдения | B8: Компания не показывает значимого пересечения по задаче, аудитории, товару и заменяемости | C8: Недостаточная рыночная и товарная близость | D8: 0,00–1,59 | E8: Нет значимых доказательств конкуренции | F8: Общее сходство отрасли без совпадения задачи и товара | G8: Исключить из основной матрицы, оставить только при методической необходимости
A9: Недостаточно данных | B9: По сайту невозможно надежно установить уровень конкуренции | C9: Недостаток фактов или противоречивые сигналы | D9: не применяется | E9: Менее трех содержательных доказательств | F9: Закрытые тарифы, неполные описания, отсутствие страниц товара, нет сегментации клиентов | G9: Вернуться к анализу после сбора дополнительных источников

Sheet 06_Сводка
A1: Сводка классификации компаний по уровням конкуренции | B1: Сводка классификации компаний по уровням конкуренции | C1: Сводка классификации компаний по уровням конкуренции | D1: Сводка классификации компаний по уровням конкуренции | E1: Сводка классификации компаний по уровням конкуренции | F1: Сводка классификации компаний по уровням конкуренции | G1: Сводка классификации компаний по уровням конкуренции | H1: Сводка классификации компаний по уровням конкуренции | I1: Сводка классификации компаний по уровням конкуренции | J1: Сводка классификации компаний по уровням конкуренции
A3: Показатель | B3: Значение
A4: Всего компаний в реестре | B4: =COUNTA('01_Компании'!$B$4:$B$25) -> 22
A5: Компаний с заполненной оценкой | B5: =COUNT('04_Оценка'!$N$4:$N$25) -> 22
A6: Средний взвешенный балл | B6: =IFERROR(AVERAGE('04_Оценка'!$N$4:$N$25),"") -> 2.8263636
A7: Компаний с уровнем «Прямой конкурент» | B7: =COUNTIF('04_Оценка'!$R$4:$R$25,"Прямой конкурент") -> 1 | C7: 0.05 | D7: Включить в основной бенчмарк и регулярный мониторинг
A8: Компаний с уровнем «Близкий альтернативный конкурент» | B8: =COUNTIF('04_Оценка'!$R$4:$R$25,"Близкий альтернативный конкурент") -> 4 | C8: 0.18 | D8: Сравнивать по причинам выбора и формату ценности
A10: Уровень конкуренции | B10: Количество | C10: Доля | D10: Методическое действие
A11: Прямой конкурент | B11: =COUNTIF('04_Оценка'!$R$4:$R$25,A11) -> 1 | C11: =IFERROR(B11/SUM($B$11:$B$16),0) -> 0.045454545 | D11: Включить в основной бенчмарк и регулярный мониторинг
A12: Близкий альтернативный конкурент | B12: =COUNTIF('04_Оценка'!$R$4:$R$25,A12) -> 4 | C12: =IFERROR(B12/SUM($B$11:$B$16),0) -> 0.18181818 | D12: Сравнивать по причинам выбора и формату ценности
A13: Косвенный конкурент / заменитель | B13: =COUNTIF('04_Оценка'!$R$4:$R$25,A13) -> 9 | C13: =IFERROR(B13/SUM($B$11:$B$16),0) -> 0.40909091 | D13: Оценивать угрозу замещения и конкуренцию за бюджет
A14: Смежная или потенциальная конкуренция | B14: =COUNTIF('04_Оценка'!$R$4:$R$25,A14) -> 7 | C14: =IFERROR(B14/SUM($B$11:$B$16),0) -> 0.31818182 | D14: Наблюдать по сигналам расширения
A15: Не конкурент / объект наблюдения | B15: =COUNTIF('04_Оценка'!$R$4:$R$25,A15) -> 0 | C15: =IFERROR(B15/SUM($B$11:$B$16),0) -> 0 | D15: Исключить из основной матрицы
A16: Недостаточно данных | B16: =COUNTIF('04_Оценка'!$R$4:$R$25,A16) -> 1 | C16: =IFERROR(B16/SUM($B$11:$B$16),0) -> 0.045454545 | D16: Дособрать доказательства
A18: Топ компаний по близости к прямой конкуренции | B18: Компания | C18: Сайт | D18: Бал | E18: Итоговый уровень | F18: Обоснование
A19: 1 | B19: {=IF(D19="","",INDEX('04_Оценка'!$B$4:$B$25,_xlfn.AGGREGATE(15,6,(ROW('04_Оценка'!$N$4:$N$25)-ROW('04_Оценка'!$N$4)+1)/('04_Оценка'!$N$4:$N$25=D19),COUNTIF($D$19:D19,D19))))} -> PlantUML | C19: {=IF(D19="","",INDEX('04_Оценка'!$C$4:$C$25,_xlfn.AGGREGATE(15,6,(ROW('04_Оценка'!$N$4:$N$25)-ROW('04_Оценка'!$N$4)+1)/('04_Оценка'!$N$4:$N$25=D19),COUNTIF($D$19:D19,D19))))} -> plantuml.com | D19: =IFERROR(LARGE('04_Оценка'!$N$4:$N$25,A19),"") -> 4.1 | E19: {=IF(D19="","",INDEX('04_Оценка'!$R$4:$R$25,_xlfn.AGGREGATE(15,6,(ROW('04_Оценка'!$N$4:$N$25)-ROW('04_Оценка'!$N$4)+1)/('04_Оценка'!$N$4:$N$25=D19),COUNTIF($D$19:D19,D19))))} -> Прямой конкурент | F19: {=IF(D19="","",INDEX('04_Оценка'!$T$4:$T$25,_xlfn.AGGREGATE(15,6,(ROW('04_Оценка'!$N$4:$N$25)-ROW('04_Оценка'!$N$4)+1)/('04_Оценка'!$N$4:$N$25=D19),COUNTIF($D$19:D19,D19))))} -> Экспертная корректировка: Расчетный балл 4,10 лишь на 0,10 ниже порога 4,20; по правилу методики (индекс 65-79 и постоянное присутствие в тех же запросах) допускается повышение до прямого. Подтверждения: (1) запрос «plantuml» - 200 запросов в месяц в Беларуси (Вордстат, 29.08-27.09.2026), максимум среди брендов текстовых DSL; (2) страница товара и описание совпадают с задачей NotaCode (title/description 30.09.2026); (3) ЛР1 табл. 44 относит PlantUML к прямым конкурентам; (4) плагины IDE: 3 712 111 установок VS Marketplace и 5 014 362 загрузки JetBrains (ЛР2-3). Уверенность: средняя. Similarweb Pro: 739 657 визитов в месяц (июнь-август 2026). Вордстат, Беларусь: 200 запр. в месяц. Цена: открытый код, бесплатно (ЛР1, табл. 42). Главное обещание совпадает с задачей NotaCode: диаграммы UML из текста
A20: 2 | B20: {=IF(D20="","",INDEX('04_Оценка'!$B$4:$B$25,_xlfn.AGGREGATE(15,6,(ROW('04_Оценка'!$N$4:$N$25)-ROW('04_Оценка'!$N$4)+1)/('04_Оценка'!$N$4:$N$25=D20),COUNTIF($D$19:D20,D20))))} -> Mermaid (библиотека) | C20: {=IF(D20="","",INDEX('04_Оценка'!$C$4:$C$25,_xlfn.AGGREGATE(15,6,(ROW('04_Оценка'!$N$4:$N$25)-ROW('04_Оценка'!$N$4)+1)/('04_Оценка'!$N$4:$N$25=D20),COUNTIF($D$19:D20,D20))))} -> mermaid.js.org | D20: =IFERROR(LARGE('04_Оценка'!$N$4:$N$25,A20),"") -> 4.07 | E20: {=IF(D20="","",INDEX('04_Оценка'!$R$4:$R$25,_xlfn.AGGREGATE(15,6,(ROW('04_Оценка'!$N$4:$N$25)-ROW('04_Оценка'!$N$4)+1)/('04_Оценка'!$N$4:$N$25=D20),COUNTIF($D$19:D20,D20))))} -> Близкий альтернативный конкурент | F20: {=IF(D20="","",INDEX('04_Оценка'!$T$4:$T$25,_xlfn.AGGREGATE(15,6,(ROW('04_Оценка'!$N$4:$N$25)-ROW('04_Оценка'!$N$4)+1)/('04_Оценка'!$N$4:$N$25=D20),COUNTIF($D$19:D20,D20))))} -> Уверенность: средняя. Similarweb Pro: 442 646 визитов в месяц (июнь-август 2026). Вордстат, Беларусь: 19 запр. в месяц. Цена: открытый код (MIT); платные планы у Mermaid Chart. Задача та же (диаграммы из текста и кода), нотаций UML/BPMN/IDEF как набора с проверкой правил в описании нет
A21: 3 | B21: {=IF(D21="","",INDEX('04_Оценка'!$B$4:$B$25,_xlfn.AGGREGATE(15,6,(ROW('04_Оценка'!$N$4:$N$25)-ROW('04_Оценка'!$N$4)+1)/('04_Оценка'!$N$4:$N$25=D21),COUNTIF($D$19:D21,D21))))} -> PlantText | C21: {=IF(D21="","",INDEX('04_Оценка'!$C$4:$C$25,_xlfn.AGGREGATE(15,6,(ROW('04_Оценка'!$N$4:$N$25)-ROW('04_Оценка'!$N$4)+1)/('04_Оценка'!$N$4:$N$25=D21),COUNTIF($D$19:D21,D21))))} -> planttext.com | D21: =IFERROR(LARGE('04_Оценка'!$N$4:$N$25,A21),"") -> 3.72 | E21: {=IF(D21="","",INDEX('04_Оценка'!$R$4:$R$25,_xlfn.AGGREGATE(15,6,(ROW('04_Оценка'!$N$4:$N$25)-ROW('04_Оценка'!$N$4)+1)/('04_Оценка'!$N$4:$N$25=D21),COUNTIF($D$19:D21,D21))))} -> Близкий альтернативный конкурент | F21: {=IF(D21="","",INDEX('04_Оценка'!$T$4:$T$25,_xlfn.AGGREGATE(15,6,(ROW('04_Оценка'!$N$4:$N$25)-ROW('04_Оценка'!$N$4)+1)/('04_Оценка'!$N$4:$N$25=D21),COUNTIF($D$19:D21,D21))))} -> Уверенность: средняя. Similarweb Pro: 339 451 визитов в месяц (июнь-август 2026). Вордстат, Беларусь: 9 запр. в месяц. Цена: заголовок страницы: Free & Fast. В заголовке заявлены бесплатность и онлайн-доступ; редактор поверх PlantUML
A22: 4 | B22: {=IF(D22="","",INDEX('04_Оценка'!$B$4:$B$25,_xlfn.AGGREGATE(15,6,(ROW('04_Оценка'!$N$4:$N$25)-ROW('04_Оценка'!$N$4)+1)/('04_Оценка'!$N$4:$N$25=D22),COUNTIF($D$19:D22,D22))))} -> Mermaid Chart | C22: {=IF(D22="","",INDEX('04_Оценка'!$C$4:$C$25,_xlfn.AGGREGATE(15,6,(ROW('04_Оценка'!$N$4:$N$25)-ROW('04_Оценка'!$N$4)+1)/('04_Оценка'!$N$4:$N$25=D22),COUNTIF($D$19:D22,D22))))} -> mermaidchart.com | D22: =IFERROR(LARGE('04_Оценка'!$N$4:$N$25,A22),"") -> 3.71 | E22: {=IF(D22="","",INDEX('04_Оценка'!$R$4:$R$25,_xlfn.AGGREGATE(15,6,(ROW('04_Оценка'!$N$4:$N$25)-ROW('04_Оценка'!$N$4)+1)/('04_Оценка'!$N$4:$N$25=D22),COUNTIF($D$19:D22,D22))))} -> Близкий альтернативный конкурент | F22: {=IF(D22="","",INDEX('04_Оценка'!$T$4:$T$25,_xlfn.AGGREGATE(15,6,(ROW('04_Оценка'!$N$4:$N$25)-ROW('04_Оценка'!$N$4)+1)/('04_Оценка'!$N$4:$N$25=D22),COUNTIF($D$19:D22,D22))))} -> Уверенность: средняя. Similarweb Pro: 2 535 визитов в месяц (июнь-август 2026). Вордстат, Беларусь: 0 запр. в месяц. Тарифы: Free (до 6 диаграмм, 15 AI-кредитов). Платная надстройка над Mermaid; домен, вероятно, перенесен на mermaid.ai (трафик mermaidchart.com -82,22 %)
A23: 5 | B23: {=IF(D23="","",INDEX('04_Оценка'!$B$4:$B$25,_xlfn.AGGREGATE(15,6,(ROW('04_Оценка'!$N$4:$N$25)-ROW('04_Оценка'!$N$4)+1)/('04_Оценка'!$N$4:$N$25=D23),COUNTIF($D$19:D23,D23))))} -> Visual Paradigm | C23: {=IF(D23="","",INDEX('04_Оценка'!$C$4:$C$25,_xlfn.AGGREGATE(15,6,(ROW('04_Оценка'!$N$4:$N$25)-ROW('04_Оценка'!$N$4)+1)/('04_Оценка'!$N$4:$N$25=D23),COUNTIF($D$19:D23,D23))))} -> visual-paradigm.com | D23: =IFERROR(LARGE('04_Оценка'!$N$4:$N$25,A23),"") -> 3.63 | E23: {=IF(D23="","",INDEX('04_Оценка'!$R$4:$R$25,_xlfn.AGGREGATE(15,6,(ROW('04_Оценка'!$N$4:$N$25)-ROW('04_Оценка'!$N$4)+1)/('04_Оценка'!$N$4:$N$25=D23),COUNTIF($D$19:D23,D23))))} -> Близкий альтернативный конкурент | F23: {=IF(D23="","",INDEX('04_Оценка'!$T$4:$T$25,_xlfn.AGGREGATE(15,6,(ROW('04_Оценка'!$N$4:$N$25)-ROW('04_Оценка'!$N$4)+1)/('04_Оценка'!$N$4:$N$25=D23),COUNTIF($D$19:D23,D23))))} -> Уверенность: средняя. Similarweb Pro: 1 516 000 визитов в месяц (июнь-август 2026). Вордстат, Беларусь: 46 запр. в месяц. Тарифы: Подписка: Modeler 6, Standard 19, Professional 35, Enterprise 89 у.е. в месяц. Широкий набор нотаций и ИИ; графический ввод, ценовой уровень выше NotaCode
A24: 6 | B24: {=IF(D24="","",INDEX('04_Оценка'!$B$4:$B$25,_xlfn.AGGREGATE(15,6,(ROW('04_Оценка'!$N$4:$N$25)-ROW('04_Оценка'!$N$4)+1)/('04_Оценка'!$N$4:$N$25=D24),COUNTIF($D$19:D24,D24))))} -> draw.io (diagrams.net) | C24: {=IF(D24="","",INDEX('04_Оценка'!$C$4:$C$25,_xlfn.AGGREGATE(15,6,(ROW('04_Оценка'!$N$4:$N$25)-ROW('04_Оценка'!$N$4)+1)/('04_Оценка'!$N$4:$N$25=D24),COUNTIF($D$19:D24,D24))))} -> app.diagrams.net | D24: =IFERROR(LARGE('04_Оценка'!$N$4:$N$25,A24),"") -> 3.24 | E24: {=IF(D24="","",INDEX('04_Оценка'!$R$4:$R$25,_xlfn.AGGREGATE(15,6,(ROW('04_Оценка'!$N$4:$N$25)-ROW('04_Оценка'!$N$4)+1)/('04_Оценка'!$N$4:$N$25=D24),COUNTIF($D$19:D24,D24))))} -> Косвенный конкурент / заменитель | F24: {=IF(D24="","",INDEX('04_Оценка'!$T$4:$T$25,_xlfn.AGGREGATE(15,6,(ROW('04_Оценка'!$N$4:$N$25)-ROW('04_Оценка'!$N$4)+1)/('04_Оценка'!$N$4:$N$25=D24),COUNTIF($D$19:D24,D24))))} -> Уверенность: средняя. Similarweb Pro: 8 497 000 визитов в месяц (июнь-август 2026). Вордстат, Беларусь: 1072 запр. в месяц. Цена: полностью бесплатный, открытый код (Apache 2.0) (ЛР1, табл. 42). Универсальный графический редактор; бесплатный, открытый код, заявлено более 100 млн пользователей
A25: 7 | B25: {=IF(D25="","",INDEX('04_Оценка'!$B$4:$B$25,_xlfn.AGGREGATE(15,6,(ROW('04_Оценка'!$N$4:$N$25)-ROW('04_Оценка'!$N$4)+1)/('04_Оценка'!$N$4:$N$25=D25),COUNTIF($D$19:D25,D25))))} -> Lucidchart | C25: {=IF(D25="","",INDEX('04_Оценка'!$C$4:$C$25,_xlfn.AGGREGATE(15,6,(ROW('04_Оценка'!$N$4:$N$25)-ROW('04_Оценка'!$N$4)+1)/('04_Оценка'!$N$4:$N$25=D25),COUNTIF($D$19:D25,D25))))} -> lucidchart.com | D25: =IFERROR(LARGE('04_Оценка'!$N$4:$N$25,A25),"") -> 3.13 | E25: {=IF(D25="","",INDEX('04_Оценка'!$R$4:$R$25,_xlfn.AGGREGATE(15,6,(ROW('04_Оценка'!$N$4:$N$25)-ROW('04_Оценка'!$N$4)+1)/('04_Оценка'!$N$4:$N$25=D25),COUNTIF($D$19:D25,D25))))} -> Косвенный конкурент / заменитель | F25: {=IF(D25="","",INDEX('04_Оценка'!$T$4:$T$25,_xlfn.AGGREGATE(15,6,(ROW('04_Оценка'!$N$4:$N$25)-ROW('04_Оценка'!$N$4)+1)/('04_Оценка'!$N$4:$N$25=D25),COUNTIF($D$19:D25,D25))))} -> Уверенность: средняя. Similarweb Pro: 703 574 визитов в месяц (июнь-август 2026). Вордстат, Беларусь: 24 запр. в месяц. Тарифы: Free (3 редактируемых документа, 75 фигур на документ). Главная страница вернула HTTP 403; описание продукта не получено, оценка по ЛР1, ЛР2-3, G2, Capterra
A26: 8 | B26: {=IF(D26="","",INDEX('04_Оценка'!$B$4:$B$25,_xlfn.AGGREGATE(15,6,(ROW('04_Оценка'!$N$4:$N$25)-ROW('04_Оценка'!$N$4)+1)/('04_Оценка'!$N$4:$N$25=D26),COUNTIF($D$19:D26,D26))))} -> Creately | C26: {=IF(D26="","",INDEX('04_Оценка'!$C$4:$C$25,_xlfn.AGGREGATE(15,6,(ROW('04_Оценка'!$N$4:$N$25)-ROW('04_Оценка'!$N$4)+1)/('04_Оценка'!$N$4:$N$25=D26),COUNTIF($D$19:D26,D26))))} -> creately.com | D26: =IFERROR(LARGE('04_Оценка'!$N$4:$N$25,A26),"") -> 2.99 | E26: {=IF(D26="","",INDEX('04_Оценка'!$R$4:$R$25,_xlfn.AGGREGATE(15,6,(ROW('04_Оценка'!$N$4:$N$25)-ROW('04_Оценка'!$N$4)+1)/('04_Оценка'!$N$4:$N$25=D26),COUNTIF($D$19:D26,D26))))} -> Косвенный конкурент / заменитель | F26: {=IF(D26="","",INDEX('04_Оценка'!$T$4:$T$25,_xlfn.AGGREGATE(15,6,(ROW('04_Оценка'!$N$4:$N$25)-ROW('04_Оценка'!$N$4)+1)/('04_Оценка'!$N$4:$N$25=D26),COUNTIF($D$19:D26,D26))))} -> Уверенность: средняя. Similarweb Pro: 784 067 визитов в месяц (июнь-август 2026). Вордстат, Беларусь: 4 запр. в месяц. Тарифы: Платные тарифы от 5 до 89 у.е. в месяц (ЛР2-3, табл. 70: 15,14 - 269,54 BYN). Универсальный редактор; отзывы на Trustpilot низкие (1,9 из 5 при 58 отзывах)
A27: 9 | B27: {=IF(D27="","",INDEX('04_Оценка'!$B$4:$B$25,_xlfn.AGGREGATE(15,6,(ROW('04_Оценка'!$N$4:$N$25)-ROW('04_Оценка'!$N$4)+1)/('04_Оценка'!$N$4:$N$25=D27),COUNTIF($D$19:D27,D27))))} -> Eraser | C27: {=IF(D27="","",INDEX('04_Оценка'!$C$4:$C$25,_xlfn.AGGREGATE(15,6,(ROW('04_Оценка'!$N$4:$N$25)-ROW('04_Оценка'!$N$4)+1)/('04_Оценка'!$N$4:$N$25=D27),COUNTIF($D$19:D27,D27))))} -> eraser.io | D27: =IFERROR(LARGE('04_Оценка'!$N$4:$N$25,A27),"") -> 2.96 | E27: {=IF(D27="","",INDEX('04_Оценка'!$R$4:$R$25,_xlfn.AGGREGATE(15,6,(ROW('04_Оценка'!$N$4:$N$25)-ROW('04_Оценка'!$N$4)+1)/('04_Оценка'!$N$4:$N$25=D27),COUNTIF($D$19:D27,D27))))} -> Косвенный конкурент / заменитель | F27: {=IF(D27="","",INDEX('04_Оценка'!$T$4:$T$25,_xlfn.AGGREGATE(15,6,(ROW('04_Оценка'!$N$4:$N$25)-ROW('04_Оценка'!$N$4)+1)/('04_Оценка'!$N$4:$N$25=D27),COUNTIF($D$19:D27,D27))))} -> Уверенность: средняя. Вордстат, Беларусь: 2 запр. в месяц. Тарифы: Free (0 у.е.. ИИ-режим сопоставим с режимами ИИ-ассистента NotaCode; раздел обзора Similarweb данных не показал
A28: 10 | B28: {=IF(D28="","",INDEX('04_Оценка'!$B$4:$B$25,_xlfn.AGGREGATE(15,6,(ROW('04_Оценка'!$N$4:$N$25)-ROW('04_Оценка'!$N$4)+1)/('04_Оценка'!$N$4:$N$25=D28),COUNTIF($D$19:D28,D28))))} -> dbdiagram.io | C28: {=IF(D28="","",INDEX('04_Оценка'!$C$4:$C$25,_xlfn.AGGREGATE(15,6,(ROW('04_Оценка'!$N$4:$N$25)-ROW('04_Оценка'!$N$4)+1)/('04_Оценка'!$N$4:$N$25=D28),COUNTIF($D$19:D28,D28))))} -> dbdiagram.io | D28: =IFERROR(LARGE('04_Оценка'!$N$4:$N$25,A28),"") -> 2.9 | E28: {=IF(D28="","",INDEX('04_Оценка'!$R$4:$R$25,_xlfn.AGGREGATE(15,6,(ROW('04_Оценка'!$N$4:$N$25)-ROW('04_Оценка'!$N$4)+1)/('04_Оценка'!$N$4:$N$25=D28),COUNTIF($D$19:D28,D28))))} -> Косвенный конкурент / заменитель | F28: {=IF(D28="","",INDEX('04_Оценка'!$T$4:$T$25,_xlfn.AGGREGATE(15,6,(ROW('04_Оценка'!$N$4:$N$25)-ROW('04_Оценка'!$N$4)+1)/('04_Оценка'!$N$4:$N$25=D28),COUNTIF($D$19:D28,D28))))} -> Уверенность: средняя. Similarweb Pro: 655 207 визитов в месяц (июнь-август 2026). Вордстат, Беларусь: 2 запр. в месяц. Цена: описание: free tool; платный тариф около 8 у.е. (ЛР2-3). Одна нотация (ERD) с вводом текстом; ERD входит в первую волну нотаций NotaCode

Sheet 07_Карта
A1: Карта конкурентной близости | B1: Карта конкурентной близости | C1: Карта конкурентной близости | D1: Карта конкурентной близости | E1: Карта конкурентной близости | F1: Карта конкурентной близости | G1: Карта конкурентной близости | H1: Карта конкурентной близости | I1: Карта конкурентной близости | J1: Карта конкурентной близости | K1: Карта конкурентной близости
A3: ID | B3: Компания | C3: X: задача + заменяемость | D3: Y: аудитория + рынок | E3: Взвешенный балл | F3: Итоговый уровень | G3: Зона карты | H3: Комментарий | I3: Доказательства | J3: Приоритет | K3: Статус
A4: K001 | B4: =IFERROR(IF(INDEX('04_Оценка'!$B$4:$B$25,MATCH(A4,'04_Оценка'!$A$4:$A$25,0))="","",INDEX('04_Оценка'!$B$4:$B$25,MATCH(A4,'04_Оценка'!$A$4:$A$25,0))),"") -> PlantUML | C4: =IFERROR(AVERAGE('04_Оценка'!D4,'04_Оценка'!F4),"") -> 4.5 | D4: =IFERROR(AVERAGE('04_Оценка'!E4,'04_Оценка'!J4),"") -> 4 | E4: =IFERROR('04_Оценка'!N4,"") -> 4.1 | F4: =IFERROR('04_Оценка'!R4,"") -> Прямой конкурент | G4: =IF(E4="","",IF(OR(F4="Недостаточно данных",C4="",D4=""),"Нет данных",IF(AND(C4>=4,D4>=4),"Ядро прямой конкуренции",IF(AND(C4>=3,D4>=3),"Близкая альтернатива",IF(C4>=3,"Функциональный заменитель",IF(D4>=3,"Аудиторное пересечение","Периферия")))))) -> Ядро прямой конкуренции | H4: Уверенность: средняя; заполнено критериев: 10 из 10 | I4: 02_Доказательства: 11 строк | J4: =IFERROR(IF(INDEX('01_Компании'!$I$4:$I$25,MATCH(A4,'01_Компании'!$A$4:$A$25,0))="","",INDEX('01_Компании'!$I$4:$I$25,MATCH(A4,'01_Компании'!$A$4:$A$25,0))),"") -> Высокий | K4: =IFERROR(IF(INDEX('04_Оценка'!$S$4:$S$25,MATCH(A4,'04_Оценка'!$A$4:$A$25,0))="","",INDEX('04_Оценка'!$S$4:$S$25,MATCH(A4,'04_Оценка'!$A$4:$A$25,0))),"") -> В работе
A5: K002 | B5: =IFERROR(IF(INDEX('04_Оценка'!$B$4:$B$25,MATCH(A5,'04_Оценка'!$A$4:$A$25,0))="","",INDEX('04_Оценка'!$B$4:$B$25,MATCH(A5,'04_Оценка'!$A$4:$A$25,0))),"") -> Mermaid (библиотека) | C5: =IFERROR(AVERAGE('04_Оценка'!D5,'04_Оценка'!F5),"") -> 4.5 | D5: =IFERROR(AVERAGE('04_Оценка'!E5,'04_Оценка'!J5),"") -> 3.5 | E5: =IFERROR('04_Оценка'!N5,"") -> 4.07 | F5: =IFERROR('04_Оценка'!R5,"") -> Близкий альтернативный конкурент | G5: =IF(E5="","",IF(OR(F5="Недостаточно данных",C5="",D5=""),"Нет данных",IF(AND(C5>=4,D5>=4),"Ядро прямой конкуренции",IF(AND(C5>=3,D5>=3),"Близкая альтернатива",IF(C5>=3,"Функциональный заменитель",IF(D5>=3,"Аудиторное пересечение","Периферия")))))) -> Близкая альтернатива | H5: Уверенность: средняя; заполнено критериев: 10 из 10 | I5: 02_Доказательства: 11 строк | J5: =IFERROR(IF(INDEX('01_Компании'!$I$4:$I$25,MATCH(A5,'01_Компании'!$A$4:$A$25,0))="","",INDEX('01_Компании'!$I$4:$I$25,MATCH(A5,'01_Компании'!$A$4:$A$25,0))),"") -> Высокий | K5: =IFERROR(IF(INDEX('04_Оценка'!$S$4:$S$25,MATCH(A5,'04_Оценка'!$A$4:$A$25,0))="","",INDEX('04_Оценка'!$S$4:$S$25,MATCH(A5,'04_Оценка'!$A$4:$A$25,0))),"") -> В работе
A6: K003 | B6: =IFERROR(IF(INDEX('04_Оценка'!$B$4:$B$25,MATCH(A6,'04_Оценка'!$A$4:$A$25,0))="","",INDEX('04_Оценка'!$B$4:$B$25,MATCH(A6,'04_Оценка'!$A$4:$A$25,0))),"") -> Mermaid Chart | C6: =IFERROR(AVERAGE('04_Оценка'!D6,'04_Оценка'!F6),"") -> 4.5 | D6: =IFERROR(AVERAGE('04_Оценка'!E6,'04_Оценка'!J6),"") -> 2.5 | E6: =IFERROR('04_Оценка'!N6,"") -> 3.71 | F6: =IFERROR('04_Оценка'!R6,"") -> Близкий альтернативный конкурент | G6: =IF(E6="","",IF(OR(F6="Недостаточно данных",C6="",D6=""),"Нет данных",IF(AND(C6>=4,D6>=4),"Ядро прямой конкуренции",IF(AND(C6>=3,D6>=3),"Близкая альтернатива",IF(C6>=3,"Функциональный заменитель",IF(D6>=3,"Аудиторное пересечение","Периферия")))))) -> Функциональный заменитель | H6: Уверенность: средняя; заполнено критериев: 10 из 10 | I6: 02_Доказательства: 10 строк | J6: =IFERROR(IF(INDEX('01_Компании'!$I$4:$I$25,MATCH(A6,'01_Компании'!$A$4:$A$25,0))="","",INDEX('01_Компании'!$I$4:$I$25,MATCH(A6,'01_Компании'!$A$4:$A$25,0))),"") -> Высокий | K6: =IFERROR(IF(INDEX('04_Оценка'!$S$4:$S$25,MATCH(A6,'04_Оценка'!$A$4:$A$25,0))="","",INDEX('04_Оценка'!$S$4:$S$25,MATCH(A6,'04_Оценка'!$A$4:$A$25,0))),"") -> В работе
A7: K004 | B7: =IFERROR(IF(INDEX('04_Оценка'!$B$4:$B$25,MATCH(A7,'04_Оценка'!$A$4:$A$25,0))="","",INDEX('04_Оценка'!$B$4:$B$25,MATCH(A7,'04_Оценка'!$A$4:$A$25,0))),"") -> D2 (Terrastruct) | C7: =IFERROR(AVERAGE('04_Оценка'!D7,'04_Оценка'!F7),"") -> 3.5 | D7: =IFERROR(AVERAGE('04_Оценка'!E7,'04_Оценка'!J7),"") -> 2.5 | E7: =IFERROR('04_Оценка'!N7,"") -> 2.82 | F7: =IFERROR('04_Оценка'!R7,"") -> Косвенный конкурент / заменитель | G7: =IF(E7="","",IF(OR(F7="Недостаточно данных",C7="",D7=""),"Нет данных",IF(AND(C7>=4,D7>=4),"Ядро прямой конкуренции",IF(AND(C7>=3,D7>=3),"Близкая альтернатива",IF(C7>=3,"Функциональный заменитель",IF(D7>=3,"Аудиторное пересечение","Периферия")))))) -> Функциональный заменитель | H7: Уверенность: средняя; заполнено критериев: 8 из 10 | I7: 02_Доказательства: 9 строк | J7: =IFERROR(IF(INDEX('01_Компании'!$I$4:$I$25,MATCH(A7,'01_Компании'!$A$4:$A$25,0))="","",INDEX('01_Компании'!$I$4:$I$25,MATCH(A7,'01_Компании'!$A$4:$A$25,0))),"") -> Средний | K7: =IFERROR(IF(INDEX('04_Оценка'!$S$4:$S$25,MATCH(A7,'04_Оценка'!$A$4:$A$25,0))="","",INDEX('04_Оценка'!$S$4:$S$25,MATCH(A7,'04_Оценка'!$A$4:$A$25,0))),"") -> В работе
A8: K005 | B8: =IFERROR(IF(INDEX('04_Оценка'!$B$4:$B$25,MATCH(A8,'04_Оценка'!$A$4:$A$25,0))="","",INDEX('04_Оценка'!$B$4:$B$25,MATCH(A8,'04_Оценка'!$A$4:$A$25,0))),"") -> Kroki | C8: =IFERROR(AVERAGE('04_Оценка'!D8,'04_Оценка'!F8),"") -> 2.5 | D8: =IFERROR(AVERAGE('04_Оценка'!E8,'04_Оценка'!J8),"") -> 2.5 | E8: =IFERROR('04_Оценка'!N8,"") -> 2.07 | F8: =IFERROR('04_Оценка'!R8,"") -> Смежная или потенциальная конкуренция | G8: =IF(E8="","",IF(OR(F8="Недостаточно данных",C8="",D8=""),"Нет данных",IF(AND(C8>=4,D8>=4),"Ядро прямой конкуренции",IF(AND(C8>=3,D8>=3),"Близкая альтернатива",IF(C8>=3,"Функциональный заменитель",IF(D8>=3,"Аудиторное пересечение","Периферия")))))) -> Периферия | H8: Уверенность: средняя; заполнено критериев: 7 из 10 | I8: 02_Доказательства: 8 строк | J8: =IFERROR(IF(INDEX('01_Компании'!$I$4:$I$25,MATCH(A8,'01_Компании'!$A$4:$A$25,0))="","",INDEX('01_Компании'!$I$4:$I$25,MATCH(A8,'01_Компании'!$A$4:$A$25,0))),"") -> Низкий | K8: =IFERROR(IF(INDEX('04_Оценка'!$S$4:$S$25,MATCH(A8,'04_Оценка'!$A$4:$A$25,0))="","",INDEX('04_Оценка'!$S$4:$S$25,MATCH(A8,'04_Оценка'!$A$4:$A$25,0))),"") -> В работе
A9: K006 | B9: =IFERROR(IF(INDEX('04_Оценка'!$B$4:$B$25,MATCH(A9,'04_Оценка'!$A$4:$A$25,0))="","",INDEX('04_Оценка'!$B$4:$B$25,MATCH(A9,'04_Оценка'!$A$4:$A$25,0))),"") -> PlantText | C9: =IFERROR(AVERAGE('04_Оценка'!D9,'04_Оценка'!F9),"") -> 4.5 | D9: =IFERROR(AVERAGE('04_Оценка'!E9,'04_Оценка'!J9),"") -> 3 | E9: =IFERROR('04_Оценка'!N9,"") -> 3.72 | F9: =IFERROR('04_Оценка'!R9,"") -> Близкий альтернативный конкурент | G9: =IF(E9="","",IF(OR(F9="Недостаточно данных",C9="",D9=""),"Нет данных",IF(AND(C9>=4,D9>=4),"Ядро прямой конкуренции",IF(AND(C9>=3,D9>=3),"Близкая альтернатива",IF(C9>=3,"Функциональный заменитель",IF(D9>=3,"Аудиторное пересечение","Периферия")))))) -> Близкая альтернатива | H9: Уверенность: средняя; заполнено критериев: 10 из 10 | I9: 02_Доказательства: 9 строк | J9: =IFERROR(IF(INDEX('01_Компании'!$I$4:$I$25,MATCH(A9,'01_Компании'!$A$4:$A$25,0))="","",INDEX('01_Компании'!$I$4:$I$25,MATCH(A9,'01_Компании'!$A$4:$A$25,0))),"") -> Средний | K9: =IFERROR(IF(INDEX('04_Оценка'!$S$4:$S$25,MATCH(A9,'04_Оценка'!$A$4:$A$25,0))="","",INDEX('04_Оценка'!$S$4:$S$25,MATCH(A9,'04_Оценка'!$A$4:$A$25,0))),"") -> В работе
A10: K007 | B10: =IFERROR(IF(INDEX('04_Оценка'!$B$4:$B$25,MATCH(A10,'04_Оценка'!$A$4:$A$25,0))="","",INDEX('04_Оценка'!$B$4:$B$25,MATCH(A10,'04_Оценка'!$A$4:$A$25,0))),"") -> StarUML | C10: =IFERROR(AVERAGE('04_Оценка'!D10,'04_Оценка'!F10),"") -> 3.5 | D10: =IFERROR(AVERAGE('04_Оценка'!E10,'04_Оценка'!J10),"") -> 3.5 | E10: =IFERROR('04_Оценка'!N10,"") -> 2.81 | F10: =IFERROR('04_Оценка'!R10,"") -> Косвенный конкурент / заменитель | G10: =IF(E10="","",IF(OR(F10="Недостаточно данных",C10="",D10=""),"Нет данных",IF(AND(C10>=4,D10>=4),"Ядро прямой конкуренции",IF(AND(C10>=3,D10>=3),"Близкая альтернатива",IF(C10>=3,"Функциональный заменитель",IF(D10>=3,"Аудиторное пересечение","Периферия")))))) -> Близкая альтернатива | H10: Уверенность: средняя; заполнено критериев: 7 из 10 | I10: 02_Доказательства: 7 строк | J10: =IFERROR(IF(INDEX('01_Компании'!$I$4:$I$25,MATCH(A10,'01_Компании'!$A$4:$A$25,0))="","",INDEX('01_Компании'!$I$4:$I$25,MATCH(A10,'01_Компании'!$A$4:$A$25,0))),"") -> Средний | K10: =IFERROR(IF(INDEX('04_Оценка'!$S$4:$S$25,MATCH(A10,'04_Оценка'!$A$4:$A$25,0))="","",INDEX('04_Оценка'!$S$4:$S$25,MATCH(A10,'04_Оценка'!$A$4:$A$25,0))),"") -> В работе
A11: K008 | B11: =IFERROR(IF(INDEX('04_Оценка'!$B$4:$B$25,MATCH(A11,'04_Оценка'!$A$4:$A$25,0))="","",INDEX('04_Оценка'!$B$4:$B$25,MATCH(A11,'04_Оценка'!$A$4:$A$25,0))),"") -> Visual Paradigm | C11: =IFERROR(AVERAGE('04_Оценка'!D11,'04_Оценка'!F11),"") -> 4 | D11: =IFERROR(AVERAGE('04_Оценка'!E11,'04_Оценка'!J11),"") -> 4 | E11: =IFERROR('04_Оценка'!N11,"") -> 3.63 | F11: =IFERROR('04_Оценка'!R11,"") -> Близкий альтернативный конкурент | G11: =IF(E11="","",IF(OR(F11="Недостаточно данных",C11="",D11=""),"Нет данных",IF(AND(C11>=4,D11>=4),"Ядро прямой конкуренции",IF(AND(C11>=3,D11>=3),"Близкая альтернатива",IF(C11>=3,"Функциональный заменитель",IF(D11>=3,"Аудиторное пересечение","Периферия")))))) -> Ядро прямой конкуренции | H11: Уверенность: средняя; заполнено критериев: 9 из 10 | I11: 02_Доказательства: 9 строк | J11: =IFERROR(IF(INDEX('01_Компании'!$I$4:$I$25,MATCH(A11,'01_Компании'!$A$4:$A$25,0))="","",INDEX('01_Компании'!$I$4:$I$25,MATCH(A11,'01_Компании'!$A$4:$A$25,0))),"") -> Высокий | K11: =IFERROR(IF(INDEX('04_Оценка'!$S$4:$S$25,MATCH(A11,'04_Оценка'!$A$4:$A$25,0))="","",INDEX('04_Оценка'!$S$4:$S$25,MATCH(A11,'04_Оценка'!$A$4:$A$25,0))),"") -> В работе
A12: K009 | B12: =IFERROR(IF(INDEX('04_Оценка'!$B$4:$B$25,MATCH(A12,'04_Оценка'!$A$4:$A$25,0))="","",INDEX('04_Оценка'!$B$4:$B$25,MATCH(A12,'04_Оценка'!$A$4:$A$25,0))),"") -> Sparx Systems (Enterprise Architect) | C12: =IFERROR(AVERAGE('04_Оценка'!D12,'04_Оценка'!F12),"") -> 3.5 | D12: =IFERROR(AVERAGE('04_Оценка'!E12,'04_Оценка'!J12),"") -> 4 | E12: =IFERROR('04_Оценка'!N12,"") -> 1.9 | F12: =IFERROR('04_Оценка'!R12,"") -> Недостаточно данных | G12: =IF(E12="","",IF(OR(F12="Недостаточно данных",C12="",D12=""),"Нет данных",IF(AND(C12>=4,D12>=4),"Ядро прямой конкуренции",IF(AND(C12>=3,D12>=3),"Близкая альтернатива",IF(C12>=3,"Функциональный заменитель",IF(D12>=3,"Аудиторное пересечение","Периферия")))))) -> Нет данных | H12: Уверенность: низкая; заполнено критериев: 5 из 10 | I12: 02_Доказательства: 7 строк | J12: =IFERROR(IF(INDEX('01_Компании'!$I$4:$I$25,MATCH(A12,'01_Компании'!$A$4:$A$25,0))="","",INDEX('01_Компании'!$I$4:$I$25,MATCH(A12,'01_Компании'!$A$4:$A$25,0))),"") -> Низкий | K12: =IFERROR(IF(INDEX('04_Оценка'!$S$4:$S$25,MATCH(A12,'04_Оценка'!$A$4:$A$25,0))="","",INDEX('04_Оценка'!$S$4:$S$25,MATCH(A12,'04_Оценка'!$A$4:$A$25,0))),"") -> Требует уточнения
A13: K010 | B13: =IFERROR(IF(INDEX('04_Оценка'!$B$4:$B$25,MATCH(A13,'04_Оценка'!$A$4:$A$25,0))="","",INDEX('04_Оценка'!$B$4:$B$25,MATCH(A13,'04_Оценка'!$A$4:$A$25,0))),"") -> bpmn.io | C13: =IFERROR(AVERAGE('04_Оценка'!D13,'04_Оценка'!F13),"") -> 2.5 | D13: =IFERROR(AVERAGE('04_Оценка'!E13,'04_Оценка'!J13),"") -> 3.5 | E13: =IFERROR('04_Оценка'!N13,"") -> 2.44 | F13: =IFERROR('04_Оценка'!R13,"") -> Смежная или потенциальная конкуренция | G13: =IF(E13="","",IF(OR(F13="Недостаточно данных",C13="",D13=""),"Нет данных",IF(AND(C13>=4,D13>=4),"Ядро прямой конкуренции",IF(AND(C13>=3,D13>=3),"Близкая альтернатива",IF(C13>=3,"Функциональный заменитель",IF(D13>=3,"Аудиторное пересечение","Периферия")))))) -> Аудиторное пересечение | H13: Уверенность: средняя; заполнено критериев: 8 из 10 | I13: 02_Доказательства: 9 строк | J13: =IFERROR(IF(INDEX('01_Компании'!$I$4:$I$25,MATCH(A13,'01_Компании'!$A$4:$A$25,0))="","",INDEX('01_Компании'!$I$4:$I$25,MATCH(A13,'01_Компании'!$A$4:$A$25,0))),"") -> Средний | K13: =IFERROR(IF(INDEX('04_Оценка'!$S$4:$S$25,MATCH(A13,'04_Оценка'!$A$4:$A$25,0))="","",INDEX('04_Оценка'!$S$4:$S$25,MATCH(A13,'04_Оценка'!$A$4:$A$25,0))),"") -> В работе
A14: K011 | B14: =IFERROR(IF(INDEX('04_Оценка'!$B$4:$B$25,MATCH(A14,'04_Оценка'!$A$4:$A$25,0))="","",INDEX('04_Оценка'!$B$4:$B$25,MATCH(A14,'04_Оценка'!$A$4:$A$25,0))),"") -> Camunda (Modeler) | C14: =IFERROR(AVERAGE('04_Оценка'!D14,'04_Оценка'!F14),"") -> 2 | D14: =IFERROR(AVERAGE('04_Оценка'!E14,'04_Оценка'!J14),"") -> 2.5 | E14: =IFERROR('04_Оценка'!N14,"") -> 1.92 | F14: =IFERROR('04_Оценка'!R14,"") -> Смежная или потенциальная конкуренция | G14: =IF(E14="","",IF(OR(F14="Недостаточно данных",C14="",D14=""),"Нет данных",IF(AND(C14>=4,D14>=4),"Ядро прямой конкуренции",IF(AND(C14>=3,D14>=3),"Близкая альтернатива",IF(C14>=3,"Функциональный заменитель",IF(D14>=3,"Аудиторное пересечение","Периферия")))))) -> Периферия | H14: Уверенность: средняя; заполнено критериев: 8 из 10 | I14: 02_Доказательства: 7 строк | J14: =IFERROR(IF(INDEX('01_Компании'!$I$4:$I$25,MATCH(A14,'01_Компании'!$A$4:$A$25,0))="","",INDEX('01_Компании'!$I$4:$I$25,MATCH(A14,'01_Компании'!$A$4:$A$25,0))),"") -> Низкий | K14: =IFERROR(IF(INDEX('04_Оценка'!$S$4:$S$25,MATCH(A14,'04_Оценка'!$A$4:$A$25,0))="","",INDEX('04_Оценка'!$S$4:$S$25,MATCH(A14,'04_Оценка'!$A$4:$A$25,0))),"") -> В работе
A15: K012 | B15: =IFERROR(IF(INDEX('04_Оценка'!$B$4:$B$25,MATCH(A15,'04_Оценка'!$A$4:$A$25,0))="","",INDEX('04_Оценка'!$B$4:$B$25,MATCH(A15,'04_Оценка'!$A$4:$A$25,0))),"") -> Storm (StormBPMN) | C15: =IFERROR(AVERAGE('04_Оценка'!D15,'04_Оценка'!F15),"") -> 2.5 | D15: =IFERROR(AVERAGE('04_Оценка'!E15,'04_Оценка'!J15),"") -> 4 | E15: =IFERROR('04_Оценка'!N15,"") -> 2.26 | F15: =IFERROR('04_Оценка'!R15,"") -> Смежная или потенциальная конкуренция | G15: =IF(E15="","",IF(OR(F15="Недостаточно данных",C15="",D15=""),"Нет данных",IF(AND(C15>=4,D15>=4),"Ядро прямой конкуренции",IF(AND(C15>=3,D15>=3),"Близкая альтернатива",IF(C15>=3,"Функциональный заменитель",IF(D15>=3,"Аудиторное пересечение","Периферия")))))) -> Аудиторное пересечение | H15: Уверенность: средняя; заполнено критериев: 7 из 10 | I15: 02_Доказательства: 7 строк | J15: =IFERROR(IF(INDEX('01_Компании'!$I$4:$I$25,MATCH(A15,'01_Компании'!$A$4:$A$25,0))="","",INDEX('01_Компании'!$I$4:$I$25,MATCH(A15,'01_Компании'!$A$4:$A$25,0))),"") -> Средний | K15: =IFERROR(IF(INDEX('04_Оценка'!$S$4:$S$25,MATCH(A15,'04_Оценка'!$A$4:$A$25,0))="","",INDEX('04_Оценка'!$S$4:$S$25,MATCH(A15,'04_Оценка'!$A$4:$A$25,0))),"") -> В работе
... A25: K022 | B25: =IFERROR(IF(INDEX('04_Оценка'!$B$4:$B$25,MATCH(A25,'04_Оценка'!$A$4:$A$25,0))="","",INDEX('04_Оценка'!$B$4:$B$25,MATCH(A25,'04_Оценка'!$A$4:$A$25,0))),"") -> Microsoft Visio | C25: =IFERROR(AVERAGE('04_Оценка'!D25,'04_Оценка'!F25),"") -> 2.5 | D25: =IFERROR(AVERAGE('04_Оценка'!E25,'04_Оценка'!J25),"") -> 3.5 | E25: =IFERROR('04_Оценка'!N25,"") -> 2.65 | F25: =IFERROR('04_Оценка'!R25,"") -> Косвенный конкурент / заменитель | G25: =IF(E25="","",IF(OR(F25="Недостаточно данных",C25="",D25=""),"Нет данных",IF(AND(C25>=4,D25>=4),"Ядро прямой конкуренции",IF(AND(C25>=3,D25>=3),"Близкая альтернатива",IF(C25>=3,"Функциональный заменитель",IF(D25>=3,"Аудиторное пересечение","Периферия")))))) -> Аудиторное пересечение | H25: Уверенность: низкая; заполнено критериев: 8 из 10 | I25: 02_Доказательства: 2 строк | J25: =IFERROR(IF(INDEX('01_Компании'!$I$4:$I$25,MATCH(A25,'01_Компании'!$A$4:$A$25,0))="","",INDEX('01_Компании'!$I$4:$I$25,MATCH(A25,'01_Компании'!$A$4:$A$25,0))),"") -> Средний | K25: =IFERROR(IF(INDEX('04_Оценка'!$S$4:$S$25,MATCH(A25,'04_Оценка'!$A$4:$A$25,0))="","",INDEX('04_Оценка'!$S$4:$S$25,MATCH(A25,'04_Оценка'!$A$4:$A$25,0))),"") -> В работе

Sheet 08_Справочники
A1: Уровни конкуренции | B1: Статусы | C1: Приоритеты | D1: Типы сигналов с сайта | E1: Справочники для выпадающих списков | F1: Шкала оценки | G1: Интерпретация | H1: Справочники для выпадающих списков
A2: Прямой конкурент | B2: Не начато | C2: Высокий | D2: Потребительская задача | F2: Балл | G2: Смысл
A3: Близкий альтернативный конкурент | B3: В работе | C3: Средний | D3: Целевая аудитория | F3: 0 | G3: нет признака / данных
A4: Косвенный конкурент / заменитель | B4: Проверено | C4: Низкий | D4: Цифровой товар | F4: 1 | G4: слабое или косвенное совпадение
A5: Смежная или потенциальная конкуренция | B5: Требует уточнения | D5: Функциональность | F5: 2 | G5: частичное совпадение
A6: Не конкурент / объект наблюдения | B6: Исключено | D6: Цена и тарифы | F6: 3 | G6: существенное совпадение
A7: Недостаточно данных | D7: Монетизация | F7: 4 | G7: высокое совпадение
D8: Каналы продаж | F8: 5 | G8: полное совпадение
D9: География и язык
D10: Доверие и зрелость
D11: Замена и переключение

Sheet 09_Журнал
A1: Журнал рабочей копии: исправления шаблона, шкала, правила баллов, незаполненные данные
A3: Раздел | B3: Код | C3: Содержание
A4: Исправления рабочей копии шаблона | B4: Д-1 | C4: Лист 01_Компании, столбец I (Приоритет): проверка данных ссылалась на список уровней конкуренции ('08_Справочники'!A2:A7). Заменена на список приоритетов ('08_Справочники'!C2:C4)
A5: Исправления рабочей копии шаблона | B5: Д-2 | C5: Лист 02_Доказательства, столбец G (Сила сигнала 1-5): проверка данных ссылалась на список блоков критериев. Заменена на целые числа от 1 до 5
A6: Исправления рабочей копии шаблона | B6: Д-3 | C6: Лист 04_Оценка, столбец S (Статус решения): проверка данных ссылалась на список уровней. Заменена на список статусов ('08_Справочники'!B2:B6)
A7: Исправления рабочей копии шаблона | B7: Д-4 | C7: Лист 06_Сводка, B19:F28 (топ-10): при равных баллах MATCH возвращал первое совпадение, и одна компания повторялась в нескольких строках. Формулы заменены вариантом с AGGREGATE и COUNTIF (n-е совпадение); логика (LARGE по взвешенному баллу) сохранена
A8: Исправления рабочей копии шаблона | B8: Д-6 | C8: Лист 04_Оценка, столбец N (Взвешенный балл): SUMPRODUCT получал строку D:M (1x10) и столбец весов E4:E13 (10x1), размеры не совпадают, результат во всех строках - #ЗНАЧ!. Формула заменена явной суммой произведений баллов на веса, деленной на сумму весов (математика методики: SUMPRODUCT(C1...C10; веса) / SUM(весов))
A9: Исправления рабочей копии шаблона | B9: Д-7 | C9: Формулы XLOOKUP (листы 02_Доказательства, 04_Оценка, 07_Карта) записаны в файле шаблона без префикса _xlfn, Excel читал их как неизвестную функцию и название компании не подтягивалось. Формулы введены повторно (текст не менялся), название и сайт подтягиваются
A10: Исправления рабочей копии шаблона | B10: Д-8 | C10: Листы 04_Оценка (B, C) и 07_Карта (B, J, K): для ID без компании XLOOKUP возвращал пустую ячейку как 0, и в 78 строках показывались нули; добавлена проверка на пустое значение. Лист 07_Карта, столбец G: для строк со статусом «Недостаточно данных» или без X/Y зона не определялась корректно (текст сравнивался как больше числа); добавлено значение «Нет данных»
A11: Исправления рабочей копии шаблона | B11: Д-5 | C11: Формулы листов 04_Оценка (N, O, P, R) и 07_Карта (X, Y, зона) сверены с правилами методики (ЗАДАНИЕ, п. 5.4) и расчетом на Python (Python/02_verify.py); расхождений нет, формулы не менялись
A12: Шкала | B12: Ш-1 | C12: Использована шкала Excel-шаблона: 10 критериев C1-C10, баллы 0-5, веса в сумме 100, 5 уровней и значение «Недостаточно данных». Шкала методики (8 критериев, 0-4, индекс 0-100, 7 уровней) для расчета не применялась; определения уровней и правила корректировки взяты из методики
A13: Шкала | B13: Ш-2 | C13: Пустая ячейка критерия в формуле шаблона равна 0 (в числитель не входит, в знаменатель входит вес). Критерий оставлен пустым, если данных нет; при заполнении менее шести критериев ограничитель дает «Недостаточно данных»
A14: Правила баллов | B14: П-1 | C14: C1-C4 назначены аналитиком по тексту главной страницы и описанию продукта: 5 - главная страница заявляет ту же задачу (диаграммы из текста или кода); 4 - нотационный моделер или ИИ-генерация диаграмм; 3 - универсальный редактор или одна нотация; 2 - доска или платформа с редактором как модулем
... A29: не собрано | B29: Т-7 | C29: не собрано: рекламные объявления (Google Ads Transparency Center, LinkedIn Ad Library) и выдача Яндекса по запросам ядра: не проверялись (доступ закрыт, капча)
