Workbook

Sheet 11_Вариант_М2
A1: Вариант по М2 (табл. 9, 11, 21): охват 0,45 / 0,65 / 0,85; коммерчески релевантная доля 20 / 35 / 50 %; годовой объем = месячный × 12
A3: Показатель | B3: Осторожный | C3: Базовый | D3: Оптимистичный | E3: Комментарий
A4: V_sample: визиты выборки, мес. (Σ) | B4: =SUM('02_Конкуренты_SW'!E4:E7) -> 9005500 | C4: =SUM('02_Конкуренты_SW'!E4:E7) -> 9005500 | D4: =SUM('02_Конкуренты_SW'!E4:E7) -> 9005500 | E4: М2 табл. 8
A5: Доля географии (РБ), Д-01 | B5: ='02_Конкуренты_SW'!F4 -> 0.001958 | C5: ='02_Конкуренты_SW'!F4 -> 0.001958 | D5: ='02_Конкуренты_SW'!F4 -> 0.001958
A6: V_geo = V_sample × доля географии | B6: =B4*B5 -> 17632.769 | C6: =C4*C5 -> 17632.769 | D6: =D4*D5 -> 17632.769
A7: Коэффициент охвата выборки | B7: 0.45 | C7: 0.65 | D7: 0.85 | E7: М2 табл. 21 (шкала табл. 9: 0,40–0,55 / 0,60–0,75 / 0,80–0,90)
A8: V_total = V_geo / охват | B8: =B6/B7 -> 39183.931 | C8: =C6/C7 -> 27127.337 | D8: =D6/D7 -> 20744.434 | E8: Осторожный сценарий дает БОЛЬШЕ трафика (W-15)
A9: Коммерчески релевантная доля | B9: 0.2 | C9: 0.35 | D9: 0.5 | E9: М2 табл. 21
A10: Коммерчески релевантные визиты, мес. | B10: =B8*B9 -> 7836.7862 | C10: =C8*C9 -> 9494.5679 | D10: =D8*D9 -> 10372.217
A11: CR1 (визит → заявка) | B11: 0.0035 | C11: 0.01 | D11: 0.0225 | E11: середины диапазонов М2 табл. 11
A12: CR2 (заявка → оплата Pro) | B12: 0.03 | C12: 0.04 | D12: 0.05 | E12: допущение проекта Free → Pro 3–5 % (шкала М2 5–40 % для freemium неприменима)
A13: Средний чек, BYN/год | B13: 121.14 | C13: 121.14 | D13: 290.74 | E13: 40 у.е./год (осторожный, базовый); медиана входных тарифов конкурентов
A14: Месячный объем, BYN | B14: =B10*B11*B12*B13 -> 99.68157 | C14: =C10*C11*C12*C13 -> 460.06878 | D14: =D10*D11*D12*D13 -> 3392.5707
A15: Годовой объем, BYN (× 12, М2) | B15: =B14*12 -> 1196.1788 | C15: =C14*12 -> 5520.8254 | D15: =D14*12 -> 40710.848 | E15: М2: × 12 (в SW-X: × 12 × покупок)
A16: Достижимая доля (SOM) | B16: 0.005 | C16: 0.015 | D16: 0.035 | E16: как в листе 06
A17: SOM, BYN/год | B17: =B15*B16 -> 5.9808942 | C17: =C15*C16 -> 82.812381 | D17: =D15*D16 -> 1424.8797

Sheet 10_TAM_SAM_SOM_М1
A1: TAM / SAM / SOM цифрового внимания по М1 табл. 22 (базовый сценарий листа 06)
A3: TAM цифрового внимания: суммарный трафик релевантных сайтов категории, визиты/мес | B3: =SUM('02_Конкуренты_SW'!E4:E7) -> 9005500
A4: Доля страны (Беларусь), допущение Д-01 | B4: ='02_Конкуренты_SW'!F4 -> 0.001958
A5: SAM по географии, визиты/мес. = TAM × доля страны | B5: =B3*B4 -> 17632.769
A6: Доля релевантных каналов (Organic Search, plantuml.com) | B6: ='03_Каналы'!B5 -> 0.4847
A7: SAM по каналу, визиты/мес | B7: =B5*B6 -> 8546.6031
A8: Достижимая доля (базовая, лист 06) | B8: ='06_Воронка_сценарии'!C13 -> 0.015
A9: SOM по трафику, визиты/мес. = SAM × достижимая доля | B9: =B7*B8 -> 128.19905
A10: CR1 (лист 06, базовый) | B10: ='06_Воронка_сценарии'!D6 -> 0.015
A11: CR2 (лист 06, базовый) | B11: ='06_Воронка_сценарии'!E6 -> 0.04
A12: Средний чек, BYN (лист 06) | B12: ='06_Воронка_сценарии'!F6 -> 121.14
A13: Число покупок в год | B13: ='06_Воронка_сценарии'!G6 -> 1
A14: SOM по выручке, BYN/год = SOM по трафику × 12 × CR1 × CR2 × чек × число покупок | B14: =B9*12*B10*B11*B12*B13 -> 111.81623
A15: Проверка конкурентами: средняя выручка конкурента (при параметрах NotaCode), BYN/год | B15: =AVERAGE('02_Конкуренты_SW'!G4:G7)*12*B10*B11*B12*B13 -> 3844.8605
A16: Число активных конкурентов в выборке | B16: ='01_Параметры'!B8 -> 4
A17: Проверка конкурентами: сумма, BYN/год | B17: =B15*B16 -> 15379.442
A20: Канальный SAM рассчитан по доле Organic одного домена (plantuml.com) – остальные доли в бесплатном доступе не показаны. Проверка поиском – лист 05_Запросы

Sheet 09_Концентрация
A1: Концентрация цифрового трафика: CR3, CR5, HHI (дополнение к шаблону, Р-42; М1 §7.2, М2 §12)
A3: Домен | B3: Визиты/мес. (сырые) | C3: Доля по сырым визитам (М1 ф. 2, SWБ §7) | D3: Доля² × 10 000 (сырые) | E3: Релевантные визиты (РБ) | F3: Доля по релевантным визитам (М2 §7) | G3: Доля² × 10 000 (релевантные) | H3: Доля релевантного трафика (Д-02) | I3: Релевантные визиты с учетом Д-02 | J3: Доля по визитам с учетом Д-02 | K3: Доля² × 10 000 (с учетом Д-02)
A4: ='02_Конкуренты_SW'!A4 -> plantuml.com | B4: ='02_Конкуренты_SW'!E4 -> 507000 | C4: =B4/SUM($B$4:$B$7) -> 0.056298928 | D4: =C4^2*10000 -> 31.695693 | E4: ='02_Конкуренты_SW'!G4 -> 992.706 | F4: =E4/SUM($E$4:$E$7) -> 0.056298928 | G4: =F4^2*10000 -> 31.695693 | H4: 0.75 | I4: =E4*H4 -> 744.5295 | J4: =I4/SUM($I$4:$I$7) -> 0.10978779 | K4: =J4^2*10000 -> 120.53358
A5: ='02_Конкуренты_SW'!A5 -> app.diagrams.net | B5: ='02_Конкуренты_SW'!E5 -> 7800000 | C5: =B5/SUM($B$4:$B$7) -> 0.86613736 | D5: =C5^2*10000 -> 7501.9393 | E5: ='02_Конкуренты_SW'!G5 -> 15272.4 | F5: =E5/SUM($E$4:$E$7) -> 0.86613736 | G5: =F5^2*10000 -> 7501.9393 | H5: 0.35 | I5: =E5*H5 -> 5345.34 | J5: =I5/SUM($I$4:$I$7) -> 0.78822001 | K5: =J5^2*10000 -> 6212.9078
A6: ='02_Конкуренты_SW'!A6 -> eraser.io | B6: ='02_Конкуренты_SW'!E6 -> 678500 | C6: =B6/SUM($B$4:$B$7) -> 0.075342846 | D6: =C6^2*10000 -> 56.765444 | E6: ='02_Конкуренты_SW'!G6 -> 1328.503 | F6: =E6/SUM($E$4:$E$7) -> 0.075342846 | G6: =F6^2*10000 -> 56.765444 | H6: 0.5 | I6: =E6*H6 -> 664.2515 | J6: =I6/SUM($I$4:$I$7) -> 0.097950051 | K6: =J6^2*10000 -> 95.942124
A7: ='02_Конкуренты_SW'!A7 -> mermaidchart.com | B7: ='02_Конкуренты_SW'!E7 -> 20000 | C7: =B7/SUM($B$4:$B$7) -> 0.002220865 | D7: =C7^2*10000 -> 0.049322415 | E7: ='02_Конкуренты_SW'!G7 -> 39.16 | F7: =E7/SUM($E$4:$E$7) -> 0.002220865 | G7: =F7^2*10000 -> 0.049322415 | H7: 0.7 | I7: =E7*H7 -> 27.412 | J7: =I7/SUM($I$4:$I$7) -> 0.0040421539 | K7: =J7^2*10000 -> 0.16339008
A9: Сумма | B9: =SUM(B4:B7) -> 9005500 | D9: =SUM(D4:D7) -> 7590.4497 | E9: =SUM(E4:E7) -> 17632.769 | G9: =SUM(G4:G7) -> 7590.4497 | I9: =SUM(I4:I7) -> 6781.533 | K9: =SUM(K4:K7) -> 6429.5469
A11: Показатель | B11: По сырым визитам | C11: По релевантным визитам | D11: С учетом доли релевантного (Д-02)
A12: CR3, % | B12: =(LARGE(C4:C7,1)+LARGE(C4:C7,2)+LARGE(C4:C7,3))*100 -> 99.777913 | C12: =(LARGE(F4:F7,1)+LARGE(F4:F7,2)+LARGE(F4:F7,3))*100 -> 99.777913 | D12: =(LARGE(J4:J7,1)+LARGE(J4:J7,2)+LARGE(J4:J7,3))*100 -> 99.595785
A13: CR5, % | B13: =SUM(C4:C7)*100 -> 100 | C13: =SUM(F4:F7)*100 -> 100 | D13: =SUM(J4:J7)*100 -> 100
A14: HHI = Σ (доля в %)² | B14: =D9 -> 7590.4497 | C14: =G9 -> 7590.4497 | D14: =K9 -> 6429.5469
A15: Уровень по шкале М2 табл. 16 | B15: =IF(B14<1500,"низкая концентрация",IF(B14<=2500,"умеренная","высокая")) -> высокая | C15: =IF(C14<1500,"низкая концентрация",IF(C14<=2500,"умеренная","высокая")) -> высокая | D15: =IF(D14<1500,"низкая концентрация",IF(D14<=2500,"умеренная","высокая")) -> высокая
A16: Проверка: HHI ≥ CR3² / 3 | B16: =IF(B14>=B12^2/3,"выполняется","НЕ выполняется") -> выполняется | C16: =IF(C14>=C12^2/3,"выполняется","НЕ выполняется") -> выполняется | D16: =IF(D14>=D12^2/3,"выполняется","НЕ выполняется") -> выполняется
A18: Пояснения: шкала М2 табл. 16 – до 1 500 низкая, 1 500–2 500 умеренная, выше 2 500 высокая; М1 табл. 10 задает три качественных уровня без чисел. Значения – оценка концентрации ЦИФРОВОГО ТРАФИКА выборки из 4 доменов (не выручки и не рыночной власти); CR5 при 4 доменах равен 100 %. Выборка меньше минимума М2 (5 доменов) и состоит из доменов разных типов; доминирует универсальный редактор draw.io

Sheet 00_Методика
A1: Методика оценки объема рынка электронного бизнеса по данным Similarweb
A3: Блок | B3: Цель | C3: Действие | D3: Что фиксировать | E3: Расчетный результат | F3: Ограничения | G3: Лист Excel | H3: Выходной вывод
A4: 1. Границы рынка | B4: Уточнить, какой рынок оценивается | C4: Зафиксировать продукт, географию, аудиторию и цифровые каналы | D4: Название рынка, территория, период, сегменты | E4: Паспорт расчетной модели | F4: Без границ рынка трафик конкурентов нельзя трактовать как объем рынка | G4: 01_Параметры | H4: Что именно считается рынком
A5: 2. Конкуренты | B5: Определить ядро цифрового рынка | C5: Собрать сайты прямых и частичных конкурентов | D5: Домен, сегмент, тип конкурента | E5: Список цифровых игроков | F5: Малые сайты могут отображаться неполно | G5: 02_Конкуренты_SW | H5: Кто формирует цифровое предложение
A6: 3. Трафик | B6: Оценить цифровой масштаб сегмента | C6: Внести посещения, географическую долю и релевантность | D6: Monthly visits, доля выбранной географии, релевантная доля | E6: Релевантный месячный и годовой трафик | F6: Трафик не равен покупкам | G6: 02_Конкуренты_SW | H6: Насколько велик цифровой поток аудитории
A7: 4. Каналы | B7: Понять структуру привлечения аудитории | C7: Разложить трафик по Direct, Organic, Referral, Social, Paid, Mail, Display | D7: Доли каналов по конкурентам | E7: Канальная структура рынка | F7: Доли каналов оценочные | G7: 03_Каналы | H7: Какие каналы важны для входа на рынок
A8: 5. География | B8: Проверить территориальную концентрацию спроса | C8: Сопоставить страны/регионы по доле трафика | D8: Страна, доля, интерпретация | E8: Приоритетные географии | F8: Доля трафика не равна платежеспособности | G8: 04_География | H8: Где целесообразно анализировать рынок
A9: 6. Поиск | B9: Определить коммерческий спрос внутри трафика | C9: Зафиксировать ключевые запросы и намерение аудитории | D9: Запрос, доля или объем, тип намерения | E9: Индекс коммерческого интереса | F9: Запросы видны неполно в бесплатном доступе | G9: 05_Запросы | H9: Какие потребности приводят аудиторию
A10: 7. Воронка | B10: Перевести трафик в возможные заказы | C10: Задать конверсии и средний чек | D10: CR в заявку, CR в продажу, средний чек | E10: Оценка объема рынка в деньгах | F10: Конверсии задаются сценарно | G10: 06_Воронка_сценарии | H10: Диапазон рынка по сценариям
A11: 8. Проверка | B11: Снизить риск завышения оценки | C11: Сопоставить расчет с другими источниками | D11: Google Trends, Вордстат, статистика, рекламные кабинеты | E11: Уточненный диапазон оценки | F11: Источники измеряют разные показатели | G11: 08_Источники | H11: Насколько расчет устойчив
A13: Ключевая расчетная логика
A14: 1 | B14: Наблюдаемый цифровой сегмент | C14: Сумма релевантного трафика выбранных конкурентов | D14: = сумма посещений × доля географии × доля релевантности
A15: 2 | B15: Оценка всего цифрового рынка | C15: Наблюдаемый сегмент / коэффициент покрытия конкурентов | D15: Если список конкурентов покрывает 70% рынка, общий рынок = наблюдаемый трафик / 70%
A16: 3 | B16: Оценка заявок | C16: Рыночный трафик × конверсия в заявку | D16: Конверсия задается по сценариям
A17: 4 | B17: Оценка продаж | C17: Заявки × конверсия в продажу | D17: Отражает платежеспособный спрос
A18: 5 | B18: Денежный объем | C18: Продажи × средний чек × повторные покупки | D18: Итоговый объем рынка за год

Sheet 01_Параметры
A1: Параметры оценки рынка
A3: Параметр | B3: Значение | C3: Единица / формат | D3: Комментарий
A4: Название рынка | B4: Веб-инструменты построения и проверки диаграмм формальных нотаций (UML, BPMN, ERD, IDEF, DFD) для студентов и специалистов по ПО | C4: текст | D4: Замените на ваш рынок
A5: Географическая граница | B5: Республика Беларусь | C5: текст | D5: Страна, регион или город
A6: Период анализа | B6: последние 3 месяца (июнь–август 2026); требование М1 «не менее 12 мес.» при бесплатном доступе невыполнимо | C6: текст | D6: Период, показанный в Similarweb
A7: Дата фиксации данных | B7: 46294.875 | C7: дата | D7: Дата ручного сбора или выгрузки
A8: Количество конкурентов в выборке | B8: =COUNT('02_Конкуренты_SW'!E4:E7) -> 4 | C8: формула | D8: Заполняется автоматически
A9: Наблюдаемый релевантный трафик, мес. | B9: =SUM('02_Конкуренты_SW'!G4:G7) -> 17632.769 | C9: посещения | D9: Исправлено в рабочей копии (П-1): суммирование с 4-й строки; в шаблоне диапазон G5:G24 терял первого конкурента
A10: Наблюдаемый релевантный трафик, год | B10: =SUM('02_Конкуренты_SW'!H4:H7) -> 211593.23 | C10: посещения | D10: Исправлено (П-1): H4:H23
A11: Коэффициент покрытия конкурентов | B11: 0.7 | C11: % | D11: Значение шаблона (базовый сценарий листа 06 – 0,7); шкала М2 табл. 9 для типовой ситуации 0,60–0,75
A12: Оценка всего цифрового трафика рынка, мес. | B12: =IFERROR(B9/B11,0) -> 25189.67 | C12: посещения | D12: Наблюдаемый трафик / покрытие
A13: Оценка всего цифрового трафика рынка, год | B13: =IFERROR(B10/B11,0) -> 302276.04 | C13: посещения | D13: Наблюдаемый трафик / покрытие
A15: Правила заполнения
A16: 1 | B16: Сначала зафиксируйте границы рынка | C16: Без этого нельзя решить, какие сайты считать конкурентами
A17: 2 | B17: В Similarweb соберите данные по 5–20 сайтам | C17: Чем шире выборка, тем устойчивее оценка
A18: 3 | B18: Вносите только сопоставимый период | C18: Например, последние 3 месяца для всех сайтов
A19: 4 | B19: Разделяйте весь трафик и релевантный трафик | C19: Не все посещения сайта относятся к анализируемому рынку
A20: 5 | B20: Итог давайте диапазоном | C20: Осторожный, базовый и оптимистичный сценарии

Sheet 02_Конкуренты_SW
A1: Ввод данных Similarweb по конкурентам
A3: Домен | B3: Название / конкурент | C3: Сегмент | D3: Тип | E3: Monthly visits | F3: Доля выбранной географии | G3: Релевантный трафик, мес. | H3: Релевантный трафик, год | I3: Доля рынка по трафику | J3: Bounce rate | K3: Pages / visit | L3: Avg duration | M3: Direct | N3: Organic search | O3: Referral | P3: Social | Q3: Paid search | R3: Display | S3: Комментарий
A4: plantuml.com | B4: PlantUML | C4: диаграммы по тексту | D4: прямой | E4: 507000 | F4: 0.001958 | G4: =IFERROR(E4*F4,0) -> 992.706 | H4: =G4*12 -> 11912.472 | I4: =IFERROR(G4/SUM($G$4:$G$7),0) -> 0.056298928 | J4: 0.4552 | K4: 3.18 | L4: 0.0022685185 | M4: – | N4: 0.4847 | O4: – | P4: – | Q4: – | R4: – | S4: ФАКТ (Similarweb, авг. 2026, скриншот). Доля РБ – допущение Д-01 (Similarweb не показывает). Каналы: бесплатная карточка показывает только Organic (plantuml.com); остальные – «нет данных в бесплатном доступе»
A5: app.diagrams.net | B5: draw.io (diagrams.net) | C5: визуальные редакторы | D5: заменитель | E5: 7800000 | F5: 0.001958 | G5: =IFERROR(E5*F5,0) -> 15272.4 | H5: =G5*12 -> 183268.8 | I5: =IFERROR(G5/SUM($G$4:$G$7),0) -> 0.86613736 | J5: – | K5: – | L5: – | M5: – | N5: – | O5: – | P5: – | Q5: – | R5: – | S5: отчет ЛР1, без скриншота. Доля РБ – допущение Д-01 (Similarweb не показывает). Каналы: бесплатная карточка показывает только Organic (plantuml.com); остальные – «нет данных в бесплатном доступе»
A6: eraser.io | B6: Eraser | C6: диаграммы по тексту | D6: прямой | E6: 678500 | F6: 0.001958 | G6: =IFERROR(E6*F6,0) -> 1328.503 | H6: =G6*12 -> 15942.036 | I6: =IFERROR(G6/SUM($G$4:$G$7),0) -> 0.075342846 | J6: – | K6: – | L6: – | M6: – | N6: – | O6: – | P6: – | Q6: – | R6: – | S6: предварительный замер 17–23.09.2026, не подтвержден. Доля РБ – допущение Д-01 (Similarweb не показывает). Каналы: бесплатная карточка показывает только Organic (plantuml.com); остальные – «нет данных в бесплатном доступе»
A7: mermaidchart.com | B7: Mermaid Chart | C7: диаграммы по тексту | D7: прямой | E7: 20000 | F7: 0.001958 | G7: =IFERROR(E7*F7,0) -> 39.16 | H7: =G7*12 -> 469.92 | I7: =IFERROR(G7/SUM($G$4:$G$7),0) -> 0.002220865 | J7: – | K7: – | L7: – | M7: – | N7: – | O7: – | P7: – | Q7: – | R7: – | S7: предварительный замер: «менее 20 тыс.» (верхняя граница), не подтвержден. Доля РБ – допущение Д-01 (Similarweb не показывает). Каналы: бесплатная карточка показывает только Organic (plantuml.com); остальные – «нет данных в бесплатном доступе»
A8: ИТОГО / среднее | E8: =SUM(E4:E7) -> 9005500 | G8: =SUM(G4:G7) -> 17632.769 | H8: =SUM(H4:H7) -> 211593.23 | I8: =SUM(I4:I7) -> 1 | J8: =AVERAGE(J4:J7) -> 0.4552 | K8: =AVERAGE(K4:K7) -> 3.18 | M8: =IFERROR(SUMPRODUCT($G$4:$G$7,M4:M7)/SUMIF(M4:M7,">0",$G$4:$G$7),0) -> 0 | N8: =IFERROR(SUMPRODUCT($G$4:$G$7,N4:N7)/SUMIF(N4:N7,">0",$G$4:$G$7),0) -> 0.4847 | O8: =IFERROR(SUMPRODUCT($G$4:$G$7,O4:O7)/SUMIF(O4:O7,">0",$G$4:$G$7),0) -> 0 | P8: =IFERROR(SUMPRODUCT($G$4:$G$7,P4:P7)/SUMIF(P4:P7,">0",$G$4:$G$7),0) -> 0 | Q8: =IFERROR(SUMPRODUCT($G$4:$G$7,Q4:Q7)/SUMIF(Q4:Q7,">0",$G$4:$G$7),0) -> 0 | R8: =IFERROR(SUMPRODUCT($G$4:$G$7,R4:R7)/SUMIF(R4:R7,">0",$G$4:$G$7),0) -> 0
A10: Каналы: у plantuml.com показана только доля Organic Search 48,47 %; Direct и Referrals названы 2-м и 3-м без долей, Social, Paid, Mail, Display бесплатная карточка не показывает. Средневзвешенные доли каналов (строка 25) в копии считаются только по строкам, где доля показана (П-18)

Sheet 03_Каналы
A1: Канальная структура рынка по данным Similarweb
A3: Канал | B3: Средневзвешенная доля | C3: Оценка рыночного трафика, мес. | D3: Оценка рыночного трафика, год | E3: Коммерческая интерпретация | F3: Что проверить дополнительно | G3: Ограничение | H3: Приоритет
A4: Direct | B4: ='02_Конкуренты_SW'!M8 -> 0 | C4: =B4*'01_Параметры'!$B$12 -> 0 | D4: =C4*12 -> 0 | E4: Сила бренда и повторные посещения | F4: Узнаваемость конкурентов, прямые заходы | G4: Не всегда означает новый спрос | H4: нет данных
A5: Organic search | B5: ='02_Конкуренты_SW'!N8 -> 0.4847 | C5: =B5*'01_Параметры'!$B$12 -> 12209.433 | D5: =C5*12 -> 146513.2 | E5: Поисковый спрос и эффективность содержания | F5: Семантическое ядро, видимость в поиске | G5: Запросы могут быть информационными | H5: =IF(B5>=0.3,"высокий",IF(B5>=0.15,"средний","низкий")) -> высокий
A6: Referral | B6: ='02_Конкуренты_SW'!O8 -> 0 | C6: =B6*'01_Параметры'!$B$12 -> 0 | D6: =C6*12 -> 0 | E6: Партнерские и справочные источники | F6: Каталоги, публикации, партнеры | G6: Часть переходов может быть нерелевантна | H6: нет данных
A7: Social | B7: ='02_Конкуренты_SW'!P8 -> 0 | C7: =B7*'01_Параметры'!$B$12 -> 0 | D7: =C7*12 -> 0 | E7: Спрос через социальные сети | F7: Активность в соцсетях и сообществах | G7: Социальный трафик не всегда конверсионный | H7: нет данных
A8: Paid search | B8: ='02_Конкуренты_SW'!Q8 -> 0 | C8: =B8*'01_Параметры'!$B$12 -> 0 | D8: =C8*12 -> 0 | E8: Платный спрос и рекламная конкуренция | F8: Стоимость клика, рекламные объявления | G8: Высокая доля может отражать закупку трафика | H8: нет данных
A9: Display | B9: ='02_Конкуренты_SW'!R8 -> 0 | C9: =B9*'01_Параметры'!$B$12 -> 0 | D9: =C9*12 -> 0 | E9: Медийная реклама и охват | F9: Баннеры, ретаргетинг | G9: Слабее связан с намерением покупки | H9: нет данных
A11: Показан только Organic (plantuml.com); остальные доли – «нет данных в бесплатном доступе»; приоритет по каналам, кроме Organic, не определяется

Sheet 04_География
A1: Географическая структура цифрового рынка
A3: Страна / регион | B3: Доля трафика по Similarweb | C3: Оценка месячного трафика рынка | D3: Оценка годового трафика рынка | E3: Платежеспособность / доступность | F3: Конкурентная плотность | G3: Приоритет рынка | H3: Комментарий | I3: Корректно (П-10): трафик до географического сужения × доля, мес. | J3: Корректно, год
A4: Республика Беларусь | B4: 0.001958 | C4: =B4*'01_Параметры'!$B$12 -> 49.321374 | D4: =C4*12 -> 591.85649 | E4: средняя | F4: средняя | G4: =IF(B4>=0.35,"высокий",IF(B4>=0.15,"средний","низкий")) -> низкий | H4: Основная география (В-6). Доля – допущение Д-01 | I4: =B4*SUM('02_Конкуренты_SW'!$E$4:$E$7)/'01_Параметры'!$B$11 -> 25189.67 | J4: =I4*12 -> 302276.04
A5: Минск (город) | B5: 0.001428 | C5: =B5*'01_Параметры'!$B$12 -> 35.970849 | D5: =C5*12 -> 431.65019 | E5: выше средней | F5: высокая | G5: =IF(B5>=0.35,"высокий",IF(B5>=0.15,"средний","низкий")) -> низкий | H5: Вордстат, plantuml: Минск 124 из 170 запросов РБ (73 %), окно 29.08–27.09.2026 | I5: =B5*SUM('02_Конкуренты_SW'!$E$4:$E$7)/'01_Параметры'!$B$11 -> 18371.22 | J5: =I5*12 -> 220454.64
A6: Остальная Беларусь (включая областные центры) | B6: 0.00053 | C6: =B6*'01_Параметры'!$B$12 -> 13.350525 | D6: =C6*12 -> 160.2063 | E6: средняя | F6: средняя | G6: =IF(B6>=0.35,"высокий",IF(B6>=0.15,"средний","низкий")) -> низкий | H6: Разница; данных по областным центрам нет | I6: =B6*SUM('02_Конкуренты_SW'!$E$4:$E$7)/'01_Параметры'!$B$11 -> 6818.45 | J6: =I6*12 -> 81821.4
A7: Россия (другие русскоязычные рынки) | B7: 0.0907 | C7: =B7*'01_Параметры'!$B$12 -> 2284.7031 | D7: =C7*12 -> 27416.437 | E7: разная | F7: высокая | G7: =IF(B7>=0.35,"высокий",IF(B7>=0.15,"средний","низкий")) -> низкий | H7: Similarweb, plantuml.com, август 2026: 9,07 % (факт); гипотеза расширения, вне итогового диапазона (В-6) | I7: =B7*SUM('02_Конкуренты_SW'!$E$4:$E$7)/'01_Параметры'!$B$11 -> 1166855.5 | J7: =I7*12 -> 14002266
A9: В шаблоне (столбцы C, D) доля умножается на B12 – трафик, уже суженный до Беларуси (П-10); корректный вариант – столбцы I, J

Sheet 05_Запросы
A1: Поисковые запросы и коммерческий интерес
A3: Запрос / ключевая фраза | B3: Источник | C3: Доля поискового трафика | D3: Оценочный месячный трафик | E3: Тип намерения | F3: Коммерческий вес | G3: Индекс коммерческого интереса | H3: Сегмент | I3: Решение | J3: Комментарий | K3: Корректно (П-11): D × доля Organic
A4: uml купить | B4: Яндекс Вордстат (РБ, Топы, 30 дней) | C4: 0.0068 | D4: =C4*'01_Параметры'!$B$12 -> 171.28976 | E4: коммерческий | F4: 1 | G4: =D4*F4 -> 171.28976 | H4: S-02/S-03 | I4: включить | J4: Частотность 5 запр./мес.; доля – среди перечисленных запросов (Similarweb долей запросов в бесплатном доступе не показывает) | K4: =D4*'03_Каналы'!$B$5 -> 83.024145
A5: visio купить | B5: Яндекс Вордстат (РБ, Топы, 30 дней) | C5: 0.0096 | D5: =C5*'01_Параметры'!$B$12 -> 241.82083 | E5: коммерческий | F5: 1 | G5: =D5*F5 -> 241.82083 | H5: S-02/S-03 | I5: включить (конкурент) | J5: Частотность 7 запр./мес.; доля – среди перечисленных запросов (Similarweb долей запросов в бесплатном доступе не показывает) | K5: =D5*'03_Каналы'!$B$5 -> 117.21056
A6: нейросеть схема | B6: Яндекс Вордстат (РБ, Топы, 30 дней) | C6: 0.1038 | D6: =C6*'01_Параметры'!$B$12 -> 2614.6877 | E6: инструментальный | F6: 0.7 | G6: =D6*F6 -> 1830.2814 | H6: все | I6: включить | J6: Частотность 76 запр./мес.; доля – среди перечисленных запросов (Similarweb долей запросов в бесплатном доступе не показывает) | K6: =D6*'03_Каналы'!$B$5 -> 1267.3392
A7: uml онлайн | B7: Яндекс Вордстат (РБ, Топы, 30 дней) | C7: 0.0383 | D7: =C7*'01_Параметры'!$B$12 -> 964.76436 | E7: инструментальный | F7: 0.7 | G7: =D7*F7 -> 675.33505 | H7: S-01/S-03 | I7: включить | J7: Частотность 28 запр./мес.; доля – среди перечисленных запросов (Similarweb долей запросов в бесплатном доступе не показывает) | K7: =D7*'03_Каналы'!$B$5 -> 467.62129
A8: plantuml online | B8: Яндекс Вордстат (РБ, Топы, 30 дней) | C8: 0.0191 | D8: =C8*'01_Параметры'!$B$12 -> 481.1227 | E8: инструментальный | F8: 0.7 | G8: =D8*F8 -> 336.78589 | H8: S-03 | I8: включить | J8: Частотность 14 запр./мес.; доля – среди перечисленных запросов (Similarweb долей запросов в бесплатном доступе не показывает) | K8: =D8*'03_Каналы'!$B$5 -> 233.20017
A9: idef0 как | B9: Яндекс Вордстат (РБ, Топы, 30 дней) | C9: 0.015 | D9: =C9*'01_Параметры'!$B$12 -> 377.84505 | E9: проблемный | F9: 0.6 | G9: =D9*F9 -> 226.70703 | H9: S-01 | I9: включить | J9: Частотность 11 запр./мес.; доля – среди перечисленных запросов (Similarweb долей запросов в бесплатном доступе не показывает) | K9: =D9*'03_Каналы'!$B$5 -> 183.1415
A10: uml | B10: Яндекс Вордстат (РБ, Топы, 30 дней) | C10: 0.8074 | D10: =C10*'01_Параметры'!$B$12 -> 20338.14 | E10: информационный | F10: 0.1 | G10: =D10*F10 -> 2033.814 | H10: S-01 | I10: исключить (не подтверждает платежеспособный спрос) | J10: Частотность 591 запр./мес.; доля – среди перечисленных запросов (Similarweb долей запросов в бесплатном доступе не показывает) | K10: =D10*'03_Каналы'!$B$5 -> 9857.8962
A12: Столбец D в шаблоне = доля × трафик всего рынка (П-11), что вероятно завышает поисковую часть; в столбце K – умножение на долю Organic (48,47 %, plantuml.com). Веса намерений SW-X (проблемный 0,6–0,8, информационный 0,1) отличаются от ПС табл. 9 (проблемный 0,30–0,60) – Р-44

Sheet 06_Воронка_сценарии
A1: Расчет объема рынка через цифровую воронку и сценарии
A3: Сценарные допущения
A4: Сценарий | B4: Коэффициент покрытия конкурентов | C4: Оценка рынка: посещения/мес | D4: Конверсия в заявку | E4: Конверсия заявки в продажу | F4: Средний чек | G4: Покупок/клиента в год | H4: Заказов/мес | I4: Выручка/мес | J4: Выручка/год
A5: Осторожный | B5: 0.8 | C5: =IFERROR('01_Параметры'!$B$9/B5,0) -> 22040.961 | D5: 0.008 | E5: 0.03 | F5: 121.14 | G5: 1 | H5: =C5*D5*E5 -> 5.2898307 | I5: =H5*F5 -> 640.81009 | J5: =I5*12*G5 -> 7689.7211
A6: Базовый | B6: 0.7 | C6: =IFERROR('01_Параметры'!$B$9/B6,0) -> 25189.67 | D6: 0.015 | E6: 0.04 | F6: 121.14 | G6: 1 | H6: =C6*D6*E6 -> 15.113802 | I6: =H6*F6 -> 1830.886 | J6: =I6*12*G6 -> 21970.632
A7: Оптимистичный | B7: 0.55 | C7: =IFERROR('01_Параметры'!$B$9/B7,0) -> 32059.58 | D7: 0.025 | E7: 0.05 | F7: 290.74 | G7: 1 | H7: =C7*D7*E7 -> 40.074475 | I7: =H7*F7 -> 11651.253 | J7: =I7*12*G7 -> 139815.03
A10: Достижимая доля нового бизнеса (SOM)
A11: Сценарий | B11: Рыночная выручка/год | C11: Достижимая доля нового бизнеса | D11: Потенциальная выручка нового бизнеса/год | E11: Комментарий | F11: Ограничение
A12: Осторожный | B12: =J5 -> 7689.7211 | C12: 0.005 | D12: =B12*C12 -> 38.448605 | E12: Первые клиенты, тестирование канала | F12: Не учитывать как гарантированный доход
A13: Базовый | B13: =J6 -> 21970.632 | C13: 0.015 | D13: =B13*C13 -> 329.55948 | E13: Устойчивый канал привлечения | F13: Требуется конкурентный анализ
A14: Оптимистичный | B14: =J7 -> 139815.03 | C14: 0.035 | D14: =B14*C14 -> 4893.5262 | E14: Сильное позиционирование и повторные продажи | F14: Требуется подтверждение продажами
A17: Формула итогового вывода
A18: Оценочный цифровой объем рынка за год определяется как диапазон между осторожным и оптимистичным сценариями
A19: Минимум | C19: База | E19: Максимум | G19: Единица | H19: руб./год
A20: =A12 -> Осторожный | B20: =D12 -> 38.448605 | C20: =A13 -> Базовый | D20: =D13 -> 329.55948 | E20: =A14 -> Оптимистичный | F20: =D14 -> 4893.5262
A21: Рыночная выручка минимум | B21: =J5 -> 7689.7211 | C21: Рыночная выручка база | D21: =J6 -> 21970.632 | E21: Рыночная выручка максимум | F21: =J7 -> 139815.03
A22: Вывод | B22: ="При заданных допущениях годовой объем цифрового рынка оценивается в диапазоне от "&TEXT(J5,"# ##0")&" до "&TEXT(J7,"# ##0")&" руб., а достижимая выручка нового бизнеса – от "&TEXT(D12,"# ##0")&" до "&TEXT(D14,"# ##0")&" руб. в год." -> При заданных допущениях годовой объем цифрового рынка оценивается в диапазоне от 7 690 до 139 815 руб., а достижимая выручка нового бизнеса – от 38 до 4 894 руб. в год.

Sheet 07_Дашборд
A1: Итоговая панель оценки объема рынка по Similarweb
A3: Ключевые показатели
A4: Рынок | B4: ='01_Параметры'!B4 -> Веб-инструменты построения и проверки диаграмм формальных нотаций (UML, BPMN, ERD, IDEF, DFD) для студентов и специалистов по ПО | C4: География | D4: ='01_Параметры'!B5 -> Республика Беларусь | E4: Конкурентов | F4: ='01_Параметры'!B8 -> 4 | G4: Наблюдаемый трафик/мес | H4: ='01_Параметры'!B9 -> 17632.769 | I4: Оценка трафика рынка/мес | J4: ='01_Параметры'!B12 -> 25189.67
A5: Осторожный рынок/год | B5: ='06_Воронка_сценарии'!J5 -> 7689.7211 | C5: Базовый рынок/год | D5: ='06_Воронка_сценарии'!J6 -> 21970.632 | E5: Оптимистичный рынок/год | F5: ='06_Воронка_сценарии'!J7 -> 139815.03 | G5: SOM базовый/год | H5: ='06_Воронка_сценарии'!D13 -> 329.55948 | I5: Главный канал | J5: =INDEX('03_Каналы'!A4:A9,MATCH(MAX('03_Каналы'!B4:B9),'03_Каналы'!B4:B9,0)) -> Organic search
A6: Главный конкурент | B6: =INDEX('02_Конкуренты_SW'!B4:B7,MATCH(MAX('02_Конкуренты_SW'!G4:G7),'02_Конкуренты_SW'!G4:G7,0)) -> draw.io (diagrams.net) | C6: Доля главного конкурента | D6: =MAX('02_Конкуренты_SW'!I4:I7) -> 0.86613736 | E6: Главный поисковый запрос | F6: =INDEX('05_Запросы'!A4:A10,MATCH(MAX('05_Запросы'!G4:G10),'05_Запросы'!G4:G10,0)) -> uml | G6: Коммерческий индекс | H6: =MAX('05_Запросы'!G4:G10) -> 2033.814
A7: Итоговый вывод | B7: ='06_Воронка_сценарии'!B22 -> При заданных допущениях годовой объем цифрового рынка оценивается в диапазоне от 7 690 до 139 815 руб., а достижимая выручка нового бизнеса – от 38 до 4 894 руб. в год.
A10: Сценарий | B10: Рынок, год | C10: SOM нового бизнеса, год
A11: Осторожный | B11: ='06_Воронка_сценарии'!J5 -> 7689.7211 | C11: ='06_Воронка_сценарии'!D12 -> 38.448605
A12: Базовый | B12: ='06_Воронка_сценарии'!J6 -> 21970.632 | C12: ='06_Воронка_сценарии'!D13 -> 329.55948
A13: Оптимистичный | B13: ='06_Воронка_сценарии'!J7 -> 139815.03 | C13: ='06_Воронка_сценарии'!D14 -> 4893.5262
A16: Канал | B16: Доля | C16: Трафик/мес
A17: Direct | B17: ='03_Каналы'!B4 -> 0 | C17: ='03_Каналы'!C4 -> 0
A18: Organic search | B18: ='03_Каналы'!B5 -> 0.4847 | C18: ='03_Каналы'!C5 -> 12209.433
A19: Referral | B19: ='03_Каналы'!B6 -> 0 | C19: ='03_Каналы'!C6 -> 0
A20: Social | B20: ='03_Каналы'!B7 -> 0 | C20: ='03_Каналы'!C7 -> 0
A21: Paid search | B21: ='03_Каналы'!B8 -> 0 | C21: ='03_Каналы'!C8 -> 0
A22: Display | B22: ='03_Каналы'!B9 -> 0 | C22: ='03_Каналы'!C9 -> 0

Sheet 08_Источники
A1: Источники данных и журнал фиксации
A3: Источник | B3: Что брать | C3: Как фиксировать | D3: Ссылка | E3: Дата обращения | F3: Ограничение
A4: Similarweb Website Analysis | B4: Посещаемость, каналы, география, похожие сайты, поисковые запросы | C4: Ручной ввод или экспорт при наличии доступа | D4: https://www.similarweb.com/website/ | E4: 29.09.2026 | F4: Данные оценочные, полнота зависит от доступа
A5: Similarweb Data Methodology | B5: Описание природы и ограничений данных | C5: Использовать для методологических оговорок | D5: https://support.similarweb.com/hc/en-us/articles/360001631538-Similarweb-Data-Methodology | E5: 29.09.2026 | F5: Методология может обновляться
A6: Similarweb Data Exporter | B6: Выгрузка настраиваемых наборов данных | C6: Использовать при наличии платного доступа или единиц извлечения | D6: https://support.similarweb.com/hc/en-us/articles/13252032019101-Data-Exporter | E6: 29.09.2026 | F6: Может быть недоступно в бесплатной версии
A7: Google Trends | B7: Динамика относительного поискового интереса | C7: CSV-выгрузка и фиксация параметров | D7: https://trends.google.com/ | E7: 29.09.2026 | F7: Индекс 0–100, не абсолютный объем спроса
A8: Яндекс Вордстат | B8: Частотность и динамика поисковых запросов | C8: CSV/XLSX или ручная фиксация | D8: https://wordstat.yandex.ru/ | E8: 29.09.2026 | F8: Отражает аудиторию Яндекса
A9: Белстат / официальная статистика | B9: Количество организаций, отрасли, население, доходы | C9: Использовать для проверки сегмента клиентов | D9: https://www.belstat.gov.by/ | E9: 29.09.2026 | F9: Официальные категории могут не совпадать с цифровым рынком
A12: Журнал ручного сбора данных
A13: Дата | B13: Сайт / домен | C13: Раздел Similarweb | D13: Показатель | E13: Значение | F13: Комментарий / снимок экрана
A14: 46294.875 | B14: plantuml.com | C14: Overview | D14: Total visits (август 2026) | E14: 507000 | F14: скриншот similarweb_traffic_plantuml.com_global_last3months_2026-09-30.png
A15: 46294.875 | B15: plantuml.com | C15: Overview | D15: Global Rank | E15: 93517 | F15: ранг; Country Rank #24 334 (Россия); Category Rank #692
A16: 46294.875 | B16: plantuml.com | C16: Geography | D16: Доля России в трафике | E16: 0.0907 | F16: Беларусь в топ-5 стран не показана: нет данных в бесплатном доступе
A17: 46294.875 | B17: plantuml.com | C17: Marketing Channels | D17: Organic Search | E17: 0.4847 | F17: Direct и Referrals – 2-е и 3-е места без долей
A18: 46294.875 | B18: plantuml.com | C18: Engagement | D18: Bounce rate | E18: 0.4552 | F18: Pages/visit 3,18; Avg duration 00:03:16
A19: 46294.875 | B19: app.diagrams.net | C19: Overview | D19: Total visits | E19: доступ закрыт | F19: лимит бесплатных просмотров (скриншот ...global_limit_2026-09-30.png); значение 7,8 млн – из выгрузки ЛР1
A20: 46294.875 | B20: mermaid.live | C20: Overview | D20: Total visits | E20: доступ закрыт | F20: лимит бесплатных просмотров
A21: 46294.875 | B21: lucidchart.com | C21: Overview | D21: Total visits | E21: доступ закрыт | F21: лимит бесплатных просмотров; не собрано: Similarweb, страница lucidchart.com, снимок экрана (вручную, по странице источника; табл. 91, п. 1)
A24: Значения eraser.io (678,5 тыс.), app.diagrams.net (7,8 млн), mermaidchart.com (< 20 тыс.) указаны без скриншота (app.diagrams.net – по отчету ЛР1, остальные – предварительный замер 17–23.09.2026); повторный замер 30.09.2026 невозможен (лимит). не собрано минимум еще 6 доменов
