Workbook

Sheet 00_Методика
A1: Excel-шаблон: оценка объема рынка через поисковый спрос
A3: Назначение | B3: Шаблон переводит поисковый спрос в оценку потенциальных переходов, заявок, продаж и денежного объема рынка
A4: Логика | B4: Семантическое ядро → частотность и индекс интереса → нормализация → цифровая воронка → сценарный диапазон рынка
A5: Ключевое ограничение | B5: Поисковый спрос не равен фактическому объему рынка. Расчет показывает ориентир, который нужно проверять через конкурентов, статистику, платформы и реальные продажи
A6: Источники данных | B6: Google Trends, Яндекс Вордстат, рекламные кабинеты, данные сайта, CRM, экспертные оценки среднего чека и конверсий
A7: Как работать | B7: Заполните листы 01–04, проверьте расчет на листах 05–07 и используйте лист 08 для итогового вывода
A9: Порядок заполнения
A10: № | B10: Действие | C10: Лист
A11: 1 | B11: Заполнить параметры рынка и конверсий | C11: 01_Параметры
A12: 2 | B12: Внести запросы, группы и намерения аудитории | C12: 02_Семантика
A13: 3 | B13: Внести выгрузку Google Trends по месяцам | C13: 03_Google_Trends
A14: 4 | B14: Внести данные Яндекс Вордстат по частотности | C14: 04_Wordstat
A15: 5 | B15: Проверить нормализацию и сводный индекс | C15: 05_Нормализация
A16: 6 | B16: Рассчитать цифровую воронку | C16: 06_Воронка
A17: 7 | B17: Сравнить осторожный, базовый и оптимистичный сценарии | C17: 07_Сценарии
A18: 8 | B18: Сформулировать итоговый вывод | C18: 08_Дашборд

Sheet 01_Параметры
A1: Исходные параметры и допущения
A3: Параметр | B3: Значение | C3: Единица | D3: Комментарий
A4: Регион анализа | B4: Республика Беларусь | C4: текст | D4: Можно заменить на страну, область или город
A5: Период анализа | B5: сентябрь 2025 – август 2026 (12 мес.) | C5: текст | D5: Желательно использовать одинаковый период во всех источниках
A6: Средний чек | B6: 121.14 | C6: BYN/год | D6: Годовой чек Pro: 40 у.е. × курс НБРБ 3,0285 (30.09.2026). Альтернатива 4 у.е. × 12 = 48 у.е./год – 145,37 BYN
A7: Доля переходов из поиска | B7: 0.08 | C7: доля | D7: Базовое значение шкалы ПС табл. 17 (5–8 %)
A8: Конверсия посетитель → заявка | B8: 0.04 | C8: доля | D8: Посетитель → регистрация (заявка). ПС табл. 17: 3–5 %
A9: Конверсия заявка → продажа | B9: 0.04 | C9: доля | D9: Регистрация → оплата Pro. Допущение проекта (концепция NotaCode: Free → Pro 3–5 %); шкала ПС 25–35 % для freemium неприменима
A10: Коэффициент учета повторных покупок | B10: 1.2 | C10: раз | D10: Среднее число годовых оплат на платящего пользователя; шкала шаблона, срок удержания – допущение проекта (данных нет)
A11: Вес Google Trends в сводном индексе | B11: 0.4 | C11: доля | D11: В расчете 05_Нормализация; механическое сложение GT и Вордстат запрещено ПС §3 – показан для сравнения (см. отчет)
A12: Вес Яндекс Вордстат в сводном индексе | B12: 0.6 | C12: доля | D12: Сумма весов Google Trends и Вордстат должна быть равна 1
A13: Минимальная коммерческая близость | B13: 0.5 | C13: доля | D13: Не используется формулами (особенность шаблона П-13)

Sheet 02_Семантика
A1: Семантическое ядро и коммерческая близость запросов
A3: № | B3: Запрос | C3: Группа | D3: Намерение | E3: Регион | F3: Частотность Wordstat / мес. | G3: Индекс Google Trends | H3: Вес релевантности | I3: Коммерческая близость | J3: Взвешенный спрос
A4: 1 | B4: uml купить | C4: Коммерческий спрос | D4: коммерческое | E4: РБ | F4: 5 | G4: н/д | H4: 1 | I4: 0.9 | J4: =F4*H4*I4 -> 4.5
A5: 2 | B5: visio купить | C5: Коммерческий спрос | D5: коммерческое | E5: РБ | F5: 7 | G5: н/д | H5: 0.7 | I5: 0.85 | J5: =F5*H5*I5 -> 4.165
A6: 3 | B6: uml онлайн | C6: Инструментальный спрос | D6: инструментальное | E6: РБ | F6: 28 | G6: н/д | H6: 1 | I6: 0.65 | J6: =F6*H6*I6 -> 18.2
A7: 4 | B7: bpmn онлайн | C7: Инструментальный спрос | D7: инструментальное | E7: РБ | F7: 28 | G7: н/д | H7: 0.9 | I7: 0.65 | J7: =F7*H7*I7 -> 16.38
A8: 5 | B8: plantuml online | C8: Инструментальный спрос | D8: инструментальное | E8: РБ | F8: 14 | G8: н/д | H8: 0.9 | I8: 0.7 | J8: =F8*H8*I8 -> 8.82
A9: 6 | B9: нейросеть схема | C9: Инструментальный спрос | D9: инструментальное (AI) | E9: РБ | F9: 76 | G9: н/д | H9: 0.7 | I9: 0.55 | J9: =F9*H9*I9 -> 29.26
A10: 7 | B10: idef0 как | C10: Проблемный спрос | D10: проблемное | E10: РБ | F10: 11 | G10: н/д | H10: 1 | I10: 0.45 | J10: =F10*H10*I10 -> 4.95
A11: 8 | B11: bpmn пример | C11: Проблемный спрос | D11: проблемное | E11: РБ | F11: 10 | G11: н/д | H11: 0.9 | I11: 0.4 | J11: =F11*H11*I11 -> 3.6
A12: 9 | B12: uml | C12: Общий тематический спрос | D12: информационное | E12: РБ | F12: 591 | G12: 14.52 | H12: 1 | I12: 0.2 | J12: =F12*H12*I12 -> 118.2
A13: 10 | B13: mermaid | C13: Исключаемый (омоним) | D13: омоним: фильм | E13: РБ | F13: 1163 | G13: н/д | H13: 0 | I13: 0 | J13: =F13*H13*I13 -> 0
A15: Примечание | B15: Частотность – Яндекс Вордстат, Беларусь, «Топы запросов», 25.08–23.09.2026, все устройства. GT-индекс: н/д = недостаточно данных по Беларуси; у «uml» – среднее недельного ряда за 12 мес. по данным ЛР1. «mermaid» без уточнения – омоним (фильм «Русалочка»), вес 0,00 по ПС табл. 9 (особенность шаблона П-14)

Sheet 03_Google_Trends
A1: Данные Google Trends: месячный индекс интереса
A3: Месяц | B3: UML | C3: BPMN | D3: PlantUML | E3: IDEF0 | F3: Средний индекс GT | G3: Комментарий
A4: 45900.875 | B4: 0 | C4: 0 | D4: 0 | E4: 0 | F4: =AVERAGE(B4:E4) -> 0 | G4: все значения 0: недостаточно данных Google Trends по Беларуси
A5: 45930.875 | B5: 27.75 | C5: 48 | D5: 0 | E5: 0 | F5: =AVERAGE(B5:E5) -> 18.9375 | G5: –
A6: 45961.875 | B6: 18.2 | C6: 16.4 | D6: 0 | E6: 0 | F6: =AVERAGE(B6:E6) -> 8.65 | G6: –
A7: 45991.875 | B7: 67 | C7: 13 | D7: 30.5 | E7: 0 | F7: =AVERAGE(B7:E7) -> 27.625 | G7: –
A8: 46022.875 | B8: 0 | C8: 14.25 | D8: 0 | E8: 0 | F8: =AVERAGE(B8:E8) -> 3.5625 | G8: –
A9: 46053.875 | B9: 27 | C9: 52 | D9: 0 | E9: 0 | F9: =AVERAGE(B9:E9) -> 19.75 | G9: –
A10: 46081.875 | B10: 11.4 | C10: 0 | D10: 0 | E10: 0 | F10: =AVERAGE(B10:E10) -> 2.85 | G10: –
A11: 46112.875 | B11: 18.75 | C11: 13.5 | D11: 12.25 | E11: 14.25 | F11: =AVERAGE(B11:E11) -> 14.6875 | G11: –
A12: 46142.875 | B12: 0 | C12: 0 | D12: 0 | E12: 0 | F12: =AVERAGE(B12:E12) -> 0 | G12: все значения 0: недостаточно данных Google Trends по Беларуси
A13: 46173.875 | B13: 0 | C13: 0 | D13: 0 | E13: 0 | F13: =AVERAGE(B13:E13) -> 0 | G13: все значения 0: недостаточно данных Google Trends по Беларуси
A14: 46203.875 | B14: 0 | C14: 0 | D14: 0 | E14: 0 | F14: =AVERAGE(B14:E14) -> 0 | G14: все значения 0: недостаточно данных Google Trends по Беларуси
A15: 46234.875 | B15: 0 | C15: 0 | D15: 0 | E15: 0 | F15: =AVERAGE(B15:E15) -> 0 | G15: все значения 0: недостаточно данных Google Trends по Беларуси
A17: Источник: Google Trends, Беларусь, today 12-m, категория «все», веб-поиск, один запрос из 4 терминов (единая шкала); недельные значения усреднены по месяцам (по дате начала недели). Выгрузка 30.09.2026

Sheet 04_Wordstat
A1: Данные Яндекс Вордстат: частотность запросов
A3: Месяц | B3: Коммерческие запросы | C3: Проблемные запросы | D3: Инструментальные запросы | E3: Локальные запросы | F3: Суммарная частотность | G3: Коммерческий коэффициент | H3: Взвешенная частотность | K3: Вес намерения | L3: ПС табл. 9
A4: 45900.875 | B4: 21 | C4: 119 | D4: 425 | E4: 0 | F4: =SUM(B4:E4) -> 565 | G4: =IF(F4=0,0,(B4*$L$4+C4*$L$5+D4*$L$6+E4*$L$7)/F4) -> 0.61716814 | H4: =F4*G4 -> 348.7 | K4: Коммерческие запросы | L4: 0.9
A5: 45930.875 | B5: 17 | C5: 113 | D5: 562 | E5: 0 | F5: =SUM(B5:E5) -> 692 | G5: =IF(F5=0,0,(B5*$L$4+C5*$L$5+D5*$L$6+E5*$L$7)/F5) -> 0.62348266 | H5: =F5*G5 -> 431.45 | K5: Проблемные запросы | L5: 0.45
A6: 45961.875 | B6: 15 | C6: 110 | D6: 574 | E6: 0 | F6: =SUM(B6:E6) -> 699 | G6: =IF(F6=0,0,(B6*$L$4+C6*$L$5+D6*$L$6+E6*$L$7)/F6) -> 0.62389127 | H6: =F6*G6 -> 436.1 | K6: Инструментальные запросы | L6: 0.65
A7: 45991.875 | B7: 20 | C7: 158 | D7: 669 | E7: 0 | F7: =SUM(B7:E7) -> 847 | G7: =IF(F7=0,0,(B7*$L$4+C7*$L$5+D7*$L$6+E7*$L$7)/F7) -> 0.61859504 | H7: =F7*G7 -> 523.95 | K7: Локальные запросы | L7: 0.3
A8: 46022.875 | B8: 32 | C8: 64 | D8: 238 | E8: 0 | F8: =SUM(B8:E8) -> 334 | G8: =IF(F8=0,0,(B8*$L$4+C8*$L$5+D8*$L$6+E8*$L$7)/F8) -> 0.63562874 | H8: =F8*G8 -> 212.3 | K8: Коммерческий коэффициент (столбец G) – средневзвешенный вес намерения по составу месяца
A9: 46053.875 | B9: 12 | C9: 46 | D9: 284 | E9: 0 | F9: =SUM(B9:E9) -> 342 | G9: =IF(F9=0,0,(B9*$L$4+C9*$L$5+D9*$L$6+E9*$L$7)/F9) -> 0.63187135 | H9: =F9*G9 -> 216.1
A10: 46081.875 | B10: 50 | C10: 105 | D10: 494 | E10: 0 | F10: =SUM(B10:E10) -> 649 | G10: =IF(F10=0,0,(B10*$L$4+C10*$L$5+D10*$L$6+E10*$L$7)/F10) -> 0.63690293 | H10: =F10*G10 -> 413.35
A11: 46112.875 | B11: 52 | C11: 94 | D11: 541 | E11: 0 | F11: =SUM(B11:E11) -> 687 | G11: =IF(F11=0,0,(B11*$L$4+C11*$L$5+D11*$L$6+E11*$L$7)/F11) -> 0.6415575 | H11: =F11*G11 -> 440.75
A12: 46142.875 | B12: 23 | C12: 69 | D12: 589 | E12: 0 | F12: =SUM(B12:E12) -> 681 | G12: =IF(F12=0,0,(B12*$L$4+C12*$L$5+D12*$L$6+E12*$L$7)/F12) -> 0.63817915 | H12: =F12*G12 -> 434.6
A13: 46173.875 | B13: 12 | C13: 66 | D13: 340 | E13: 0 | F13: =SUM(B13:E13) -> 418 | G13: =IF(F13=0,0,(B13*$L$4+C13*$L$5+D13*$L$6+E13*$L$7)/F13) -> 0.62559809 | H13: =F13*G13 -> 261.5
A14: 46203.875 | B14: 18 | C14: 43 | D14: 125 | E14: 0 | F14: =SUM(B14:E14) -> 186 | G14: =IF(F14=0,0,(B14*$L$4+C14*$L$5+D14*$L$6+E14*$L$7)/F14) -> 0.62795699 | H14: =F14*G14 -> 116.8
A15: 46234.875 | B15: 14 | C15: 34 | D15: 107 | E15: 0 | F15: =SUM(B15:E15) -> 155 | G15: =IF(F15=0,0,(B15*$L$4+C15*$L$5+D15*$L$6+E15*$L$7)/F15) -> 0.62870968 | H15: =F15*G15 -> 97.45
A17: Источник: Яндекс Вордстат, Беларусь (id=149), все устройства, вкладка «Динамика», месячные значения; групповой ряд – сумма рядов отдельных формулировок (операторы группировки в «Динамике» не поддерживаются). Состав групп и учет пересечений – в отчете. Локальные запросы: ряд ниже порога отображения (Топы: uml минск 3, bpmn минск 4 за 30 дней)

Sheet 05_Нормализация
A1: Нормализация данных и сводный индекс поискового спроса
A3: Месяц | B3: Средний индекс GT | C3: Нормированный GT | D3: Взвешенная частотность WS | E3: Нормированный WS | F3: Сводный индекс спроса | G3: Оценка уровня | H3: Комментарий
A4: ='03_Google_Trends'!A4 -> 45900.875 | B4: ='03_Google_Trends'!F4 -> 0 | C4: =IF(MAX($B$4:$B$15)=0,0,B4/MAX($B$4:$B$15)*100) -> 0 | D4: ='04_Wordstat'!H4 -> 348.7 | E4: =IF(MAX($D$4:$D$15)=0,0,D4/MAX($D$4:$D$15)*100) -> 66.552152 | F4: =C4*'01_Параметры'!$B$11+E4*'01_Параметры'!$B$12 -> 39.931291 | G4: =IF(F4>=75,"высокий",IF(F4>=45,"средний","низкий")) -> низкий | H4: –
A5: ='03_Google_Trends'!A5 -> 45930.875 | B5: ='03_Google_Trends'!F5 -> 18.9375 | C5: =IF(MAX($B$4:$B$15)=0,0,B5/MAX($B$4:$B$15)*100) -> 68.552036 | D5: ='04_Wordstat'!H5 -> 431.45 | E5: =IF(MAX($D$4:$D$15)=0,0,D5/MAX($D$4:$D$15)*100) -> 82.345644 | F5: =C5*'01_Параметры'!$B$11+E5*'01_Параметры'!$B$12 -> 76.828201 | G5: =IF(F5>=75,"высокий",IF(F5>=45,"средний","низкий")) -> высокий | H5: –
A6: ='03_Google_Trends'!A6 -> 45961.875 | B6: ='03_Google_Trends'!F6 -> 8.65 | C6: =IF(MAX($B$4:$B$15)=0,0,B6/MAX($B$4:$B$15)*100) -> 31.312217 | D6: ='04_Wordstat'!H6 -> 436.1 | E6: =IF(MAX($D$4:$D$15)=0,0,D6/MAX($D$4:$D$15)*100) -> 83.233133 | F6: =C6*'01_Параметры'!$B$11+E6*'01_Параметры'!$B$12 -> 62.464767 | G6: =IF(F6>=75,"высокий",IF(F6>=45,"средний","низкий")) -> средний | H6: –
A7: ='03_Google_Trends'!A7 -> 45991.875 | B7: ='03_Google_Trends'!F7 -> 27.625 | C7: =IF(MAX($B$4:$B$15)=0,0,B7/MAX($B$4:$B$15)*100) -> 100 | D7: ='04_Wordstat'!H7 -> 523.95 | E7: =IF(MAX($D$4:$D$15)=0,0,D7/MAX($D$4:$D$15)*100) -> 100 | F7: =C7*'01_Параметры'!$B$11+E7*'01_Параметры'!$B$12 -> 100 | G7: =IF(F7>=75,"высокий",IF(F7>=45,"средний","низкий")) -> высокий | H7: –
A8: ='03_Google_Trends'!A8 -> 46022.875 | B8: ='03_Google_Trends'!F8 -> 3.5625 | C8: =IF(MAX($B$4:$B$15)=0,0,B8/MAX($B$4:$B$15)*100) -> 12.895928 | D8: ='04_Wordstat'!H8 -> 212.3 | E8: =IF(MAX($D$4:$D$15)=0,0,D8/MAX($D$4:$D$15)*100) -> 40.519134 | F8: =C8*'01_Параметры'!$B$11+E8*'01_Параметры'!$B$12 -> 29.469851 | G8: =IF(F8>=75,"высокий",IF(F8>=45,"средний","низкий")) -> низкий | H8: –
A9: ='03_Google_Trends'!A9 -> 46053.875 | B9: ='03_Google_Trends'!F9 -> 19.75 | C9: =IF(MAX($B$4:$B$15)=0,0,B9/MAX($B$4:$B$15)*100) -> 71.493213 | D9: ='04_Wordstat'!H9 -> 216.1 | E9: =IF(MAX($D$4:$D$15)=0,0,D9/MAX($D$4:$D$15)*100) -> 41.244394 | F9: =C9*'01_Параметры'!$B$11+E9*'01_Параметры'!$B$12 -> 53.343921 | G9: =IF(F9>=75,"высокий",IF(F9>=45,"средний","низкий")) -> средний | H9: –
A10: ='03_Google_Trends'!A10 -> 46081.875 | B10: ='03_Google_Trends'!F10 -> 2.85 | C10: =IF(MAX($B$4:$B$15)=0,0,B10/MAX($B$4:$B$15)*100) -> 10.316742 | D10: ='04_Wordstat'!H10 -> 413.35 | E10: =IF(MAX($D$4:$D$15)=0,0,D10/MAX($D$4:$D$15)*100) -> 78.891116 | F10: =C10*'01_Параметры'!$B$11+E10*'01_Параметры'!$B$12 -> 51.461366 | G10: =IF(F10>=75,"высокий",IF(F10>=45,"средний","низкий")) -> средний | H10: –
A11: ='03_Google_Trends'!A11 -> 46112.875 | B11: ='03_Google_Trends'!F11 -> 14.6875 | C11: =IF(MAX($B$4:$B$15)=0,0,B11/MAX($B$4:$B$15)*100) -> 53.167421 | D11: ='04_Wordstat'!H11 -> 440.75 | E11: =IF(MAX($D$4:$D$15)=0,0,D11/MAX($D$4:$D$15)*100) -> 84.120622 | F11: =C11*'01_Параметры'!$B$11+E11*'01_Параметры'!$B$12 -> 71.739342 | G11: =IF(F11>=75,"высокий",IF(F11>=45,"средний","низкий")) -> средний | H11: –
A12: ='03_Google_Trends'!A12 -> 46142.875 | B12: ='03_Google_Trends'!F12 -> 0 | C12: =IF(MAX($B$4:$B$15)=0,0,B12/MAX($B$4:$B$15)*100) -> 0 | D12: ='04_Wordstat'!H12 -> 434.6 | E12: =IF(MAX($D$4:$D$15)=0,0,D12/MAX($D$4:$D$15)*100) -> 82.946846 | F12: =C12*'01_Параметры'!$B$11+E12*'01_Параметры'!$B$12 -> 49.768108 | G12: =IF(F12>=75,"высокий",IF(F12>=45,"средний","низкий")) -> средний | H12: –
A13: ='03_Google_Trends'!A13 -> 46173.875 | B13: ='03_Google_Trends'!F13 -> 0 | C13: =IF(MAX($B$4:$B$15)=0,0,B13/MAX($B$4:$B$15)*100) -> 0 | D13: ='04_Wordstat'!H13 -> 261.5 | E13: =IF(MAX($D$4:$D$15)=0,0,D13/MAX($D$4:$D$15)*100) -> 49.909342 | F13: =C13*'01_Параметры'!$B$11+E13*'01_Параметры'!$B$12 -> 29.945605 | G13: =IF(F13>=75,"высокий",IF(F13>=45,"средний","низкий")) -> низкий | H13: –
A14: ='03_Google_Trends'!A14 -> 46203.875 | B14: ='03_Google_Trends'!F14 -> 0 | C14: =IF(MAX($B$4:$B$15)=0,0,B14/MAX($B$4:$B$15)*100) -> 0 | D14: ='04_Wordstat'!H14 -> 116.8 | E14: =IF(MAX($D$4:$D$15)=0,0,D14/MAX($D$4:$D$15)*100) -> 22.292203 | F14: =C14*'01_Параметры'!$B$11+E14*'01_Параметры'!$B$12 -> 13.375322 | G14: =IF(F14>=75,"высокий",IF(F14>=45,"средний","низкий")) -> низкий | H14: –
A15: ='03_Google_Trends'!A15 -> 46234.875 | B15: ='03_Google_Trends'!F15 -> 0 | C15: =IF(MAX($B$4:$B$15)=0,0,B15/MAX($B$4:$B$15)*100) -> 0 | D15: ='04_Wordstat'!H15 -> 97.45 | E15: =IF(MAX($D$4:$D$15)=0,0,D15/MAX($D$4:$D$15)*100) -> 18.599103 | F15: =C15*'01_Параметры'!$B$11+E15*'01_Параметры'!$B$12 -> 11.159462 | G15: =IF(F15>=75,"высокий",IF(F15>=45,"средний","низкий")) -> низкий | H15: –

Sheet 06_Воронка
A1: Цифровая воронка: перевод поискового спроса в продажи и выручку
A3: Показатель | B3: Осторожный | C3: Базовый | D3: Оптимистичный | E3: Комментарий
A4: Взвешенный поисковый спрос / мес. | B4: =AVERAGE('04_Wordstat'!$H$4:$H$15) -> 327.75417 | C4: =AVERAGE('04_Wordstat'!$H$4:$H$15) -> 327.75417 | D4: =AVERAGE('04_Wordstat'!$H$4:$H$15) -> 327.75417 | E4: Берется из листа 04_Wordstat как среднее значение
A5: Доля переходов из поиска | B5: 0.04 | C5: 0.08 | D5: 0.12 | E5: CTR или доля пользователей, перешедших на сайт / страницу
A6: Посещения / мес. | B6: =B4*B5 -> 13.110167 | C6: =C4*C5 -> 26.220333 | D6: =D4*D5 -> 39.3305 | E6: Поисковый спрос × доля переходов
A7: Конверсия посетитель → заявка | B7: 0.02 | C7: 0.04 | D7: 0.07 | E7: Зависит от качества предложения и сайта
A8: Заявки / мес. | B8: =B6*B7 -> 0.26220333 | C8: =C6*C7 -> 1.0488133 | D8: =D6*D7 -> 2.753135 | E8: Посещения × конверсия в заявку
A9: Конверсия заявка → продажа | B9: 0.03 | C9: 0.04 | D9: 0.05 | E9: Регистрация → оплата Pro: допущение проекта 3–5 % (вне шкалы ПС 10–50 %)
A10: Продажи / мес. | B10: =B8*B9 -> 0.0078661 | C10: =C8*C9 -> 0.041952533 | D10: =D8*D9 -> 0.13765675 | E10: Заявки × конверсия в продажу
A11: Средний чек | B11: 121.14 | C11: 121.14 | D11: 290.74 | E11: Годовой чек Pro, BYN: 40 у.е./год (осторожный и базовый); медиана входных платных тарифов конкурентов (8 у.е./мес. × 12)
A12: Коэффициент повторных покупок | B12: 1 | C12: 1.2 | D12: 1.5 | E12: Число годовых оплат на платящего; шкала шаблона (1 / 1,2 / 1,5), срок удержания – допущение
A13: Выручка / мес. | B13: =B10*B11*B12 -> 0.95289935 | C13: =C10*C11*C12 -> 6.0985559 | D13: =D10*D11*D12 -> 60.033485 | E13: Продажи × средний чек × повторные покупки
A14: Выручка / год | B14: =B13*12 -> 11.434792 | C14: =C13*12 -> 73.18267 | D14: =D13*12 -> 720.40182 | E14: Месячная выручка × 12

Sheet 07_Сценарии
A1: Сценарная оценка объема рынка
A3: Сценарий | B3: Переходы / мес. | C3: Заявки / мес. | D3: Продажи / мес. | E3: Средний чек | F3: Выручка / мес. | G3: Выручка / год | H3: Интерпретация
A4: Осторожный | B4: ='06_Воронка'!B6 -> 13.110167 | C4: ='06_Воронка'!B8 -> 0.26220333 | D4: ='06_Воронка'!B10 -> 0.0078661 | E4: ='06_Воронка'!B11 -> 121.14 | F4: ='06_Воронка'!B13 -> 0.95289935 | G4: ='06_Воронка'!B14 -> 11.434792 | H4: Нижняя граница оценки при слабой конверсии
A5: Базовый | B5: ='06_Воронка'!C6 -> 26.220333 | C5: ='06_Воронка'!C8 -> 1.0488133 | D5: ='06_Воронка'!C10 -> 0.041952533 | E5: ='06_Воронка'!C11 -> 121.14 | F5: ='06_Воронка'!C13 -> 6.0985559 | G5: ='06_Воронка'!C14 -> 73.18267 | H5: Рабочий ориентир для планирования
A6: Оптимистичный | B6: ='06_Воронка'!D6 -> 39.3305 | C6: ='06_Воронка'!D8 -> 2.753135 | D6: ='06_Воронка'!D10 -> 0.13765675 | E6: ='06_Воронка'!D11 -> 290.74 | F6: ='06_Воронка'!D13 -> 60.033485 | G6: ='06_Воронка'!D14 -> 720.40182 | H6: Верхняя граница при сильном предложении и продвижении

Sheet 08_Дашборд
A1: Итоговая панель оценки рынка через поисковый спрос
A3: Показатель | B3: Значение | C3: Комментарий
A4: Средний сводный индекс спроса | B4: =AVERAGE('05_Нормализация'!F4:F15) -> 49.123936 | C4: Среднее по листу нормализации
A5: Максимальный сводный индекс спроса | B5: =MAX('05_Нормализация'!F4:F15) -> 100 | C5: Пик интереса за период
A6: Средняя взвешенная частотность | B6: =AVERAGE('04_Wordstat'!H4:H15) -> 327.75417 | C6: Средний коммерчески взвешенный спрос / мес.
A7: Базовая выручка / мес. | B7: ='06_Воронка'!C13 -> 6.0985559 | C7: Расчет по базовому сценарию
A8: Базовая выручка / год | B8: ='06_Воронка'!C14 -> 73.18267 | C8: Расчет по базовому сценарию
A9: Диапазон годовой выручки | B9: =TEXT('06_Воронка'!B14,"# ##0")&" – "&TEXT('06_Воронка'!D14,"# ##0") -> 11 – 720 | C9: Осторожный – оптимистичный сценарий
A10: Уровень интереса | B10: =IF(B4>=75,"высокий",IF(B4>=45,"средний","низкий")) -> средний | C10: Автоматическая классификация по среднему индексу

Sheet 09_Источники
A1: Источники данных и журнал фиксации
A3: Источник | B3: Что брать | C3: Период / регион | D3: Дата фиксации | E3: Ссылка / примечание
A4: Google Trends | B4: Индекс интереса, динамика, региональность, связанные запросы | C4: Беларусь; 12 мес. (сент. 2025 – авг. 2026) | D4: 29.09.2026 | E4: https://trends.google.com/
A5: Справка Google Trends | B5: Описание нормированного индекса и выгрузки CSV | C5: общая методика | D5: 29.09.2026 | E5: https://support.google.com/trends/answer/4365533
A6: Яндекс Вордстат | B6: Частотность запросов, динамика, регионы, похожие запросы | C6: Беларусь (id=149); 24 мес. и 30 дней | D6: 29.09.2026 | E6: https://wordstat.yandex.ru/
A7: Справка Яндекс Вордстат | B7: Описание интерфейса, динамики, регионов и экспорта | C7: общая методика | D7: 29.09.2026 | E7: https://yandex.ru/support2/wordstat/ru/
A8: Рекламные кабинеты | B8: Оценка охвата, кликабельности, стоимости клика | C8: указать | D8: 02.05.2026 | E8: не собрано: Google Ads Keyword Planner / Яндекс Директ (прогноз показов и CPC) – нужны рекламные кабинеты (нужен доступ)
A9: Сайт / CRM / продажи | B9: Фактические конверсии, заявки, средний чек | C9: указать | D9: 02.05.2026 | E9: Собственной аналитики нет (MVP не запущен): конверсии – допущение проекта (концепция NotaCode: Free → Pro 3–5 %)
A10: Курс НБРБ у.е./BYN | B10: 3,0285 BYN за 1 у.е. | C10: – | D10: 29.09.2026 | E10: https://api.nbrb.by/exrates/rates/431
A11: Концепция NotaCode | B11: Цена Pro 40 у.е./год (помесячно 4 у.е.); конверсия Free → Pro 3–5 % (гипотеза A-06) | C11: – | D11: 29.09.2026 | E11: документ проекта (концепция, раздел 6)
A12: Тарифы конкурентов | B12: Входные платные тарифы, медиана 8 у.е./мес. при оплате за год | C12: – | D12: 29.09.2026 | E12: страницы тарифов Miro, Lucidchart, Mermaid Chart и др.
