Workbook

Sheet 00_Методика
A1: Excel-шаблон оценки рынка через цифровую воронку
A3: Назначение файла | B3: Как использовать | C3: Основная формула | D3: Что является входом | E3: Что является расчетом | F3: Что проверять | G3: Ограничения | H3: Итог
A4: Оценить потенциальный объем рынка электронного бизнеса через охват, трафик, заявки, продажи, средний чек, повторные покупки и платформенную модель | B4: Заполнить желтые ячейки на листах 01–03, затем проверить расчеты на листах 04–08 | C4: Выручка = релевантные посещения × конверсия в заявку × конверсия в продажу × средний чек × повторные покупки | D4: Данные Google Trends, Яндекс Вордстат, Similarweb, рекламных кабинетов, аналитики сайта и экспертных допущений | E4: Зеленые ячейки содержат формулы и автоматически пересчитывают заявки, продажи, выручку, GMV и рыночный диапазон | F4: Согласованность допущений, реалистичность конверсий, различие между интересом аудитории и платежеспособным спросом | G4: Все расчеты являются оценочными; цифровая воронка не заменяет анализ конкурентов, цен, платежеспособности и фактических продаж | H4: Сценарный диапазон объема рынка и достижимой выручки
A6: Этап | B6: Действие | C6: Где заполнять | D6: Результат
A7: 1 | B7: Зафиксировать географию, продуктовую категорию и период расчета | C7: 01_Параметры | D7: Единая база исследования
A8: 2 | B8: Собрать исходные данные об охвате и трафике по каналам | C8: 02_Трафик_охват | D8: Релевантные посещения рынка
A9: 3 | B9: Зафиксировать данные конкурентов из Similarweb и других открытых источников | C9: 03_Конкуренты_SW | D9: Оценка видимого цифрового объема сегмента
A10: 4 | B10: Задать конверсии в заявку и продажу по трем сценариям | C10: 04_Воронка | D10: Расчет заявок, продаж и выручки
A11: 5 | B11: Сравнить осторожный, базовый и оптимистичный сценарии | C11: 05_Сценарии | D11: Диапазон возможного объема рынка
A12: 6 | B12: Учесть повторные покупки и жизненную ценность клиента | C12: 06_Повторы_LTV | D12: Годовая и расширенная оценка выручки
A13: 7 | B13: Если бизнес является платформой, рассчитать GMV и комиссионную выручку | C13: 07_Платформа_GMV | D13: Разделение оборота платформы и собственной выручки
A14: 8 | B14: Проверить итоговую панель и сформулировать вывод | C14: 08_Дашборд | D14: Готовые показатели для отчета
A16: Цвет ячеек | B16: Значение | C16: Можно изменять? | D16: Комментарий
A17: Желтый | B17: Исходные данные / допущения | C17: Да | D17: Заполняются пользователем
A18: Зеленый | B18: Расчетные ячейки | C18: Нет | D18: Содержат формулы
A19: Серый | B19: Пояснения и методические комментарии | C19: Да | D19: Можно адаптировать под отчет

Sheet 01_Параметры
A1: 01. Исходные параметры оценки рынка
A3: Параметр | B3: Значение | C3: Единица | D3: Источник/обоснование | E3: Комментарий | F3: Статус
A4: Название бизнес-идеи | B4: NotaCode – веб-IDE для построения и проверки диаграмм формальных нотаций (UML, BPMN, ERD, IDEF, DFD) как текста | C4: текст | D4: Пользователь | E4: Можно заменить на любую бизнес-идею | F4: ввод
A5: Географические границы | B5: Республика Беларусь | C5: территория | D5: Ранее зафиксированные границы рынка | E5: При необходимости указать город или регион | F5: ввод
A6: Период расчета | B6: месяц / год | C6: период | D6: Методика | E6: Для рынка услуг удобно считать месяц и год | F6: ввод
A7: Валюта расчета | B7: BYN | C7: валюта | D7: Пользователь | E7: Можно заменить на RUB, у.е., EUR | F7: ввод
A8: Целевой клиент | B8: пользователи-физические лица: студенты (S-01), аналитики (S-02), архитекторы и разработчики (S-03), преподаватели (S-04) | C8: сегмент | D8: Границы рынка | E8: Кто потенциально покупает услугу | F8: ввод
A9: Средний чек базовый | B9: 121.14 | C9: BYN/оплата (год) | D9: Pro: годовой тариф 40 у.е. × 3,0285 (курс НБРБ 30.09.2026) | E9: Используется в базовом сценарии | F9: ввод
A10: Средний чек осторожный | B10: 121.14 | C10: BYN/оплата (год) | D10: Альтернативный вариант: 4 у.е. × 12 = 48 у.е. × 3,0285 = 145,37 BYN | E10: Нижняя граница чека | F10: ввод
A11: Средний чек оптимистичный | B11: 290.74 | C11: BYN/оплата (год) | D11: Медиана входных платных тарифов конкурентов (8 у.е./мес.) × 12 × 3,0285 | E11: Верхняя граница чека | F11: ввод
A12: Целевая доля релевантного трафика | B12: 0.3846 | C12: доля | D12: Допущение Д-02: средневзвешенная по визитам доля релевантного трафика четырех доменов выборки (расчет в 03_Конкуренты_SW); в формулах шаблона не должна использоваться как покрытие (П-2) | E12: Какая часть собранного трафика относится к анализируемому рынку | F12: ввод
A13: Коэффициент покрытия конкурентов | B13: 0.65 | C13: доля | D13: Допущение Д-05: коэффициент покрытия выборки; значение базового сценария М2 табл. 21 (0,65); шкала М2 табл. 9 для типовой ситуации 0,60–0,75 | E13: Доля рынка, представленная найденными сайтами конкурентов | F13: ввод
A14: Дата обновления файла | B14: 46294.875 | C14: дата | D14: Пользователь | E14: Обновлять при новой выгрузке данных | F14: ввод
A16: Сценарий | B16: Доля достижимого трафика | C16: Конверсия посещение → заявка | D16: Конверсия заявка → продажа | E16: Средний чек | F16: Повторных покупок в год
A17: Осторожный | B17: 0.15 | C17: 0.01 | D17: 0.03 | E17: =B10 -> 121.14 | F17: 1
A18: Базовый | B18: 0.25 | C18: 0.025 | D18: 0.04 | E18: =B9 -> 121.14 | F18: 1.2
A19: Оптимистичный | B19: 0.4 | C19: 0.05 | D19: 0.05 | E19: =B11 -> 290.74 | F19: 1.5

Sheet 02_Трафик_охват
A1: 02. Охват и трафик по цифровым каналам
A3: Канал | B3: Источник данных | C3: Охват/показы/посещения в месяц | D3: CTR или доля переходов | E3: Посещения в месяц | F3: Доля релевантной аудитории | G3: Релевантные посещения | H3: Качество данных | I3: Комментарий
A4: Органический поиск | B4: Яндекс Вордстат (Беларусь), взвешенная частотность ядра, среднее за 12 мес. (см. расчет ПС) | C4: 327.75 | D4: 0.08 | E4: =C4*D4 -> 26.22 | F4: 1 | G4: =E4*F4 -> 26.22 | H4: среднее | I4: Релевантность учтена весами ядра (ПС), поэтому доля релевантной аудитории = 1; CTR – базовое значение ПС табл. 17
A5: Платный поиск | B5: Google Ads / Яндекс Директ | C5: 0 | D5: 0 | E5: =C5*D5 -> 0 | F5: 0 | G5: =E5*F5 -> 0 | H5: нет данных | I5: не собрано: прогноз показов/кликов Яндекс Директ или Google Ads Keyword Planner по ядру запросов (нужен рекламный кабинет)
A6: Социальные сети | B6: Meta Ads / VK / TikTok / статистика страниц | C6: 0 | D6: 0 | E6: =C6*D6 -> 0 | F6: 0 | G6: =E6*F6 -> 0 | H6: нет данных | I6: не собрано: оценка охвата аудитории в рекламных кабинетах VK / Meta (нужен рекламный кабинет)
A7: Реферальные площадки | B7: Каталоги / партнеры / платформы | C7: 0 | D7: 0 | E7: =C7*D7 -> 0 | F7: 0 | G7: =E7*F7 -> 0 | H7: нет данных | I7: Нет данных: продукт не размещен в каталогах и у партнеров (MVP не запущен)
A8: Прямой трафик | B8: Similarweb / Google Analytics | C8: 0 | D8: 1 | E8: =C8*D8 -> 0 | F8: 0 | G8: =E8*F8 -> 0 | H8: нет данных | I8: Нет данных: бренд NotaCode не запущен, прямых заходов нет
A9: Маркетплейсы услуг | B9: Платформы / каталоги исполнителей | C9: 0 | D9: 0 | E9: =C9*D9 -> 0 | F9: 0 | G9: =E9*F9 -> 0 | H9: нет данных | I9: Не применяется: NotaCode не размещается на маркетплейсах услуг
A10: Прочие каналы | B10: Экспертная оценка | C10: 0 | D10: 0 | E10: =C10*D10 -> 0 | F10: 0 | G10: =E10*F10 -> 0 | H10: нет данных | I10: Нет данных
A12: Итог | B12: Формула | C12: Значение | D12: Единица | E12: Комментарий | F12: Используется далее
A13: Общие посещения в месяц | B13: SUM(E4:E10) | C13: =SUM(E4:E10) -> 26.22 | D13: посещений | E13: Оценка всех переходов по каналам | F13: да
A14: Релевантные посещения в месяц | B14: SUM(G4:G10) | C14: =SUM(G4:G10) -> 26.22 | D14: посещений | E14: Трафик, относящийся к рынку | F14: да
A15: Релевантные посещения в год | B15: C14*12 | C15: =C14*12 -> 314.64 | D15: посещений | E15: Годовая база для сценариев | F15: да

Sheet 03_Конкуренты_SW
A1: 03. Данные Similarweb и конкурентов
A3: Конкурент / сайт | B3: Тип игрока | C3: Посещения в месяц по Similarweb | D3: Доля целевой географии | E3: Доля релевантной категории | F3: Релевантные посещения | G3: Оценочная конверсия в продажу | H3: Средний чек | I3: Оценочная выручка в месяц | J3: Комментарий
A4: plantuml.com | B4: прямой (текстовый DSL) | C4: 507000 | D4: 0.001958 | E4: 0.75 | F4: =C4*D4*E4 -> 744.5295 | G4: 0.001 | H4: 121.14 | I4: =F4*G4*H4 -> 90.192304 | J4: Визиты: ФАКТ (Similarweb, авг. 2026, скриншот). Доля Беларуси – допущение Д-01 (Similarweb не показывает). Конверсия = CR1 × CR2 базового сценария; чек = цена Pro
A5: app.diagrams.net | B5: заменитель (визуальный редактор) | C5: 7800000 | D5: 0.001958 | E5: 0.35 | F5: =C5*D5*E5 -> 5345.34 | G5: 0.001 | H5: 121.14 | I5: =F5*G5*H5 -> 647.53449 | J5: Визиты: отчет ЛР1, без скриншота. Доля Беларуси – допущение Д-01 (Similarweb не показывает). Конверсия = CR1 × CR2 базового сценария; чек = цена Pro
A6: eraser.io | B6: прямой (AI + diagram as code) | C6: 678500 | D6: 0.001958 | E6: 0.5 | F6: =C6*D6*E6 -> 664.2515 | G6: 0.001 | H6: 121.14 | I6: =F6*G6*H6 -> 80.467427 | J6: Визиты: предварительный замер 17–23.09.2026, не подтвержден. Доля Беларуси – допущение Д-01 (Similarweb не показывает). Конверсия = CR1 × CR2 базового сценария; чек = цена Pro
A7: mermaidchart.com | B7: прямой (текстовый DSL) | C7: 20000 | D7: 0.001958 | E7: 0.7 | F7: =C7*D7*E7 -> 27.412 | G7: 0.001 | H7: 121.14 | I7: =F7*G7*H7 -> 3.3206897 | J7: Визиты: предварительный замер: «менее 20 тыс.» (верхняя граница), не подтвержден. Доля Беларуси – допущение Д-01 (Similarweb не показывает). Конверсия = CR1 × CR2 базового сценария; чек = цена Pro
F8: =C8*D8*E8 -> 0 | I8: =F8*G8*H8 -> 0 | J8: Строка не заполнена: выборка – 4 домена; не собрано минимум еще 6–16 доменов (Similarweb, вручную)
A10: Показатель | B10: Формула | C10: Значение | D10: Комментарий
A11: Суммарные релевантные посещения конкурентов | B11: SUM(F4:F8) | C11: =SUM(F4:F8) -> 6781.533 | D11: Видимый объем цифрового сегмента по найденным сайтам
A12: Оценка полного трафика сегмента | B12: B11 / коэффициент покрытия | C12: =C11/'01_Параметры'!B13 -> 10433.128 | D12: Исправлено в рабочей копии (П-2): деление на коэффициент покрытия B13, в шаблоне – на долю релевантного трафика B12
A13: Оценочная выручка видимых конкурентов в месяц | B13: SUM(I4:I8) | C13: =SUM(I4:I8) -> 821.51491 | D13: Ориентировочная оценка по конверсии и среднему чеку
A14: Оценочная выручка сегмента в год | B14: C13 / коэффициент покрытия * 12 | C14: =C13/'01_Параметры'!B13*12 -> 15166.429 | D14: Исправлено (П-2): C13 / B13 × 12

Sheet 04_Воронка
A1: 04. Расчет цифровой воронки по сценариям
A3: Показатель | B3: Осторожный | C3: Базовый | D3: Оптимистичный | E3: Комментарий
A4: Релевантные посещения в месяц | B4: ='02_Трафик_охват'!C14 -> 26.22 | C4: ='02_Трафик_охват'!C14 -> 26.22 | D4: ='02_Трафик_охват'!C14 -> 26.22 | E4: Берется с листа 02_Трафик_охват
A5: Достижимая доля трафика | B5: ='01_Параметры'!B17 -> 0.15 | C5: ='01_Параметры'!B18 -> 0.25 | D5: ='01_Параметры'!B19 -> 0.4 | E5: Сценарное допущение
A6: Достижимые посещения в месяц | B6: =B4*B5 -> 3.933 | C6: =C4*C5 -> 6.555 | D6: =D4*D5 -> 10.488 | E6: Релевантные посещения × достижимая доля
A7: Конверсия посещение → заявка | B7: ='01_Параметры'!C17 -> 0.01 | C7: ='01_Параметры'!C18 -> 0.025 | D7: ='01_Параметры'!C19 -> 0.05 | E7: Сценарное допущение
A8: Заявки в месяц | B8: =B6*B7 -> 0.03933 | C8: =C6*C7 -> 0.163875 | D8: =D6*D7 -> 0.5244 | E8: Достижимые посещения × конверсия в заявку
A9: Конверсия заявка → продажа | B9: ='01_Параметры'!D17 -> 0.03 | C9: ='01_Параметры'!D18 -> 0.04 | D9: ='01_Параметры'!D19 -> 0.05 | E9: Сценарное допущение
A10: Продажи в месяц | B10: =B8*B9 -> 0.0011799 | C10: =C8*C9 -> 0.006555 | D10: =D8*D9 -> 0.02622 | E10: Заявки × конверсия в продажу
A11: Средний чек | B11: ='01_Параметры'!E17 -> 121.14 | C11: ='01_Параметры'!E18 -> 121.14 | D11: ='01_Параметры'!E19 -> 290.74 | E11: Сценарный средний чек
A12: Выручка в месяц | B12: =B10*B11 -> 0.14293309 | C12: =C10*C11 -> 0.7940727 | D12: =D10*D11 -> 7.6232028 | E12: Продажи × средний чек
A13: Выручка в год | B13: =B12*12 -> 1.715197 | C13: =C12*12 -> 9.5288724 | D13: =D12*12 -> 91.478434 | E13: Месячная выручка × 12

Sheet 05_Сценарии
A1: 05. Сценарная оценка объема рынка
A3: Сценарий | B3: Достижимые посещения/мес | C3: Заявки/мес | D3: Продажи/мес | E3: Выручка/мес | F3: Выручка/год | G3: Интерпретация
A4: Осторожный | B4: ='04_Воронка'!B6 -> 3.933 | C4: ='04_Воронка'!B8 -> 0.03933 | D4: ='04_Воронка'!B10 -> 0.0011799 | E4: ='04_Воронка'!B12 -> 0.14293309 | F4: ='04_Воронка'!B13 -> 1.715197 | G4: Нижняя граница при слабом охвате и низких конверсиях
A5: Базовый | B5: ='04_Воронка'!C6 -> 6.555 | C5: ='04_Воронка'!C8 -> 0.163875 | D5: ='04_Воронка'!C10 -> 0.006555 | E5: ='04_Воронка'!C12 -> 0.7940727 | F5: ='04_Воронка'!C13 -> 9.5288724 | G5: Наиболее реалистичный сценарий при умеренной эффективности
A6: Оптимистичный | B6: ='04_Воронка'!D6 -> 10.488 | C6: ='04_Воронка'!D8 -> 0.5244 | D6: ='04_Воронка'!D10 -> 0.02622 | E6: ='04_Воронка'!D12 -> 7.6232028 | F6: ='04_Воронка'!D13 -> 91.478434 | G6: Верхняя граница при высокой эффективности каналов
A8: Показатель | B8: Формула | C8: Значение | D8: Комментарий
A9: Минимальная годовая выручка | B9: MIN(F4:F6) | C9: =MIN(F4:F6) -> 1.715197 | D9: Нижняя граница расчетного диапазона
A10: Базовая годовая выручка | B10: F5 | C10: =F5 -> 9.5288724 | D10: Основной ориентир для отчета
A11: Максимальная годовая выручка | B11: MAX(F4:F6) | C11: =MAX(F4:F6) -> 91.478434 | D11: Верхняя граница расчетного диапазона
A12: Размах оценки | B12: C11-C9 | C12: =C11-C9 -> 89.763237 | D12: Показывает неопределенность оценки

Sheet 06_Повторы_LTV
A1: 06. Повторные покупки и жизненная ценность клиента
A3: Сценарий | B3: Продажи/мес | C3: Средний чек | D3: Повторных покупок в год | E3: Годовая выручка с учетом повторов | F3: Средняя ценность клиента за год | G3: Комментарий
A4: Осторожный | B4: ='04_Воронка'!B10 -> 0.0011799 | C4: ='04_Воронка'!B11 -> 121.14 | D4: ='01_Параметры'!F17 -> 1 | E4: =B4*C4*D4*12 -> 1.715197 | F4: =C4*D4 -> 121.14 | G4: Разовые или редкие повторные покупки
A5: Базовый | B5: ='04_Воронка'!C10 -> 0.006555 | C5: ='04_Воронка'!C11 -> 121.14 | D5: ='01_Параметры'!F18 -> 1.2 | E5: =B5*C5*D5*12 -> 11.434647 | F5: =C5*D5 -> 145.368 | G5: Умеренная повторяемость заказов
A6: Оптимистичный | B6: ='04_Воронка'!D10 -> 0.02622 | C6: ='04_Воронка'!D11 -> 290.74 | D6: ='01_Параметры'!F19 -> 1.5 | E6: =B6*C6*D6*12 -> 137.21765 | F6: =C6*D6 -> 436.11 | G6: Регулярное сопровождение или подписочная модель
A8: Показатель | B8: Осторожный | C8: Базовый | D8: Оптимистичный
A9: Годовая выручка без учета повторов | B9: ='04_Воронка'!B13 -> 1.715197 | C9: ='04_Воронка'!C13 -> 9.5288724 | D9: ='04_Воронка'!D13 -> 91.478434
A10: Годовая выручка с учетом повторов | B10: =E4 -> 1.715197 | C10: =E5 -> 11.434647 | D10: =E6 -> 137.21765

Sheet 07_Платформа_GMV
A1: 07. Платформенная модель: GMV и выручка платформы
A3: Параметр | B3: Осторожный | C3: Базовый | D3: Оптимистичный | E3: Единица | F3: Источник/обоснование | G3: Комментарий | H3: Тип
A4: Количество сделок в месяц | B4: 0 | C4: 0 | D4: 0 | E4: сделок | F4: Сценарная оценка | G4: Не применяется: NotaCode – не многосторонняя платформа (подписка одного вида клиента); решение В-3 | H4: ввод
A5: Средняя сумма сделки | B5: 0 | C5: 0 | D5: 0 | E5: BYN | F5: Цены конкурентов / экспертно | G5: Не применяется | H5: ввод
A6: GMV в месяц | B6: =B4*B5 -> 0 | C6: =C4*C5 -> 0 | D6: =D4*D5 -> 0 | E6: BYN | F6: расчет | G6: Общий объем сделок на платформе | H6: расчет
A7: Комиссия платформы | B7: 0 | C7: 0 | D7: 0 | E7: доля | F7: Бизнес-модель | G7: Не применяется | H7: ввод
A8: Выручка платформы в месяц | B8: =B6*B7 -> 0 | C8: =C6*C7 -> 0 | D8: =D6*D7 -> 0 | E8: BYN | F8: расчет | G8: Доход платформы от комиссии | H8: расчет
A9: Выручка платформы в год | B9: =B8*12 -> 0 | C9: =C8*12 -> 0 | D9: =D8*12 -> 0 | E9: BYN | F9: расчет | G9: Годовая комиссионная выручка | H9: расчет

Sheet 08_Дашборд
A1: 08. Итоговая панель оценки рынка через цифровую воронку
A3: Ключевой показатель | B3: Значение | C3: Единица | D3: Комментарий
A4: Релевантные посещения в месяц | B4: ='02_Трафик_охват'!C14 -> 26.22 | C4: посещений | D4: База для расчета воронки
A5: Релевантные посещения в год | B5: ='02_Трафик_охват'!C15 -> 314.64 | C5: посещений | D5: Годовая база трафика
A6: Оценка полного трафика сегмента по Similarweb | B6: ='03_Конкуренты_SW'!C12 -> 10433.128 | C6: посещений/мес | D6: Оценка через конкурентов и коэффициент покрытия
A7: Годовая выручка – осторожный сценарий | B7: ='05_Сценарии'!C9 -> 1.715197 | C7: BYN/год | D7: Нижняя граница
A8: Годовая выручка – базовый сценарий | B8: ='05_Сценарии'!C10 -> 9.5288724 | C8: BYN/год | D8: Основной ориентир
A9: Годовая выручка – оптимистичный сценарий | B9: ='05_Сценарии'!C11 -> 91.478434 | C9: BYN/год | D9: Верхняя граница
A10: Годовая выручка с учетом повторов – базовый сценарий | B10: ='06_Повторы_LTV'!C10 -> 11.434647 | C10: BYN/год | D10: Учитывает повторные покупки
A11: GMV платформы – базовый сценарий | B11: ='07_Платформа_GMV'!C6*12 -> 0 | C11: BYN/год | D11: Использовать только для платформенной модели
A12: Комиссионная выручка платформы – базовый сценарий | B12: ='07_Платформа_GMV'!C9 -> 0 | C12: BYN/год | D12: Собственная выручка платформы, если применимо
A14: Итоговый вывод для отчета
A15: На основе цифровой воронки рынок оценивается через последовательность: релевантный охват → посещения → заявки → продажи → средний чек → повторные покупки. Базовый сценарий следует использовать как основной ориентир, а осторожный и оптимистичный сценарии – как нижнюю и верхнюю границы оценки. Расчет необходимо сопоставить с данными Similarweb, поискового спроса, конкурентного анализа и фактическими продажами при их наличии

Sheet 09_Источники
A1: 09. Источники данных и журнал фиксации
A3: Источник | B3: Что брать | C3: Ссылка / место хранения | D3: Дата обращения | E3: Качество | F3: Комментарий
A4: Google Analytics | B4: трафик, источники, конверсии, события | C4: собственного сайта нет (MVP не запущен) | D4: 29.09.2026 | E4: высокое | F4: Использовать для собственного сайта
A5: Google Ads | B5: показы, клики, стоимость, конверсии | C5: не собрано: рекламный кабинет (нужен доступ) | D5: 29.09.2026 | E5: высокое | F5: Использовать для рекламной воронки
A6: Яндекс Вордстат | B6: частотность запросов, регионы, динамика | C6: https://yandex.ru/support2/wordstat/ru/ | D6: 29.09.2026 | E6: среднее | F6: Отражает аудиторию Яндекса
A7: Google Trends | B7: относительная динамика интереса | C7: https://support.google.com/trends/answer/4365533 | D7: 29.09.2026 | E7: среднее | F7: Индекс 0–100, не абсолютное число запросов
A8: Similarweb | B8: посещаемость конкурентов, каналы, география | C8: https://www.similarweb.com/website/plantuml.com/ (замер 30.09.2026); остальные домены – отчет ЛР1 и предварительный замер 17–23.09.2026 | D8: 29.09.2026 | E8: среднее | F8: Оценочные данные, особенно осторожно для малых сайтов
A9: Рекламные кабинеты социальных сетей | B9: оценка охвата, клики, заявки | C9: не собрано: рекламные кабинеты VK / Meta | D9: 29.09.2026 | E9: среднее | F9: Фиксировать настройки аудитории
A10: Сайты конкурентов | B10: цены, услуги, офферы, формы заявки | C10: Страницы тарифов конкурентов (30.09.2026); курс НБРБ https://api.nbrb.by/exrates/rates/431 | D10: 29.09.2026 | E10: среднее | F10: Использовать для среднего чека и структуры предложения
